Workbook
Name _10._PITS: '[1]10. Pits'!$C$2
Name _11_UNDERGROUND_MINES: '[1]11.Underground Mines'!$C$2
Name _12._PORTS: '[1]12. Ports'!$C$2
Name _13._INVESTIGATION_CONTAMINATION_SCRAP_LEVY: '[1]13. Investigation Contamination'!$C$2
Name _14._GENERAL_LAND_REHABILITATION: '[1]14. General Land Rehabilitation'!$C$2
Name _15._MOBILISATION___DEMOBILISATION_AND_ADDITIONAL_USER_ITEMS: '[1]15. Mobilisation and User'!$C$2
Name _2._EXPLORATION: '[1]2. Exploration'!$C$2
Name _3._INFRASTRUCTURE: '[1]3. Infrastructure'!$C$2
Name _5._WATER_STORAGE: '[1]5. Water Storage'!$C$2
Name _6._WATER_TREATMENT_AND_PUMPING: '[1]6. Water Treatment'!$C$2
Name _7._WASTE_ROCK_DUMPS__OVERBURDEN_DUMPS__SPOIL_PILES_AND_STOCKPILES: '[1]7. Overburden Dumps Piles'!$C$2
Name _8._HEAP_LEACH_PADS: '[1]8. Heap Leach Pads'!$C$2
Name _9._TAILING_STORAGE_FACILITIES__REJECTS__SLIMES__SLIMES_STORAGE_FACILITIES: '[1]9. Tailings Storage Facilities'!$C$2
Name Building_list: [1]Lists!$B$190:$B$195
Name Cost_Schedule: '2024 Cost Schedule for Tool'!$C$10:$F$296
Name Cost_Schedule: #REF!
Name ELIGIBLE_MINING_ACTIVITIES: '[1]1. Eligible Mining Activities'!$C$2
Name Select_Haul_Dist_315: [2]System!$A$27:$A$30
Name Select_Haul_Dist_315_Index: [2]System!$A$27:$B$30
Name Select_Haul_Dist_805_Index: [2]System!$A$32:$B$35
Name Select_Haul_Distance: [2]System!$A$3:$A$7
Name Select_Haul_Distance_Here: [2]System!$A$22:$A$25
Name Select_Haul_distance_Here_index: [2]System!$A$22:$B$25
Name Select_Haul_Distance_Index: [2]System!$A$3:$B$7
Name Select_HAZMAT: [2]System!$A$38:$A$41
Name Select_HAZMAT_Index: [2]System!$A$38:$B$41
Name Select_Op: [2]System!#REF!
Name Select_Push_Length: [2]System!$A$9:$A$13
Name Select_Push_Length_Index: [2]System!$A$9:$B$13
Name Select_Volume: [2]System!$A$15:$A$19
Name Select_Volume_Index: [2]System!$A$15:$B$19
Name Total_Liability: #REF!

Sheet High Level Summary
A1: Item Number | B1: Estimated Cost 2024 Triennial Review
A2: Domain 1 - Surface Infrastructure | B2: 74443158
A3: Domain 2 - Tailings and Reject Emplacement Areas | B3: 1.2640301e+08
A4: Domain 3 - Overburden / Waste Emplacement Areas | B4: 26410704
A5: Domain 4 - Active Mining, Pits and Voids | B5: 2.1653769e+08
A6: Domain 5 - Water Management | B6: 5720137.5
A7: Domain 6 - Existing Rehabilitation Areas | B7: 23229568
A8: Domain 7 - Offset Areas | B8: 0
A9: Domain 8 - Underground Mining Areas | B9: 18102520
A10: Domain 9 - Other Lands | B10: 1137592
A11: Whole of Site - Sundry Items and HR/Admin/Stakeholders | B11: 2130821.3
A12: Contingencies etc | B12: 1.7294032e+08
A13: Holding Costs | B13: 2.3294449e+08
A14: Total | B14: =SUM(B2:B13) -> 900000000

Sheet Planned Closure Detail
A1: Springbok Creek | B1: Planned Closure Costing (2024) | F1: Total Liability | G1: 45536
G2: =G474 -> 9e+08
A5: Item Number | B5: Activity / Description | C5: 2024 Quantity | D5: Unit | E5: Cost code | F5: 2024 Unit Rate | G5: Estimated Cost 2024 Triennial Review | H5: 2024 Comments
A6: Domain 1 - Surface Infrastructure | G6: =SUM(G7,G19,G25,G29,G46,G54,G57,G108,G60,G71,G84,G93,G102) -> 74443158
A7: Domain 1A - MIA (Admin, workshops, bathhouse, car park etc) | G7: =SUM(G8,G14,G16) -> 5591103.5
A8: Termination of Services and Demolition Works | G8: =SUM(G9:G13) -> 4487897.3
A9: 1.001 | B9: Disconnect and terminate all services (Water, electricity, gas etc. at point of attachment to site). | C9: 1 | D9: @ | E9: 1.01 | F9: =VLOOKUP(E9,'2024 Cost Schedule for Tool'!$C$9:$F$299,4,0) -> 47518.457 | G9: =IF(D9="",0,C9*F9) -> 47518.457 | H9: No change in quantity in 2024 review. A provisional amount used to allow for the removal of services.
A10: 1.002 | B10: Demolish and remove small buildings/tanks (admin buildings - single story etc). | C10: 12531.099 | D10: m2 | E10: 1.09 | F10: =VLOOKUP(E10,'2024 Cost Schedule for Tool'!$C$9:$F$299,4,0) -> 91.359913 | G10: =IF(D10="",0,C10*F10) -> 1144840.1 | H10: No change in quantity in 2024 review.
A11: 1.003 | B11: Remove concrete pads and footings (< 0.3 m thickness) from small buildings and dumping in void. | C11: 13784.209 | D11: m2 | E11: 1.43 | F11: =VLOOKUP(E11,'2024 Cost Schedule for Tool'!$C$9:$F$299,4,0) -> 41.116034 | G11: =IF(D11="",0,C11*F11) -> 566752.01 | H11: No change in quantity in 2024 review. Estimate includes additional 10% for aprons, pathways etc.
A12: 1.004 | B12: Demolish and remove medium buildings | C12: 14731.545 | D12: m2/level | E12: 1.1 | F12: =VLOOKUP(E12,'2024 Cost Schedule for Tool'!$C$9:$F$299,4,0) -> 92.297865 | G12: =IF(D12="",0,C12*F12) -> 1359690.2 | H12: No change in quantity in 2024 review. Areas calculated for medium buildings in domain.
A13: 1.005 | B13: Remove concrete pads and footings (> 0.3 m thickness) from medium buildings and dumping in void. | C13: 16205.202 | D13: m2 | E13: 1.44 | F13: =VLOOKUP(E13,'2024 Cost Schedule for Tool'!$C$9:$F$299,4,0) -> 84.485002 | G13: =IF(D13="",0,C13*F13) -> 1369096.5 | H13: No change in quantity in 2024 review. Estimate includes additional 10% for aprons, pathways etc.
A14: Minor Reshaping, Final Trim (Roads) | C14: 0 | G14: =SUM(G15) -> 982125.65
A15: 1.006 | B15: Remove hardstand material (spillage or otherwise) from footprint of Domain (Does not include product stockpiles, CHPP or ROM) (haul distance > 1 km but < 2 km). | C15: 171335.15 | D15: m3 | E15: 3.08 | F15: =VLOOKUP(E15,'2024 Cost Schedule for Tool'!$C$9:$F$299,4,0) -> 5.7321901 | G15: =IF(D15="",0,C15*F15) -> 982125.65 | H15: No change in quantity in 2024 review. Assume 0.3 m depth hardstand material removed.
A16: Contaminated materials | C16: 0 | G16: =SUM(G17:G18) -> 121080.53
A17: 1.007 | B17: Onsite remediation of hydrocarbon contaminated soils (>1000m3) | C17: 1003.8532 | D17: m3 | E17: 4.12 | F17: =VLOOKUP(E17,'2024 Cost Schedule for Tool'!$C$9:$F$299,4,0) -> 84.485002 | G17: =IF(D17="",0,C17*F17) -> 84810.537 | H17: No change in quantity in 2024 review. Provisional sum.
A18: 1.008 | B18: Construct and set up bioremediation pad | C18: 0.933296 | D18: allow | E18: 4.09a | F18: =VLOOKUP(E18,'2024 Cost Schedule for Tool'!$C$9:$F$299,4,0) -> 38862.259 | G18: =IF(D18="",0,C18*F18) -> 36269.991 | H18: No change in quantity in 2024 review.
A19: Domain 1B - CHPP Main Plant | C19: 0 | G19: =SUM(G20:G24) -> 17123864
A20: Termination of Services and Demolition Works | C20: 0 | G20: =SUM(G22:G24) -> 0
A21: 1.009 | B21: Demolish and remove CHPP | C21: 0.933296 | D21: @ | E21: SS | F21: =15768913+2578818 -> 18347731 | G21: =IF(D21="",0,C21*F21) -> 17123864
A22: 1.01 | B22: Demolish and remove CHPP (include the area of each floor of the structure) | C22: 0 | D22: m2/level | E22: 1.12 | F22: =VLOOKUP(E22,'2024 Cost Schedule for Tool'!$C$9:$F$299,4,0) -> 247.82643 | G22: =IF(D22="",0,C22*F22) -> 0 | H22: Captured above
A23: 1.011 | B23: Demolish and remove heavy industrial buildings - crushers, sizing stations, rotary breakers, etc (area of each floor of the structure). | C23: 0 | D23: m2/level | E23: 1.13 | F23: =VLOOKUP(E23,'2024 Cost Schedule for Tool'!$C$9:$F$299,4,0) -> 253.455 | G23: =IF(D23="",0,C23*F23) -> 0 | H23: Captured above
A24: 1.012 | B24: Remove concrete pads and footings (> 0.3 m thickness) and dumping in void. | C24: 0 | D24: m2 | E24: 1.44 | F24: =VLOOKUP(E24,'2024 Cost Schedule for Tool'!$C$9:$F$299,4,0) -> 84.485002 | G24: =IF(D24="",0,C24*F24) -> 0 | H24: Captured above
A25: Domain 1C - CHPP MOD 4 | C25: 0 | G25: =SUM(G26) -> 838423.35
A26: Termination of Services and Demolition Works | C26: 0 | G26: =SUM(G27:G28) -> 838423.35
A27: 1.013 | B27: Demolish and remove CHPP (include the area of each floor of the structure) | C27: 3147.0797 | D27: m2/level | E27: 1.12 | F27: =VLOOKUP(E27,'2024 Cost Schedule for Tool'!$C$9:$F$299,4,0) -> 247.82643 | G27: =IF(D27="",0,C27*F27) -> 779929.52 | H27: No change in quantity in 2024 review. ~627 m2 x 5 levels.
A28: 1.014 | B28: Remove concrete pads and footings (> 300 mm thickness) and dumping in void. | C28: 692.35754 | D28: m2 | E28: 1.44 | F28: =VLOOKUP(E28,'2024 Cost Schedule for Tool'!$C$9:$F$299,4,0) -> 84.485002 | G28: =IF(D28="",0,C28*F28) -> 58493.828 | H28: No change in quantity in 2024 review. Estimate includes additional 10% for aprons, pathways etc.
A29: Domain 1D - Product Stockpiles and ROM (includes relevant Rail Loop infrastructure) | C29: 0 | G29: =SUM(G30,G39,G41,G43) -> 13036272
A30: Termination of Services and Demolition Works | C30: 0 | G30: =SUM(G31:G38) -> 11698302
A31: 1.015 | B31: Demolish and remove bucket wheel stacker/reclaimer | C31: 3.733184 | D31: @ | E31: 1.15 | F31: =VLOOKUP(E31,'2024 Cost Schedule for Tool'!$C$9:$F$299,4,0) -> 2252933.4 | G31: =IF(D31="",0,C31*F31) -> 8410614.8 | H31: No change in quantity in 2024 review. Just removal of the bucket wheel stacker/reclaim unit - does not include terminate services, remove rails and ballast etc.
A32: 1.016 | B32: Demolish and remove on ground conveyors, transfer stations & gantries (scrap only – does not include dismantling for reuse at another site). | C32: 6392.8681 | D32: m | E32: 1.21 | F32: =VLOOKUP(E32,'2024 Cost Schedule for Tool'!$C$9:$F$299,4,0) -> 225.64273 | G32: =IF(D32="",0,C32*F32) -> 1442504.2 | H32: No change in quantity in 2024 review. All within the CHPP/stockpile area.
A33: 1.017 | B33: Demolish and remove elevated conveyors, transfer stations & gantries (scrap only – does not include dismantling for reuse at another site). | C33: 355.15934 | D33: m | E33: 1.22 | F33: =VLOOKUP(E33,'2024 Cost Schedule for Tool'!$C$9:$F$299,4,0) -> 463.05751 | G33: =IF(D33="",0,C33*F33) -> 164459.2 | H33: No change in quantity in 2024 review. All within the CHPP/stockpile area.
A34: 1.018 | B34: Demolish and remove overhead conveyors, transfer stations & gantries (scrap only – does not include dismantling for reuse at another site) | C34: 355.15934 | D34: m | E34: 1.23 | F34: =VLOOKUP(E34,'2024 Cost Schedule for Tool'!$C$9:$F$299,4,0) -> 957.49669 | G34: =IF(D34="",0,C34*F34) -> 340063.89 | H34: No change in quantity in 2024 review. All within the CHPP/stockpile area.
A35: 1.019 | B35: Demolish reclaim tunnel, cut reo and expose reclaim conveyor, then collapse into the reclaim tunnel void (Does not include excavation to expose reclaim tunnel, removal of conveyor or backfilling void). | C35: 11293.348 | D35: m2 | E35: 1.24 | F35: =VLOOKUP(E35,'2024 Cost Schedule for Tool'!$C$9:$F$299,4,0) -> 107.01434 | G35: =IF(D35="",0,C35*F35) -> 1208550.2 | H35: No change in quantity in 2024 review.
A36: 1.02 | B36: Remove and demolish conveyor from reclaim tunnel (Does not include excavation and demolition of reclaim tunnel roof). | C36: 150.57798 | D36: m | E36: 1.25 | F36: =VLOOKUP(E36,'2024 Cost Schedule for Tool'!$C$9:$F$299,4,0) -> 168.97 | G36: =IF(D36="",0,C36*F36) -> 25443.161 | H36: No change in quantity in 2024 review. Estimate for underground conveyor infrastructure to be removed.
A37: 1.021 | B37: Remove concrete pads and footings (> 300 mm thickness) and dumping in void. | C37: 401.54127 | D37: m2 | E37: 1.44 | F37: =VLOOKUP(E37,'2024 Cost Schedule for Tool'!$C$9:$F$299,4,0) -> 84.485002 | G37: =IF(D37="",0,C37*F37) -> 33924.215 | H37: No change in quantity in 2024 review. Assume ~0.5 m footings.
A38: 1.022 | B38: Demolish and remove rejects bin | C38: 0.933296 | D38: @ | E38: 1.19 | F38: =VLOOKUP(E38,'2024 Cost Schedule for Tool'!$C$9:$F$299,4,0) -> 77940.938 | G38: =IF(D38="",0,C38*F38) -> 72741.965 | H38: No change in quantity in 2024 review. Assumes 1250 t coal bin.
A39: Minor Reshaping, Final Trim (Roads) | C39: 0 | G39: =SUM(G40) -> 0
A40: 1.023 | B40: Unsealed roads / vehicle park-up areas – Minor earthworks, final trim and deep rip and seed (pasture grass) | C40: 0 | D40: ha | E40: 3.03 | F40: =VLOOKUP(E40,'2024 Cost Schedule for Tool'!$C$9:$F$299,4,0) -> 3723.4649 | G40: =IF(D40="",0,C40*F40) -> 0 | H40: Zeroed as these are now consolidated at the bottom of the infrastructure domain.
A41: Contaminated materials | C41: 0 | G41: =SUM(G42) -> 1327472.7
A42: 1.024 | B42: Remove carbonaceous material (spillage or otherwise) from footprint of the CHPP, ROM, Product stockpiles & Roadways (haul distance > 1 km but < 2 km). | C42: 231739.51 | D42: m3 | E42: 4.04 | F42: =VLOOKUP(E42,'2024 Cost Schedule for Tool'!$C$9:$F$299,4,0) -> 5.728297 | G42: =IF(D42="",0,C42*F42) -> 1327472.7 | H42: No change in quantity in 2024 review. Includes scalping carbonaceous material from ROM and two product stockpile areas to depth of 0.5 m.
A43: Earthworks / Structural Works | C43: 0 | G43: =SUM(G44:G45) -> 10497.691
A44: 1.025 | B44: Replace material from above to expose the concrete reclaim tunnel. 150m - 200 m push length, D11 | C44: 1355.2018 | D44: m3 | E44: 8.04a | F44: =VLOOKUP(E44,'2024 Cost Schedule for Tool'!$C$9:$F$299,4,0) -> 3.2026388 | G44: =IF(D44="",0,C44*F44) -> 4340.2218 | H44: No change in quantity in 2024 review. Average excavation depth of 3 m over 450 m2 and will be stockpiled locally and replaced.
A45: 1.026 | B45: Excavate material from above to expose the concrete reclaim tunnel. | C45: 1355.2018 | D45: m3 | E45: 9.04 | F45: =VLOOKUP(E45,'2024 Cost Schedule for Tool'!$C$9:$F$299,4,0) -> 4.543581 | G45: =IF(D45="",0,C45*F45) -> 6157.4691 | H45: No change in quantity in 2024 review. Average excavation depth of 3 m over 450 m2 and will be stockpiled locally and replaced.
A46: Domain 1E - Camp (80 man camp) | C46: 0 | G46: =SUM(G47,G51) -> 194123.22
A47: Termination of Services and Demolition Works | C47: 0 | G47: =SUM(G48:G50) -> 194123.22
A48: 1.027 | B48: Disconnect and terminate all services (Water, electricity, gas etc. at point of attachment to site). | C48: 0.933296 | D48: @ | E48: 1.02 | F48: =VLOOKUP(E48,'2024 Cost Schedule for Tool'!$C$9:$F$299,4,0) -> 9490.4819 | G48: =IF(D48="",0,C48*F48) -> 8857.4288 | H48: No change in quantity in 2024 review. A provisional amount used to allow for the removal of services.
A49: 1.028 | B49: Demolish and remove infrastructure (accommodation) | C49: 1766.7816 | D49: m2 | E49: 1.08 | F49: =VLOOKUP(E49,'2024 Cost Schedule for Tool'!$C$9:$F$299,4,0) -> 45.058668 | G49: =IF(D49="",0,C49*F49) -> 79608.824 | H49: No change in quantity in 2024 review. Assume 80 demountable buildings @ 22 m2 area.
A50: 1.029 | B50: Remove bitumen (car park and access roads) for dumping in a void on the site. | C50: 12506.003 | D50: m2 | E50: 1.41 | F50: =VLOOKUP(E50,'2024 Cost Schedule for Tool'!$C$9:$F$299,4,0) -> 8.4485002 | G50: =IF(D50="",0,C50*F50) -> 105656.97 | H50: No change in quantity in 2024 review.
A51: Minor Reshaping, Final Trim (Roads) | C51: 0 | G51: =SUM(G52:G53) -> 0
A52: 1.03 | B52: Remove stabilised material (blue metal, aggregate etc.) from roadways / hardstands / laydown areas and dump in a void on-site (haul distance >1 km but <2 km) | C52: 0 | D52: m3 | E52: 3.08 | F52: =VLOOKUP(E52,'2024 Cost Schedule for Tool'!$C$9:$F$299,4,0) -> 5.7321901 | G52: =IF(D52="",0,C52*F52) -> 0 | H52: Not required. Discussed with site.
A53: 1.031 | B53: Unsealed roads / vehicle park-up areas – Minor earthworks, final trim and deep rip and seed (pasture grass) | C53: 0 | D53: ha | E53: 3.03 | F53: =VLOOKUP(E53,'2024 Cost Schedule for Tool'!$C$9:$F$299,4,0) -> 3723.4649 | G53: =IF(D53="",0,C53*F53) -> 0 | H53: Zeroed as these are now consolidated at the bottom of the infrastructure domain.
A54: Domain 1G - Lake horn | C54: 0 | G54: =SUM(G55:G56) -> 21671.071
A55: 1.032 | B55: Remove surface pipelines. | C55: 100.38532 | D55: m | E55: 1.39 | F55: =VLOOKUP(E55,'2024 Cost Schedule for Tool'!$C$9:$F$299,4,0) -> 16.897 | G55: =IF(D55="",0,C55*F55) -> 1696.2107 | H55: No change in quantity in 2024 review. Estimate assumes some pipes/pumps are located within the dam.
A56: 1.033 | B56: Remove pump and pontoon from a small lake or dam including pipes and electrical supply or diesel tank/s. | C56: 0.933296 | D56: @ | E56: 1.40a | F56: =VLOOKUP(E56,'2024 Cost Schedule for Tool'!$C$9:$F$299,4,0) -> 21402.492 | G56: =IF(D56="",0,C56*F56) -> 19974.86 | H56: No change in quantity in 2024 review.
A57: Domain 1H - Roads | C57: 0 | G57: =SUM(G58) -> 1292512.6
A58: Termination of Services and Demolition Works | C58: 0 | G58: =SUM(G59) -> 1292512.6
A59: 1.034 | B59: Remove bitumen (car park and access roads) for dumping in a void on the site. | C59: 152987.22 | D59: m2 | E59: 1.41 | F59: =VLOOKUP(E59,'2024 Cost Schedule for Tool'!$C$9:$F$299,4,0) -> 8.4485002 | G59: =IF(D59="",0,C59*F59) -> 1292512.6 | H59: No change in quantity in 2024 review. Includes all sealed road except for that asP6iated with the Camp, OC1 and surface.
A60: Domain 1I - Other Infrastructure | C60: 0 | G60: =SUM(G61:G70) -> 8508966.5
A61: 1.035 | B61: Airstrip - Remove bitumen material and dumping in void. | C61: 32986.615 | D61: m2 | E61: 1.42 | F61: =VLOOKUP(E61,'2024 Cost Schedule for Tool'!$C$9:$F$299,4,0) -> 22.529334 | G61: =IF(D61="",0,C61*F61) -> 743166.47 | H61: No change in quantity in 2024 review.
A62: 1.036 | B62: Removal of powerlines (this includes disconnection, rolling up the wires and removing the poles). It does not include the removal of substations. | C62: 181.79781 | D62: km | E62: 1.03 | F62: =VLOOKUP(E62,'2024 Cost Schedule for Tool'!$C$9:$F$299,4,0) -> 17002.238 | G62: =IF(D62="",0,C62*F62) -> 3090969.7 | H62: No change in quantity in 2024 review. Based on the length of all powerlines on site in ERC.
A63: 1.037 | B63: Miscellaneous clean-up around site (carbonaceous materials etc) | C63: 0.933296 | D63: @ | E63: SS | F63: =100000*1.16 -> 116000 | G63: =IF(D63="",0,C63*F63) -> 108262.34 | H63: Includes 16% escalation for site specific rates in 2014.Provisional sum.
A64: 1.038 | B64: Unsealed roads / vehicle park-up areas – Minor earthworks, final trim and deep rip and seed (pasture grass) | C64: 0 | D64: ha | E64: 3.03 | F64: =VLOOKUP(E64,'2024 Cost Schedule for Tool'!$C$9:$F$299,4,0) -> 3723.4649 | G64: =IF(D64="",0,C64*F64) -> 0 | H64: Zeroed as these are now captured within other domains.
A65: 1.039 | B65: Provision to dewater sumps and general tidy up of site prior to the commencement of demolition | C65: 0.933296 | D65: @ | E65: SS | F65: =50000*1.16 -> 58000 | G65: =IF(D65="",0,C65*F65) -> 54131.168 | H65: Includes 16% escalation for site specific rates in 2014.Provisional sum.
A66: 1.04 | B66: Remove stabilised material (blue metal, aggregate etc.) from roadways / hardstands / laydown areas and dump in a void on-site (haul distance >1 km but <2 km) | C66: 0 | D66: m3 | E66: 3.08 | F66: =VLOOKUP(E66,'2024 Cost Schedule for Tool'!$C$9:$F$299,4,0) -> 5.7321901 | G66: =IF(D66="",0,C66*F66) -> 0 | H66: Not required. Discussed with site.
A67: 1.041 | B67: Fence removal | C67: 4015.4127 | D67: m | E67: 1.48 | F67: =VLOOKUP(E67,'2024 Cost Schedule for Tool'!$C$9:$F$299,4,0) -> 22.529334 | G67: =IF(D67="",0,C67*F67) -> 90464.573 | H67: No change in quantity in 2024 review. Provisional sum.
A68: 1.042 | B68: Demolish and remove small buildings/tanks | C68: 2992.9481 | D68: m2 | E68: 1.09 | F68: =VLOOKUP(E68,'2024 Cost Schedule for Tool'!$C$9:$F$299,4,0) -> 91.359913 | G68: =IF(D68="",0,C68*F68) -> 273435.48 | H68: No change in quantity in 2024 review. Areas calculated for small buildings in Other Lands domain based on rate review. Assume all are single storey buildings.
A69: 1.043 | B69: Remove concrete pads and footings (< 0.3 m thickness) from small buildings and dumping in void. | C69: 3292.2429 | D69: m2 | E69: 1.43 | F69: =VLOOKUP(E69,'2024 Cost Schedule for Tool'!$C$9:$F$299,4,0) -> 41.116034 | G69: =IF(D69="",0,C69*F69) -> 135363.97 | H69: No change in quantity in 2024 review. Assume 10% additional footprint for aprons, etc.
A70: 1.044 | B70: Demolition/Removal of Dragline. | C70: 0.933296 | D70: @ | E70: SS | F70: 4300000 | G70: =IF(D70="",0,C70*F70) -> 4013172.8 | H70: New Line Added. Rate is based on quote. Quote was $2.7M for the small dragline (CAT 8000 Dragline - BE 1370) and $4.3M for the big one (CAT 8750 Dragline - Marion 8750). Site to confirm size of dragline and most applicable rate. Draglines are 1370s with total out of pocket expense of $2M combined (includes $2.3M for scrap steel , total $4.3M).
A71: Domain 9K - Camp Infrastructure | C71: 0 | G71: =SUM(G72,G81) -> 18192403
A72: Termination of Services and Demolition Works | C72: 0 | G72: =SUM(G73:G80) -> 17952709 | H72: Note that in the 2021 costing cells R777-779 were double counted.
A73: 1.045 | B73: Disconnect and terminate all services (Water, electricity, gas etc. at point of attachment to site) | C73: 0.933296 | D73: @ | E73: 1.01 | F73: =VLOOKUP(E73,'2024 Cost Schedule for Tool'!$C$9:$F$299,4,0) -> 47518.457 | G73: =IF(D73="",0,C73*F73) -> 44348.785 | H73: No change in quantity in 2024 review. For disconnection of all services, at building boundaries, physical cut at the distributions board.
A74: 1.046 | B74: Demolish and/or remove substations (Assumes they are in a closed building) | C74: 35.134861 | D74: m2 | E74: 1.06 | F74: =VLOOKUP(E74,'2024 Cost Schedule for Tool'!$C$9:$F$299,4,0) -> 701.8524 | G74: =IF(D74="",0,C74*F74) -> 24659.486 | H74: No change in quantity in 2024 review.
A75: 1.047 | B75: Removal of services (rolling up the wires and removing the poles, removing water/sewage pipes). It does not include the removal of substations. | C75: 33.127155 | D75: km | E75: 1.03 | F75: =VLOOKUP(E75,'2024 Cost Schedule for Tool'!$C$9:$F$299,4,0) -> 17002.238 | G75: =IF(D75="",0,C75*F75) -> 563235.78 | H75: No change in quantity in 2024 review. Assumes underground powerlines run along-side roads, therefore equal in length.
A76: 1.048 | B76: Demolish and remove small buildings - houses | C76: 506.94585 | D76: @ | E76: SS | F76: =20000*1.16 -> 23200 | G76: =IF(D76="",0,C76*F76) -> 11761144 | H76: Includes 16% escalation for site specific rates in 2014.Approximately 505 dwellings.
A77: 1.049 | B77: Remove all demountables | C77: 86.331373 | D77: @ | E77: SS | F77: =7000*1.16 -> 8120 | G77: =IF(D77="",0,C77*F77) -> 701010.75 | H77: Includes 16% escalation for site specific rates in 2014.86 single person dwellings.
A78: 1.05 | B78: Demolish and remove moderate buildings (e.g. school, shopping centre) | C78: 26501.724 | D78: m2 | E78: 1.1 | F78: =VLOOKUP(E78,'2024 Cost Schedule for Tool'!$C$9:$F$299,4,0) -> 92.297865 | G78: =IF(D78="",0,C78*F78) -> 2446052.5 | H78: No change in quantity in 2024 review. This includes schools, shopping centres, public building etc (0.75+0.49+0.16+0.17+0.23+0.84= 2.6 ha).
A79: 1.051 | B79: Remove concrete pads & footings (<300mm thickness) and dumping in void | C79: 29151.896 | D79: m2 | E79: 1.43 | F79: =VLOOKUP(E79,'2024 Cost Schedule for Tool'!$C$9:$F$299,4,0) -> 41.116034 | G79: =IF(D79="",0,C79*F79) -> 1198610.4 | H79: No change in quantity in 2024 review. Estimate includes additional 10% for aprons, pathways etc.
A80: 1.052 | B80: Remove bitumen (e.g. car park and access roads) | C80: 143652.39 | D80: m2 | E80: 1.41 | F80: =VLOOKUP(E80,'2024 Cost Schedule for Tool'!$C$9:$F$299,4,0) -> 8.4485002 | G80: =IF(D80="",0,C80*F80) -> 1213647.3 | H80: No change in quantity in 2024 review. The total length of all road at Camp are ~ 20.5 km, assume an average width of 7 m. Demolition expert estimate however economies of scale could reduce this number
A81: Contaminated materials | C81: 0 | G81: =SUM(G82:G83) -> 239694.23
A82: 1.053 | B82: Remove and dispose of asbestos | C82: 5019.2659 | D82: m2 | E82: 4.16 | F82: =VLOOKUP(E82,'2024 Cost Schedule for Tool'!$C$9:$F$299,4,0) -> 45.058668 | G82: =IF(D82="",0,C82*F82) -> 226161.43 | H82: No change in quantity in 2024 review. Remove, contain, transport and dispose of asbestos materials
A83: 1.054 | B83: Sale of houses at Middlemount | C83: 23.3324 | D83: @ | E83: SS | F83: =500*1.16 -> 580 | G83: =IF(D83="",0,C83*F83) -> 13532.792 | H83: Includes 16% escalation for site specific rates in 2014.Number of houses confirmed with SCC. Provisional sum for managing sale of houses.
A84: Domain 9L - Camp Water Treatment Plant | C84: 0 | G84: =SUM(G85,G89,G91) -> 232670.29
A85: Termination of Services and Demolition Works | C85: 0 | G85: =SUM(G86:G88) -> 217674.92
A86: 1.055 | B86: Water treatment plant infrastructure | C86: 672.58163 | D86: m2 | E86: 1.1 | F86: =VLOOKUP(E86,'2024 Cost Schedule for Tool'!$C$9:$F$299,4,0) -> 92.297865 | G86: =IF(D86="",0,C86*F86) -> 62077.848 | H86: No change in quantity in 2024 review. The infrastructure includes small building (220 m2 and 450 m2).
A87: 1.056 | B87: Demolish and remove small tank clean (thickener etc 3-9 m diameter) | C87: 1.866592 | D87: @ | E87: 1.28 | F87: =VLOOKUP(E87,'2024 Cost Schedule for Tool'!$C$9:$F$299,4,0) -> 11264.667 | G87: =IF(D87="",0,C87*F87) -> 21026.537 | H87: No change in quantity in 2024 review.
A88: 1.057 | B88: Demolish and remove small tank clean (thickener etc 15-30 m diameter) | C88: 1.866592 | D88: @ | E88: 1.3 | F88: =VLOOKUP(E88,'2024 Cost Schedule for Tool'!$C$9:$F$299,4,0) -> 72094.244 | G88: =IF(D88="",0,C88*F88) -> 134570.54 | H88: No change in quantity in 2024 review.
A89: Contaminated materials | C89: 0 | G89: =SUM(G90) -> 0
A90: 1.058 | B90: Remove stabilised material (blue metal, aggregate etc) from roadways and dump in a void on-site (haul distance >2 km but <5 km) | C90: 0 | D90: m3 | E90: 4.05 | F90: =VLOOKUP(E90,'2024 Cost Schedule for Tool'!$C$9:$F$299,4,0) -> 7.4858426 | G90: =IF(D90="",0,C90*F90) -> 0 | H90: Not required. Discussed with site.
A91: Earthworks / Structural Works | C91: 0 | G91: =SUM(G92:G92) -> 14995.368
A92: 1.059 | B92: Major bulk pushing to achieve grades nominated in the approval/permit - 50 m-100 m push length, D11 | C92: 9679.1523 | D92: ha | E92: 8.02a | F92: =VLOOKUP(E92,'2024 Cost Schedule for Tool'!$C$9:$F$299,4,0) -> 1.5492439 | G92: =IF(D92="",0,C92*F92) -> 14995.368 | H92: Assumes No change in quantity in 2024 review. Assume a average depth of 2.6 m. Assumes evaporation ponds will be pushed in and recontoured.
A93: Domain 9M - Camp Sewage Treatment Plant | C93: 0 | G93: =SUM(G94,G99) -> 270344.98
A94: Termination of Services and Demolition Works | C94: 0 | G94: =SUM(G95:G98) -> 265679.34
A95: 1.06 | B95: Sewage treatment plant infrastructure | C95: 150.57798 | D95: m2 | E95: 1.1 | F95: =VLOOKUP(E95,'2024 Cost Schedule for Tool'!$C$9:$F$299,4,0) -> 92.297865 | G95: =IF(D95="",0,C95*F95) -> 13898.026 | H95: No change in quantity in 2024 review. The infrastructure includes small building (50 m2 and 100 m2).
A96: 1.061 | B96: Demolish and remove small tank clean (thickener etc 10-15 m diameter) | C96: 1.866592 | D96: @ | E96: 1.29 | F96: =VLOOKUP(E96,'2024 Cost Schedule for Tool'!$C$9:$F$299,4,0) -> 33794.001 | G96: =IF(D96="",0,C96*F96) -> 63079.611 | H96: No change in quantity in 2024 review. Concrete tanks with booms.
A97: 1.062 | B97: Demolish and remove small tank clean (thickener etc 15-30 m diameter) | C97: 1.866592 | D97: @ | E97: 1.3 | F97: =VLOOKUP(E97,'2024 Cost Schedule for Tool'!$C$9:$F$299,4,0) -> 72094.244 | G97: =IF(D97="",0,C97*F97) -> 134570.54 | H97: No change in quantity in 2024 review. Concrete tanks with booms.
A98: 1.063 | B98: Remove contaminated water from maturation pond | C98: 0.933296 | D98: @ | E98: SS | F98: =50000*1.16 -> 58000 | G98: =IF(D98="",0,C98*F98) -> 54131.168 | H98: Includes 16% escalation for site specific rates in 2014. Provisional sum.
A99: Minor Reshaping, Final Trim (Roads) | C99: 0 | G99: =SUM(G100:G101) -> 4665.6404
A100: 1.064 | B100: Major bulk pushing to achieve grades nominated in the approval/permit - 50 m-100 m push length, D11. CampSewage Treatment Plant | C100: 3011.5595 | D100: m3 | E100: 8.02a | F100: =VLOOKUP(E100,'2024 Cost Schedule for Tool'!$C$9:$F$299,4,0) -> 1.5492439 | G100: =IF(D100="",0,C100*F100) -> 4665.6404 | H100: Assumes No change in quantity in 2024 review. Assumes the dam wall will be pushed in and recontoured - 100 x 5 x 3 m. Also includes recontouring around the concrete tanks after removal.
A101: 1.065 | B101: Remove stabilised material (blue metal, aggregate etc.) from roadways / hardstands / laydown areas and dump in a void on-site (haul distance >1 km but <2 km) | C101: 0 | D101: m3 | E101: 3.08 | F101: =VLOOKUP(E101,'2024 Cost Schedule for Tool'!$C$9:$F$299,4,0) -> 5.7321901 | G101: =IF(D101="",0,C101*F101) -> 0 | H101: Not required. Discussed with site.
A102: Domain 9N - Camp Landfill | C102: 0 | G102: =SUM(G103,G106) -> 890210.96
...

Sheet BulkPush
B3: Planned Closure Cost Volumes and Push Lengths Required:
B4: Equipment (Dozer) | C4: Planned closure (Active Mining, Pits and Voids): | D4: 2024 Volume (m3) | S4: Planned Closure Volume (m3) | Y4: Comments
D5: P1 | E5: P2 | F5: P3 | G5: P4 | H5: P5 | I5: P6 | J5: G6 | K5: A3 | L5: A4 | M5: G8 | N5: G5 | O5: G3 | P5: G4 | Q5: G7 | R5: G9 | S5: Pit 1 (insert pit name) | T5: Pit 2 | U5: Pit 3 | V5: Pit 4 | W5: Pit 5 | X5: Total
B6: Benches, high wall treatment | C6: Active pit area – benches blasted and doze to acceptable grade | X6: =SUM(S6:W6) -> 0
C7: Drill & blast faces to make safe | X7: =SUM(S7:W7) -> 0
C8: High wall treatment – (trench and safety berm) no additional works required to establish | X8: =SUM(S8:W8) -> 0
C9: High wall treatment – (trench and safety berm) with additional treatment of adjacent loose weathered material | X9: =SUM(S9:W9) -> 0
B10: D10 Major bulk | C10: 50m push length. | X10: =SUM(S10:W10) -> 0
C11: 50m-100m push length | X11: =SUM(S11:W11) -> 0
C12: 100m-150m push length | X12: =SUM(S12:W12) -> 0
C13: 150m - 200 m push length | X13: =SUM(S13:W13) -> 0
C14: 200m - 300 m push length | X14: =SUM(S14:W14) -> 0
C15: >300 m push length | S15: Use load and haul for distances greater than 300m. | X15: =SUM(S15:W15) -> 0
B16: D11 Major bulk | C16: 50m push length. | X16: =SUM(S16:W16) -> 0
C17: 50m-100m push length | X17: =SUM(S17:W17) -> 0
C18: 100m-150m push length | D18: 11495082 | E18: 1099857.5 | F18: 12027602 | G18: 6976693.1 | H18: 3614573.6 | I18: 1394252.8 | J18: 2834489.9 | K18: 4594261.9 | L18: 2708791.9 | M18: 2331697.9 | N18: 2080301.9 | O18: 1577509.9 | P18: 1577509.9 | Q18: 3588677.9 | R18: 1074717.9 | X18: =SUM(D18:W18) -> 58976020
C19: 150m - 200 m push length | X19: =SUM(S19:W19) -> 0
C20: 200m - 300 m push length | X20: =SUM(S20:W20) -> 0
C21: >300 m push length | S21: Use load and haul for distances greater than 300m. | X21: =SUM(S21:W21) -> 0
B23: Equipment (Dozer) | C23: Planned closure (Overburden/Waste Emplacement Areas): | S23: Planned Closure Volume (m3) | Y23: Comments
S24: Dump 1 (insert dump name | T24: Dump 2 | U24: Dump 3 | V24: Dump 4 | W24: Dump 5 | X24: Total
B25: D10 Major bulk | C25: 50m push length. | X25: =SUM(S25:W25) -> 0
C26: 50m-100m push length | X26: =SUM(S26:W26) -> 0
C27: 100m-150m push length | X27: =SUM(S27:W27) -> 0
C28: 150m - 200 m push length | X28: =SUM(S28:W28) -> 0
C29: 200m - 300 m push length | X29: =SUM(S29:W29) -> 0
C30: >300 m push length | S30: Use load and haul for distances greater than 300m. | X30: =SUM(S30:W30) -> 0
B31: D11 Major bulk | C31: 50m push length. | X31: =SUM(S31:W31) -> 0
C32: 50m-100m push length | X32: =SUM(S32:W32) -> 0
C33: 100m-150m push length | X33: =SUM(S33:W33) -> 0
C34: 150m - 200 m push length | X34: =SUM(S34:W34) -> 0
C35: 200m - 300 m push length | X35: =SUM(S35:W35) -> 0
C36: >300 m push length | S36: Use load and haul for distances greater than 300m. | X36: =SUM(S36:W36) -> 0
B38: Equipment (Dozer) | C38: Planned closure (Tailings Dams): Assuming material that is placed on the approved cap. Ie. Material to get to final landform, after capping. | S38: Planned Closure Volume (m3) | Y38: Comments
S39: Tailings Dam 1 (insert TD name | T39: Tailings Dam 2 (insert TD name | U39: Tailings Dam 3 (insert TD name | V39: Tailings Dam 4 (insert TD name | W39: Tailings Dam 5 (insert TD name | X39: Total
B40: D10 Major bulk | C40: 50m push length. | X40: =SUM(S40:W40) -> 0
C41: 50m-100m push length | X41: =SUM(S41:W41) -> 0
C42: 100m-150m push length | X42: =SUM(S42:W42) -> 0
C43: 150m - 200 m push length | X43: =SUM(S43:W43) -> 0
C44: 200m - 300 m push length | X44: =SUM(S44:W44) -> 0
C45: >300 m push length | S45: Use load and haul for distances greater than 300m. | X45: =SUM(S45:W45) -> 0
B46: D11 Major bulk | C46: 50m push length. | X46: =SUM(S46:W46) -> 0
C47: 50m-100m push length | X47: =SUM(S47:W47) -> 0
C48: 100m-150m push length | X48: =SUM(S48:W48) -> 0
C49: 150m - 200 m push length | X49: =SUM(S49:W49) -> 0
C50: 200m - 300 m push length | X50: =SUM(S50:W50) -> 0
C51: >300 m push length | S51: Use load and haul for distances greater than 300m. | X51: =SUM(S51:W51) -> 0

Sheet Haulage
B1: Imminent Closure - Volumes and Load and Haul Lengths Required: | AF1: Planned Closure - Volumes and Load and Haul Lengths Required:
B2: Imminent closure: | C2: =+AG2 -> P1 | D2: =+AH2 -> P2 | E2: =+AI2 -> P3 | F2: =+AJ2 -> P4 | G2: =+AK2 -> P5 | H2: =+AL2 -> P6 | I2: =+AM2 -> W6 | J2: =+AN2 -> A3 | ... W2: =+BA2 -> 0 | X2: Haul 1 (m3) | Y2: Haul 2 (m3) | Z2: Haul 3 (m3) | AA2: Total (m3) | AB2: Comments | AF2: Planned closure: | AG2: P1 | AH2: P2 | AI2: P3 | AJ2: P4 | AK2: P5 | AL2: P6 | AM2: W6 | AN2: A3 | AO2: A4 | AP2: W8 | AQ2: W5 | AR2: W3 | AS2: W4 | AT2: W7 | AU2: W9 | AV2: Total (m3) | AW2: Comments
B3: 800t fleet - Flat | AF3: 100t fleet - Flat
B4: Load and haul 800 t fleet, flat, <1km | D4: =+AH4 -> 568569.88 | E4: =+AI4 -> 5812126.5 | F4: =+AJ4 -> 1116340 | G4: =+AK4 -> 1372948.5 | H4: =+AL4 -> 3843896 | AA4: =SUM(C4:Z4) -> 12713881 | AF4: Load and haul 100 t fleet, flat, <1km | AG4: 1638064.1 | AH4: 568569.88 | AI4: 5812126.5 | AJ4: 1116340 | AK4: 1372948.5 | AL4: 3843896 | AV4: =SUM(AG4:AU4) -> 14351945
B5: Load and haul 800 t fleet, flat, 1-2km | J5: 300000 | K5: 400000 | L5: 500000 | M5: 400000 | O5: 100000 | Q5: 100000 | AA5: =SUM(C5:Z5) -> 1800000 | AB5: See the conceptual option4 | AF5: Load and haul 100 t fleet, flat, 1-2km | AM5: 835943.44 | AN5: 434883.1 | AO5: 568569.88 | AP5: 702256.66 | AQ5: 568569.88 | AR5: 167509.54 | AS5: 167509.54 | AT5: 180878.22 | AU5: 167509.54 | AV5: =SUM(AG5:AU5) -> 3793629.8
B6: Load and haul 800 t fleet, flat, 2-5km | AA6: =SUM(X6:Z6) -> 0 | AF6: Load and haul 800 t fleet, flat, 2-5km | AV6: =SUM(AS6:AU6) -> 0
B7: Load and haul 800 t fleet, flat, >5km | AA7: =SUM(X7:Z7) -> 0 | AF7: Load and haul 800 t fleet, flat, >5km | AV7: =SUM(AS7:AU7) -> 0
B8: 600t fleet - Flat | AF8: 600t fleet - Flat
B9: Load and haul 600 t fleet, flat, <1km | AA9: =SUM(X9:Z9) -> 0 | AF9: Load and haul 600 t fleet, flat, <1km | AV9: =SUM(AS9:AU9) -> 0
B10: Load and haul 600 t fleet, flat, 1-2km | AA10: =SUM(X10:Z10) -> 0 | AF10: Load and haul 600 t fleet, flat, 1-2km | AV10: =SUM(AS10:AU10) -> 0
B11: Load and haul 600 t fleet, flat, 2-5km | AA11: =SUM(X11:Z11) -> 0 | AF11: Load and haul 600 t fleet, flat, 2-5km | AV11: =SUM(AS11:AU11) -> 0
B12: Load and haul 600 t fleet, flat, >5km | AA12: =SUM(X12:Z12) -> 0 | AF12: Load and haul 600 t fleet, flat, >5km | AV12: =SUM(AS12:AU12) -> 0
B13: 400t fleet - Flat | AF13: 400t fleet - Flat
B14: Load and haul 400 t fleet, flat, <1km | C14: 517079.75 | I14: 487189.06 | K14: 542263.77 | N14: 366634.47 | P14: 1539595.5 | AA14: =SUM(C14:Z14) -> 3452762.5 | AB14: Assumed the smaller Truck and Excavator Fleet will be applied. | AF14: Load and haul 400 t fleet, flat, <1km | AV14: =SUM(AG14:AU14) -> 0
B15: Load and haul 400 t fleet, flat, 1-2km | AA15: =SUM(X15:Z15) -> 0 | AF15: Load and haul 400 t fleet, flat, 1-2km | AV15: =SUM(AS15:AU15) -> 0
B16: Load and haul 400 t fleet, flat, 2-5km | AA16: =SUM(X16:Z16) -> 0 | AF16: Load and haul 400 t fleet, flat, 2-5km | AV16: =SUM(AS16:AU16) -> 0
B17: Load and haul 400 t fleet, flat, >5km | AA17: =SUM(X17:Z17) -> 0 | AF17: Load and haul 400 t fleet, flat, >5km | AV17: =SUM(AS17:AU17) -> 0
B18: 800 t fleet - 50m Elevation | AF18: 800 t fleet - 50m Elevation
B19: Load and haul 800 t fleet, 50m Elevation, <1km | AA19: =SUM(X19:Z19) -> 0 | AF19: Load and haul 800 t fleet, 50m Elevation, <1km | AV19: =SUM(AS19:AU19) -> 0
B20: Load and haul 800 t fleet, 50m Elevation, <1-2km | AA20: =SUM(X20:Z20) -> 0 | AF20: Load and haul 800 t fleet, 50m Elevation, <1-2km | AV20: =SUM(AS20:AU20) -> 0
B21: Load and haul 800 t fleet, 50m Elevation, 2-5km | AA21: =SUM(X21:Z21) -> 0 | AF21: Load and haul 800 t fleet, 50m Elevation, 2-5km | AV21: =SUM(AS21:AU21) -> 0
B22: Load and haul 800 t fleet, 50m Elevation, >5km | AA22: =SUM(X22:Z22) -> 0 | AF22: Load and haul 800 t fleet, 50m Elevation, >5km | AV22: =SUM(AS22:AU22) -> 0
B23: 600 t fleet - 50m Elevation | AF23: 600 t fleet - 50m Elevation
B24: Load and haul 600 t fleet, 50m Elevation, <1km | AA24: =SUM(X24:Z24) -> 0 | AF24: Load and haul 600 t fleet, 50m Elevation, <1km | AV24: =SUM(AS24:AU24) -> 0
B25: Load and haul 600 t fleet, 50m Elevation, <1-2km | AA25: =SUM(X25:Z25) -> 0 | AF25: Load and haul 600 t fleet, 50m Elevation, <1-2km | AV25: =SUM(AS25:AU25) -> 0
B26: Load and haul 600 t fleet, 50m Elevation, 2-5km | AA26: =SUM(X26:Z26) -> 0 | AF26: Load and haul 600 t fleet, 50m Elevation, 2-5km | AV26: =SUM(AS26:AU26) -> 0
B27: Load and haul 600 t fleet, 50m Elevation, >5km | AA27: =SUM(X27:Z27) -> 0 | AF27: Load and haul 600 t fleet, 50m Elevation, >5km | AV27: =SUM(AS27:AU27) -> 0
B28: 400 t fleet - 50m Elevation | AF28: 400 t fleet - 50m Elevation
B29: Load and haul 400 t fleet, 50m Elevation, <1km | AA29: =SUM(X29:Z29) -> 0 | AF29: Load and haul 400 t fleet, 50m Elevation, <1km | AV29: =SUM(AS29:AU29) -> 0
B30: Load and haul 400 t fleet, 50m Elevation, <1-2km | AA30: =SUM(X30:Z30) -> 0 | AF30: Load and haul 400 t fleet, 50m Elevation, <1-2km | AV30: =SUM(AS30:AU30) -> 0
B31: Load and haul 400 t fleet, 50m Elevation, 2-5km | AA31: =SUM(X31:Z31) -> 0 | AF31: Load and haul 400 t fleet, 50m Elevation, 2-5km | AV31: =SUM(AS31:AU31) -> 0
B32: Load and haul 400 t fleet, 50m Elevation, >5km | AA32: =SUM(X32:Z32) -> 0 | AF32: Load and haul 400 t fleet, 50m Elevation, >5km | AV32: =SUM(AS32:AU32) -> 0
B33: 800 t fleet - 100m Elevation | AF33: 800 t fleet - 100m Elevation
B34: Load and haul 800 t fleet, 100m Elevation, <1km | AA34: =SUM(X34:Z34) -> 0 | AF34: Load and haul 800 t fleet, 100m Elevation, <1km | AV34: =SUM(AS34:AU34) -> 0
B35: Load and haul 800 t fleet, 100m Elevation, <1-2km | AA35: =SUM(X35:Z35) -> 0 | AF35: Load and haul 800 t fleet, 100m Elevation, <1-2km | AV35: =SUM(AS35:AU35) -> 0
B36: Load and haul 800 t fleet, 100m Elevation, 2-5km | AA36: =SUM(X36:Z36) -> 0 | AF36: Load and haul 800 t fleet, 100m Elevation, 2-5km | AV36: =SUM(AS36:AU36) -> 0
B37: Load and haul 800 t fleet, 100m Elevation, >5km | AA37: =SUM(X37:Z37) -> 0 | AF37: Load and haul 800 t fleet, 100m Elevation, >5km | AV37: =SUM(AS37:AU37) -> 0
B38: 600 t fleet - 100m Elevation | AF38: 600 t fleet - 100m Elevation
B39: Load and haul 600 t fleet, 100m Elevation, <1km | AA39: =SUM(X39:Z39) -> 0 | AF39: Load and haul 600 t fleet, 100m Elevation, <1km | AV39: =SUM(AS39:AU39) -> 0
B40: Load and haul 600 t fleet, 100m Elevation, <1-2km | AA40: =SUM(X40:Z40) -> 0 | AF40: Load and haul 600 t fleet, 100m Elevation, <1-2km | AV40: =SUM(AS40:AU40) -> 0
B41: Load and haul 600 t fleet, 100m Elevation, 2-5km | AA41: =SUM(X41:Z41) -> 0 | AF41: Load and haul 600 t fleet, 100m Elevation, 2-5km | AV41: =SUM(AS41:AU41) -> 0
B42: Load and haul 600 t fleet, 100m Elevation, >5km | AA42: =SUM(X42:Z42) -> 0 | AF42: Load and haul 600 t fleet, 100m Elevation, >5km | AV42: =SUM(AS42:AU42) -> 0
B43: 400 t fleet -100m Elevation | AF43: 400 t fleet -100m Elevation
B44: Load and haul 400 t fleet, 100m Elevation, <1km | AA44: =SUM(X44:Z44) -> 0 | AF44: Load and haul 400 t fleet, 100m Elevation, <1km | AV44: =SUM(AS44:AU44) -> 0
B45: Load and haul 400 t fleet, 100m Elevation, <1-2km | AA45: =SUM(X45:Z45) -> 0 | AF45: Load and haul 400 t fleet, 100m Elevation, <1-2km | AV45: =SUM(AS45:AU45) -> 0
B46: Load and haul 400 t fleet, 100m Elevation, 2-5km | AA46: =SUM(X46:Z46) -> 0 | AF46: Load and haul 400 t fleet, 100m Elevation, 2-5km | AV46: =SUM(AS46:AU46) -> 0
B47: Load and haul 400 t fleet, 100m Elevation, >5km | AA47: =SUM(X47:Z47) -> 0 | AF47: Load and haul 400 t fleet, 100m Elevation, >5km | AV47: =SUM(AS47:AU47) -> 0
B51: Fleet Definitions
B52: Fleet Cost ($/bcm) derived on the following basis: Nominal Dig Fleet Combinations: 800t Digger/300t Truck, 600t Digger/220t Truck, 400t Digger/190t Truck Assumed 30% min Pass Match to optimise Full Bucket/Full Truck and define non-haul duration Travel Time assumes 40 km/hr Equivalent Flat Haul Speed, EQF distance calculated from straight line distance and elevation change from WM reference site haul model. Additional operating costs included in unit rates = Dozer @ 1.6hrs per dig hour, Grader/Water Truck @ 0.1 Hrs per Truck Hour, Supervision @ $0.15/bcm

Sheet Holding Costs
C2: Springbok Creek
B3: Holding Costs | C3: 2023 | D3: 2024 YTD | E3: 2024 Fcst | F3: Holding | G3: Execution 5 yr | H3: Post execution (15 yr) | I3: Total holding | J3: yr 1 | K3: yr 2 | L3: yr 3 | M3: yr 4 | N3: yr 5 | O3: yr 6 | P3: yr 7 | Q3: yr 8 | R3: yr 9 | S3: yr 10 | T3: yr 11 | U3: yr 12 | V3: yr 13 | W3: yr 14 | X3: yr 15
B4: 520110 | Technical Consulting Recharge | C4: 5487150.4 | D4: 3513622.3 | E4: 6023352.5 | F4: 1600000 | G4: =F4*5 -> 8000000 | H4: =SUM(J4:X4) -> 6352870.9 | I4: =SUM(G4:H4) -> 14352871 | J4: 800000 | K4: =J4*0.9 -> 720000 | L4: =K4*0.9 -> 648000 | M4: =L4*0.9 -> 583200 | N4: =M4*0.9 -> 524880 | O4: =N4*0.9 -> 472392 | P4: =O4*0.9 -> 425152.8 | Q4: =P4*0.9 -> 382637.52 | R4: =Q4*0.9 -> 344373.77 | ... X4: =W4*0.9 -> 183014.34
B5: 540320 | Bank Charges | C5: 157654.42 | D5: 363442.16 | E5: 623043.7 | F5: 623043.7 | G5: =F5*5 -> 3115218.5 | H5: =SUM(J5:X5) -> 4452880.8 | I5: =SUM(G5:H5) -> 7568099.3 | J5: =F5*0.9 -> 560739.33 | K5: =J5*0.9 -> 504665.4 | L5: =K5*0.9 -> 454198.86 | M5: =L5*0.9 -> 408778.97 | N5: =M5*0.9 -> 367901.08 | O5: =N5*0.9 -> 331110.97 | P5: =O5*0.9 -> 297999.87 | Q5: =P5*0.9 -> 268199.88 | R5: =Q5*0.9 -> 241379.9 | ... X5: =W5*0.9 -> 128279.17
B6: 540410 | Council Rates | C6: 8224499.1 | D6: 5397383.6 | E6: 9252657.5 | F6: 9252657.5 | G6: =F6*5 -> 46263288 | H6: =SUM(J6:X6) -> 66128557 | I6: =SUM(G6:H6) -> 1.1239184e+08 | J6: =F6*0.9 -> 8327391.8 | K6: =J6*0.9 -> 7494652.6 | L6: =K6*0.9 -> 6745187.3 | M6: =L6*0.9 -> 6070668.6 | N6: =M6*0.9 -> 5463601.7 | O6: =N6*0.9 -> 4917241.6 | P6: =O6*0.9 -> 4425517.4 | Q6: =P6*0.9 -> 3982965.7 | R6: =Q6*0.9 -> 3584669.1 | ... X6: =W6*0.9 -> 1905040.1
B7: 540450 | Land Tax | C7: 1857162.6 | D7: 1062435 | E7: 1821317.2 | F7: 1821317.2 | G7: =F7*5 -> 9106586.1 | H7: =SUM(J7:X7) -> 13016917 | I7: =SUM(G7:H7) -> 22123503 | J7: =F7*0.9 -> 1639185.5 | K7: =J7*0.9 -> 1475266.9 | L7: =K7*0.9 -> 1327740.2 | M7: =L7*0.9 -> 1194966.2 | N7: =M7*0.9 -> 1075469.6 | O7: =N7*0.9 -> 967922.64 | P7: =O7*0.9 -> 871130.38 | Q7: =P7*0.9 -> 784017.34 | R7: =Q7*0.9 -> 705615.6 | ... X7: =W7*0.9 -> 374993.06
B8: Town maintenance | C8: 0 | D8: 0 | E8: 0 | F8: 2000000 | G8: =F8*5 -> 10000000 | H8: =SUM(J8:X8) -> 14293960 | I8: =SUM(G8:H8) -> 24293960 | J8: =F8*0.9 -> 1800000 | K8: =J8*0.9 -> 1620000 | L8: =K8*0.9 -> 1458000 | M8: =L8*0.9 -> 1312200 | N8: =M8*0.9 -> 1180980 | O8: =N8*0.9 -> 1062882 | P8: =O8*0.9 -> 956593.8 | Q8: =P8*0.9 -> 860934.42 | R8: =Q8*0.9 -> 774840.98 | ... X8: =W8*0.9 -> 411782.26
B9: 540460 | Licences / Permits / Registrations | C9: 2574614.2 | D9: 1340811.7 | E9: 2298534.3 | F9: 2298534.3 | G9: =F9*5 -> 11492671 | H9: =SUM(J9:X9) -> 16427578 | I9: =SUM(G9:H9) -> 27920250 | J9: =F9*0.9 -> 2068680.9 | K9: =J9*0.9 -> 1861812.8 | L9: =K9*0.9 -> 1675631.5 | M9: =L9*0.9 -> 1508068.3 | N9: =M9*0.9 -> 1357261.5 | O9: =N9*0.9 -> 1221535.4 | P9: =O9*0.9 -> 1099381.8 | Q9: =P9*0.9 -> 989443.64 | R9: =Q9*0.9 -> 890499.28 | ... X9: =W9*0.9 -> 473247.83
B10: 540470 | Mine Subsidence Levy | C10: 0 | D10: 0 | E10: 0 | F10: 0 | G10: =F10*5 -> 0 | H10: =SUM(J10:X10) -> 0 | I10: =SUM(G10:H10) -> 0 | J10: =F10*0.9 -> 0 | K10: =J10*0.9 -> 0 | L10: =K10*0.9 -> 0 | M10: =L10*0.9 -> 0 | N10: =M10*0.9 -> 0 | O10: =N10*0.9 -> 0 | P10: =O10*0.9 -> 0 | Q10: =P10*0.9 -> 0 | R10: =Q10*0.9 -> 0 | ... X10: =W10*0.9 -> 0
B11: 540480 | Mines Rescue Levy | C11: 0 | D11: 0 | E11: 0 | F11: 0 | G11: =F11*5 -> 0 | H11: =SUM(J11:X11) -> 0 | I11: =SUM(G11:H11) -> 0 | J11: =F11*0.9 -> 0 | K11: =J11*0.9 -> 0 | L11: =K11*0.9 -> 0 | M11: =L11*0.9 -> 0 | N11: =M11*0.9 -> 0 | O11: =N11*0.9 -> 0 | P11: =O11*0.9 -> 0 | Q11: =P11*0.9 -> 0 | R11: =Q11*0.9 -> 0 | ... X11: =W11*0.9 -> 0
B12: 540510 | Insurance | C12: 16616587 | D12: 8873879.9 | E12: 15212365 | F12: 1500000 | G12: =F12*5 -> 7500000 | H12: =SUM(J12:X12) -> 10720470 | I12: =SUM(G12:H12) -> 18220470 | J12: =F12*0.9 -> 1350000 | K12: =J12*0.9 -> 1215000 | L12: =K12*0.9 -> 1093500 | M12: =L12*0.9 -> 984150 | N12: =M12*0.9 -> 885735 | O12: =N12*0.9 -> 797161.5 | P12: =O12*0.9 -> 717445.35 | Q12: =P12*0.9 -> 645700.81 | R12: =Q12*0.9 -> 581130.73 | ... X12: =W12*0.9 -> 308836.7
B13: 540620 | Legal Expenses - Tax Deductible | C13: 213924.91 | D13: 141153.75 | E13: 241977.86 | F13: 500000 | G13: =F13*5 -> 2500000 | H13: =SUM(J13:X13) -> 3573489.9 | I13: =SUM(G13:H13) -> 6073489.9 | J13: =F13*0.9 -> 450000 | K13: =J13*0.9 -> 405000 | L13: =K13*0.9 -> 364500 | M13: =L13*0.9 -> 328050 | N13: =M13*0.9 -> 295245 | O13: =N13*0.9 -> 265720.5 | P13: =O13*0.9 -> 239148.45 | Q13: =P13*0.9 -> 215233.61 | R13: =Q13*0.9 -> 193710.24 | ... X13: =W13*0.9 -> 102945.57
B14: 540760 | Shared Services Fee | C14: 270000.13 | D14: 174953.09 | E14: 299919.58 | F14: 0 | G14: =F14*5 -> 0 | H14: =SUM(J14:X14) -> 0 | I14: =SUM(G14:H14) -> 0 | J14: =F14*0.9 -> 0 | K14: =J14*0.9 -> 0 | L14: =K14*0.9 -> 0 | M14: =L14*0.9 -> 0 | N14: =M14*0.9 -> 0 | O14: =N14*0.9 -> 0 | P14: =O14*0.9 -> 0 | Q14: =P14*0.9 -> 0 | R14: =Q14*0.9 -> 0 | ... X14: =W14*0.9 -> 0
C16: =SUM(C4:C14) -> 35401593 | D16: =SUM(D4:D14) -> 20867681 | E16: =SUM(E4:E14) -> 35773168 | F16: =SUM(F4:F14) -> 19595553 | G16: =SUM(G4:G14) -> 97977764 | H16: =SUM(H4:H14) -> 1.3496672e+08 | I16: =SUM(I4:I14) -> 2.3294449e+08

Sheet 2024 Cost Schedule for Tool
C1: 1 | D1: 2 | E1: 3 | F1: 5
C3: WM Mine Closure Rates
C7: # | D7: Activity / Description | E7: Unit | F7: WM 2024 Rate
B9: Activity | C9: 1 | D9: Termination of Services and Demolition Works
B10: Demo | C10: 1.01 | D10: Disconnect and terminate all services (Water, electricity, gas etc. at point of attachment to site) | E10: @ | F10: 47518.457
B11: Demo | C11: 1.02 | D11: Disconnect and terminate services at remote areas (admin buildings, workshops) | E11: @ | F11: 9490.4819
B12: Demo | C12: 1.03 | D12: Removal of power lines (this includes disconnection, rolling up the wires and removing the poles). It does not include the removal of substations. | E12: km | F12: 17002.238
B13: Demo | C13: 1.04 | D13: Removal of >66kV power lines (this includes disconnection, rolling up the wires and removing the poles). It does not include the removal of substations. | E13: km | F13: 112646.67
B14: Demo | C14: 1.05a | D14: Remove small rail, road, water course overpass - smaller structure with minimal civil works | E14: Item | F14: 394263.34
B15: Demo | C15: 1.05b | D15: Remove medium rail, road, water course overpass - medium structure with minimal civil works | E15: Item | F15: 563233.34
B16: Demo | C16: 1.05c | D16: Remove large/significant rail, road, water course overpass - large structure with significant water management and civil works | E16: Item | F16: 2186002.1
B17: Demo | C17: 1.06 | D17: Demolish and/or remove substations (Assumes they are in a closed building) | E17: m2 | F17: 701.8524
B18: Demo | C18: 1.07 | D18: Demolish and remove switchyard/gas flare plant | E18: m2 | F18: 73.548396
B19: Demo | C19: 1.08 | D19: Demolish and remove demountable structures on concrete stumps - assumes not being re-used | E19: m2 | F19: 45.058668
B20: Demo | C20: 1.08a | D20: Demolish and remove demountable structures on concrete stumps - assumes not being re-used - each | E20: Unit | F20: 2467.2437
B21: Demo | C21: 1.09 | D21: Demolish and remove small buildings/tanks (admin buildings, single story accommodation etc.) | E21: m2 | F21: 91.359913
B22: Demo | C22: 1.1 | D22: Demolish and remove light industrial buildings | E22: m2/floor | F22: 92.297865
B23: Demo | C23: 1.11 | D23: Demolish and remove industrial buildings (workshops tyre change and servicing area etc. - not CHPP) | E23: m2/floor | F23: 175.7288
B24: Demo | C24: 1.12 | D24: Demolish and remove CHPP (include the area of each floor of the structure) | E24: m2/floor | F24: 247.82643
B25: Demo | C25: 1.13 | D25: Demolish and remove crushers, hoppers, sizing stations, rotary breakers, etc. (include the area of each floor of the structure). | E25: m2/floor | F25: 253.455
B26: Demo | C26: 1.14 | D26: Demolish and remove stacker or reclaimer (radial or luffing etc.) | E26: @ | F26: 1099045.8
B27: Demo | C27: 1.15 | D27: Demolish and remove bucket wheel stacker/reclaimer | E27: @ | F27: 2252933.4
B28: Demo | C28: 1.16 | D28: Remove stacker/reclaimer rails and ballast etc. | E28: m | F28: 84.485002
B29: Demo | C29: 1.17 | D29: Collapse, Cut and Remove 5000T coal silo | E29: @ | F29: 123726.65
B30: Demo | C30: 1.18 | D30: Collapse, Cut and Remove 2000/3000 T coal silo | E30: @ | F30: 104120.73
B31: Demo | C31: 1.19 | D31: Collapse, Cut and Remove 1250 T coal silo | E31: @ | F31: 77940.938
B32: Demo | C32: 1.2 | D32: Collapse, Cut and Remove rail loading bins | E32: @ | F32: 76881.352
B33: Demo | C33: 1.20a | D33: Demolish and Remove large concrete rail loading bin - and disposal on-site/locally | E33: allow | F33: 518174.68
B34: Demo | C34: 1.21 | D34: Demolish and remove on-ground conveyors, transfer stations & gantries (scrap only – does not include dismantling for reuse at another site) | E34: m | F34: 225.64273
B35: Demo | C35: 1.22 | D35: Demolish and remove elevated conveyors, transfer stations & gantries (scrap only – does not include dismantling for reuse at another site) | E35: m | F35: 463.05751
B36: Demo | C36: 1.23 | D36: Demolish and remove overhead conveyors, transfer stations & gantries (scrap only – does not include dismantling for reuse at another site) | E36: m | F36: 957.49669
B37: Demo | C37: 1.24 | D37: Demolish reclaim tunnel, cut reo and expose reclaim conveyor, then collapse into the reclaim tunnel void (Does not include excavation to expose reclaim tunnel, removal of conveyor or backfilling void) | E37: m2 | F37: 107.01434
B38: Demo | C38: 1.25 | D38: Remove and demolish conveyor from reclaim tunnel (Does not include excavation and demolition of reclaim tunnel roof) | E38: m | F38: 168.97
B39: Demo | C39: 1.26 | D39: Demolition of reclaim tunnel concrete (Assumes complete removal and dumping in mine pit void) | E39: m | F39: 1070.1434
B40: Demo | C40: 1.27 | D40: Demolition and removal of vent raise fans, electrical substation and winch | E40: @ | F40: 50127.768
B41: Demo | C41: 1.28 | D41: Demolish and remove small tank clean (Thickener etc. 3 - 9 m diameter) | E41: @ | F41: 11264.667
B42: Demo | C42: 1.29 | D42: Demolish and remove medium tank clean (Thickener etc. 10 - 15 m diameter) | E42: @ | F42: 33794.001
B43: Demo | C43: 1.3 | D43: Demolish and remove large tank clean (Thickener etc. 15 - 30 m diameter) | E43: @ | F43: 72094.244
B44: Demo | C44: 1.31 | D44: Demolish and remove extra large tank clean (Thickener etc. >30 m diameter) | E44: @ | F44: 104198.17
B45: Demo | C45: 1.32 | D45: Demolish and remove tank clean (Thickener etc.) >50 m diameter | E45: @ | F45: 197131.67
... B53: Demo | C53: 1.4 | D53: Remove pump and pontoon from a large lake or dam including pipes and electrical supply or diesel tank/s | E53: @ | F53: 0
B54: Demo | C54: 1.40a | D54: Remove pump and pontoon from a small lake or dam including pipes and electrical supply or diesel tank/s | E54: @ | F54: 21402.492
B55: Demo | C55: 1.41 | D55: Remove bitumen (car park and access roads) for dumping in a void on the site | E55: m2 | F55: 8.4485002
B56: Demo | C56: 1.42 | D56: Remove bitumen (airstrip) for dumping in a void on-site | E56: m2 | F56: 22.529334
B57: Demo | C57: 1.43 | D57: Remove concrete pads & footings (<300mm thickness) and dumping in void | E57: m2 | F57: 41.116034
B58: Demo | C58: 1.44 | D58: Remove concrete pads & footings (>300mm thickness)and dumping in void | E58: m2 | F58: 84.485002
B59: Demo | C59: 1.45 | D59: Crush concrete to make road aggregate - 75mm | E59: tonne | F59: 11.264667
B60: Demo | C60: 1.46 | D60: Crush concrete to make road aggregate - 50mm | E60: tonne | F60: 15.488917
B61: Demo | C61: 1.47 | D61: Crush concrete to make road aggregate - 30mm | E61: tonne | F61: 17.178617
B62: Demo | C62: 1.48 | D62: Remove fence (cyclone/wire fence) | E62: m | F62: 22.529334
B63: Demo | C63: 1.49 | D63: Removal and disposal of radiation devices | E63: each | F63: 22651.839
B64: Demo | C64: 1.5 | D64: Removal of small plastic tanks | E64: each | F64: 1126.4667
B65: Demo | C65: 1.51 | D65: Demolish and remove communication towers | E65: each | F65: 5632.3334
B66: Demo | C66: 1.52 | D66: Removal of UG services (power within main gate areas, etc.) | E66: allow | F66: 56323.334
... B68: Demo | C68: 1.54 | D68: Waste disposal to Council landfill - fees (industrial demolition / concrete / scrap metal) | E68: tonne | F68: 273.39577
B69: Demo | C69: 2 | D69: Rail Infrastructure
B70: Demo | C70: 2.01 | D70: Remove rail loop and spur, ballast etc. | E70: m | F70: 63.082135
B71: Demo | C71: 2.02 | D71: Remove train loading facilities | E71: m2 | F71: 208.39634
B72: Demo | C72: 2.03 | D72: Reshape rail spur and load out areas - does not include topsoil and revegetation | E72: ha | F72: 3221.6947
B73: Earthworks | C73: 3 | D73: Minor Reshaping, Final Trim (Roads)
B74: Earthworks | C74: 3.01 | D74: Unsealed roads / vehicle park-up areas – minor works including deep rip and trim | E74: ha | F74: 1035.1075
B75: Earthworks | C75: 3.02 | D75: Unsealed roads / access tracks / vehicle park-up areas with windrows and/or small earthen bunds – minor earthworks and deep rip and trim | E75: ha | F75: 1697.2017
B76: Earthworks | C76: 3.03 | D76: Unsealed roads / vehicle park-up areas – Minor earthworks, final trim and deep rip and seed (pasture grass) | E76: ha | F76: 3723.4649
B77: Earthworks | C77: 3.04 | D77: Unsealed roads / vehicle park-up areas – Minor earthworks, final trim and deep rip, ameliorate and seed (native tree/shrub/grass) | E77: ha | F77: 5185.7374
B78: Earthworks | C78: 3.05 | D78: Unsealed roads / haul roads / vehicle park-up areas with windrows and/or small earthen bunds – Minor earthworks, final trim and deep rip, ameliorate and seed (pasture grass) | E78: ha | F78: 5232.5598
B79: Earthworks | C79: 3.06 | D79: Unsealed roads / haul roads / vehicle park-up areas with windrows and/or small earthen bunds – Minor earthworks, final trim and deep rip, ameliorate and seed (native tree/shrub/grass) | E79: ha | F79: 7461.6042
B80: Load and haul | C80: 3.07 | D80: Remove stabilised material (blue metal, aggregate etc.) from roadways and dump in a void on-site (haul distance < 1km) | E80: m3 | F80: 4.6772144
B81: Load and haul | C81: 3.08 | D81: Remove stabilised material (blue metal, aggregate etc.) from roadways and dump in a void on-site (haul distance >1 km but <2 km) | E81: m3 | F81: 5.7321901
B82: Load and haul | C82: 3.09 | D82: Remove stabilised material (blue metal, aggregate etc.) from roadways and dump in a void on-site (haul distance >2 km but <5 km) | E82: m3 | F82: 8.1105602
B83: Load and haul | C83: 3.1 | D83: Remove stabilised material (blue metal, aggregate etc.) from roadways and dump in a void on-site (haul distance >5 km) | E83: m3 | F83: 10.64511
B84: Contam | C84: 4 | D84: Contaminated Materials
B85: Contam | C85: 4.01 | D85: Undertake Phase 1 contamination assessment - assumes potential contamination is localised. If there are multiple work areas on site, additional studies should be included. | E85: Item | F85: 14573.347
B86: Contam | C86: 4.01a | D86: Undertake an intrusive (or Phase 2) site investigation. This accounts for current and historical locations where areas of disturbance are clustered (i.e. located in close proximity and easily accessible such as same MIA, STP and nearby camp, or other areas within ~ 5km). If there are multiple cluster areas on site, multiple intrusive investigations should be included. | E86: Cluster | F86: 103567.92
B87: Contam | C87: 4.01b | D87: Develop a Remediation Action Plan on sites with large footprints based on outcomes of intrusive investigation including strategies to address contamination exceedances | E87: allow | F87: 34004.477
B88: Contam | C88: 4.02 | D88: Removal and disposal of oil contaminated water from bunded areas and sumps | E88: L | F88: 0.34004477
B89: Load and haul | C89: 4.03 | D89: Remove carbonaceous material (spillage or otherwise) from footprint of the CHPP, ROM, Product stockpiles & Roadways (haul distance < 1km) | E89: m3 | F89: 4.543581
B90: Load and haul | C90: 4.04 | D90: Remove carbonaceous material (spillage or otherwise) from footprint of the CHPP, ROM, Product stockpiles & Roadway (haul distance >1km but <2km) | E90: m3 | F90: 5.728297
B91: Load and haul | C91: 4.05 | D91: Remove carbonaceous material (spillage or otherwise) from footprint of the CHPP, ROM, Product stockpiles & Roadway (haul distance >2km but <5km) | E91: m3 | F91: 7.4858426
B92: Load and haul | C92: 4.06 | D92: Remove carbonaceous material (spillage or otherwise) from footprint of the CHPP, ROM, Product stockpiles & Roadway (haul distance >5km) | E92: m3 | F92: 10.037539
B93: Load and haul | C93: 4.07 | D93: Load, cart and disposal of Restricted classified contaminated material off site to a licensed landfill. Add $50/m3 for cartage from regional areas | E93: m3 | F93: 743.46801
B94: Load and haul | C94: 4.07a | D94: Load, cart and dispose of Hazardous classified contaminated material off site to a licensed landfill. Assumes cartage to a licensed landfill. | E94: m3 | F94: 901.17335
B95: Load and haul | C95: 4.08 | D95: Load, cart and disposal of Low Level contaminated material off site to a licensed landfill. Add $50/m3 for cartage to regional landfill | E95: m3 | F95: 247.82267
B96: Contam | C96: 4.09 | D96: Onsite remediation of hydrocarbon contaminated soils (<50m3) - manual land farming | E96: m3 | F96: 112.64667
B97: Contam | C97: 4.09a | D97: Construct and set up bioremediation pad | E97: allow | F97: 38862.259
B98: Contam | C98: 4.1 | D98: Onsite remediation of hydrocarbon contaminated soils (>50m3 but <100m3) - manual land farming | E98: m3 | F98: 116.22883
B99: Contam | C99: 4.11 | D99: Onsite remediation of hydrocarbon contaminated soils (>100m3 but <500m3) - manual land farming | E99: m3 | F99: 89.148574
B100: Contam | C100: 4.12 | D100: Onsite remediation of hydrocarbon contaminated soils (>500m3) - manual land farming | E100: m3 | F100: 84.485002
B101: Contam | C101: 4.13 | D101: Mobilisation of mobile treatment unit for hydrocarbon contaminated soil treatment | E101: Item | F101: 168970
B102: Contam | C102: 4.14 | D102: Onsite remediation of hydrocarbon contaminated soils - using a mobile treatment unit | E102: m3 | F102: 185.867
B103: Contam | C103: 4.15 | D103: Remove and dispose of asbestos (Single storey structure) | E103: m2 | F103: 137.96102
B104: Contam | C104: 4.16 | D104: Remove and dispose of asbestos (Double storey structure) | E104: m2 | F104: 45.058668
B105: Contam | C105: 4.17a | D105: Waste disposal to Council landfill - fees (asbestos) | E105: tonne | F105: 317.32937
B106: Contam | C106: 4.19 | D106: Removal and disposal of plastic liner (i.e. dam, leach pad etc.) | E106: m2 | F106: 1.1264667
B107: Contam | C107: 4.19a | D107: Removal and remediation of hydrocarbons | E107: allow | F107: 291466.94
B108: Contam | C108: 4.2 | D108: Medium HAZMAT Clean-up - cleaning and decontaminating plant and equipment, chemical storage locations, oil and grease traps, tanks, vessels, and pipe work etc. | E108: @ | F108: 340044.77
B109: Contam | C109: 4.20a | D109: Large HAZMAT Clean-up - cleaning and decontaminating plant and equipment, chemical storage locations, oil and grease traps, tanks, vessels, and pipe work etc | E109: @ | F109: 732203.35
B110: Contam | C110: 4.21 | D110: Collection, destruction and certification of washery control panels containing Sulfur Hexafluoride ( SF6 ) | E110: @ | F110: 1165.8678
B111: Contam | C111: 4.22 | D111: Disposal of Firebox AFFF 6% fire fighting foam at certified disposal site | E111: kg | F111: 6.8008953
B112: Mining/sealing | C112: 5 | D112: Mining and Exploration Works
B113: Mining/sealing | C113: 5.01 | D113: Active pit area – benches blasted and doze to acceptable grade | E113: m3 | F113: 2.9040486
...
