Workbook
Name A: #REF!
Name a: Springbok!$D$69:$W$69
Name Ac: #REF!
Name Ac: #REF!
Name afhKJADF: #REF!
Name afhKJADF: #REF!
Name C_C_Balance: #REF!
Name C_C_Balance: #REF!
Name coalfield: #REF!
Name CoalPP: #REF!
Name CPP: #REF!
Name CPP: #REF!
Name CPPe: #REF!
Name CPPe: #REF!
Name CPPout: #REF!
Name CPPout: #REF!
Name Critical_Component: #REF!
Name Critical_Component: #REF!
Name d: #REF!
Name d: #REF!
Name Db: #REF!
Name Db: #REF!
Name Dc: #REF!
Name Dc: #REF!
Name Deisel: #REF!
Name Deisel: #REF!
Name diesel: #REF!
Name diesel: #REF!
Name Effective_Tax_Rate: #REF!
Name Effective_Tax_Rate: #REF!
Name Elunits: #REF!
Name Em: #REF!
Name Em: #REF!
Name equiptype: #REF!
Name Es: #REF!
Name Es: #REF!
Name f: #REF!
Name f: #REF!
Name Factor: #REF!
Name Factor: #REF!
Name Fuel: #REF!
Name FuelList: #REF!
Name FuelTypes: #REF!
Name FuelTypes: #REF!
Name Fueluse: #REF!
Name Fueluse: #REF!
Name gs: #REF!
Name gs: #REF!
Name H: #REF!
Name H: #REF!
Name HFC: #REF!
Name HFCunit: #REF!
Name howoften: #REF!
Name km: #REF!
Name L: #REF!
Name L: #REF!
Name Liquidunits: #REF!
Name LPG: #REF!
Name LPG: #REF!
Name LVkm: #REF!

Sheet Assumptions
A1: Corporate Assumptions | D1: =E1-1 -> 2021 | E1: =F1-1 -> 2022 | F1: =G1-1 -> 2023 | G1: =H1-1 -> 2024 | H1: =I1-1 -> 2025 | I1: 2026 | J1: =I1+1 -> 2027 | K1: =J1+1 -> 2028 | L1: =K1+1 -> 2029 | M1: =L1+1 -> 2030 | N1: =M1+1 -> 2031 | O1: =N1+1 -> 2032 | P1: =O1+1 -> 2033 | Q1: =P1+1 -> 2034 | ... BV1: =BU1+1 -> 2091
A2: Discount Rate | B2: 0.08 | D2: 1 | E2: 1 | F2: 1 | G2: 1 | H2: 1 | I2: =(1+$B2)^-(I$1-$I$1+0.5) -> 0.96225045 | J2: =(1+$B2)^-(J$1-$I$1+0.5) -> 0.89097264 | K2: =(1+$B2)^-(K$1-$I$1+0.5) -> 0.82497466 | L2: =(1+$B2)^-(L$1-$I$1+0.5) -> 0.76386543 | M2: =(1+$B2)^-(M$1-$I$1+0.5) -> 0.70728281 | N2: =(1+$B2)^-(N$1-$I$1+0.5) -> 0.65489149 | O2: =(1+$B2)^-(O$1-$I$1+0.5) -> 0.60638101 | P2: =(1+$B2)^-(P$1-$I$1+0.5) -> 0.56146389 | ... BV2: =(1+$B2)^-(BV$1-$I$1+0.5) -> 0.0064676129
A3: Foreign Exchange Forecast
A4: Foreign Exchange Rate | B4: USD:AUD | D4: 0.743 | E4: 0.694 | F4: 0.6646 | G4: 0.6629 | H4: 0.6306 | I4: 0.69 | J4: 0.69 | K4: 0.69 | L4: 0.69 | M4: 0.69 | N4: =M4 -> 0.69 | O4: =N4 -> 0.69 | P4: =O4 -> 0.69 | Q4: =P4 -> 0.69 | R4: =Q4 -> 0.69 | S4: =R4 -> 0.69 | T4: =S4 -> 0.69 | U4: =T4 -> 0.69 | ... BV4: =BU4 -> 0.69
A5: Pricing Forecasts (real terms 2023)
A6: Premium Hard Coking Coal | B6: USD/t | C6: PLV | D6: ='Historical Performance'!D23 -> 295 | E6: ='Historical Performance'!E23 -> 360 | F6: ='Historical Performance'!F23 -> 345 | G6: ='Historical Performance'!G23 -> 310 | H6: ='Historical Performance'!H23 -> 300 | I6: ='Historical Performance'!I23 -> 315 | J6: 240 | K6: 240 | L6: 240 | M6: 240 | N6: =M6 -> 240 | O6: =N6 -> 240 | P6: =O6 -> 240 | Q6: =P6 -> 240 | R6: =Q6 -> 240 | S6: =R6 -> 240 | T6: =S6 -> 240 | U6: =T6 -> 240 | ... BV6: =BU6 -> 240
A7: 88% PHCC | B7: USD/t | C7: Benchmark | J7: =J6*0.88 -> 211.2 | K7: =K6*0.88 -> 211.2 | L7: =L6*0.88 -> 211.2 | M7: =M6*0.88 -> 211.2 | N7: =M7 -> 211.2 | O7: =N7 -> 211.2 | P7: =O7 -> 211.2 | Q7: =P7 -> 211.2 | R7: =Q7 -> 211.2 | S7: =R7 -> 211.2 | T7: =S7 -> 211.2 | U7: =T7 -> 211.2 | ... BV7: =BU7 -> 211.2
A8: 6000NAR (GCN) | B8: USD/t | C8: Thermal Product A | J8: 118 | K8: 118 | L8: 118 | M8: 118 | N8: 118 | O8: 118 | P8: 118 | Q8: 118 | R8: 118 | S8: 118 | T8: 118 | U8: 118 | V8: 118 | W8: 118 | X8: 118 | Y8: 118 | Z8: 118 | AA8: 118 | AB8: 118 | AC8: 118 | AD8: 118 | AE8: 118 | AF8: 118 | AG8: 118 | AH8: 118 | AI8: 118 | AJ8: 118 | AK8: 118 | AL8: 118 | AM8: 118 | AN8: 118 | AO8: 118 | AP8: 118 | AQ8: 118 | AR8: 118 | AS8: 118 | AT8: 118 | AU8: 118 | AV8: 118 | AW8: 118 | AX8: 118 | AY8: 118 | AZ8: 118 | BA8: 118 | BB8: 118 | BC8: 118 | BD8: 118 | BE8: 118 | BF8: 118 | BG8: 118 | BH8: 118 | BI8: 118 | BJ8: 118 | BK8: 118 | BL8: 118 | BM8: 118 | BN8: 118 | BO8: 118 | BP8: 118 | BQ8: 118 | BR8: 118 | BS8: 118 | BT8: 118 | BU8: 118 | BV8: 118
A9: 5500NAR | B9: USD/t | C9: Thermal Product B | J9: 105 | K9: 105 | L9: 105 | M9: 105 | N9: 105 | O9: 105 | P9: 105 | Q9: 105 | R9: 105 | S9: 105 | T9: 105 | U9: 105 | V9: 105 | W9: 105 | X9: 105 | Y9: 105 | Z9: 105 | AA9: 105 | AB9: 105 | AC9: 105 | AD9: 105 | AE9: 105 | AF9: 105 | AG9: 105 | AH9: 105 | AI9: 105 | AJ9: 105 | AK9: 105 | AL9: 105 | AM9: 105 | AN9: 105 | AO9: 105 | AP9: 105 | AQ9: 105 | AR9: 105 | AS9: 105 | AT9: 105 | AU9: 105 | AV9: 105 | AW9: 105 | AX9: 105 | AY9: 105 | AZ9: 105 | BA9: 105 | BB9: 105 | BC9: 105 | BD9: 105 | BE9: 105 | BF9: 105 | BG9: 105 | BH9: 105 | BI9: 105 | BJ9: 105 | BK9: 105 | BL9: 105 | BM9: 105 | BN9: 105 | BO9: 105 | BP9: 105 | BQ9: 105 | BR9: 105 | BS9: 105 | BT9: 105 | BU9: 105 | BV9: 105
A11: Thermal Categories | I11: Thermal category minimum spec
A12: Benchmark Thermal | B12: kcal/kg(nar) | I12: 5950 | J12: 5950 | K12: 5950 | L12: 5950 | M12: 5950 | N12: 5950 | O12: 5950 | P12: 5950 | Q12: 5950 | R12: 5950 | S12: 5950 | T12: 5950 | U12: 5950 | V12: 5950 | W12: 5950 | X12: 5950 | Y12: 5950 | Z12: 5950 | AA12: 5950 | AB12: 5950 | AC12: 5950 | AD12: 5950 | AE12: 5950 | AF12: 5950 | AG12: 5950 | AH12: 5950 | AI12: 5950 | AJ12: 5950 | AK12: 5950 | AL12: 5950 | AM12: 5950 | AN12: 5950 | AO12: 5950 | AP12: 5950 | AQ12: 5950 | AR12: 5950 | AS12: 5950 | AT12: 5950 | AU12: 5950 | AV12: 5950 | AW12: 5950 | AX12: 5950 | AY12: 5950 | AZ12: 5950 | BA12: 5950 | BB12: 5950 | BC12: 5950 | BD12: 5950 | BE12: 5950 | BF12: 5950 | BG12: 5950 | BH12: 5950 | BI12: 5950 | BJ12: 5950 | BK12: 5950 | BL12: 5950 | BM12: 5950 | BN12: 5950 | BO12: 5950 | BP12: 5950 | BQ12: 5950 | BR12: 5950 | BS12: 5950 | BT12: 5950 | BU12: 5950 | BV12: 5950
A13: 5500NAR | B13: kcal/kg(nar) | I13: 5300 | J13: 5300 | K13: 5300 | L13: 5300 | M13: 5300 | N13: 5300 | O13: 5300 | P13: 5300 | Q13: 5300 | R13: 5300 | S13: 5300 | T13: 5300 | U13: 5300 | V13: 5300 | W13: 5300 | X13: 5300 | Y13: 5300 | Z13: 5300 | AA13: 5300 | AB13: 5300 | AC13: 5300 | AD13: 5300 | AE13: 5300 | AF13: 5300 | AG13: 5300 | AH13: 5300 | AI13: 5300 | AJ13: 5300 | AK13: 5300 | AL13: 5300 | AM13: 5300 | AN13: 5300 | AO13: 5300 | AP13: 5300 | AQ13: 5300 | AR13: 5300 | AS13: 5300 | AT13: 5300 | AU13: 5300 | AV13: 5300 | AW13: 5300 | AX13: 5300 | AY13: 5300 | AZ13: 5300 | BA13: 5300 | BB13: 5300 | BC13: 5300 | BD13: 5300 | BE13: 5300 | BF13: 5300 | BG13: 5300 | BH13: 5300 | BI13: 5300 | BJ13: 5300 | BK13: 5300 | BL13: 5300 | BM13: 5300 | BN13: 5300 | BO13: 5300 | BP13: 5300 | BQ13: 5300 | BR13: 5300 | BS13: 5300 | BT13: 5300 | BU13: 5300 | BV13: 5300
A14: 5100NAR | B14: kcal/kg(nar) | I14: 0 | J14: 0 | K14: 0 | L14: 0 | M14: 0 | N14: 0 | O14: 0 | P14: 0 | Q14: 0 | R14: 0 | S14: 0 | T14: 0 | U14: 0 | V14: 0 | W14: 0 | X14: 0 | Y14: 0 | Z14: 0 | AA14: 0 | AB14: 0 | AC14: 0 | AD14: 0 | AE14: 0 | AF14: 0 | AG14: 0 | AH14: 0 | AI14: 0 | AJ14: 0 | AK14: 0 | AL14: 0 | AM14: 0 | AN14: 0 | AO14: 0 | AP14: 0 | AQ14: 0 | AR14: 0 | AS14: 0 | AT14: 0 | AU14: 0 | AV14: 0 | AW14: 0 | AX14: 0 | AY14: 0 | AZ14: 0 | BA14: 0 | BB14: 0 | BC14: 0 | BD14: 0 | BE14: 0 | BF14: 0 | BG14: 0 | BH14: 0 | BI14: 0 | BJ14: 0 | BK14: 0 | BL14: 0 | BM14: 0 | BN14: 0 | BO14: 0 | BP14: 0 | BQ14: 0 | BR14: 0 | BS14: 0 | BT14: 0 | BU14: 0 | BV14: 0
A16: GAR-> NAR adjustment | B16: 260 | C16: kcal/kg
A17: Basis of coal prices | B17: 6000 | C17: kcal/kg(nar)
A20: Carbon Scenario | C20: Accelerated Transition
A23: Other Assumptions
A25: QLD royalty assumptions
A27: Threshold
A28: Tier 1 | B28: AUD/t | D28: 0 | E28: 0 | F28: 0 | G28: 0 | H28: 0 | I28: 0 | J28: 0 | K28: 0 | L28: 0 | M28: 0 | N28: 0 | O28: 0 | P28: 0 | Q28: 0 | R28: 0 | S28: 0 | T28: 0 | U28: 0 | V28: 0 | W28: 0 | X28: 0 | Y28: 0 | Z28: 0 | AA28: 0 | AB28: 0 | AC28: 0 | AD28: 0 | AE28: 0 | AF28: 0 | AG28: 0 | AH28: 0 | AI28: 0 | AJ28: 0 | AK28: 0 | AL28: 0 | AM28: 0 | AN28: 0 | AO28: 0 | AP28: 0 | AQ28: 0 | AR28: 0 | AS28: 0 | AT28: 0 | AU28: 0 | AV28: 0 | AW28: 0 | AX28: 0 | AY28: 0 | AZ28: 0 | BA28: 0 | BB28: 0 | BC28: 0 | BD28: 0 | BE28: 0 | BF28: 0 | BG28: 0 | BH28: 0 | BI28: 0 | BJ28: 0 | BK28: 0 | BL28: 0 | BM28: 0 | BN28: 0 | BO28: 0 | BP28: 0 | BQ28: 0 | BR28: 0 | BS28: 0 | BT28: 0 | BU28: 0 | BV28: 0
A29: Tier 2 | B29: AUD/t | D29: 100 | E29: 100 | F29: 100 | G29: 100 | H29: 100 | I29: 100 | J29: 100 | K29: 100 | L29: 100 | M29: 100 | N29: 100 | O29: 100 | P29: 100 | Q29: 100 | R29: 100 | S29: 100 | T29: 100 | U29: 100 | V29: 100 | W29: 100 | X29: 100 | Y29: 100 | Z29: 100 | AA29: 100 | AB29: 100 | AC29: 100 | AD29: 100 | AE29: 100 | AF29: 100 | AG29: 100 | AH29: 100 | AI29: 100 | AJ29: 100 | AK29: 100 | AL29: 100 | AM29: 100 | AN29: 100 | AO29: 100 | AP29: 100 | AQ29: 100 | AR29: 100 | AS29: 100 | AT29: 100 | AU29: 100 | AV29: 100 | AW29: 100 | AX29: 100 | AY29: 100 | AZ29: 100 | BA29: 100 | BB29: 100 | BC29: 100 | BD29: 100 | BE29: 100 | BF29: 100 | BG29: 100 | BH29: 100 | BI29: 100 | BJ29: 100 | BK29: 100 | BL29: 100 | BM29: 100 | BN29: 100 | BO29: 100 | BP29: 100 | BQ29: 100 | BR29: 100 | BS29: 100 | BT29: 100 | BU29: 100 | BV29: 100
A30: Tier 3 | B30: AUD/t | D30: 150 | E30: 150 | F30: 150 | G30: 150 | H30: 150 | I30: 150 | J30: 150 | K30: 150 | L30: 150 | M30: 150 | N30: 150 | O30: 150 | P30: 150 | Q30: 150 | R30: 150 | S30: 150 | T30: 150 | U30: 150 | V30: 150 | W30: 150 | X30: 150 | Y30: 150 | Z30: 150 | AA30: 150 | AB30: 150 | AC30: 150 | AD30: 150 | AE30: 150 | AF30: 150 | AG30: 150 | AH30: 150 | AI30: 150 | AJ30: 150 | AK30: 150 | AL30: 150 | AM30: 150 | AN30: 150 | AO30: 150 | AP30: 150 | AQ30: 150 | AR30: 150 | AS30: 150 | AT30: 150 | AU30: 150 | AV30: 150 | AW30: 150 | AX30: 150 | AY30: 150 | AZ30: 150 | BA30: 150 | BB30: 150 | BC30: 150 | BD30: 150 | BE30: 150 | BF30: 150 | BG30: 150 | BH30: 150 | BI30: 150 | BJ30: 150 | BK30: 150 | BL30: 150 | BM30: 150 | BN30: 150 | BO30: 150 | BP30: 150 | BQ30: 150 | BR30: 150 | BS30: 150 | BT30: 150 | BU30: 150 | BV30: 150
A31: Tier 4 | B31: AUD/t | F31: 175 | G31: 175 | H31: 175 | I31: 175 | J31: 175 | K31: 175 | L31: 175 | M31: 175 | N31: 175 | O31: 175 | P31: 175 | Q31: 175 | R31: 175 | S31: 175 | T31: 175 | U31: 175 | V31: 175 | W31: 175 | X31: 175 | Y31: 175 | Z31: 175 | AA31: 175 | AB31: 175 | AC31: 175 | AD31: 175 | AE31: 175 | AF31: 175 | AG31: 175 | AH31: 175 | AI31: 175 | AJ31: 175 | AK31: 175 | AL31: 175 | AM31: 175 | AN31: 175 | AO31: 175 | AP31: 175 | AQ31: 175 | AR31: 175 | AS31: 175 | AT31: 175 | AU31: 175 | AV31: 175 | AW31: 175 | AX31: 175 | AY31: 175 | AZ31: 175 | BA31: 175 | BB31: 175 | BC31: 175 | BD31: 175 | BE31: 175 | BF31: 175 | BG31: 175 | BH31: 175 | BI31: 175 | BJ31: 175 | BK31: 175 | BL31: 175 | BM31: 175 | BN31: 175 | BO31: 175 | BP31: 175 | BQ31: 175 | BR31: 175 | BS31: 175 | BT31: 175 | BU31: 175 | BV31: 175
A32: Tier 5 | B32: AUD/t | F32: 225 | G32: 225 | H32: 225 | I32: 225 | J32: 225 | K32: 225 | L32: 225 | M32: 225 | N32: 225 | O32: 225 | P32: 225 | Q32: 225 | R32: 225 | S32: 225 | T32: 225 | U32: 225 | V32: 225 | W32: 225 | X32: 225 | Y32: 225 | Z32: 225 | AA32: 225 | AB32: 225 | AC32: 225 | AD32: 225 | AE32: 225 | AF32: 225 | AG32: 225 | AH32: 225 | AI32: 225 | AJ32: 225 | AK32: 225 | AL32: 225 | AM32: 225 | AN32: 225 | AO32: 225 | AP32: 225 | AQ32: 225 | AR32: 225 | AS32: 225 | AT32: 225 | AU32: 225 | AV32: 225 | AW32: 225 | AX32: 225 | AY32: 225 | AZ32: 225 | BA32: 225 | BB32: 225 | BC32: 225 | BD32: 225 | BE32: 225 | BF32: 225 | BG32: 225 | BH32: 225 | BI32: 225 | BJ32: 225 | BK32: 225 | BL32: 225 | BM32: 225 | BN32: 225 | BO32: 225 | BP32: 225 | BQ32: 225 | BR32: 225 | BS32: 225 | BT32: 225 | BU32: 225 | BV32: 225
A33: Tier 6 | B33: AUD/t | F33: 300 | G33: 300 | H33: 300 | I33: 300 | J33: 300 | K33: 300 | L33: 300 | M33: 300 | N33: 300 | O33: 300 | P33: 300 | Q33: 300 | R33: 300 | S33: 300 | T33: 300 | U33: 300 | V33: 300 | W33: 300 | X33: 300 | Y33: 300 | Z33: 300 | AA33: 300 | AB33: 300 | AC33: 300 | AD33: 300 | AE33: 300 | AF33: 300 | AG33: 300 | AH33: 300 | AI33: 300 | AJ33: 300 | AK33: 300 | AL33: 300 | AM33: 300 | AN33: 300 | AO33: 300 | AP33: 300 | AQ33: 300 | AR33: 300 | AS33: 300 | AT33: 300 | AU33: 300 | AV33: 300 | AW33: 300 | AX33: 300 | AY33: 300 | AZ33: 300 | BA33: 300 | BB33: 300 | BC33: 300 | BD33: 300 | BE33: 300 | BF33: 300 | BG33: 300 | BH33: 300 | BI33: 300 | BJ33: 300 | BK33: 300 | BL33: 300 | BM33: 300 | BN33: 300 | BO33: 300 | BP33: 300 | BQ33: 300 | BR33: 300 | BS33: 300 | BT33: 300 | BU33: 300 | BV33: 300
A34: Rate
A35: Tier 1 | B35: % | D35: 0.07 | E35: 0.07 | F35: 0.07 | G35: 0.07 | H35: 0.07 | I35: 0.07 | J35: 0.07 | K35: 0.07 | L35: 0.07 | M35: 0.07 | N35: 0.07 | O35: 0.07 | P35: 0.07 | Q35: 0.07 | R35: 0.07 | S35: 0.07 | T35: 0.07 | U35: 0.07 | V35: 0.07 | W35: 0.07 | X35: 0.07 | Y35: 0.07 | Z35: 0.07 | AA35: 0.07 | AB35: 0.07 | AC35: 0.07 | AD35: 0.07 | AE35: 0.07 | AF35: 0.07 | AG35: 0.07 | AH35: 0.07 | AI35: 0.07 | AJ35: 0.07 | AK35: 0.07 | AL35: 0.07 | AM35: 0.07 | AN35: 0.07 | AO35: 0.07 | AP35: 0.07 | AQ35: 0.07 | AR35: 0.07 | AS35: 0.07 | AT35: 0.07 | AU35: 0.07 | AV35: 0.07 | AW35: 0.07 | AX35: 0.07 | AY35: 0.07 | AZ35: 0.07 | BA35: 0.07 | BB35: 0.07 | BC35: 0.07 | BD35: 0.07 | BE35: 0.07 | BF35: 0.07 | BG35: 0.07 | BH35: 0.07 | BI35: 0.07 | BJ35: 0.07 | BK35: 0.07 | BL35: 0.07 | BM35: 0.07 | BN35: 0.07 | BO35: 0.07 | BP35: 0.07 | BQ35: 0.07 | BR35: 0.07 | BS35: 0.07 | BT35: 0.07 | BU35: 0.07 | BV35: 0.07
A36: Tier 2 | B36: % | D36: 0.125 | E36: 0.125 | F36: 0.125 | G36: 0.125 | H36: 0.125 | I36: 0.125 | J36: 0.125 | K36: 0.125 | L36: 0.125 | M36: 0.125 | N36: 0.125 | O36: 0.125 | P36: 0.125 | Q36: 0.125 | R36: 0.125 | S36: 0.125 | T36: 0.125 | U36: 0.125 | V36: 0.125 | W36: 0.125 | X36: 0.125 | Y36: 0.125 | Z36: 0.125 | AA36: 0.125 | AB36: 0.125 | AC36: 0.125 | AD36: 0.125 | AE36: 0.125 | AF36: 0.125 | AG36: 0.125 | AH36: 0.125 | AI36: 0.125 | AJ36: 0.125 | AK36: 0.125 | AL36: 0.125 | AM36: 0.125 | AN36: 0.125 | AO36: 0.125 | AP36: 0.125 | AQ36: 0.125 | AR36: 0.125 | AS36: 0.125 | AT36: 0.125 | AU36: 0.125 | AV36: 0.125 | AW36: 0.125 | AX36: 0.125 | AY36: 0.125 | AZ36: 0.125 | BA36: 0.125 | BB36: 0.125 | BC36: 0.125 | BD36: 0.125 | BE36: 0.125 | BF36: 0.125 | BG36: 0.125 | BH36: 0.125 | BI36: 0.125 | BJ36: 0.125 | BK36: 0.125 | BL36: 0.125 | BM36: 0.125 | BN36: 0.125 | BO36: 0.125 | BP36: 0.125 | BQ36: 0.125 | BR36: 0.125 | BS36: 0.125 | BT36: 0.125 | BU36: 0.125 | BV36: 0.125
A37: Tier 3 | B37: % | D37: 0.15 | E37: 0.15 | F37: 0.15 | G37: 0.15 | H37: 0.15 | I37: 0.15 | J37: 0.15 | K37: 0.15 | L37: 0.15 | M37: 0.15 | N37: 0.15 | O37: 0.15 | P37: 0.15 | Q37: 0.15 | R37: 0.15 | S37: 0.15 | T37: 0.15 | U37: 0.15 | V37: 0.15 | W37: 0.15 | X37: 0.15 | Y37: 0.15 | Z37: 0.15 | AA37: 0.15 | AB37: 0.15 | AC37: 0.15 | AD37: 0.15 | AE37: 0.15 | AF37: 0.15 | AG37: 0.15 | AH37: 0.15 | AI37: 0.15 | AJ37: 0.15 | AK37: 0.15 | AL37: 0.15 | AM37: 0.15 | AN37: 0.15 | AO37: 0.15 | AP37: 0.15 | AQ37: 0.15 | AR37: 0.15 | AS37: 0.15 | AT37: 0.15 | AU37: 0.15 | AV37: 0.15 | AW37: 0.15 | AX37: 0.15 | AY37: 0.15 | AZ37: 0.15 | BA37: 0.15 | BB37: 0.15 | BC37: 0.15 | BD37: 0.15 | BE37: 0.15 | BF37: 0.15 | BG37: 0.15 | BH37: 0.15 | BI37: 0.15 | BJ37: 0.15 | BK37: 0.15 | BL37: 0.15 | BM37: 0.15 | BN37: 0.15 | BO37: 0.15 | BP37: 0.15 | BQ37: 0.15 | BR37: 0.15 | BS37: 0.15 | BT37: 0.15 | BU37: 0.15 | BV37: 0.15
A38: Tier 4 | B38: % | F38: 0.2 | G38: 0.2 | H38: 0.2 | I38: 0.2 | J38: 0.2 | K38: 0.2 | L38: 0.2 | M38: 0.2 | N38: 0.2 | O38: 0.2 | P38: 0.2 | Q38: 0.2 | R38: 0.2 | S38: 0.2 | T38: 0.2 | U38: 0.2 | V38: 0.2 | W38: 0.2 | X38: 0.2 | Y38: 0.2 | Z38: 0.2 | AA38: 0.2 | AB38: 0.2 | AC38: 0.2 | AD38: 0.2 | AE38: 0.2 | AF38: 0.2 | AG38: 0.2 | AH38: 0.2 | AI38: 0.2 | AJ38: 0.2 | AK38: 0.2 | AL38: 0.2 | AM38: 0.2 | AN38: 0.2 | AO38: 0.2 | AP38: 0.2 | AQ38: 0.2 | AR38: 0.2 | AS38: 0.2 | AT38: 0.2 | AU38: 0.2 | AV38: 0.2 | AW38: 0.2 | AX38: 0.2 | AY38: 0.2 | AZ38: 0.2 | BA38: 0.2 | BB38: 0.2 | BC38: 0.2 | BD38: 0.2 | BE38: 0.2 | BF38: 0.2 | BG38: 0.2 | BH38: 0.2 | BI38: 0.2 | BJ38: 0.2 | BK38: 0.2 | BL38: 0.2 | BM38: 0.2 | BN38: 0.2 | BO38: 0.2 | BP38: 0.2 | BQ38: 0.2 | BR38: 0.2 | BS38: 0.2 | BT38: 0.2 | BU38: 0.2 | BV38: 0.2
A39: Tier 5 | B39: % | F39: 0.3 | G39: 0.3 | H39: 0.3 | I39: 0.3 | J39: 0.3 | K39: 0.3 | L39: 0.3 | M39: 0.3 | N39: 0.3 | O39: 0.3 | P39: 0.3 | Q39: 0.3 | R39: 0.3 | S39: 0.3 | T39: 0.3 | U39: 0.3 | V39: 0.3 | W39: 0.3 | X39: 0.3 | Y39: 0.3 | Z39: 0.3 | AA39: 0.3 | AB39: 0.3 | AC39: 0.3 | AD39: 0.3 | AE39: 0.3 | AF39: 0.3 | AG39: 0.3 | AH39: 0.3 | AI39: 0.3 | AJ39: 0.3 | AK39: 0.3 | AL39: 0.3 | AM39: 0.3 | AN39: 0.3 | AO39: 0.3 | AP39: 0.3 | AQ39: 0.3 | AR39: 0.3 | AS39: 0.3 | AT39: 0.3 | AU39: 0.3 | AV39: 0.3 | AW39: 0.3 | AX39: 0.3 | AY39: 0.3 | AZ39: 0.3 | BA39: 0.3 | BB39: 0.3 | BC39: 0.3 | BD39: 0.3 | BE39: 0.3 | BF39: 0.3 | BG39: 0.3 | BH39: 0.3 | BI39: 0.3 | BJ39: 0.3 | BK39: 0.3 | BL39: 0.3 | BM39: 0.3 | BN39: 0.3 | BO39: 0.3 | BP39: 0.3 | BQ39: 0.3 | BR39: 0.3 | BS39: 0.3 | BT39: 0.3 | BU39: 0.3 | BV39: 0.3
A40: Tier 6 | B40: % | F40: 0.4 | G40: 0.4 | H40: 0.4 | I40: 0.4 | J40: 0.4 | K40: 0.4 | L40: 0.4 | M40: 0.4 | N40: 0.4 | O40: 0.4 | P40: 0.4 | Q40: 0.4 | R40: 0.4 | S40: 0.4 | T40: 0.4 | U40: 0.4 | V40: 0.4 | W40: 0.4 | X40: 0.4 | Y40: 0.4 | Z40: 0.4 | AA40: 0.4 | AB40: 0.4 | AC40: 0.4 | AD40: 0.4 | AE40: 0.4 | AF40: 0.4 | AG40: 0.4 | AH40: 0.4 | AI40: 0.4 | AJ40: 0.4 | AK40: 0.4 | AL40: 0.4 | AM40: 0.4 | AN40: 0.4 | AO40: 0.4 | AP40: 0.4 | AQ40: 0.4 | AR40: 0.4 | AS40: 0.4 | AT40: 0.4 | AU40: 0.4 | AV40: 0.4 | AW40: 0.4 | AX40: 0.4 | AY40: 0.4 | AZ40: 0.4 | BA40: 0.4 | BB40: 0.4 | BC40: 0.4 | BD40: 0.4 | BE40: 0.4 | BF40: 0.4 | BG40: 0.4 | BH40: 0.4 | BI40: 0.4 | BJ40: 0.4 | BK40: 0.4 | BL40: 0.4 | BM40: 0.4 | BN40: 0.4 | BO40: 0.4 | BP40: 0.4 | BQ40: 0.4 | BR40: 0.4 | BS40: 0.4 | BT40: 0.4 | BU40: 0.4 | BV40: 0.4
A42: Royalty on first threshold | B42: AUD/t | D42: =D29*D35 -> 7 | E42: =E29*E35 -> 7 | F42: =F29*F35 -> 7 | G42: =G29*G35 -> 7 | H42: =H29*H35 -> 7 | I42: =I29*I35 -> 7 | J42: =J29*J35 -> 7 | K42: =K29*K35 -> 7 | ... BV42: =BV29*BV35 -> 7
A43: Royalty up to second threshold | B43: AUD/t | D43: =D42+(D30-D29)*D36 -> 13.25 | E43: =E42+(E30-E29)*E36 -> 13.25 | F43: =F42+(F30-F29)*F36 -> 13.25 | G43: =G42+(G30-G29)*G36 -> 13.25 | H43: =H42+(H30-H29)*H36 -> 13.25 | I43: =I42+(I30-I29)*I36 -> 13.25 | J43: =J42+(J30-J29)*J36 -> 13.25 | K43: =K42+(K30-K29)*K36 -> 13.25 | ... BV43: =BV42+(BV30-BV29)*BV36 -> 13.25
A44: Royalty up to third threshold | B44: AUD/t | F44: =F43+(F31-F30)*F37 -> 17 | G44: =G43+(G31-G30)*G37 -> 17 | H44: =H43+(H31-H30)*H37 -> 17 | I44: =I43+(I31-I30)*I37 -> 17 | J44: =J43+(J31-J30)*J37 -> 17 | K44: =K43+(K31-K30)*K37 -> 17 | L44: =L43+(L31-L30)*L37 -> 17 | M44: =M43+(M31-M30)*M37 -> 17 | ... BV44: =BV43+(BV31-BV30)*BV37 -> 17
A45: Royalty up to fourth threshold | B45: AUD/t | F45: =F44+(F32-F31)*F38 -> 27 | G45: =G44+(G32-G31)*G38 -> 27 | H45: =H44+(H32-H31)*H38 -> 27 | I45: =I44+(I32-I31)*I38 -> 27 | J45: =J44+(J32-J31)*J38 -> 27 | K45: =K44+(K32-K31)*K38 -> 27 | L45: =L44+(L32-L31)*L38 -> 27 | M45: =M44+(M32-M31)*M38 -> 27 | ... BV45: =BV44+(BV32-BV31)*BV38 -> 27
A46: Royalty up to fifth threshold | B46: AUD/t | F46: =F45+(F33-F32)*F39 -> 49.5 | G46: =G45+(G33-G32)*G39 -> 49.5 | H46: =H45+(H33-H32)*H39 -> 49.5 | I46: =I45+(I33-I32)*I39 -> 49.5 | J46: =J45+(J33-J32)*J39 -> 49.5 | K46: =K45+(K33-K32)*K39 -> 49.5 | L46: =L45+(L33-L32)*L39 -> 49.5 | M46: =M45+(M33-M32)*M39 -> 49.5 | ... BV46: =BV45+(BV33-BV32)*BV39 -> 49.5
A49: AUD CPI | B49: % | D49: 0.01 | E49: 0.01 | F49: 0.01 | G49: 0.01 | H49: 0.01 | I49: 0.01 | J49: 0.0265 | K49: 0.0265 | L49: 0.0265 | M49: 0.0265 | N49: 0.0265 | O49: 0.0265 | P49: 0.0265 | Q49: 0.0265 | R49: 0.0265 | S49: 0.0265 | T49: 0.0265 | U49: 0.0265 | V49: 0.0265 | W49: 0.0265 | X49: 0.0265 | Y49: 0.0265 | Z49: 0.0265 | AA49: 0.0265 | AB49: 0.0265 | AC49: 0.0265 | AD49: 0.0265 | AE49: 0.0265 | AF49: 0.0265 | AG49: 0.0265 | AH49: 0.0265 | AI49: 0.0265 | AJ49: 0.0265 | AK49: 0.0265 | AL49: 0.0265 | AM49: 0.0265 | AN49: 0.0265 | AO49: 0.0265 | AP49: 0.0265 | AQ49: 0.0265 | AR49: 0.0265 | AS49: 0.0265 | AT49: 0.0265 | AU49: 0.0265 | AV49: 0.0265 | AW49: 0.0265 | AX49: 0.0265 | AY49: 0.0265 | AZ49: 0.0265 | BA49: 0.0265 | BB49: 0.0265 | BC49: 0.0265 | BD49: 0.0265 | BE49: 0.0265 | BF49: 0.0265 | BG49: 0.0265 | BH49: 0.0265 | BI49: 0.0265 | BJ49: 0.0265 | BK49: 0.0265 | BL49: 0.0265 | BM49: 0.0265 | BN49: 0.0265 | BO49: 0.0265 | BP49: 0.0265 | BQ49: 0.0265 | BR49: 0.0265 | BS49: 0.0265 | BT49: 0.0265 | BU49: 0.0265 | BV49: 0.0265
A52: Flood Rate
A53: 0
A54: 100000
A55: 250000
A56: 500000
A57: 750000
A58: 10000000

Sheet Analysis
C1: 2021Act | D1: 2022Act | E1: 2023Act | F1: 2024Act | G1: 2025Act | H1: 2026FYF | I1: 2027 | J1: =I1+1 -> 2028 | K1: =J1+1 -> 2029 | L1: =K1+1 -> 2030 | M1: =L1+1 -> 2031 | N1: =M1+1 -> 2032 | O1: =N1+1 -> 2033 | P1: =O1+1 -> 2034 | Q1: =P1+1 -> 2035 | ... AH1: =AG1+1 -> 2052
A2: FOR cash cost/t
A3: Springbok Coal Complex | B3: AUD/t | C3: ='Historical Performance'!D117 -> 134.97782 | D3: ='Historical Performance'!E117 -> 144.9523 | E3: ='Historical Performance'!F117 -> 136.08293 | F3: ='Historical Performance'!G117 -> 145.64931 | G3: ='Historical Performance'!H117 -> 168.45908 | H3: ='Historical Performance'!I117 -> 147.37336 | I3: =IF(Springbok!D90=0,NA(),Springbok!D90) -> 155.73261 | J3: =IF(Springbok!E90=0,NA(),Springbok!E90) -> 154.91662 | K3: =IF(Springbok!F90=0,NA(),Springbok!F90) -> 149.10247 | L3: =IF(Springbok!G90=0,NA(),Springbok!G90) -> 143.58757 | M3: =IF(Springbok!H90=0,NA(),Springbok!H90) -> 144.30907 | N3: =IF(Springbok!I90=0,NA(),Springbok!I90) -> #N/A | O3: =IF(Springbok!J90=0,NA(),Springbok!J90) -> #N/A | P3: =IF(Springbok!K90=0,NA(),Springbok!K90) -> #N/A | ... AH3: =IF(Springbok!AC90=0,NA(),Springbok!AC90) -> #N/A
A4: Brave Blossom UG | B4: AUD/t | I4: =IF('Brave Blossom '!D90=0,NA(),'Brave Blossom '!D90) -> #N/A | J4: =IF('Brave Blossom '!E90=0,NA(),'Brave Blossom '!E90) -> #N/A | K4: =IF('Brave Blossom '!F90=0,NA(),'Brave Blossom '!F90) -> #N/A | L4: =IF('Brave Blossom '!G90=0,NA(),'Brave Blossom '!G90) -> #N/A | M4: =IF('Brave Blossom '!H90=0,NA(),'Brave Blossom '!H90) -> 1088.3876 | N4: =IF('Brave Blossom '!I90=0,NA(),'Brave Blossom '!I90) -> 1241.8899 | O4: =IF('Brave Blossom '!J90=0,NA(),'Brave Blossom '!J90) -> 120.40978 | P4: =IF('Brave Blossom '!K90=0,NA(),'Brave Blossom '!K90) -> 120.40978 | ... AH4: =IF('Brave Blossom '!AC90=0,NA(),'Brave Blossom '!AC90) -> #N/A
A6: Net Cashflow Before Tax
A7: Springbok Coal Complex | B7: AUDk | C7: ='Historical Performance'!D143 -> 522475.43 | D7: ='Historical Performance'!E143 -> 545821.27 | E7: ='Historical Performance'!F143 -> 482741.53 | F7: ='Historical Performance'!G143 -> 438805.48 | G7: ='Historical Performance'!H143 -> 351060.19 | H7: ='Historical Performance'!I143 -> 461475.23 | I7: =IF(Springbok!D118=0,NA(),Springbok!D118) -> 226119.3 | J7: =IF(Springbok!E118=0,NA(),Springbok!E118) -> 287082.17 | K7: =IF(Springbok!F118=0,NA(),Springbok!F118) -> 379815.77 | L7: =IF(Springbok!G118=0,NA(),Springbok!G118) -> 374686.35 | M7: =IF(Springbok!H118=0,NA(),Springbok!H118) -> 325082.09 | N7: =IF(Springbok!I118=0,NA(),Springbok!I118) -> -895000 | O7: =IF(Springbok!J118=0,NA(),Springbok!J118) -> #N/A | P7: =IF(Springbok!K118=0,NA(),Springbok!K118) -> #N/A | ... AH7: =IF(Springbok!AC118=0,NA(),Springbok!AC118) -> #N/A
A8: Brave Blossom UG | B8: AUDk | I8: =IF('Brave Blossom '!D118=0,NA(),'Brave Blossom '!D118) -> #N/A | J8: =IF('Brave Blossom '!E118=0,NA(),'Brave Blossom '!E118) -> #N/A | K8: =IF('Brave Blossom '!F118=0,NA(),'Brave Blossom '!F118) -> #N/A | L8: =IF('Brave Blossom '!G118=0,NA(),'Brave Blossom '!G118) -> #N/A | M8: =IF('Brave Blossom '!H118=0,NA(),'Brave Blossom '!H118) -> -76108.799 | N8: =IF('Brave Blossom '!I118=0,NA(),'Brave Blossom '!I118) -> -173927.55 | O8: =IF('Brave Blossom '!J118=0,NA(),'Brave Blossom '!J118) -> 452810.4 | P8: =IF('Brave Blossom '!K118=0,NA(),'Brave Blossom '!K118) -> 438582.14 | ... AH8: =IF('Brave Blossom '!AC118=0,NA(),'Brave Blossom '!AC118) -> -91684.509
A10: Net Cashflow Before Tax Combined
A11: Springbok Coal Complex + Brave Blossom UG - Project | B11: AUDk | C11: =C7 -> 522475.43 | D11: =D7 -> 545821.27 | E11: =E7 -> 482741.53 | F11: =F7 -> 438805.48 | G11: =G7 -> 351060.19 | H11: =H7 -> 461475.23 | I11: ='Brave Blossom '!D118+Springbok!D118 -> 226119.3 | J11: ='Brave Blossom '!E118+Springbok!E118 -> 287082.17 | K11: ='Brave Blossom '!F118+Springbok!F118 -> 379815.77 | L11: ='Brave Blossom '!G118+Springbok!G118 -> 374686.35 | M11: ='Brave Blossom '!H118+Springbok!H118 -> 248973.3 | N11: ='Brave Blossom '!I118+Springbok!I118 -> -1068927.6 | O11: ='Brave Blossom '!J118+Springbok!J118 -> 452810.4 | P11: ='Brave Blossom '!K118+Springbok!K118 -> 438582.14 | ... AH11: ='Brave Blossom '!AC118+Springbok!AC118 -> -91684.509
A13: Attributable Net Cashflow After Tax Combined
A14: Brave Blossom UG - Project + Springbok Coal Complex | B14: AUDk | C14: ='Historical Performance'!D148 -> 210281.47 | D14: ='Historical Performance'!E148 -> 210309.36 | E14: ='Historical Performance'!F148 -> 185079.12 | F14: ='Historical Performance'!G148 -> 170008.61 | G14: ='Historical Performance'!H148 -> 136101.95 | H14: ='Historical Performance'!I148 -> 178993.73 | I14: ='Brave Blossom '!D123+Springbok!D123 -> 87216.159 | J14: ='Brave Blossom '!E123+Springbok!E123 -> 115050.57 | K14: ='Brave Blossom '!F123+Springbok!F123 -> 162597.51 | L14: ='Brave Blossom '!G123+Springbok!G123 -> 163167.12 | M14: ='Brave Blossom '!H123+Springbok!H123 -> 106616.68 | N14: ='Brave Blossom '!I123+Springbok!I123 -> -641356.53 | O14: ='Brave Blossom '!J123+Springbok!J123 -> 181632.97 | P14: ='Brave Blossom '!K123+Springbok!K123 -> 176108.39 | ... AH14: ='Brave Blossom '!AC123+Springbok!AC123 -> -55010.705
A15: All | B15: AUDk | I15: ='Brave Blossom '!D123+Springbok!D123+'OC Clean'!D125 -> 87216.159 | J15: ='Brave Blossom '!E123+Springbok!E123+'OC Clean'!E125 -> 115050.57 | K15: ='Brave Blossom '!F123+Springbok!F123+'OC Clean'!F125 -> 162597.51 | L15: ='Brave Blossom '!G123+Springbok!G123+'OC Clean'!G125 -> 163167.12 | M15: ='Brave Blossom '!H123+Springbok!H123+'OC Clean'!H125 -> 106616.68 | N15: ='Brave Blossom '!I123+Springbok!I123+'OC Clean'!I125 -> -641356.53 | O15: ='Brave Blossom '!J123+Springbok!J123+'OC Clean'!J125 -> 181632.97 | P15: ='Brave Blossom '!K123+Springbok!K123+'OC Clean'!K125 -> 176108.39 | ... AH15: ='Brave Blossom '!AC123+Springbok!AC123+'OC Clean'!AC125 -> -55010.705
A17: Discounted Cashflow After Tax Combined
A18: Brave Blossom UG - Project + Springbok Coal Complex | B18: AUDk | C18: =C14 -> 210281.47 | D18: =D14 -> 210309.36 | E18: =E14 -> 185079.12 | F18: =F14 -> 170008.61 | G18: =G14 -> 136101.95 | H18: =H14 -> 178993.73 | I18: ='Brave Blossom '!D124+Springbok!D124 -> 83923.788 | J18: ='Brave Blossom '!E124+Springbok!E124 -> 170844.85 | K18: ='Brave Blossom '!F124+Springbok!F124 -> 223564.71 | L18: ='Brave Blossom '!G124+Springbok!G124 -> 207729.54 | M18: ='Brave Blossom '!H124+Springbok!H124 -> 125680.24 | N18: ='Brave Blossom '!I124+Springbok!I124 -> -700031.55 | O18: ='Brave Blossom '!J124+Springbok!J124 -> 183564.64 | P18: ='Brave Blossom '!K124+Springbok!K124 -> 164797.5 | ... AH18: ='Brave Blossom '!AC124+Springbok!AC124 -> -12882.205
A19: Springbok (Base Case) | B19: AUDk | I19: =Springbok!D124 -> 83923.788 | J19: =Springbok!E124 -> 170844.85 | K19: =Springbok!F124 -> 223564.71 | L19: =Springbok!G124 -> 207729.54 | M19: =Springbok!H124 -> 179510.69 | N19: =Springbok!I124 -> -586127.88 | O19: =Springbok!J124 -> 0 | P19: =Springbok!K124 -> 0 | ... AH19: =Springbok!AC124 -> 0
A21: Cumulative Discounted Cashflow After Tax Combined
A22: Brave Blossom UG - Project + Springbok Coal Complex | B22: AUDk | I22: =SUM($I18) -> 83923.788 | J22: =SUM($I18:J18) -> 254768.64 | K22: =SUM($I18:K18) -> 478333.34 | L22: =SUM($I18:L18) -> 686062.89 | M22: =SUM($I18:M18) -> 811743.13 | N22: =SUM($I18:N18) -> 111711.58 | O22: =SUM($I18:O18) -> 295276.21 | P22: =SUM($I18:P18) -> 460073.72 | Q22: =SUM($I18:Q18) -> 607881.55 | ... AH22: =SUM($I18:AH18) -> 1669665.3
A23: Springbok (Base Case) | B23: AUDk | I23: =SUM($H19:I19) -> 83923.788 | J23: =SUM($H19:J19) -> 254768.64 | K23: =SUM($H19:K19) -> 478333.34 | L23: =SUM($H19:L19) -> 686062.89 | M23: =SUM($H19:M19) -> 865573.58 | N23: =SUM($H19:N19) -> 279445.69 | O23: =SUM($H19:O19) -> 279445.69 | P23: =SUM($H19:P19) -> 279445.69 | ... AH23: =SUM($H19:AH19) -> 279445.69
A24: Brave Blossom UG Project Standalone | B24: AUDk | I24: =SUM('Brave Blossom '!$D$124:'Brave Blossom '!D124) -> 0 | J24: =SUM('Brave Blossom '!$D$124:'Brave Blossom '!E124) -> 0 | K24: =SUM('Brave Blossom '!$D$124:'Brave Blossom '!F124) -> 0 | L24: =SUM('Brave Blossom '!$D$124:'Brave Blossom '!G124) -> 0 | M24: =SUM('Brave Blossom '!$D$124:'Brave Blossom '!H124) -> -53830.445 | N24: =SUM('Brave Blossom '!$D$124:'Brave Blossom '!I124) -> -167734.12 | O24: =SUM('Brave Blossom '!$D$124:'Brave Blossom '!J124) -> 15830.519 | P24: =SUM('Brave Blossom '!$D$124:'Brave Blossom '!K124) -> 180628.02 | ... AH24: =SUM('Brave Blossom '!$D$124:'Brave Blossom '!AC124) -> 1390219.6

Sheet List
A1: Owner/operate | B1: 7on7off | C1: 4 | D1: Max Quality | E1: SIS | F1: Yes | G1: Preventative Maintenance | H1: Maintain
A2: Contract | B2: 5on2off | C2: 3 | D2: Max Quantity | E2: UIS | F2: No | G2: Corrective Maintenance | H2: Increase 10%
B3: Other | C3: 2 | H3: Decrease 10%
C4: 1

Sheet Summary
A1: INPUTS FOR REVENUE GRAPH | D1: 2022 | E1: 2023 | F1: 2024 | G1: 2025 | H1: 2026
D2: 2022 A | E2: 2023 A | F2: 2024 A | G2: 2025 A | H2: 2026 FYF | I2: 2027 | J2: 2028 | K2: 2029 | L2: 2030 | M2: 2031 | N2: 2032 | O2: 2033 | P2: 2034 | Q2: 2035 | R2: 2036 | S2: 2037 | T2: 2038 | U2: 2039 | V2: 2040 | W2: 2041 | X2: 2042 | Y2: 2043 | Z2: 2044 | AA2: 2045 | AB2: 2046 | AC2: 2047 | AD2: 2048 | AE2: 2049 | AF2: 2050 | AG2: 2051 | AH2: 2052
B3: Sales Revenue | C3: AUD M | D3: ='Historical Performance'!E29/1000 -> 1678.1498 | E3: ='Historical Performance'!F29/1000 -> 2073.4218 | F3: ='Historical Performance'!G29/1000 -> 1959.2335 | G3: ='Historical Performance'!H29/1000 -> 1596.6324 | H3: ='Historical Performance'!I29/1000 -> 2003.9783 | I3: =IF(I14>0,(Springbok!D62)/1000,0) -> 1209.8149 | J3: =IF(J14>0,(Springbok!E62)/1000,0) -> 1319.7575 | K3: =IF(K14>0,(Springbok!F62)/1000,0) -> 1395.4746 | L3: =IF(L14>0,(Springbok!G62)/1000,0) -> 1344.3738 | M3: =IF(M14>0,(Springbok!H62)/1000,0) -> 1222.5303 | N3: =IF(N14>0,(Springbok!I62)/1000,0) -> 0 | O3: =IF(O14>0,(Springbok!J62)/1000,0) -> 0 | P3: =IF(P14>0,(Springbok!K62)/1000,0) -> 0 | ... AH3: =IF(AH14>0,(Springbok!AC62)/1000,0) -> 0
B4: Average Realisation A$ (Ex-Mine) | C4: AUD/t | D4: ='Historical Performance'!E30 -> 502.98492 | E4: ='Historical Performance'!F30 -> 505.24374 | F4: ='Historical Performance'!G30 -> 464.21175 | G4: ='Historical Performance'!H30 -> 431.39635 | H4: ='Historical Performance'!I30 -> 470.0855 | I4: =IF(I14>0,(Springbok!D34*Springbok!D63)/Summary!I14,0) -> 347.82609 | J4: =IF(J14>0,(Springbok!E34*Springbok!E63)/Summary!J14,0) -> 347.82609 | K4: =IF(K14>0,(Springbok!F34*Springbok!F63)/Summary!K14,0) -> 347.82609 | L4: =IF(L14>0,(Springbok!G34*Springbok!G63)/Summary!L14,0) -> 347.82609 | M4: =IF(M14>0,(Springbok!H34*Springbok!H63)/Summary!M14,0) -> 347.82609 | N4: =IF(N14>0,(Springbok!I34*Springbok!I63)/Summary!N14,0) -> 0 | O4: =IF(O14>0,(Springbok!J34*Springbok!J63)/Summary!O14,0) -> 0 | P4: =IF(P14>0,(Springbok!K34*Springbok!K63)/Summary!P14,0) -> 0 | ... AH4: =IF(AH14>0,(Springbok!AC34*Springbok!AC63)/Summary!AH14,0) -> 0
B6: Direct Mining Cost | C6: AUD/t | D6: ='Historical Performance'!E78/'Historical Performance'!E20 -> 104.83961 | E6: ='Historical Performance'!F78/'Historical Performance'!F20 -> 101.45796 | F6: ='Historical Performance'!G78/'Historical Performance'!G20 -> 109.42968 | G6: ='Historical Performance'!H78/'Historical Performance'!H20 -> 136.99268 | H6: ='Historical Performance'!I78/'Historical Performance'!I20 -> 110.85684 | I6: =IF(I14>0,(Springbok!D70+Springbok!D73+Springbok!D75+Springbok!D78)/I14,0) -> 115.96569 | J6: =IF(J14>0,(Springbok!E70+Springbok!E73+Springbok!E75+Springbok!E78)/J14,0) -> 117.2813 | K6: =IF(K14>0,(Springbok!F70+Springbok!F73+Springbok!F75+Springbok!F78)/K14,0) -> 112.73986 | L6: =IF(L14>0,(Springbok!G70+Springbok!G73+Springbok!G75+Springbok!G78)/L14,0) -> 106.38174 | M6: =IF(M14>0,(Springbok!H70+Springbok!H73+Springbok!H75+Springbok!H78)/M14,0) -> 104.80828 | N6: =IF(N14>0,(Springbok!I70+Springbok!I73+Springbok!I75+Springbok!I78)/N14,0) -> 0 | O6: =IF(O14>0,(Springbok!J70+Springbok!J73+Springbok!J75+Springbok!J78)/O14,0) -> 0 | P6: =IF(P14>0,(Springbok!K70+Springbok!K73+Springbok!K75+Springbok!K78)/P14,0) -> 0 | ... AH6: =IF(AH14>0,(Springbok!AC70+Springbok!AC73+Springbok!AC75+Springbok!AC78)/AH14,0) -> 0
B7: CHPP Cash Cost | C7: AUD/t | D7: ='Historical Performance'!E89/'Historical Performance'!E20 -> 24.805187 | E7: ='Historical Performance'!F89/'Historical Performance'!F20 -> 19.601723 | F7: ='Historical Performance'!G89/'Historical Performance'!G20 -> 20.124839 | G7: ='Historical Performance'!H89/'Historical Performance'!H20 -> 27.8445 | H7: ='Historical Performance'!I89/'Historical Performance'!I20 -> 18.753983 | I7: =IF(I14>0,(Springbok!D82)/Summary!I14,0) -> 19.929176 | J7: =IF(J14>0,(Springbok!E82)/Summary!J14,0) -> 19.450165 | K7: =IF(K14>0,(Springbok!F82)/Summary!K14,0) -> 19.164162 | L7: =IF(L14>0,(Springbok!G82)/Summary!L14,0) -> 19.353649 | M7: =IF(M14>0,(Springbok!H82)/Summary!M14,0) -> 19.86937 | N7: =IF(N14>0,(Springbok!I82)/Summary!N14,0) -> 0 | O7: =IF(O14>0,(Springbok!J82)/Summary!O14,0) -> 0 | P7: =IF(P14>0,(Springbok!K82)/Summary!P14,0) -> 0 | ... AH7: =IF(AH14>0,(Springbok!AC82)/Summary!AH14,0) -> 0
B8: Overhead & Indirect Cash Cost | C8: AUD/t | D8: ='Historical Performance'!E114/'Historical Performance'!E20 -> 19.845559 | E8: ='Historical Performance'!F114/'Historical Performance'!F20 -> 18.757798 | F8: ='Historical Performance'!G114/'Historical Performance'!G20 -> 17.171115 | G8: ='Historical Performance'!H114/'Historical Performance'!H20 -> 20.936954 | H8: ='Historical Performance'!I114/'Historical Performance'!I20 -> 17.78253 | I8: =IF(I14>0,(Springbok!D87)/Summary!I14,0) -> 19.837746 | J8: =IF(J14>0,(Springbok!E87)/Summary!J14,0) -> 18.185159 | K8: =IF(K14>0,(Springbok!F87)/Summary!K14,0) -> 17.19845 | L8: =IF(L14>0,(Springbok!G87)/Summary!L14,0) -> 17.852178 | M8: =IF(M14>0,(Springbok!H87)/Summary!M14,0) -> 19.631415 | N8: =IF(N14>0,(Springbok!I87)/Summary!N14,0) -> 0 | O8: =IF(O14>0,(Springbok!J87)/Summary!O14,0) -> 0 | P8: =IF(P14>0,(Springbok!K87)/Summary!P14,0) -> 0 | ... AH8: =IF(AH14>0,(Springbok!AC87)/Summary!AH14,0) -> 0
B9: Distribution (excluding Royalty) | C9: AUD/t | D9: ='Historical Performance'!E119/'Historical Performance'!E20 -> 109.19554 | E9: ='Historical Performance'!F119/'Historical Performance'!F20 -> 128.43743 | F9: ='Historical Performance'!G119/'Historical Performance'!G20 -> 96.736444 | G9: ='Historical Performance'!H119/'Historical Performance'!H20 -> 72.174756 | H9: ='Historical Performance'!I119/'Historical Performance'!I20 -> 83.85925 | I9: =IF(I14>0,(Springbok!D93+Springbok!D94)/Summary!I14,0) -> 34 | J9: =IF(J14>0,(Springbok!E93+Springbok!E94)/Summary!J14,0) -> 34 | K9: =IF(K14>0,(Springbok!F93+Springbok!F94)/Summary!K14,0) -> 24 | L9: =IF(L14>0,(Springbok!G93+Springbok!G94)/Summary!L14,0) -> 24 | M9: =IF(M14>0,(Springbok!H93+Springbok!H94)/Summary!M14,0) -> 24 | N9: =IF(N14>0,(Springbok!I93+Springbok!I94)/Summary!N14,0) -> 0 | O9: =IF(O14>0,(Springbok!J93+Springbok!J94)/Summary!O14,0) -> 0 | P9: =IF(P14>0,(Springbok!K93+Springbok!K94)/Summary!P14,0) -> 0 | ... AH9: =IF(AH14>0,(Springbok!AC93+Springbok!AC94)/Summary!AH14,0) -> 0
B10: Other Costs (Carbon) | C10: AUD/t | D10: ='Historical Performance'!E131/'Historical Performance'!E20 -> 0 | E10: ='Historical Performance'!F131/'Historical Performance'!F20 -> 0 | F10: ='Historical Performance'!G131/'Historical Performance'!G20 -> 2.2856574 | G10: ='Historical Performance'!H131/'Historical Performance'!H20 -> 2.4227514 | H10: ='Historical Performance'!I131/'Historical Performance'!I20 -> 6.2401719 | I10: =IF(I14>0,(Springbok!D106)/I14,0) -> 2.8063866 | J10: =IF(J14>0,(Springbok!E106)/J14,0) -> 3.7689627 | K10: =IF(K14>0,(Springbok!F106)/K14,0) -> 4.8295072 | L10: =IF(L14>0,(Springbok!G106)/L14,0) -> 6.2669801 | M10: =IF(M14>0,(Springbok!H106)/M14,0) -> 8.1149314 | N10: =IF(N14>0,(Springbok!I106)/N14,0) -> 0 | O10: =IF(O14>0,(Springbok!J106)/O14,0) -> 0 | P10: =IF(P14>0,(Springbok!K106)/P14,0) -> 0 | ... AH10: =IF(AH14>0,(Springbok!AC106)/AH14,0) -> 0
B11: Royalty - Government Export | C11: AUD/t | D11: ='Historical Performance'!E120/'Historical Performance'!E20 -> 51.826537 | E11: ='Historical Performance'!F120/'Historical Performance'!F20 -> 98.144248 | F11: ='Historical Performance'!G120/'Historical Performance'!G20 -> 91.18152 | G11: ='Historical Performance'!H120/'Historical Performance'!H20 -> 84.983637 | H11: ='Historical Performance'!I120/'Historical Performance'!I20 -> 96.567101 | I11: =IF(I14>0,(Springbok!D95)/Summary!I14,0) -> 61.92181 | J11: =IF(J14>0,(Springbok!E95)/Summary!J14,0) -> 63.741704 | K11: =IF(K14>0,(Springbok!F95)/Summary!K14,0) -> 67.494049 | L11: =IF(L14>0,(Springbok!G95)/Summary!L14,0) -> 69.233218 | M11: =IF(M14>0,(Springbok!H95)/Summary!M14,0) -> 70.933105 | N11: =IF(N14>0,(Springbok!I95)/Summary!N14,0) -> 0 | O11: =IF(O14>0,(Springbok!J95)/Summary!O14,0) -> 0 | P11: =IF(P14>0,(Springbok!K95)/Summary!P14,0) -> 0 | ... AH11: =IF(AH14>0,(Springbok!AC95)/Summary!AH14,0) -> 0
B14: Total Sales Vol | I14: =Springbok!D34 -> 3478.2177 | J14: =Springbok!E34 -> 3794.3029 | K14: =Springbok!F34 -> 4011.9895 | L14: =Springbok!G34 -> 3865.0746 | M14: =Springbok!H34 -> 3514.7746 | N14: =Springbok!I34 -> 0 | O14: =Springbok!J34 -> 0 | P14: =Springbok!K34 -> 0 | ... AH14: =Springbok!AC34 -> 0
B44: Project Margin Analysis
D45: 2031 | E45: 2032 | F45: 2033 | G45: 2034 | H45: 2035 | I45: 2036 | J45: 2037 | K45: 2038 | L45: 2039 | M45: 2040 | N45: 2041 | O45: 2042 | P45: 2043 | Q45: 2044 | R45: 2045 | S45: 2046 | T45: 2047 | U45: 2048 | V45: 2049 | W45: 2050
B46: Sales Revenue | C46: AUD M | D46: =IF(D57>0,('Brave Blossom '!H62)/1000,0) -> 24.925273 | E46: =IF(E57>0,('Brave Blossom '!I62)/1000,0) -> 49.850546 | F46: =IF(F57>0,('Brave Blossom '!J62)/1000,0) -> 1652.479 | G46: =IF(G57>0,('Brave Blossom '!K62)/1000,0) -> 1652.479 | H46: =IF(H57>0,('Brave Blossom '!L62)/1000,0) -> 1652.479 | I46: =IF(I57>0,('Brave Blossom '!M62)/1000,0) -> 1652.479 | J46: =IF(J57>0,('Brave Blossom '!N62)/1000,0) -> 1652.479 | K46: =IF(K57>0,('Brave Blossom '!O62)/1000,0) -> 1652.479 | ... W46: =IF(W57>0,('Brave Blossom '!AA62)/1000,0) -> 1581.8574
B47: Average Realisation A$ (Ex-Mine) | C47: AUD/t | D47: =IF(D57>0,('Brave Blossom '!H34*'Brave Blossom '!H63)/D57,0) -> 306.08696 | E47: =IF(E57>0,('Brave Blossom '!I34*'Brave Blossom '!I63)/E57,0) -> 306.08696 | F47: =IF(F57>0,('Brave Blossom '!J34*'Brave Blossom '!J63)/F57,0) -> 306.08696 | G47: =IF(G57>0,('Brave Blossom '!K34*'Brave Blossom '!K63)/G57,0) -> 306.08696 | H47: =IF(H57>0,('Brave Blossom '!L34*'Brave Blossom '!L63)/H57,0) -> 306.08696 | I47: =IF(I57>0,('Brave Blossom '!M34*'Brave Blossom '!M63)/I57,0) -> 306.08696 | J47: =IF(J57>0,('Brave Blossom '!N34*'Brave Blossom '!N63)/J57,0) -> 306.08696 | K47: =IF(K57>0,('Brave Blossom '!O34*'Brave Blossom '!O63)/K57,0) -> 306.08696 | ... W47: =IF(W57>0,('Brave Blossom '!AA34*'Brave Blossom '!AA63)/W57,0) -> 306.08696
B49: Direct Mining Cost | C49: AUD/t | D49: =IF(D57>0,('Brave Blossom '!H70+'Brave Blossom '!H73+'Brave Blossom '!H75+'Brave Blossom '!H78)/D57,0) -> 822.99219 | E49: =IF(E57>0,('Brave Blossom '!I70+'Brave Blossom '!I73+'Brave Blossom '!I75+'Brave Blossom '!I78)/E57,0) -> 675.62997 | F49: =IF(F57>0,('Brave Blossom '!J70+'Brave Blossom '!J73+'Brave Blossom '!J75+'Brave Blossom '!J78)/F57,0) -> 89.953811 | G49: =IF(G57>0,('Brave Blossom '!K70+'Brave Blossom '!K73+'Brave Blossom '!K75+'Brave Blossom '!K78)/G57,0) -> 89.953811 | H49: =IF(H57>0,('Brave Blossom '!L70+'Brave Blossom '!L73+'Brave Blossom '!L75+'Brave Blossom '!L78)/H57,0) -> 89.953811 | I49: =IF(I57>0,('Brave Blossom '!M70+'Brave Blossom '!M73+'Brave Blossom '!M75+'Brave Blossom '!M78)/I57,0) -> 89.953811 | J49: =IF(J57>0,('Brave Blossom '!N70+'Brave Blossom '!N73+'Brave Blossom '!N75+'Brave Blossom '!N78)/J57,0) -> 89.953811 | K49: =IF(K57>0,('Brave Blossom '!O70+'Brave Blossom '!O73+'Brave Blossom '!O75+'Brave Blossom '!O78)/K57,0) -> 89.953811 | ... W49: =IF(W57>0,('Brave Blossom '!AA70+'Brave Blossom '!AA73+'Brave Blossom '!AA75+'Brave Blossom '!AA78)/W57,0) -> 77.321981
B50: CHPP Cash Cost | C50: AUD/t | D50: =IF(D57>0,('Brave Blossom '!H82)/D57,0) -> 265.39536 | E50: =IF(E57>0,('Brave Blossom '!I82)/E57,0) -> 142.59351 | F50: =IF(F57>0,('Brave Blossom '!J82)/F57,0) -> 17.675167 | G50: =IF(G57>0,('Brave Blossom '!K82)/G57,0) -> 17.675167 | H50: =IF(H57>0,('Brave Blossom '!L82)/H57,0) -> 17.675167 | I50: =IF(I57>0,('Brave Blossom '!M82)/I57,0) -> 17.675167 | J50: =IF(J57>0,('Brave Blossom '!N82)/J57,0) -> 17.675167 | K50: =IF(K57>0,('Brave Blossom '!O82)/K57,0) -> 17.675167 | ... W50: =IF(W57>0,('Brave Blossom '!AA82)/W57,0) -> 13.970588
B51: Overhead & Indirect Cash Cost | C51: AUD/t | D51: =IF(D57>0,('Brave Blossom '!H87)/D57,0) -> 0 | E51: =IF(E57>0,('Brave Blossom '!I87)/E57,0) -> 423.66637 | F51: =IF(F57>0,('Brave Blossom '!J87)/F57,0) -> 12.780798 | G51: =IF(G57>0,('Brave Blossom '!K87)/G57,0) -> 12.780798 | H51: =IF(H57>0,('Brave Blossom '!L87)/H57,0) -> 12.780798 | I51: =IF(I57>0,('Brave Blossom '!M87)/I57,0) -> 12.780798 | J51: =IF(J57>0,('Brave Blossom '!N87)/J57,0) -> 12.780798 | K51: =IF(K57>0,('Brave Blossom '!O87)/K57,0) -> 12.780798 | ... W51: =IF(W57>0,('Brave Blossom '!AA87)/W57,0) -> 13.351393
B52: Distribution (excluding Royalty) | C52: AUD/t | D52: =IF(D57>0,('Brave Blossom '!H93+'Brave Blossom '!H94)/D57,0) -> 22 | E52: =IF(E57>0,('Brave Blossom '!I93+'Brave Blossom '!I94)/E57,0) -> 22 | F52: =IF(F57>0,('Brave Blossom '!J93+'Brave Blossom '!J94)/F57,0) -> 22 | G52: =IF(G57>0,('Brave Blossom '!K93+'Brave Blossom '!K94)/G57,0) -> 22 | H52: =IF(H57>0,('Brave Blossom '!L93+'Brave Blossom '!L94)/H57,0) -> 22 | I52: =IF(I57>0,('Brave Blossom '!M93+'Brave Blossom '!M94)/I57,0) -> 22 | J52: =IF(J57>0,('Brave Blossom '!N93+'Brave Blossom '!N94)/J57,0) -> 22 | K52: =IF(K57>0,('Brave Blossom '!O93+'Brave Blossom '!O94)/K57,0) -> 22 | ... W52: =IF(W57>0,('Brave Blossom '!AA93+'Brave Blossom '!AA94)/W57,0) -> 22
B53: Other Costs (Carbon) | C53: AUD/t | D53: =IF(D57>0,('Brave Blossom '!H106)/D57,0) -> 32.006641 | E53: =IF(E57>0,('Brave Blossom '!I106)/E57,0) -> 25.521351 | F53: =IF(F57>0,('Brave Blossom '!J106)/F57,0) -> 12.162797 | G53: =IF(G57>0,('Brave Blossom '!K106)/G57,0) -> 13.237092 | H53: =IF(H57>0,('Brave Blossom '!L106)/H57,0) -> 14.355784 | I53: =IF(I57>0,('Brave Blossom '!M106)/I57,0) -> 15.518871 | J53: =IF(J57>0,('Brave Blossom '!N106)/J57,0) -> 16.029423 | K53: =IF(K57>0,('Brave Blossom '!O106)/K57,0) -> 16.539975 | ... W53: =IF(W57>0,('Brave Blossom '!AA106)/W57,0) -> 27.306502
B54: Royalty - Government Export | C54: AUD/t | D54: =IF(D57>0,('Brave Blossom '!H95)/D57,0) -> 55.122407 | E54: =IF(E57>0,('Brave Blossom '!I95)/E57,0) -> 56.756758 | F54: =IF(F57>0,('Brave Blossom '!J95)/F57,0) -> 58.354186 | G54: =IF(G57>0,('Brave Blossom '!K95)/G57,0) -> 59.915375 | H54: =IF(H57>0,('Brave Blossom '!L95)/H57,0) -> 61.441005 | I54: =IF(I57>0,('Brave Blossom '!M95)/I57,0) -> 62.931754 | J54: =IF(J57>0,('Brave Blossom '!N95)/J57,0) -> 64.388291 | K54: =IF(K57>0,('Brave Blossom '!O95)/K57,0) -> 65.811283 | ... W54: =IF(W57>0,('Brave Blossom '!AA95)/W57,0) -> 80.503475
B57: Total Sales Vol | D57: ='Brave Blossom '!H34 -> 81.432 | E57: ='Brave Blossom '!I34 -> 162.864 | F57: ='Brave Blossom '!J34 -> 5398.724 | G57: ='Brave Blossom '!K34 -> 5398.724 | H57: ='Brave Blossom '!L34 -> 5398.724 | I57: ='Brave Blossom '!M34 -> 5398.724 | J57: ='Brave Blossom '!N34 -> 5398.724 | K57: ='Brave Blossom '!O34 -> 5398.724 | ... W57: ='Brave Blossom '!AA34 -> 5168

Sheet Historical Performance
B3: Springbok Historical Performance | D3: 2021 | E3: 2022 | F3: 2023 | G3: 2024 | H3: 2025 | I3: FYF 2026
B4: PRODUCTION
B6: Development Metres | C6: m | D6: 18870.2 | E6: 17655.26 | F6: 16276.64 | G6: 18887.5 | H6: 14092.9 | I6: 17185.127
B7: ROM Production (kt) | C7: kt | D7: 5835.1904 | E7: 5207.3246 | F7: 6111.2246 | G7: 6109.0595 | H7: 5344.0865 | I7: 5943.705
B8: Operations Yield (%) | C8: % | D8: 0.65000435 | E8: 0.65130403 | F8: 0.68333809 | G8: 0.67876629 | H8: 0.69406896 | I8: 0.72284587
B9: Actual Saleable Production (kt) | C9: kt | D9: 3809.402 | E9: 3336.382 | F9: 4103.805 | G9: 4220.56 | H9: 3701.08 | I9: 4263.008
B11: CHPP
B12: Primary Feed Tonnes | C12: kt | D12: 5860.5792 | E12: 5122.6183 | F12: 6005.5265 | G12: 6217.9871 | H12: 5332.4385 | I12: 5897.5339
B13: Bypass Tonnes | C13: kt | D13: 0 | E13: 0 | F13: 0 | G13: 0 | H13: 0 | I13: 0
B14: Plant Product Tonnes | C14: kt | D14: 3809.402 | E14: 3336.382 | F14: 4103.805 | G14: 4220.56 | H14: 3701.08 | I14: 4263.008
B15: CHPP Yield | C15: % | D15: =D14/(D12+D13) -> 0.65000435 | E15: =E14/(E12+E13) -> 0.65130403 | F15: =F14/(F12+F13) -> 0.68333809 | G15: =G14/(G12+G13) -> 0.67876629 | H15: =H14/(H12+H13) -> 0.69406896 | I15: =I14/(I12+I13) -> 0.72284587
B17: Marketing
B18: PHCC | C18: kt | D18: 3780.3109 | E18: 3235.0999 | F18: 3994.1917 | G18: 4189.5997 | H18: 3356.1213 | I18: 4262.4299
B19: 88% PHCC | C19: kt
B20: Total Sales | C20: kt | D20: =SUM(D18:D19) -> 3780.3109 | E20: =SUM(E18:E19) -> 3235.0999 | F20: =SUM(F18:F19) -> 3994.1917 | G20: =SUM(G18:G19) -> 4189.5997 | H20: =SUM(H18:H19) -> 3356.1213 | I20: =SUM(I18:I19) -> 4262.4299
B22: Realised Price
B23: PHCC | C23: USD/t | D23: 295 | E23: 360 | F23: 345 | G23: 310 | H23: 300 | I23: 315
B24: 88% PHCC | C24: USD/t
B25: Average Export Realised Price | C25: USD/t
B27: Total Revenue | C27: USDk | D27: =SUMPRODUCT(D18:D19,D23:D24) -> 1115191.7 | E27: =SUMPRODUCT(E18:E19,E23:E24) -> 1164636 | F27: =SUMPRODUCT(F18:F19,F23:F24) -> 1377996.1 | G27: =SUMPRODUCT(G18:G19,G23:G24) -> 1298775.9 | H27: =SUMPRODUCT(H18:H19,H23:H24) -> 1006836.4 | I27: =SUMPRODUCT(I18:I19,I23:I24) -> 1342665.4
B28: FX | C28: USD:AUD | D28: 0.743 | E28: 0.694 | F28: 0.6646 | G28: 0.6629 | H28: 0.6306 | I28: 0.67
B29: Total Revenue | C29: AUD | D29: =D27/D28 -> 1500931 | E29: =E27/E28 -> 1678149.8 | F29: =F27/F28 -> 2073421.8 | G29: =G27/G28 -> 1959233.5 | H29: =H27/H28 -> 1596632.4 | I29: =I27/I28 -> 2003978.3
B30: Average Realisation | C30: AUD/t | D30: =IFERROR(D29/D9,0) -> 394.00698 | E30: =IFERROR(E29/E9,0) -> 502.98492 | F30: =IFERROR(F29/F9,0) -> 505.24374 | G30: =IFERROR(G29/G9,0) -> 464.21175 | H30: =IFERROR(H29/H9,0) -> 431.39635 | I30: =IFERROR(I29/I9,0) -> 470.0855
B33: PIT TOP COSTS
B35: LABOUR
B36: Roster Labour | C36: AUDk | D36: 47056.114 | E36: 48060.789 | F36: 69060.911 | G36: 76942.993 | H36: 75336.191 | I36: 80032.977
B37: Non Rostered Overtime | C37: AUDk | D37: 1681.8503 | E37: 2500.8709 | F37: 4953.1897 | G37: 5809.7424 | H37: 4013.871 | I37: 3573.1287
B38: Bonus | C38: AUDk | D38: 8535.7186 | E38: 7634.122 | F38: 12511.045 | G38: 15141.554 | H38: 14736.528 | I38: 14811.072
B39: Oncosts | C39: AUDk | D39: 19564.521 | E39: 16288.213 | F39: 33977.427 | G39: 37669.483 | H39: 37114.405 | I39: 31006.633
B40: Supplementary Labour | C40: AUDk | D40: 41000.054 | E40: 50376.88 | F40: 51764.529 | G40: 56992.705 | H40: 61400.365 | I40: 81378.813
B41: Capitalised Labour | C41: AUDk | D41: 0 | E41: 0 | F41: 0 | G41: 0 | H41: 0 | I41: 0
B42: Labour Costs / Eq Saleable | C42: AUDk | D42: =SUM(D36:D41) -> 117838.26 | E42: =SUM(E36:E41) -> 124860.88 | F42: =SUM(F36:F41) -> 172267.1 | G42: =SUM(G36:G41) -> 192556.48 | H42: =SUM(H36:H41) -> 192601.36 | I42: =SUM(I36:I41) -> 210802.62
B44: REPAIRS/MAINTENANCE
B45: Electrical Parts | C45: AUDk | D45: 9965.8191 | E45: 11877.628 | F45: 14718.803 | G45: 15671.795 | H45: 15891.335 | I45: 13435.994
B46: Mechanical Parts | C46: AUDk | D46: 28328.866 | E46: 20948.204 | F46: 28955.942 | G46: 35206.732 | H46: 31237.773 | I46: 31457.78
B47: Major Rebuilds | C47: AUDk | D47: 26852.738 | E47: 24931.614 | F47: 25186.147 | G47: 31547.04 | H47: 39030.647 | I47: 34935.981
B48: Outside Mech/Elect Repairs | C48: AUDk | D48: 17235.525 | E48: 9755.3986 | F48: 15146.939 | G48: 18187.025 | H48: 15584.941 | I48: 12582.757
B49: Maintenance Agreements | C49: AUDk | D49: 3191.9474 | E49: 3217.5357 | F49: 4460.6962 | G49: 5460.6453 | H49: 4052.5299 | I49: 5494.2062
B50: Repairs/Maintenance / Eq Saleable | C50: AUDk | D50: =SUM(D45:D49) -> 85574.896 | E50: =SUM(E45:E49) -> 70730.381 | F50: =SUM(F45:F49) -> 88468.528 | G50: =SUM(G45:G49) -> 106073.24 | H50: =SUM(H45:H49) -> 105797.23 | I50: =SUM(I45:I49) -> 97906.719
B52: CONSUMABLES
B53: Explosives | C53: AUDk | D53: 18.7772 | E53: 40.7283 | F53: 45.3799 | G53: 228.4855 | H53: 148.5753 | I53: 337.5152
B54: Tyres | C54: AUDk | D54: 1073.5635 | E54: 1055.4261 | F54: 1457.5299 | G54: 1308.8924 | H54: 1356.0306 | I54: 1171.2334
B55: Ground Engaging Tools | C55: AUDk | D55: 3998.45 | E55: 2315.0953 | F55: 2957.384 | G55: 7107.48 | H55: 8620.632 | I55: 7464.475
B56: Lubricants | C56: AUDk | D56: 2427.3909 | E56: 3532.7408 | F56: 3451.5371 | G56: 3983.1065 | H56: 3839.7272 | I56: 3894.9561
B57: Ropes and Rigging | C57: AUDk | D57: 303.7728 | E57: 273.2385 | F57: 209.8963 | G57: 245.0584 | H57: 244.054 | I57: 264.4876
B58: Concrete | C58: AUDk | D58: 405.8607 | E58: 463.511 | F58: 442.6505 | G58: 946.4025 | H58: 448.9826 | I58: 479.0482
B59: Roof Support | C59: AUDk | D59: 12401.05 | E59: 15708.221 | F59: 14089.356 | G59: 18534.293 | H59: 14905.83 | I59: 18657.272
B60: Other | C60: AUDk | D60: 18728.936 | E60: 20039.896 | F60: 24574.345 | G60: 26413.993 | H60: 26253.065 | I60: 26028.116
B61: Consumables / Eq Saleable | C61: AUDk | D61: =SUM(D53:D60) -> 39357.801 | E61: =SUM(E53:E60) -> 43428.857 | F61: =SUM(F53:F60) -> 47228.08 | G61: =SUM(G53:G60) -> 58767.711 | H61: =SUM(H53:H60) -> 55816.897 | I61: =SUM(I53:I60) -> 58297.104
B63: ENERGY COSTS
B64: Diesel | C64: AUDk | D64: 6356.8522 | E64: 9077.3091 | F64: 7331.2206 | G64: 8018.061 | H64: 6085.6392 | I64: 15378.726
B65: Electricity | C65: AUDk | D65: 5390.3299 | E65: 10821.93 | F65: 11654.576 | G65: 8736.0316 | H65: 6013.4243 | I65: 10196.788
B66: Energy / Eq Saleable | C66: AUDk | D66: =SUM(D64:D65) -> 11747.182 | E66: =SUM(E64:E65) -> 19899.239 | F66: =SUM(F64:F65) -> 18985.797 | G66: =SUM(G64:G65) -> 16754.093 | H66: =SUM(H64:H65) -> 12099.064 | I66: =SUM(I64:I65) -> 25575.513
B68: OTHER EXPENSES
B69: Contract Services | C69: AUDk | D69: 82087.117 | E69: 54550.192 | F69: 47185.167 | G69: 61402.362 | H69: 66959.562 | I69: 49131.168
B70: Plant Hire | C70: AUDk | D70: 9726.8507 | E70: 12981.243 | F70: 14096.701 | G70: 7830.3116 | H70: 7817.7935 | I70: 14870.139
B71: Safety / Training / Bathhouse | C71: AUDk | D71: 1117.276 | E71: 1283.5057 | F71: 1448.4872 | G71: 1606.9705 | H71: 1944.8257 | I71: 1197.6802
B72: Clothing and Protective Equipment | C72: AUDk | D72: 1900.4094 | E72: 1720.3171 | F72: 2110.8415 | G72: 1482.9968 | H72: 2390.1839 | I72: 1884.1478
B73: Freight | C73: AUDk | D73: 0.0966 | E73: 48.4548 | F73: 1.9457 | G73: 33.9241 | H73: 522.3591 | I73: 881.8315
B74: General Expenses | C74: AUDk | D74: 8317.9677 | E74: 9663.5439 | F74: 13449.894 | G74: 11958.457 | H74: 13814.796 | I74: 11972.575
B75: Capitalised Operating Costs (excluding Labour) | C75: AUDk | D75: 0 | E75: 0 | F75: 0 | G75: 0 | H75: 0 | I75: 0
B76: Other Expenses / Eq Saleable | C76: AUDk | D76: =SUM(D69:D75) -> 103149.72 | E76: =SUM(E69:E75) -> 80247.257 | F76: =SUM(F69:F75) -> 78293.037 | G76: =SUM(G69:G75) -> 84315.022 | H76: =SUM(H69:H75) -> 93449.52 | I76: =SUM(I69:I75) -> 79937.541
B78: TOTAL PIT-TOP COSTS | C78: AUDk | D78: =D76+D66+D61+D50+D42 -> 357667.85 | E78: =E76+E66+E61+E50+E42 -> 339166.61 | F78: =F76+F66+F61+F50+F42 -> 405242.54 | G78: =G76+G66+G61+G50+G42 -> 458466.54 | H78: =H76+H66+H61+H50+H42 -> 459764.07 | I78: =I76+I66+I61+I50+I42 -> 472519.5
B80: OTHER EXPENSES
B81: Contract Services | D81: 82087.117 | E81: 54550.192 | F81: 47185.167 | G81: 61402.362 | H81: 66959.562 | I81: 49131.168
B82: Plant Hire | C82: AUDk | D82: 9726.8507 | E82: 12981.243 | F82: 14096.701 | G82: 7830.3116 | H82: 7817.7935 | I82: 14870.139
B83: Safety / Training / Bathhouse | D83: 1117.276 | E83: 1283.5057 | F83: 1448.4872 | G83: 1606.9705 | H83: 1944.8257 | I83: 1197.6802
B84: Clothing and Protective Equipment | D84: 1900.4094 | E84: 1720.3171 | F84: 2110.8415 | G84: 1482.9968 | H84: 2390.1839 | I84: 1884.1478
B85: Freight | D85: 0.0966 | E85: 48.4548 | F85: 1.9457 | G85: 33.9241 | H85: 522.3591 | I85: 881.8315
B86: General Expenses | C86: AUDk | D86: 8317.9677 | E86: 9663.5439 | F86: 13449.894 | G86: 11958.457 | H86: 13814.796 | I86: 11972.575
B87: CHPP Toll Wash | C87: AUDk | D87: 0 | E87: 0 | F87: 0 | G87: 0 | H87: 0 | I87: 0
B88: Capitalised Operating Costs (excluding Labour) | D88: 0 | E88: 0 | F88: 0 | G88: 0 | H88: 0 | I88: 0
B89: Other Expenses / Actual Saleable | C89: AUDk | D89: =SUM(D81:D88) -> 103149.72 | E89: =SUM(E81:E88) -> 80247.257 | F89: =SUM(F81:F88) -> 78293.037 | G89: =SUM(G81:G88) -> 84315.022 | H89: =SUM(H81:H88) -> 93449.52 | I89: =SUM(I81:I88) -> 79937.541
B91: TOTAL CHPP COSTS | C91: AUDk | D91: =D89 -> 103149.72 | E91: =E89 -> 80247.257 | F91: =F89 -> 78293.037 | G91: =G89 -> 84315.022 | H91: =H89 -> 93449.52 | I91: =I89 -> 79937.541
B93: OVERHEADS
B94: OVERHEAD
B95: Labour | C95: AUDk | D95: 7082.8198 | E95: 7355.6551 | F95: 9207.0417 | G95: 10566.874 | H95: 11333.452 | I95: 11878.397
B96: Supplementary Labour | C96: AUDk | D96: 489.1809 | E96: 2257.4125 | F96: 2515.7053 | G96: 2126.2489 | H96: 1412.1474 | I96: 2230.508
B97: Contract Services | C97: AUDk | D97: 5320.2802 | E97: 4641.6007 | F97: 4209.7739 | G97: 728.3162 | H97: 132.882 | I97: 899.9729
B98: Group Coal Australia/Asia Technical Consulting Recharge | C98: AUDk | D98: 3450.9867 | E98: 4519.3981 | F98: 5487.1504 | G98: 6023.319 | H98: 6142.2062 | I98: 6097.719
B99: Group Coal Australia/Asia Management Fee | C99: AUDk | D99: 3148.2438 | E99: 3035.2759 | F99: 3287.9131 | G99: 3787.3747 | H99: 4427.2001 | I99: 4221.133
B100: Technical Consulting | C100: AUDk | D100: 313.6614 | E100: 511.1603 | F100: 1089.9891 | G100: 962.7523 | H100: 1082.5169 | I100: 947.7357
B101: Administration | C101: AUDk | D101: 2652.7202 | E101: 3849.5345 | F101: 4895.9762 | G101: 6074.1569 | H101: 5755.0063 | I101: 5923.1795
B102: Govt/Statutory Fees & Charges | C102: AUDk | D102: 6909.8637 | E102: 6192.9181 | F102: 6678.3966 | G102: 8204.0056 | H102: 8567.6016 | I102: 8698.8563
B103: Insurance | C103: AUDk | D103: 11158.417 | E103: 14335.433 | F103: 16616.587 | G103: 15182.885 | H103: 15537.319 | I103: 16239.907
B104: Legal Expenses | C104: AUDk | D104: 408.9728 | E104: 463.8655 | F104: 214.056 | G104: 474.7845 | H104: 1236.7454 | I104: 1191.1047
B105: Management & Advisory Fees & Recharges | C105: AUDk | D105: 200.8685 | E105: 281.7557 | F105: 270.0001 | G105: 299.9531 | H105: 309.3426 | I105: 300.0001
B106: Other Income / Complex Recharges | C106: AUDk | D106: -37.5424 | E106: -54.2189 | F106: -539.1893 | G106: -152.6743 | H106: -2321.9998 | I106: -126.2453
... B108: Capitalised Overhead Costs | C108: AUDk | D108: 0 | E108: 0 | F108: 0 | G108: 0 | H108: 0 | I108: 0
B109: Overhead / Eq Saleable | C109: AUDk | D109: =SUM(D95:D108) -> 45778.216 | E109: =SUM(E95:E108) -> 55350.365 | F109: =SUM(F95:F108) -> 66029.241 | G109: =SUM(G95:G108) -> 62812.1 | H109: =SUM(H95:H108) -> 60593.958 | I109: =SUM(I95:I108) -> 66122.791
B111: TOWNSHIP AND SPA
B112: Township and Spa | C112: AUDk | D112: 7589 | E112: 8852 | F112: 8893 | G112: 9128 | H112: 9673 | I112: 9674
B114: TOTAL OVERHEAD COSTS | C114: AUDk | D114: =D109+D112 -> 53367.216 | E114: =E109+E112 -> 64202.365 | F114: =F109+F112 -> 74922.241 | G114: =G109+G112 -> 71940.1 | H114: =H109+H112 -> 70266.958 | I114: =I109+I112 -> 75796.791
B115: FOR CASH COST (After Cap) | C115: AUDk | D115: =D112+D109+D91+D78-D108-D88-D75 -> 514184.79 | E115: =E112+E109+E91+E78 -> 483616.23 | F115: =F112+F109+F91+F78 -> 558457.82 | G115: =G112+G109+G91+G78 -> 614721.66 | H115: =H112+H109+H91+H78 -> 623480.54 | I115: =I112+I109+I91+I78 -> 628253.83
B116: FOR CASH COST (Before Cap) | C116: AUDk | D116: =D112+D109+D91+D78 -> 514184.79 | E116: =E112+E109+E91+E78 -> 483616.23 | F116: =F112+F109+F91+F78 -> 558457.82 | G116: =G112+G109+G91+G78 -> 614721.66 | H116: =H112+H109+H91+H78 -> 623480.54 | I116: =I112+I109+I91+I78 -> 628253.83
B117: FOR Cost/t | C117: AUD/t | D117: =D116/D9 -> 134.97782 | E117: =E116/E9 -> 144.9523 | F117: =F116/F9 -> 136.08293 | G117: =G116/G9 -> 145.64931 | H117: =H116/H9 -> 168.45908 | I117: =I116/I9 -> 147.37336
B119: Total Port, Rail and Selling Costs | C119: AUDk | D119: 226776.33 | E119: 353258.47 | F119: 513003.73 | G119: 405286.98 | H119: 242227.24 | I119: 357444.18
B120: Government Royalty | C120: AUDk | D120: =D159*D20 -> 159759.97 | E120: =E159*E20 -> 167664.02 | F120: =F159*F20 -> 392006.94 | G120: =G159*G20 -> 382014.07 | H120: =H159*H20 -> 285215.39 | I120: =I159*I20 -> 411610.5
B121: Total Direct Selling Expenses | C121: AUDk | D121: =D119+D120 -> 386536.31 | E121: =E119+E120 -> 520922.49 | F121: =F119+F120 -> 905010.67 | G121: =G119+G120 -> 787301.05 | H121: =H119+H120 -> 527442.63 | I121: =I119+I120 -> 769054.68
B123: Total FOB Costs | C123: AUDk | D123: =D115+D121 -> 900721.09 | E123: =E115+E121 -> 1004538.7 | F123: =F115+F121 -> 1463468.5 | G123: =G115+G121 -> 1402022.7 | H123: =H115+H121 -> 1150923.2 | I123: =I115+I121 -> 1397308.5
...

Sheet Springbok Assumptions
B1: Current | C1: Proposed
A3: Roster - Longwall | B3: 7on7off | C3: 7on7off
A4: Roster - Development | B4: 7on7off | C4: 5on2off
A5: Roster - Outbye | B5: 7on7off | C5: 7on7off
A6: Development Miners | B6: 3 | C6: 4
A7: Gas Drainage Strategy | B7: SIS | C7: UIS
A8: Wash Strategy | B8: Max Quality | C8: Max Quality
A9: Progressive Rehabilitation | B9: Yes | C9: No
A10: Maintenance Strategy | B10: Preventative Maintenance | C10: Corrective Maintenance

Sheet Springbok
D1: 2 | E1: =+D1+1 -> 3 | F1: =+E1+1 -> 4 | G1: =+F1+1 -> 5 | H1: =+G1+1 -> 6 | I1: =+H1+1 -> 7 | J1: =+I1+1 -> 8 | K1: =+J1+1 -> 9 | L1: =+K1+1 -> 10 | ... AD1: =+AC1+1 -> 28
A2: Springbok Complex | D2: =Assumptions!J1 -> 2027 | E2: =D2+1 -> 2028 | F2: =E2+1 -> 2029 | G2: =F2+1 -> 2030 | H2: =G2+1 -> 2031 | I2: =H2+1 -> 2032 | J2: =I2+1 -> 2033 | K2: =J2+1 -> 2034 | L2: =K2+1 -> 2035 | ... AD2: =AC2+1 -> 2053 | AF2: Total | AH2: Valuation Summary
A3: Physicals | AH3: Net Present Value (AUDM) | AI3: =AF124/1000 -> 279.44569
V4: =V6*5.5*3.55*1.45 -> 0 | W4: =W6*5.5*3.55*1.45 -> 0 | Z4: =Z6*5.5*3.55*1.45 -> 0 | AA4: =AA6*5.5*3.55*1.45 -> 0 | AC4: =AC6*5.5*3.55*1.45 -> 0 | AD4: =AD6*5.5*3.55*1.45 -> 0
A5: Mining
A6: Development Metres | B6: m | D6: 9000 | E6: 15000 | F6: 15000 | G6: 8000 | H6: 2000 | I6: 0 | J6: 0 | K6: 0 | L6: 0 | M6: 0 | N6: 0 | O6: 0 | P6: 0 | Q6: 0 | R6: 0 | S6: 0 | T6: 0 | U6: 0 | V6: 0 | W6: 0 | X6: 0 | Y6: 0 | Z6: 0 | AA6: 0 | AB6: 0 | AC6: 0 | AD6: 0 | AF6: =SUM(D6:AD6) -> 49000 | AH6: Sensitivities Table
A7: Development Tonnes | B7: kt | D7: =(3*5.2*1.45*D6)/1000 -> 203.58 | E7: =(3*5.2*1.45*E6)/1000 -> 339.3 | F7: =(3*5.2*1.45*F6)/1000 -> 339.3 | G7: =(3*5.2*1.45*G6)/1000 -> 180.96 | H7: =(3*5.2*1.45*H6)/1000 -> 45.24 | I7: =(3*5.2*1.45*I6)/1000 -> 0 | J7: =(3*5.2*1.45*J6)/1000 -> 0 | K7: =(3*5.2*1.45*K6)/1000 -> 0 | ... AD7: =(3*5.2*1.45*AD6)/1000 -> 0 | AF7: =SUM(D7:AD7) -> 1108.38 | AH7: Sales Price | AI7: 0
A8: Longwall Tonnes | B8: kt | D8: 4987.7897 | E8: 5323.8386 | F8: 5648.744 | G8: 5587.808 | H8: 5200.6922 | K8: 0 | L8: 0 | M8: 0 | N8: 0 | O8: 0 | P8: 0 | Q8: 0 | R8: 0 | S8: 0 | T8: 0 | U8: 0 | V8: 0 | W8: 0 | X8: 0 | Y8: 0 | Z8: 0 | AA8: 0 | AB8: 0 | AC8: 0 | AD8: 0 | AF8: =SUM(D8:AD8) -> 26748.873 | AH8: Development Costs | AI8: 0
A9: Total ROM production | B9: kt | D9: =D7+D8 -> 5191.3697 | E9: =E7+E8 -> 5663.1386 | F9: =F7+F8 -> 5988.044 | G9: =G7+G8 -> 5768.768 | H9: =H7+H8 -> 5245.9322 | K9: =K7+K8 -> 0 | L9: =L7+L8 -> 0 | M9: =M7+M8 -> 0 | N9: =N7+N8 -> 0 | O9: =O7+O8 -> 0 | P9: =P7+P8 -> 0 | Q9: =Q7+Q8 -> 0 | R9: =R7+R8 -> 0 | ... AD9: =AD7+AD8 -> 0 | AF9: =SUM(C9:AD9) -> 27857.253 | AH9: Longwall Costs | AI9: 0
D10: =D6/D8 -> 1.8044065 | E10: =E6/E8 -> 2.8175159 | F10: =F6/F8 -> 2.6554576 | G10: =G6/G8 -> 1.4316884 | H10: =H6/H8 -> 0.38456419 | AH10: Outbye Costs | AI10: 0
A11: CHPP | AH11: Gas Drainage Costs | AI11: 0
A12: Primary Feed Tonnes | B12: kt | D12: =D9 -> 5191.3697 | E12: =E9 -> 5663.1386 | F12: =F9 -> 5988.044 | G12: =G9 -> 5768.768 | H12: =H9 -> 5245.9322 | I12: =I9 -> 0 | J12: =J9 -> 0 | K12: =K9 -> 0 | ... AD12: =AD9 -> 0 | AF12: =SUM(C12:AD12) -> 27857.253 | AH12: CHPP Costs | AI12: 0
A13: Bypass Tonnes | B13: kt | D13: 0 | E13: 0 | F13: 0 | G13: 0 | H13: 0 | I13: 0 | J13: 0 | K13: 0 | L13: 0 | M13: 0 | N13: 0 | O13: 0 | P13: 0 | Q13: 0 | R13: 0 | S13: 0 | T13: 0 | U13: 0 | V13: 0 | W13: 0 | X13: 0 | Y13: 0 | Z13: 0 | AA13: 0 | AB13: 0 | AC13: 0 | AD13: 0 | AF13: =SUM(C13:AD13) -> 0 | AH13: Total Overhead Costs | AI13: 0
A14: Plant Product Tonnes | B14: kt | D14: =D12*$C$15 -> 3478.2177 | E14: =E12*$C$15 -> 3794.3029 | F14: =F12*$C$15 -> 4011.9895 | G14: =G12*$C$15 -> 3865.0746 | H14: =H12*$C$15 -> 3514.7746 | I14: =I12*$C$15 -> 0 | J14: =J12*$C$15 -> 0 | K14: =K12*$C$15 -> 0 | ... AD14: =AD12*$C$15 -> 0 | AF14: =SUM(C14:AD14) -> 18664.359 | AH14: Total Capital Costs | AI14: 0
A15: CHPP Yield | B15: % | C15: 0.67 | D15: =IFERROR(D14/D12,0) -> 0.67 | E15: =IFERROR(E14/E12,0) -> 0.67 | F15: =IFERROR(F14/F12,0) -> 0.67 | G15: =IFERROR(G14/G12,0) -> 0.67 | H15: =IFERROR(H14/H12,0) -> 0.67 | I15: =IFERROR(I14/I12,0) -> 0 | J15: =IFERROR(J14/J12,0) -> 0 | K15: =IFERROR(K14/K12,0) -> 0 | ... AD15: =IFERROR(AD14/AD12,0) -> 0 | AF15: =IFERROR(AF14/AF12,0) -> 0.67
AH16: LOM volumes
A17: Operations Yield | D17: =IFERROR(D19/D9,0) -> 0.67 | E17: =IFERROR(E19/E9,0) -> 0.67 | F17: =IFERROR(F19/F9,0) -> 0.67 | G17: =IFERROR(G19/G9,0) -> 0.67 | H17: =IFERROR(H19/H9,0) -> 0.67 | I17: =IFERROR(I19/(I9+H9),0) -> 0 | J17: =IFERROR(J19/(J9+I9),0) -> 0 | K17: =IFERROR(K19/K9,0) -> 0 | L17: =IFERROR(L19/L9,0) -> 0 | M17: =IFERROR(M19/M9,0) -> 0 | N17: =IFERROR(N19/N9,0) -> 0 | O17: =IFERROR(O19/O9,0) -> 0 | P17: =IFERROR(P19/P9,0) -> 0 | Q17: =IFERROR(Q19/Q9,0) -> 0 | R17: =IFERROR(R19/R9,0) -> 0 | ... AD17: =IFERROR(AD19/AD9,0) -> 0 | AF17: =IFERROR(AF19/AF9,0) -> 0.67 | AH17: Development metres (km) | AI17: =AF6/1000 -> 49
AH18: Longwall ROM tonnes / Dev Metres | AI18: =(AI17*1000)/AI20 -> 1.8318529
A19: Saleable Production | B19: kt | D19: =D13+D14 -> 3478.2177 | E19: =E13+E14 -> 3794.3029 | F19: =F13+F14 -> 4011.9895 | G19: =G13+G14 -> 3865.0746 | H19: =H13+H14 -> 3514.7746 | I19: =I13+I14 -> 0 | J19: =J13+J14 -> 0 | K19: =K13+K14 -> 0 | ... AD19: =AD13+AD14 -> 0 | AF19: =SUM(C19:AD19) -> 18664.359 | AH19: Development ROM (kt) | AI19: =AF7 -> 1108.38
AH20: Longwall ROM (kt) | AI20: =AF8 -> 26748.873
A21: Carbon | AH21: Total ROM (kt) | AI21: =AI19+AI20 -> 27857.253
A22: Coal Mine Waste Gass | B22: t CO2e | C22: 0.12 | D22: =IF(D9>0,D9*1000*$C$22+20000,0) -> 642964.37 | E22: =IF(E9>0,E9*1000*$C$22+20000,0) -> 699576.64 | F22: =IF(F9>0,F9*1000*$C$22+20000,0) -> 738565.28 | G22: =IF(G9>0,G9*1000*$C$22+20000,0) -> 712252.16 | H22: =IF(H9>0,H9*1000*$C$22+20000,0) -> 649511.87 | I22: =IF(I9>0,I9*1000*$C$22+20000,0) -> 0 | J22: =IF(J9>0,J9*1000*$C$22+20000,0) -> 0 | K22: =IF(K9>0,K9*1000*$C$22+20000,0) -> 0 | ... AD22: =IF(AD9>0,AD9*1000*$C$22+20000,0) -> 0 | AF22: =SUM(D22:AD22) -> 3442870.3
A23: Decomission Mines Emissions | B23: t CO2e | C23: Look @ Decom Mines Tab | D23: =IF('Decommissioned Mine'!$B$5="Springbok",'Decommissioned Mine'!E2,IF('Decommissioned Mine'!$B$5="Springbok + Brave Blossom",0,IF('Decommissioned Mine'!$B$5="Springbok Delayed 12 Months",'Decommissioned Mine'!E2,0))) -> 0 | E23: =IF('Decommissioned Mine'!$B$5="Springbok",'Decommissioned Mine'!F2,IF('Decommissioned Mine'!$B$5="Springbok + Brave Blossom",0,IF('Decommissioned Mine'!$B$5="Springbok Delayed 12 Months",'Decommissioned Mine'!F2,0))) -> 0 | F23: =IF('Decommissioned Mine'!$B$5="Springbok",'Decommissioned Mine'!G2,IF('Decommissioned Mine'!$B$5="Springbok + Brave Blossom",0,IF('Decommissioned Mine'!$B$5="Springbok Delayed 12 Months",'Decommissioned Mine'!G2,0))) -> 0 | G23: =IF('Decommissioned Mine'!$B$5="Springbok",'Decommissioned Mine'!H2,IF('Decommissioned Mine'!$B$5="Springbok + Brave Blossom",0,IF('Decommissioned Mine'!$B$5="Springbok Delayed 12 Months",'Decommissioned Mine'!H2,0))) -> 0 | H23: =IF('Decommissioned Mine'!$B$5="Springbok",'Decommissioned Mine'!I2,IF('Decommissioned Mine'!$B$5="Springbok + Brave Blossom",0,IF('Decommissioned Mine'!$B$5="Springbok Delayed 12 Months",'Decommissioned Mine'!I2,0))) -> 0 | I23: =IF('Decommissioned Mine'!$B$5="Springbok",'Decommissioned Mine'!J2,IF('Decommissioned Mine'!$B$5="Springbok + Brave Blossom",0,IF('Decommissioned Mine'!$B$5="Springbok Delayed 12 Months",'Decommissioned Mine'!J2,0))) -> 0 | J23: =IF('Decommissioned Mine'!$B$5="Springbok",'Decommissioned Mine'!K2,IF('Decommissioned Mine'!$B$5="Springbok + Brave Blossom",0,IF('Decommissioned Mine'!$B$5="Springbok Delayed 12 Months",'Decommissioned Mine'!K2,0))) -> 0 | K23: =IF('Decommissioned Mine'!$B$5="Springbok",'Decommissioned Mine'!L2,IF('Decommissioned Mine'!$B$5="Springbok + Brave Blossom",0,IF('Decommissioned Mine'!$B$5="Springbok Delayed 12 Months",'Decommissioned Mine'!L2,0))) -> 0 | ... AD23: =IF('Decommissioned Mine'!$B$5="Springbok",'Decommissioned Mine'!AE2,IF('Decommissioned Mine'!$B$5="Springbok + Brave Blossom",0,IF('Decommissioned Mine'!$B$5="Springbok Delayed 12 Months",'Decommissioned Mine'!AE2,0))) -> 0 | AF23: =SUM(D23:AD23) -> 0 | AH23: Remaining Mine Life | AI23: 5
A24: Total Scope 1 Emissions | B24: t CO2e | D24: =D23+D22 -> 642964.37 | E24: =E23+E22 -> 699576.64 | F24: =F23+F22 -> 738565.28 | G24: =G23+G22 -> 712252.16 | H24: =H23+H22 -> 649511.87 | I24: =I23+I22 -> 0 | J24: =J23+J22 -> 0 | K24: =K23+K22 -> 0 | ... AD24: =AD23+AD22 -> 0 | AF24: =SUM(D24:AD24) -> 3442870.3
A25: Safeguard - Hybrid Declining Baseline | B25: t CO2e | D25: =(D9*1000*'Decommissioned Mine'!E22)+'Decommissioned Mine'!E21*D23 -> 426048.29 | E25: =(E9*1000*'Decommissioned Mine'!F22)+'Decommissioned Mine'!F21*E23 -> 413564.91 | F25: =(F9*1000*'Decommissioned Mine'!G22)+'Decommissioned Mine'!G21*F23 -> 386275.6 | G25: =(G9*1000*'Decommissioned Mine'!H22)+'Decommissioned Mine'!H21*G23 -> 339600.7 | H25: =(H9*1000*'Decommissioned Mine'!I22)+'Decommissioned Mine'!I21*H23 -> 292984.94 | I25: =(I9*1000*'Decommissioned Mine'!J22)+'Decommissioned Mine'!J21*I23 -> 0 | J25: =(J9*1000*'Decommissioned Mine'!K22)+'Decommissioned Mine'!K21*J23 -> 0 | K25: =(K9*1000*'Decommissioned Mine'!L22)+'Decommissioned Mine'!L21*K23 -> 0 | ... AD25: =(AD9*1000*'Decommissioned Mine'!AE22)+'Decommissioned Mine'!AE21*AD23 -> 0
A26: Emissions above (or below) baseline | B26: t CO2e | D26: =D24-D25 -> 216916.08 | E26: =E24-E25 -> 286011.72 | F26: =F24-F25 -> 352289.68 | G26: =G24-G25 -> 372651.47 | H26: =H24-H25 -> 356526.93 | I26: =I24-I25 -> 0 | J26: =J24-J25 -> 0 | K26: =K24-K25 -> 0 | ... AD26: =AD24-AD25 -> 0
AE27: =AE23/1000 -> 0
A28: Marketing
A30: Sales
A31: PHCC | B31: kt | D31: =D19 -> 3478.2177 | E31: =E19 -> 3794.3029 | F31: =F19 -> 4011.9895 | G31: =G19 -> 3865.0746 | H31: =H19 -> 3514.7746 | I31: =I19 -> 0 | J31: =J19 -> 0 | K31: =K19 -> 0 | ... AD31: =AD19 -> 0 | AF31: =SUM(C31:AD31) -> 18664.359
A32: 88% PHCC | B32: kt | D32: 0 | E32: 0 | F32: 0 | G32: 0 | H32: 0 | I32: 0 | J32: 0 | K32: 0 | L32: 0 | M32: 0 | N32: 0 | O32: 0 | P32: 0 | Q32: 0 | R32: 0 | S32: 0 | T32: 0 | U32: 0 | V32: 0 | W32: 0 | X32: 0 | Y32: 0 | Z32: 0 | AA32: 0 | AB32: 0 | AC32: 0 | AD32: 0 | AF32: =SUM(C32:AD32) -> 0
A33: Thermal GCN | B33: kt | D33: 0 | E33: 0 | F33: 0 | G33: 0 | H33: 0 | I33: 0 | J33: 0 | K33: 0 | L33: 0 | M33: 0 | N33: 0 | O33: 0 | P33: 0 | Q33: 0 | R33: 0 | S33: 0 | T33: 0 | U33: 0 | V33: 0 | W33: 0 | X33: 0 | Y33: 0 | Z33: 0 | AA33: 0 | AB33: 0 | AC33: 0 | AD33: 0 | AF33: =SUM(C33:AD33) -> 0
A34: Total Sales | B34: kt | D34: =SUM(D31:D33) -> 3478.2177 | E34: =SUM(E31:E33) -> 3794.3029 | F34: =SUM(F31:F33) -> 4011.9895 | G34: =SUM(G31:G33) -> 3865.0746 | H34: =SUM(H31:H33) -> 3514.7746 | I34: =SUM(I31:I33) -> 0 | J34: =SUM(J31:J33) -> 0 | K34: =SUM(K31:K33) -> 0 | ... AD34: =SUM(AD31:AD33) -> 0 | AE34: =SUM(AE31:AE32) -> 0 | AF34: =SUM(AF31:AF32) -> 18664.359
A36: Product Ash (as received)
A37: =$A$31 -> PHCC | B37: % | D37: 0.095 | E37: 0.095 | F37: 0.095 | G37: 0.095 | H37: 0.095 | I37: 0.095 | J37: 0.095 | K37: 0.095 | L37: 0.095 | M37: 0.095 | N37: 0.095 | O37: 0.095 | P37: 0.095 | Q37: 0.095 | R37: 0.095 | S37: 0.095 | T37: 0.095 | U37: 0.095 | V37: 0.095 | W37: 0.095 | X37: 0.095 | Y37: 0.095 | Z37: 0.095 | AA37: 0.095 | AB37: 0.095 | AC37: 0.095 | AD37: 0.095
A38: =$A$32 -> 88% PHCC | B38: % | D38: 0 | E38: 0 | F38: 0 | G38: 0 | H38: 0 | I38: 0 | J38: 0 | K38: 0 | L38: 0 | M38: 0 | N38: 0 | O38: 0 | P38: 0 | Q38: 0 | R38: 0 | S38: 0 | T38: 0 | U38: 0 | V38: 0 | W38: 0 | X38: 0 | Y38: 0 | Z38: 0 | AA38: 0 | AB38: 0 | AC38: 0 | AD38: 0
A39: Thermal GCN | B39: % | D39: 0 | E39: 0 | F39: 0 | G39: 0 | H39: 0 | I39: 0 | J39: 0 | K39: 0 | L39: 0 | M39: 0 | N39: 0 | O39: 0 | P39: 0 | Q39: 0 | R39: 0 | S39: 0 | T39: 0 | U39: 0 | V39: 0 | W39: 0 | X39: 0 | Y39: 0 | Z39: 0 | AA39: 0 | AB39: 0 | AC39: 0 | AD39: 0
A41: Product Energy (gar)
A42: =$A$31 -> PHCC | B42: kcal/kg(gar) | D42: 6314.0456 | E42: 6296.3229 | F42: 6328.7077 | G42: 6280.3566 | H42: 6305.4267
A43: =$A$32 -> 88% PHCC | B43: kcal/kg(gar) | D43: 0 | E43: 0 | F43: 0 | G43: 0 | H43: 0 | I43: 0 | J43: 0 | K43: 0 | L43: 0 | M43: 0 | N43: 0 | O43: 0 | P43: 0 | Q43: 0 | R43: 0 | S43: 0 | T43: 0 | U43: 0 | V43: 0 | W43: 0 | X43: 0 | Y43: 0 | Z43: 0 | AA43: 0 | AB43: 0 | AC43: 0 | AD43: 0
A44: Thermal GCN | B44: kcal/kg(gar) | D44: 0 | E44: 0 | F44: 0 | G44: 0 | H44: 0 | I44: 0 | J44: 0 | K44: 0 | L44: 0 | M44: 0 | N44: 0 | O44: 0 | P44: 0 | Q44: 0 | R44: 0 | S44: 0 | T44: 0 | U44: 0 | V44: 0 | W44: 0 | X44: 0 | Y44: 0 | Z44: 0 | AA44: 0 | AB44: 0 | AC44: 0 | AD44: 0
A46: GAR-> NAR adjustment | D46: =Assumptions!$B$16 -> 260 | E46: =Assumptions!$B$16 -> 260 | F46: =Assumptions!$B$16 -> 260 | G46: =Assumptions!$B$16 -> 260 | H46: =Assumptions!$B$16 -> 260 | I46: =Assumptions!$B$16 -> 260 | J46: =Assumptions!$B$16 -> 260 | K46: =Assumptions!$B$16 -> 260 | ... AD46: =Assumptions!$B$16 -> 260
A47: Basis of coal prices | D47: =Assumptions!$B$17 -> 6000 | E47: =Assumptions!$B$17 -> 6000 | F47: =Assumptions!$B$17 -> 6000 | G47: =Assumptions!$B$17 -> 6000 | H47: =Assumptions!$B$17 -> 6000 | I47: =Assumptions!$B$17 -> 6000 | J47: =Assumptions!$B$17 -> 6000 | K47: =Assumptions!$B$17 -> 6000 | ... AD47: =Assumptions!$B$17 -> 6000
A49: Product Energy (nar)
A50: =$A$31 -> PHCC | B50: kcal/kg(nar) | D50: =IF(D31>0,D42-D$46,0) -> 6054.0456 | E50: =IF(E31>0,E42-E$46,0) -> 6036.3229 | F50: =IF(F31>0,F42-F$46,0) -> 6068.7077 | G50: =IF(G31>0,G42-G$46,0) -> 6020.3566 | H50: =IF(H31>0,H42-H$46,0) -> 6045.4267 | I50: =IF(I31>0,I42-I$46,0) -> 0 | J50: =IF(J31>0,J42-J$46,0) -> 0 | K50: =IF(K31>0,K42-K$46,0) -> 0 | ... AD50: =IF(AD31>0,AD42-AD$46,0) -> 0
A51: =$A$32 -> 88% PHCC | B51: kcal/kg(nar) | D51: =IF(D32>0,D43-D$46,0) -> 0 | E51: =IF(E32>0,E43-E$46,0) -> 0 | F51: =IF(F32>0,F43-F$46,0) -> 0 | G51: =IF(G32>0,G43-G$46,0) -> 0 | H51: =IF(H32>0,H43-H$46,0) -> 0 | I51: =IF(I32>0,I43-I$46,0) -> 0 | J51: =IF(J32>0,J43-J$46,0) -> 0 | K51: =IF(K32>0,K43-K$46,0) -> 0 | ... AD51: =IF(AD32>0,AD43-AD$46,0) -> 0
A52: Thermal GCN | B52: kcal/kg(nar) | D52: =IF(D33>0,D44-D$46,0) -> 0 | E52: =IF(E33>0,E44-E$46,0) -> 0 | F52: =IF(F33>0,F44-F$46,0) -> 0 | G52: =IF(G33>0,G44-G$46,0) -> 0 | H52: =IF(H33>0,H44-H$46,0) -> 0 | I52: =IF(I33>0,I44-I$46,0) -> 0 | J52: =IF(J33>0,J44-J$46,0) -> 0 | K52: =IF(K33>0,K44-K$46,0) -> 0 | ... AD52: =IF(AD33>0,AD44-AD$46,0) -> 0
A54: Realised Price
A55: =$A$31 -> PHCC | B55: USD/t | D55: =IF(D31>0,Assumptions!J6,0) -> 240 | E55: =IF(E31>0,Assumptions!K6,0) -> 240 | F55: =IF(F31>0,Assumptions!L6,0) -> 240 | G55: =IF(G31>0,Assumptions!M6,0) -> 240 | H55: =IF(H31>0,Assumptions!N6,0) -> 240 | I55: =IF(I31>0,Assumptions!O6,0) -> 0 | J55: =IF(J31>0,Assumptions!P6,0) -> 0 | K55: =IF(K31>0,Assumptions!Q6,0) -> 0 | ... AD55: =IF(AD31>0,Assumptions!AJ6,0) -> 0
A56: =$A$32 -> 88% PHCC | B56: USD/t | D56: =IF(D32>0,Assumptions!J$7,0) -> 0 | E56: =IF(E32>0,Assumptions!K$7,0) -> 0 | F56: =IF(F32>0,Assumptions!L$7,0) -> 0 | G56: =IF(G32>0,Assumptions!M$7,0) -> 0 | H56: =IF(H32>0,Assumptions!N$7,0) -> 0 | I56: =IF(I32>0,Assumptions!O$7,0) -> 0 | J56: =IF(J32>0,Assumptions!P$7,0) -> 0 | K56: =IF(K32>0,Assumptions!Q$7,0) -> 0 | ... AD56: =IF(AD32>0,Assumptions!AJ$7,0) -> 0
A57: Thermal GCN | B57: USD/t | D57: =IF(D33>0,IF(D52>Assumptions!J$12,Assumptions!J$8,IF(D52>Assumptions!J$13,Assumptions!J$8,Assumptions!J$9))*(D52/D$47),0) -> 0 | E57: =IF(E33>0,IF(E52>Assumptions!K$12,Assumptions!K$8,IF(E52>Assumptions!K$13,Assumptions!K$8,Assumptions!K$9))*(E52/E$47),0) -> 0 | F57: =IF(F33>0,IF(F52>Assumptions!L$12,Assumptions!L$8,IF(F52>Assumptions!L$13,Assumptions!L$8,Assumptions!L$9))*(F52/F$47),0) -> 0 | G57: =IF(G33>0,IF(G52>Assumptions!M$12,Assumptions!M$8,IF(G52>Assumptions!M$13,Assumptions!M$8,Assumptions!M$9))*(G52/G$47),0) -> 0 | H57: =IF(H33>0,IF(H52>Assumptions!N$12,Assumptions!N$8,IF(H52>Assumptions!N$13,Assumptions!N$8,Assumptions!N$9))*(H52/H$47),0) -> 0 | I57: =IF(I33>0,IF(I52>Assumptions!O$12,Assumptions!O$8,IF(I52>Assumptions!O$13,Assumptions!O$8,Assumptions!O$9))*(I52/I$47),0) -> 0 | J57: =IF(J33>0,IF(J52>Assumptions!P$12,Assumptions!P$8,IF(J52>Assumptions!P$13,Assumptions!P$8,Assumptions!P$9))*(J52/J$47),0) -> 0 | K57: =IF(K33>0,IF(K52>Assumptions!Q$12,Assumptions!Q$8,IF(K52>Assumptions!Q$13,Assumptions!Q$8,Assumptions!Q$9))*(K52/K$47),0) -> 0 | ... AD57: =IF(AD33>0,IF(AD52>Assumptions!AJ$12,Assumptions!AJ$8,IF(AD52>Assumptions!AJ$13,Assumptions!AJ$8,Assumptions!AJ$9))*(AD52/AD$47),0) -> 0
A58: Average Export Realised Price | B58: USD/t | D58: =IFERROR(SUMPRODUCT(D31:D33,D55:D57)/D34,0) -> 240 | E58: =IFERROR(SUMPRODUCT(E31:E33,E55:E57)/E34,0) -> 240 | F58: =IFERROR(SUMPRODUCT(F31:F33,F55:F57)/F34,0) -> 240 | G58: =IFERROR(SUMPRODUCT(G31:G33,G55:G57)/G34,0) -> 240 | H58: =IFERROR(SUMPRODUCT(H31:H33,H55:H57)/H34,0) -> 240 | I58: =IFERROR(SUMPRODUCT(I31:I33,I55:I57)/I34,0) -> 0 | J58: =IFERROR(SUMPRODUCT(J31:J33,J55:J57)/J34,0) -> 0 | K58: =IFERROR(SUMPRODUCT(K31:K33,K55:K57)/K34,0) -> 0 | ... AD58: =IFERROR(SUMPRODUCT(AD31:AD33,AD55:AD57)/AD34,0) -> 0
A60: Total Revenue | B60: USDk | D60: =SUMPRODUCT(D31:D32,D55:D56) -> 834772.25 | E60: =SUMPRODUCT(E31:E32,E55:E56) -> 910632.69 | F60: =SUMPRODUCT(F31:F32,F55:F56) -> 962877.48 | G60: =SUMPRODUCT(G31:G32,G55:G56) -> 927617.9 | H60: =SUMPRODUCT(H31:H32,H55:H56) -> 843545.9 | I60: =SUMPRODUCT(I31:I32,I55:I56) -> 0 | J60: =SUMPRODUCT(J31:J32,J55:J56) -> 0 | K60: =SUMPRODUCT(K31:K32,K55:K56) -> 0 | ... AF60: =SUMPRODUCT(AF31:AF32,AF55:AF56) -> 0
A61: FX | B61: USD:AUD | D61: =Assumptions!I4 -> 0.69 | E61: =Assumptions!J4 -> 0.69 | F61: =Assumptions!K4 -> 0.69 | G61: =Assumptions!L4 -> 0.69 | H61: =Assumptions!M4 -> 0.69 | I61: =Assumptions!N4 -> 0.69 | J61: =Assumptions!O4 -> 0.69 | K61: =Assumptions!P4 -> 0.69 | ... AD61: =Assumptions!AI4 -> 0.69
A62: Total Revenue | B62: AUD | D62: =(D60/D61)*(1+$AI$7) -> 1209814.9 | E62: =(E60/E61)*(1+$AI$7) -> 1319757.5 | F62: =(F60/F61)*(1+$AI$7) -> 1395474.6 | G62: =(G60/G61)*(1+$AI$7) -> 1344373.8 | H62: =(H60/H61)*(1+$AI$7) -> 1222530.3 | I62: =(I60/I61)*(1+$AI$7) -> 0 | J62: =(J60/J61)*(1+$AI$7) -> 0 | K62: =(K60/K61)*(1+$AI$7) -> 0 | ... AD62: =(AD60/AD61)*(1+$AI$7) -> 0 | AF62: =SUM(C62:AD62) -> 6491951
A63: Average Realisation | B63: AUD/t | D63: =IFERROR(D62/D19,0) -> 347.82609 | E63: =IFERROR(E62/E19,0) -> 347.82609 | F63: =IFERROR(F62/F19,0) -> 347.82609 | G63: =IFERROR(G62/G19,0) -> 347.82609 | H63: =IFERROR(H62/H19,0) -> 347.82609 | I63: =IFERROR(I62/I19,0) -> 0 | J63: =IFERROR(J62/J19,0) -> 0 | K63: =IFERROR(K62/K19,0) -> 0 | ... AD63: =IFERROR(AD62/AD19,0) -> 0 | AF63: =IFERROR(AF62/AF19,0) -> 347.82609
A65: Costs
A67: Direct Mining Costs
A69: Development Costs | B69: AUD/m | C69: 5500 | D69: =IF(D6>0,$C$69*(1+$AI$8),0) -> 5500 | E69: =IF(E6>0,$C$69*(1+$AI$8),0) -> 5500 | F69: =IF(F6>0,$C$69*(1+$AI$8),0) -> 5500 | G69: =IF(G6>0,$C$69*(1+$AI$8),0) -> 5500 | H69: =IF(H6>0,$C$69*(1+$AI$8),0) -> 5500 | I69: =IF(I6>0,$C$69*(1+$AI$8),0) -> 0 | J69: =IF(J6>0,$C$69*(1+$AI$8),0) -> 0 | K69: =IF(K6>0,$C$69*(1+$AI$8),0) -> 0 | ... AD69: =IF(AD6>0,$C$69*(1+$AI$8),0) -> 0
A70: Total Development Costs | B70: AUDk | D70: =D6*D69/1000 -> 49500 | E70: =E6*E69/1000 -> 82500 | F70: =F6*F69/1000 -> 82500 | G70: =G6*G69/1000 -> 44000 | H70: =H6*H69/1000 -> 11000 | I70: =I6*I69/1000 -> 0 | J70: =J6*J69/1000 -> 0 | K70: =K6*K69/1000 -> 0 | ... AD70: =AD6*AD69/1000 -> 0 | AF70: =SUM(C70:AD70) -> 269500
A72: Longwall Costs | B72: AUD/LWt | C72: 14.5 | D72: =IF(D8>0,$C$72*(1+$AI$9),0) -> 14.5 | E72: =IF(E8>0,$C$72*(1+$AI$9),0) -> 14.5 | F72: =IF(F8>0,$C$72*(1+$AI$9),0) -> 14.5 | G72: =IF(G8>0,$C$72*(1+$AI$9),0) -> 14.5 | H72: =IF(H8>0,$C$72*(1+$AI$9),0) -> 14.5 | I72: =IF(I8>0,$C$72*(1+$AI$9),0) -> 0 | J72: =IF(J8>0,$C$72*(1+$AI$9),0) -> 0 | K72: =IF(K8>0,$C$72*(1+$AI$9),0) -> 0 | ... AD72: =IF(AD8>0,$C$72*(1+$AI$9),0) -> 0
A73: Total Longwall Costs | B73: AUDk | D73: =D8*D72 -> 72322.951 | E73: =E8*E72 -> 77195.66 | F73: =F8*F72 -> 81906.788 | G73: =G8*G72 -> 81023.217 | H73: =H8*H72 -> 75410.038 | I73: =I8*I72 -> 0 | J73: =J8*J72 -> 0 | K73: =K8*K72 -> 0 | ... AD73: =AD8*AD72 -> 0 | AF73: =SUM(C73:AD73) -> 387858.65
A75: Total Outbye Costs | B75: AUDk | C75: 240000 | D75: =IF(D9>0,$C$75)*(1+$AI$10) -> 240000 | E75: =IF(E9>0,$C$75)*(1+$AI$10) -> 240000 | F75: =IF(F9>0,$C$75)*(1+$AI$10) -> 240000 | G75: =IF(G9>0,$C$75)*(1+$AI$10) -> 240000 | H75: =IF(H9>0,$C$75)*(1+$AI$10) -> 240000 | I75: =IF(I9>0,$C$75)*(1+$AI$10) -> 0 | J75: =IF(J9>0,$C$75)*(1+$AI$10) -> 0 | K75: =IF(K9>0,$C$75)*(1+$AI$10) -> 0 | ... AD75: =IF(AD9>0,$C$75)*(1+$AI$10) -> 0 | AF75: =SUM(C75:AD75) -> 1440000
A77: Gas Drainage Costs | B77: AUD/t | C77: 8 | D77: =IF(D9>0,$C$77*(1+$AI$11),0) -> 8 | E77: =IF(E9>0,$C$77*(1+$AI$11),0) -> 8 | F77: =IF(F9>0,$C$77*(1+$AI$11),0) -> 8 | G77: =IF(G9>0,$C$77*(1+$AI$11),0) -> 8 | H77: =IF(H9>0,$C$77*(1+$AI$11),0) -> 8 | I77: =IF(I9>0,$C$77*(1+$AI$11),0) -> 0 | J77: =IF(J9>0,$C$77*(1+$AI$11),0) -> 0 | K77: =IF(K9>0,$C$77*(1+$AI$11),0) -> 0 | ... AD77: =IF(AD9>0,$C$77*(1+$AI$11),0) -> 0
A78: Total Gas Drainage Costs | B78: AUDk | D78: =D77*D9 -> 41530.958 | E78: =E77*E9 -> 45305.109 | F78: =F77*F9 -> 47904.352 | G78: =G77*G9 -> 46150.144 | H78: =H77*H9 -> 41967.458 | I78: =I77*I9 -> 0 | J78: =J77*J9 -> 0 | K78: =K77*K9 -> 0 | ... AD78: =AD77*AD9 -> 0 | AF78: =SUM(C78:AD78) -> 222858.02
A80: Fixed CHPP Costs | B80: AUDk | C80: 20000 | D80: =IF(D6>0,$C$80,0) -> 20000 | E80: =IF(E6>0,$C$80,0) -> 20000 | F80: =IF(F6>0,$C$80,0) -> 20000 | G80: =IF(G6>0,$C$80,0) -> 20000 | H80: =IF(H6>0,$C$80,0) -> 20000 | I80: =IF(I6>0,$C$80,0) -> 0 | J80: =IF(J6>0,$C$80,0) -> 0 | K80: =IF(K6>0,$C$80,0) -> 0 | ... AD80: =IF(AD6>0,$C$80,0) -> 0
A81: Variable CHPP Costs | B81: AUD/feedt | C81: 9.5 | D81: =IF(D12>0,$C$81*(1+$AI$12),0) -> 9.5 | E81: =IF(E12>0,$C$81*(1+$AI$12),0) -> 9.5 | F81: =IF(F12>0,$C$81*(1+$AI$12),0) -> 9.5 | G81: =IF(G12>0,$C$81*(1+$AI$12),0) -> 9.5 | H81: =IF(H12>0,$C$81*(1+$AI$12),0) -> 9.5 | I81: =IF(I12>0,$C$81*(1+$AI$12),0) -> 0 | J81: =IF(J12>0,$C$81*(1+$AI$12),0) -> 0 | K81: =IF(K12>0,$C$81*(1+$AI$12),0) -> 0 | ... AD81: =IF(AD12>0,$C$81*(1+$AI$12),0) -> 0
A82: Total CHPP Costs | B82: AUDk | D82: =D9*D81+D80 -> 69318.012 | E82: =E9*E81+E80 -> 73799.817 | F82: =F9*F81+F80 -> 76886.418 | G82: =G9*G81+G80 -> 74803.296 | H82: =H9*H81+H80 -> 69836.356 | I82: =I9*I81+I80 -> 0 | J82: =J9*J81+J80 -> 0 | K82: =K9*K81+K80 -> 0 | ... AD82: =AD9*AD81+AD80 -> 0 | AF82: =SUM(C82:AD82) -> 364643.9
A84: Overhead - Site Administration | B84: AUDk | C84: 45000 | D84: =IF(D$19>0,$C84,0) -> 45000 | E84: =IF(E$19>0,$C84,0) -> 45000 | F84: =IF(F$19>0,$C84,0) -> 45000 | G84: =IF(G$19>0,$C84,0) -> 45000 | H84: =IF(H$19>0,$C84,0) -> 45000 | I84: =IF(I$19>0,$C84,0) -> 0 | J84: =IF(J$19>0,$C84,0) -> 0 | K84: =IF(K$19>0,$C84,0) -> 0 | ... AD84: =IF(AD$19>0,$C84,0) -> 0
A85: Overhead - Town Management | B85: AUDk | C85: 9000 | D85: =IF(D$19>0,$C85,0) -> 9000 | E85: =IF(E$19>0,$C85,0) -> 9000 | F85: =IF(F$19>0,$C85,0) -> 9000 | G85: =IF(G$19>0,$C85,0) -> 9000 | H85: =IF(H$19>0,$C85,0) -> 9000 | I85: =IF(I$19>0,$C85,0) -> 0 | J85: =IF(J$19>0,$C85,0) -> 0 | K85: =IF(K$19>0,$C85,0) -> 0 | ... AD85: =IF(AD$19>0,$C85,0) -> 0
A86: Overhead - Corporate Fees | B86: AUDk | C86: 15000 | D86: =IF(D$19>0,$C86,0) -> 15000 | E86: =IF(E$19>0,$C86,0) -> 15000 | F86: =IF(F$19>0,$C86,0) -> 15000 | G86: =IF(G$19>0,$C86,0) -> 15000 | H86: =IF(H$19>0,$C86,0) -> 15000 | I86: =IF(I$19>0,$C86,0) -> 0 | J86: =IF(J$19>0,$C86,0) -> 0 | K86: =IF(K$19>0,$C86,0) -> 0 | ... AD86: =IF(AD$19>0,$C86,0) -> 0
A87: Total Overhead Costs | B87: AUDk | D87: =IF(D9>0,SUM(D84:D86)*(1+$AI$13),0) -> 69000 | E87: =IF(E9>0,SUM(E84:E86)*(1+$AI$13),0) -> 69000 | F87: =IF(F9>0,SUM(F84:F86)*(1+$AI$13),0) -> 69000 | G87: =IF(G9>0,SUM(G84:G86)*(1+$AI$13),0) -> 69000 | H87: =IF(H9>0,SUM(H84:H86)*(1+$AI$13),0) -> 69000 | I87: =IF(I9>0,SUM(I84:I86)*(1+$AI$13),0) -> 0 | J87: =IF(J9>0,SUM(J84:J86)*(1+$AI$13),0) -> 0 | K87: =IF(K9>0,SUM(K84:K86)*(1+$AI$13),0) -> 0 | ... AD87: =IF(AD9>0,SUM(AD84:AD86)*(1+$AI$13),0) -> 0 | AF87: =SUM(C87:AD87) -> 345000
A89: Total FOR Costs | D89: =SUM(D70,D73,D75,D78,D82,D87) -> 541671.92 | E89: =SUM(E70,E73,E75,E78,E82,E87) -> 587800.59 | F89: =SUM(F70,F73,F75,F78,F82,F87) -> 598197.56 | G89: =SUM(G70,G73,G75,G78,G82,G87) -> 554976.66 | H89: =SUM(H70,H73,H75,H78,H82,H87) -> 507213.85 | I89: =SUM(I70,I73,I75,I78,I82,I87) -> 0 | J89: =SUM(J70,J73,J75,J78,J82,J87) -> 0 | K89: =SUM(K70,K73,K75,K78,K82,K87) -> 0 | ... AD89: =SUM(AD70,AD73,AD75,AD78,AD82,AD87) -> 0 | AF89: =SUM(C89:AD89) -> 2789860.6
A90: FOR Cost/t | B90: AUD/t | D90: =IFERROR(D89/D19,0) -> 155.73261 | E90: =IFERROR(E89/E19,0) -> 154.91662 | F90: =IFERROR(F89/F19,0) -> 149.10247 | G90: =IFERROR(G89/G19,0) -> 143.58757 | H90: =IFERROR(H89/H19,0) -> 144.30907 | I90: =IFERROR(I89/I19,0) -> 0 | J90: =IFERROR(J89/J19,0) -> 0 | K90: =IFERROR(K89/K19,0) -> 0 | ... AD90: =IFERROR(AD89/AD19,0) -> 0 | AF90: =IFERROR(AF89/AF19,0) -> 149.47529
A92: Direct Selling Expenses | C92: ToP Liability? | D92: Y | E92: Y | F92: N | G92: N | H92: N
A93: Total Port, Rail and Selling Costs | B93: AUD/t | C93: 24 | D93: =$C$93*D34 -> 83477.225 | E93: =$C$93*E34 -> 91063.269 | F93: =$C$93*F34 -> 96287.748 | G93: =$C$93*G34 -> 92761.79 | H93: =$C$93*H34 -> 84354.59 | I93: =$C$93*I34 -> 0 | J93: =$C$93*J34 -> 0 | K93: =$C$93*K34 -> 0 | ... AD93: =$C$93*AD34 -> 0 | AF93: =SUM(C93:AD93) -> 447968.62
A94: Additional take or pay liability | B94: AUD/t | C94: 10 | D94: =IF(D$92="Y",$C$94*D34,0) -> 34782.177 | E94: =IF(E$92="Y",$C$94*E34,0) -> 37943.029 | F94: =IF(F$92="Y",$C$94*F34,0) -> 0 | G94: =IF(G$92="Y",$C$94*G34,0) -> 0 | H94: =IF(H$92="Y",$C$94*H34,0) -> 0 | I94: =IF(I$92="Y",$C$94*I34,0) -> 0 | J94: =IF(J$92="Y",$C$94*J34,0) -> 0 | K94: =IF(K$92="Y",$C$94*K34,0) -> 0 | ... AD94: =IF(AD$92="Y",$C$94*AD34,0) -> 0
A95: Government Royalty | B95: AUDk | D95: =D148*D34 -> 215377.54 | E95: =E148*E34 -> 241855.33 | F95: =F148*F34 -> 270785.42 | G95: =G148*G34 -> 267591.55 | H95: =H148*H34 -> 249313.88 | I95: =I148*I34 -> 0 | J95: =J148*J34 -> 0 | K95: =K148*K34 -> 0 | ... AD95: =AD148*AD34 -> 0 | AF95: =SUM(C95:AD95) -> 1244923.7
A96: Total Direct Selling Expenses | B96: AUDk | D96: =SUM(D93:D95) -> 333636.94 | E96: =SUM(E93:E95) -> 370861.63 | F96: =SUM(F93:F95) -> 367073.16 | G96: =SUM(G93:G95) -> 360353.34 | H96: =SUM(H93:H95) -> 333668.47 | I96: =SUM(I93:I95) -> 0 | J96: =SUM(J93:J95) -> 0 | K96: =SUM(K93:K95) -> 0 | ... AD96: =SUM(AD93:AD95) -> 0 | AF96: =SUM(AF93:AF95) -> 1692892.3
A98: Total FOB Costs | B98: AUDk | D98: =D89+D96 -> 875308.86 | E98: =E89+E96 -> 958662.22 | F98: =F89+F96 -> 965270.72 | G98: =G89+G96 -> 915330 | H98: =H89+H96 -> 840882.32 | I98: =I89+I96 -> 0 | J98: =J89+J96 -> 0 | K98: =K89+K96 -> 0 | ... AD98: =AD89+AD96 -> 0 | AF98: =SUM(C98:AD98) -> 4555454.1
A99: FOB Cost/t | B99: AUD/t | D99: =IFERROR(D98/D19,0) -> 251.65442 | E99: =IFERROR(E98/E19,0) -> 252.65833 | F99: =IFERROR(F98/F19,0) -> 240.59652 | G99: =IFERROR(G98/G19,0) -> 236.82079 | H99: =IFERROR(H98/H19,0) -> 239.24217 | I99: =IFERROR(I98/I19,0) -> 0 | J99: =IFERROR(J98/J19,0) -> 0 | K99: =IFERROR(K98/K19,0) -> 0 | ... AD99: =IFERROR(AD98/AD19,0) -> 0 | AF99: =IFERROR(AF98/AF19,0) -> 244.07235
A101: Mine Earnings before Other Costs and Taxes | B101: AUDk | D101: =D62-D98 -> 334506 | E101: =E62-E98 -> 361095.31 | F101: =F62-F98 -> 430203.88 | G101: =G62-G98 -> 429043.77 | H101: =H62-H98 -> 381647.98 | I101: =I62-I98 -> 0 | J101: =J62-J98 -> 0 | K101: =K62-K98 -> 0 | ... AD101: =AD62-AD98 -> 0 | AF101: =AF62-AF98 -> 1936496.9
A103: Other Costs
A104: Progressive Rehabiliation Costs | B104: AUDk | C104: 2500 | D104: =IF(D9>0,$C$104,0) -> 2500 | E104: =IF(E9>0,$C$104,0) -> 2500 | F104: =IF(F9>0,$C$104,0) -> 2500 | G104: =IF(G9>0,$C$104,0) -> 2500 | H104: =IF(H9>0,$C$104,0) -> 2500 | I104: =IF(I9>0,$C$104,0) -> 0 | J104: =IF(J9>0,$C$104,0) -> 0 | K104: =IF(K9>0,$C$104,0) -> 0 | ... AD104: =IF(AD9>0,$C$104,0) -> 0 | AF104: =SUM(C104:AD104) -> 15000
A105: Mine Closure Costs | B105: AUDk | C105: 900000 | I105: =C105 -> 900000 | AF105: =SUM(C105:AD105) -> 1800000
A106: Carbon Costs | B106: AUDk | D106: =IF(Assumptions!$C$20="Zero Carbon Liability",Springbok!D26*Carbon!B2,Springbok!D26*Carbon!B3)/1000 -> 9761.2235 | E106: =IF(Assumptions!$C$20="Zero Carbon Liability",Springbok!E26*Carbon!C2,Springbok!E26*Carbon!C3)/1000 -> 14300.586 | F106: =IF(Assumptions!$C$20="Zero Carbon Liability",Springbok!F26*Carbon!D2,Springbok!F26*Carbon!D3)/1000 -> 19375.932 | G106: =IF(Assumptions!$C$20="Zero Carbon Liability",Springbok!G26*Carbon!E2,Springbok!G26*Carbon!E3)/1000 -> 24222.345 | H106: =IF(Assumptions!$C$20="Zero Carbon Liability",Springbok!H26*Carbon!F2,Springbok!H26*Carbon!F3)/1000 -> 28522.155 | I106: =IF(Assumptions!$C$20="Zero Carbon Liability",Springbok!I26*Carbon!G2,Springbok!I26*Carbon!G3)/1000 -> 0 | J106: =IF(Assumptions!$C$20="Zero Carbon Liability",Springbok!J26*Carbon!H2,Springbok!J26*Carbon!H3)/1000 -> 0 | K106: =IF(Assumptions!$C$20="Zero Carbon Liability",Springbok!K26*Carbon!I2,Springbok!K26*Carbon!I3)/1000 -> 0 | ... AD106: =IF(Assumptions!$C$20="Zero Carbon Liability",Springbok!AD26*Carbon!AB2,Springbok!AD26*Carbon!AB3)/1000 -> 0
A107: Other Revenue | B107: AUDk | D107: 0 | E107: 0 | F107: 0 | G107: 0 | H107: 0 | I107: =-5000 -> -5000 | J107: 0 | K107: 0 | L107: 0 | M107: 0 | N107: 0 | O107: 0 | P107: 0 | Q107: 0 | R107: 0 | S107: 0 | T107: 0 | U107: 0 | V107: 0 | W107: 0 | X107: 0 | Y107: 0 | Z107: 0 | AA107: 0 | AB107: 0 | AC107: 0 | AD107: 0
A108: Total Other Costs | B108: AUDk | D108: =SUM(D104:D107) -> 12261.223 | E108: =SUM(E104:E107) -> 16800.586 | F108: =SUM(F104:F107) -> 21875.932 | G108: =SUM(G104:G107) -> 26722.345 | H108: =SUM(H104:H107) -> 31022.155 | I108: =SUM(I104:I107) -> 895000 | J108: =SUM(J104:J107) -> 0 | K108: =SUM(K104:K107) -> 0 | ... AD108: =SUM(AD104:AD107) -> 0 | AF108: =SUM(AF104:AF105) -> 1815000
A109: Total other - closure credits | D109: =IF(D105<=0,(D104+D106),D108) -> 12261.223 | E109: =IF(E105<=0,(E104+E106),E108) -> 16800.586 | F109: =IF(F105<=0,(F104+F106),F108) -> 21875.932 | G109: =IF(G105<=0,(G104+G106),G108) -> 26722.345 | H109: =IF(H105<=0,(H104+H106),H108) -> 31022.155 | I109: =IF(I105<=0,(I104+I106),I108) -> 895000 | J109: =IF(J105<=0,(J104+J106),J108) -> 0 | K109: =IF(K105<=0,(K104+K106),K108) -> 0 | ... AD109: =IF(AD105<=0,(AD104+AD106),AD108) -> 0 | AE109: =IF(AE105>=0,(AE104+AE106),AE108) -> 0
A111: Capital Costs
A112: Project Capital | B112: AUDk | D112: 0 | E112: 0 | F112: 0 | G112: 0 | H112: 0 | I112: 0 | J112: 0 | K112: 0 | L112: 0 | M112: 0 | N112: 0 | O112: 0 | P112: 0 | Q112: 0 | R112: 0 | S112: 0 | T112: 0 | U112: 0 | V112: 0 | W112: 0 | X112: 0 | Y112: 0 | Z112: 0 | AA112: 0 | AB112: 0 | AC112: 0 | AD112: 0 | AF112: =SUM(C112:AD112) -> 0
A113: Mining Equipment/Major Capital | B113: AUDk | D113: =SpringbokCapital!D39 -> 75360 | E113: =SpringbokCapital!E39 -> 34560 | F113: =SpringbokCapital!F39 -> 4560 | G113: =SpringbokCapital!G39 -> 4560 | H113: =SpringbokCapital!H39 -> 4560 | I113: =SpringbokCapital!I39 -> 0 | J113: =SpringbokCapital!J39 -> 0 | K113: =SpringbokCapital!K39 -> 0 | ... AD113: =SpringbokCapital!AD39 -> 0 | AF113: =SUM(C113:AD113) -> 123600
A114: Sustaining Capital | B114: AUD/ROMt | C114: 4 | D114: =$C$114*D9 -> 20765.479 | E114: =$C$114*E9 -> 22652.555 | F114: =$C$114*F9 -> 23952.176 | G114: =$C$114*G9 -> 23075.072 | H114: =$C$114*H9 -> 20983.729 | I114: =$C$114*I9 -> 0 | J114: =$C$114*J9 -> 0 | K114: =$C$114*K9 -> 0 | ... AD114: =$C$114*AD9 -> 0 | AF114: =SUM(C114:AD114) -> 111433.01
A115: Total Capital | B115: AUDk | D115: =SUM(D112:D114)*(1+$AI$14) -> 96125.479 | E115: =SUM(E112:E114)*(1+$AI$14) -> 57212.555 | F115: =SUM(F112:F114)*(1+$AI$14) -> 28512.176 | G115: =SUM(G112:G114)*(1+$AI$14) -> 27635.072 | H115: =SUM(H112:H114)*(1+$AI$14) -> 25543.729 | I115: =SUM(I112:I114)*(1+$AI$14) -> 0 | J115: =SUM(J112:J114)*(1+$AI$14) -> 0 | K115: =SUM(K112:K114)*(1+$AI$14) -> 0 | ... AD115: =SUM(AD112:AD114)*(1+$AI$14) -> 0 | AF115: =SUM(C115:AD115) -> 235029.01
A116: Depreciation | B116: AUDk | D116: =D132 -> 53048.005 | E116: =E132 -> 26524.002 | F116: =F132 -> 45594.854 | G116: =G132 -> 59850.942 | H116: =H132 -> 113029.74 | I116: =I132 -> 0 | J116: =J132 -> 0 | K116: =K132 -> 0 | ... AD116: =AD132 -> 0
A118: Net Cashflow Before Tax | B118: AUDk | D118: =D101-D108-D115 -> 226119.3 | E118: =E101-E108-E115 -> 287082.17 | F118: =F101-F108-F115 -> 379815.77 | G118: =G101-G108-G115 -> 374686.35 | H118: =H101-H108-H115 -> 325082.09 | I118: =I101-I108-I115 -> -895000 | J118: =J101-J108-J115 -> 0 | K118: =K101-K108-K115 -> 0 | ... AD118: =AD101-AD108-AD115 -> 0 | AF118: =AF101-AF108-AF115 -> -113532.08
A119: Tax Paid | B119: AUDk | C119: 0.3 | D119: =IF((D101-D109-D116)*$C$119>0,(D101-D109-D116)*$C$119,0) -> 80759.031 | E119: =IF((E101-E109-E116)*$C$119>0,(E101-E109-E116)*$C$119,0) -> 95331.216 | F119: =IF((F101-F109-F116)*$C$119>0,(F101-F109-F116)*$C$119,0) -> 108819.93 | G119: =IF((G101-G109-G116)*$C$119>0,(G101-G109-G116)*$C$119,0) -> 102741.14 | H119: =IF((H101-H109-H116)*$C$119>0,(H101-H109-H116)*$C$119,0) -> 71278.824 | I119: =IF((I101-I109-I116)*$C$119>0,(I101-I109-I116)*$C$119,0) -> 0 | J119: =IF((J101-J109-J116)*$C$119>0,(J101-J109-J116)*$C$119,0) -> 0 | K119: =IF((K101-K109-K116)*$C$119>0,(K101-K109-K116)*$C$119,0) -> 0 | ... AD119: =IF((AD101-AD109-AD116)*$C$119>0,(AD101-AD109-AD116)*$C$119,0) -> 0 | AF119: =SUM(D119:AD119) -> 458930.14
D120: 1 | E120: 1 | F120: 1 | G120: 1 | H120: 1 | I120: 0 | J120: 1 | K120: 1 | L120: 1 | M120: 1 | N120: 1 | O120: 1 | P120: 1 | Q120: 1 | R120: 1 | S120: 1 | T120: 1 | U120: 1 | V120: 1 | W120: 1 | X120: 1 | Y120: 1 | Z120: 1 | AA120: 1 | AB120: 1 | AC120: 1 | AD120: 1
A122: Cashflows After Tax | B122: AUDk | D122: =D118-D119 -> 145360.26 | E122: =E118-E119 -> 191750.95 | F122: =F118-F119 -> 270995.84 | G122: =G118-G119 -> 271945.21 | H122: =H118-H119 -> 253803.27 | I122: =I118-I119 -> -895000 | J122: =J118-J119 -> 0 | K122: =K118-K119 -> 0 | ... AD122: =AD118-AD119 -> 0 | AF122: =AF118-AF119 -> -572462.22
A123: Attributable Cashflow After Tax (60%) | B123: AUDk | C123: 0.6 | D123: =IFERROR(D122*$C$123,0) -> 87216.159 | E123: =IFERROR(E122*$C$123,0) -> 115050.57 | F123: =IFERROR(F122*$C$123,0) -> 162597.51 | G123: =IFERROR(G122*$C$123,0) -> 163167.12 | H123: =IFERROR(H122*$C$123,0) -> 152281.96 | I123: =IFERROR(I122*$C$123,0) -> -537000 | J123: =IFERROR(J122*$C$123,0) -> 0 | K123: =IFERROR(K122*$C$123,0) -> 0 | ... AD123: =IFERROR(AD122*$C$123,0) -> 0
...

Sheet SpringbokCapital
A1: Springbok Capital | D1: =Springbok!D2 -> 2027 | E1: =D1+1 -> 2028 | F1: =E1+1 -> 2029 | G1: =F1+1 -> 2030 | H1: =G1+1 -> 2031 | I1: =H1+1 -> 2032 | J1: =I1+1 -> 2033 | K1: =J1+1 -> 2034 | L1: =K1+1 -> 2035 | ... V1: =U1+1 -> 2045
A3: Capital Items - Units | D3: Insert Unit Numbers by Year Below
A4: Replacement Miner | B4: AUD$k | C4: 9000 | D4: 1
A5: Ventilation Shaft | B5: AUD$k | C5: 20000 | D5: 0.5 | E5: 0.5
A6: SIS Drill program | B6: AUD$k | C6: 30000 | D6: 0.5 | E6: 0.5 | F6: 0 | G6: 0
A7: Replacement Roof Supports | B7: AUD$k | C7: 1000 | D7: 10
A8: Conveyor Belt Replacement | B8: AUD$k | C8: 3000 | D8: 1 | E8: 1 | F8: 1 | G8: 1 | H8: 1
A9: Barada Community Program | B9: AUD$k | C9: 5000 | D9: 1
A10: Tailings Storage Facility | B10: AUD$k | C10: 10000 | D10: 1
A11: Exploration Drilling | B11: AUD$k | C11: 800 | D11: 1 | E11: 1 | F11: 1 | G11: 1 | H11: 1
B12: AUD$k
B13: AUD$k
B14: AUD$k
B15: AUD$k
B16: AUD$k
A21: Capital Cost - Cost | D21: Do not change cells below
A22: =A4 -> Replacement Miner | B22: AUD$k | C22: =C4 -> 9000 | D22: =$C4*D4 -> 9000 | E22: =$C4*E4 -> 0 | F22: =$C4*F4 -> 0 | G22: =$C4*G4 -> 0 | H22: =$C4*H4 -> 0 | I22: =$C4*I4 -> 0 | J22: =$C4*J4 -> 0 | K22: =$C4*K4 -> 0 | ... V22: =$C4*V4 -> 0
A23: =A5 -> Ventilation Shaft | B23: AUD$k | C23: =C5 -> 20000 | D23: =$C5*D5 -> 10000 | E23: =$C5*E5 -> 10000 | F23: =$C5*F5 -> 0 | G23: =$C5*G5 -> 0 | H23: =$C5*H5 -> 0 | I23: =$C5*I5 -> 0 | J23: =$C5*J5 -> 0 | K23: =$C5*K5 -> 0 | ... V23: =$C5*V5 -> 0
A24: =A6 -> SIS Drill program | B24: AUD$k | C24: =C6 -> 30000 | D24: =$C6*D6 -> 15000 | E24: =$C6*E6 -> 15000 | F24: =$C6*F6 -> 0 | G24: =$C6*G6 -> 0 | H24: =$C6*H6 -> 0 | I24: =$C6*I6 -> 0 | J24: =$C6*J6 -> 0 | K24: =$C6*K6 -> 0 | ... V24: =$C6*V6 -> 0
A25: =A7 -> Replacement Roof Supports | B25: AUD$k | C25: =C7 -> 1000 | D25: =$C7*D7 -> 10000 | E25: =$C7*E7 -> 0 | F25: =$C7*F7 -> 0 | G25: =$C7*G7 -> 0 | H25: =$C7*H7 -> 0 | I25: =$C7*I7 -> 0 | J25: =$C7*J7 -> 0 | K25: =$C7*K7 -> 0 | ... V25: =$C7*V7 -> 0
A26: =A8 -> Conveyor Belt Replacement | B26: AUD$k | C26: =C8 -> 3000 | D26: =$C8*D8 -> 3000 | E26: =$C8*E8 -> 3000 | F26: =$C8*F8 -> 3000 | G26: =$C8*G8 -> 3000 | H26: =$C8*H8 -> 3000 | I26: =$C8*I8 -> 0 | J26: =$C8*J8 -> 0 | K26: =$C8*K8 -> 0 | ... V26: =$C8*V8 -> 0
A27: =A9 -> Barada Community Program | B27: AUD$k | C27: =C9 -> 5000 | D27: =$C9*D9 -> 5000 | E27: =$C9*E9 -> 0 | F27: =$C9*F9 -> 0 | G27: =$C9*G9 -> 0 | H27: =$C9*H9 -> 0 | I27: =$C9*I9 -> 0 | J27: =$C9*J9 -> 0 | K27: =$C9*K9 -> 0 | ... V27: =$C9*V9 -> 0
A28: =A10 -> Tailings Storage Facility | B28: AUD$k | C28: =C10 -> 10000 | D28: =$C10*D10 -> 10000 | E28: =$C10*E10 -> 0 | F28: =$C10*F10 -> 0 | G28: =$C10*G10 -> 0 | H28: =$C10*H10 -> 0 | I28: =$C10*I10 -> 0 | J28: =$C10*J10 -> 0 | K28: =$C10*K10 -> 0 | ... V28: =$C10*V10 -> 0
A29: =A11 -> Exploration Drilling | B29: AUD$k | C29: =C11 -> 800 | D29: =$C11*D11 -> 800 | E29: =$C11*E11 -> 800 | F29: =$C11*F11 -> 800 | G29: =$C11*G11 -> 800 | H29: =$C11*H11 -> 800 | I29: =$C11*I11 -> 0 | J29: =$C11*J11 -> 0 | K29: =$C11*K11 -> 0 | ... V29: =$C11*V11 -> 0
A30: =A12 -> 0 | B30: AUD$k | C30: =C12 -> 0 | D30: =$C12*D12 -> 0 | E30: =$C12*E12 -> 0 | F30: =$C12*F12 -> 0 | G30: =$C12*G12 -> 0 | H30: =$C12*H12 -> 0 | I30: =$C12*I12 -> 0 | J30: =$C12*J12 -> 0 | K30: =$C12*K12 -> 0 | ... V30: =$C12*V12 -> 0
A31: =A13 -> 0 | B31: AUD$k | C31: =C13 -> 0 | D31: =$C13*D13 -> 0 | E31: =$C13*E13 -> 0 | F31: =$C13*F13 -> 0 | G31: =$C13*G13 -> 0 | H31: =$C13*H13 -> 0 | I31: =$C13*I13 -> 0 | J31: =$C13*J13 -> 0 | K31: =$C13*K13 -> 0 | ... V31: =$C13*V13 -> 0
A32: =A14 -> 0 | B32: AUD$k | C32: =C14 -> 0 | D32: =$C14*D14 -> 0 | E32: =$C14*E14 -> 0 | F32: =$C14*F14 -> 0 | G32: =$C14*G14 -> 0 | H32: =$C14*H14 -> 0 | I32: =$C14*I14 -> 0 | J32: =$C14*J14 -> 0 | K32: =$C14*K14 -> 0 | ... V32: =$C14*V14 -> 0
A33: =A15 -> 0 | B33: AUD$k | C33: =C15 -> 0 | D33: =$C15*D15 -> 0 | E33: =$C15*E15 -> 0 | F33: =$C15*F15 -> 0 | G33: =$C15*G15 -> 0 | H33: =$C15*H15 -> 0 | I33: =$C15*I15 -> 0 | J33: =$C15*J15 -> 0 | K33: =$C15*K15 -> 0 | ... V33: =$C15*V15 -> 0
... A35: =A17 -> 0 | B35: AUD$k | C35: =C17 -> 0 | D35: =$C17*D17 -> 0 | E35: =$C17*E17 -> 0 | F35: =$C17*F17 -> 0 | G35: =$C17*G17 -> 0 | H35: =$C17*H17 -> 0 | I35: =$C17*I17 -> 0 | J35: =$C17*J17 -> 0 | K35: =$C17*K17 -> 0 | ... V35: =$C17*V17 -> 0
A36: =A17 -> 0 | B36: AUD$k | C36: =C18 -> 0 | D36: =$C18*D18 -> 0 | E36: =$C18*E18 -> 0 | F36: =$C18*F18 -> 0 | G36: =$C18*G18 -> 0 | H36: =$C18*H18 -> 0 | I36: =$C18*I18 -> 0 | J36: =$C18*J18 -> 0 | K36: =$C18*K18 -> 0 | ... V36: =$C18*V18 -> 0
A37: Total | D37: =SUM(D22:D36) -> 62800 | E37: =SUM(E22:E36) -> 28800 | F37: =SUM(F22:F36) -> 3800 | G37: =SUM(G22:G36) -> 3800 | H37: =SUM(H22:H36) -> 3800 | I37: =SUM(I22:I36) -> 0 | J37: =SUM(J22:J36) -> 0 | K37: =SUM(K22:K36) -> 0 | ... V37: =SUM(V22:V36) -> 0
A38: Contingency | B38: % | C38: 0.2 | D38: =$C$38*D37 -> 12560 | E38: =$C$38*E37 -> 5760 | F38: =$C$38*F37 -> 760 | G38: =$C$38*G37 -> 760 | H38: =$C$38*H37 -> 760 | I38: =$C$38*I37 -> 0 | J38: =$C$38*J37 -> 0 | K38: =$C$38*K37 -> 0 | ... V38: =$C$38*V37 -> 0
A39: Total Capital | D39: =D38+D37 -> 75360 | E39: =E38+E37 -> 34560 | F39: =F38+F37 -> 4560 | G39: =G38+G37 -> 4560 | H39: =H38+H37 -> 4560 | I39: =I38+I37 -> 0 | J39: =J38+J37 -> 0 | K39: =K38+K37 -> 0 | ... V39: =V38+V37 -> 0

Sheet Brave Blossom 
D1: 2 | E1: =+D1+1 -> 3 | F1: =+E1+1 -> 4 | G1: =+F1+1 -> 5 | H1: =+G1+1 -> 6 | I1: =+H1+1 -> 7 | J1: =+I1+1 -> 8 | K1: =+J1+1 -> 9 | L1: =+K1+1 -> 10 | ... AD1: =+AC1+1 -> 28 | AE1: =+AC1+1 -> 28 | AF1: =+AD1+1 -> 29 | AG1: =+AE1+1 -> 29 | AH1: =+AF1+1 -> 30 | AI1: =+AG1+1 -> 30 | AJ1: =+AH1+1 -> 31 | AK1: =+AI1+1 -> 31 | AL1: =+AJ1+1 -> 32 | ... BO1: =+BM1+1 -> 46
A2: Brave Blossom UG | D2: =Assumptions!J1 -> 2027 | E2: =D2+1 -> 2028 | F2: =E2+1 -> 2029 | G2: =F2+1 -> 2030 | H2: =G2+1 -> 2031 | I2: =H2+1 -> 2032 | J2: =I2+1 -> 2033 | K2: =J2+1 -> 2034 | L2: =K2+1 -> 2035 | ... AD2: =AC2+1 -> 2053 | AE2: =AC2+1 -> 2053 | AF2: =AD2+1 -> 2054 | AG2: =AE2+1 -> 2054 | AH2: =AF2+1 -> 2055 | AI2: =AG2+1 -> 2055 | AJ2: =AH2+1 -> 2056 | AK2: =AI2+1 -> 2056 | AL2: =AJ2+1 -> 2057 | ... BO2: =BM2+1 -> 2071 | BQ2: Total | BS2: Valuation Summary
A3: Physicals | BS3: Net Present Value (AUDM) | BT3: =BQ124/1000 -> 1320.0778
V4: =V6*5.5*3.55*1.45 -> 424668.75 | W4: =W6*5.5*3.55*1.45 -> 424668.75 | Z4: =Z6*5.5*3.55*1.45 -> 0 | AA4: =AA6*5.5*3.55*1.45 -> 0 | AC4: =AC6*5.5*3.55*1.45 -> 0 | AD4: =AD6*5.5*3.55*1.45 -> 0 | AE4: =AE6*5.5*3.55*1.45 -> 0 | AF4: =AF6*5.5*3.55*1.45 -> 0 | AG4: =AG6*5.5*3.55*1.45 -> 0 | AH4: =AH6*5.5*3.55*1.45 -> 0 | AI4: =AI6*5.5*3.55*1.45 -> 0 | AJ4: =AJ6*5.5*3.55*1.45 -> 0 | ... BO4: =BO6*5.5*3.55*1.45 -> 0
A5: Mining
A6: Development Metres | B6: m | D6: 0 | E6: 0 | F6: 0 | G6: 0 | H6: 7500 | I6: 15000 | J6: 15000 | K6: 15000 | L6: 15000 | M6: 15000 | N6: 15000 | O6: 15000 | P6: 15000 | Q6: 15000 | R6: 15000 | S6: 15000 | T6: 15000 | U6: 15000 | V6: 15000 | W6: 15000 | X6: 15000 | Y6: 7500 | AB6: 0 | AC6: 0 | AD6: 0 | AE6: 0 | AF6: 0 | AG6: 0 | AH6: 0 | AI6: 0 | AJ6: 0 | AK6: 0 | AL6: 0 | AM6: 0 | AN6: 0 | AO6: 0 | AP6: 0 | AQ6: 0 | AR6: 0 | AS6: 0 | AT6: 0 | AU6: 0 | AV6: 0 | AW6: 0 | AX6: 0 | AY6: 0 | AZ6: 0 | BA6: 0 | BB6: 0 | BC6: 0 | BD6: 0 | BE6: 0 | BF6: 0 | BG6: 0 | BH6: 0 | BI6: 0 | BJ6: 0 | BK6: 0 | BL6: 0 | BM6: 0 | BN6: 0 | BO6: 0 | BQ6: =SUM(D6:BO6) -> 255000 | BS6: Sensitivities Table
A7: Development Tonnes | B7: kt | D7: =(3*5.2*1.45*D6)/1000 -> 0 | E7: =(3*5.2*1.45*E6)/1000 -> 0 | F7: =(3*5.2*1.45*F6)/1000 -> 0 | G7: =(3*5.2*1.45*G6)/1000 -> 0 | H7: =(3*5.2*1.45*H6)/1000 -> 169.65 | I7: =(3*5.2*1.45*I6)/1000 -> 339.3 | J7: =(3*5.2*1.45*J6)/1000 -> 339.3 | K7: =(3*5.2*1.45*K6)/1000 -> 339.3 | ... BO7: =(3*5.2*1.45*BO6)/1000 -> 0 | BQ7: =SUM(D7:BO7) -> 5768.1 | BS7: Sales Price | BT7: 0
A8: Longwall Tonnes | B8: kt | J8: 7600 | K8: 7600 | L8: 7600 | M8: 7600 | N8: 7600 | O8: 7600 | P8: 7600 | Q8: 7600 | R8: 7600 | S8: 7600 | T8: 7600 | U8: 7600 | V8: 7600 | W8: 7600 | X8: 7600 | Y8: 7600 | Z8: 7600 | AA8: 7600 | AB8: 0 | AC8: 0 | AD8: 0 | AE8: 0 | AF8: 0 | AG8: 0 | AH8: 0 | AI8: 0 | AJ8: 0 | AK8: 0 | AL8: 0 | AM8: 0 | AN8: 0 | AO8: 0 | AP8: 0 | AQ8: 0 | AR8: 0 | AS8: 0 | AT8: 0 | AU8: 0 | AV8: 0 | AW8: 0 | AX8: 0 | AY8: 0 | AZ8: 0 | BA8: 0 | BB8: 0 | BC8: 0 | BD8: 0 | BE8: 0 | BF8: 0 | BG8: 0 | BH8: 0 | BI8: 0 | BJ8: 0 | BK8: 0 | BL8: 0 | BM8: 0 | BN8: 0 | BO8: 0 | BQ8: =SUM(D8:BO8) -> 136800 | BS8: Development Costs | BT8: 0
A9: Total ROM production | B9: kt | D9: =D7+D8 -> 0 | E9: =E7+E8 -> 0 | F9: =F7+F8 -> 0 | G9: =G7+G8 -> 0 | H9: =H7+H8 -> 169.65 | I9: =I7+I8 -> 339.3 | J9: =J7+J8 -> 7939.3 | K9: =K7+K8 -> 7939.3 | ... BO9: =BO7+BO8 -> 0 | BQ9: =SUM(D9:BO9) -> 142568.1 | BS9: Longwall Costs | BT9: 0
BS10: Outbye Costs | BT10: 0
A11: CHPP | BS11: Gas Drainage Costs | BT11: 0
A12: Primary Feed Tonnes | B12: kt | D12: =D9 -> 0 | E12: =E9 -> 0 | F12: =F9 -> 0 | G12: =G9 -> 0 | H12: =H9 -> 169.65 | I12: =I9 -> 339.3 | J12: =J9 -> 7939.3 | K12: =K9 -> 7939.3 | ... BO12: =BO9 -> 0 | BQ12: =SUM(D12:BO12) -> 142568.1 | BS12: CHPP Costs | BT12: 0
A13: Bypass Tonnes | B13: kt | D13: 0 | E13: 0 | F13: 0 | G13: 0 | H13: 0 | I13: 0 | J13: 0 | K13: 0 | L13: 0 | M13: 0 | N13: 0 | O13: 0 | P13: 0 | Q13: 0 | R13: 0 | S13: 0 | T13: 0 | U13: 0 | V13: 0 | W13: 0 | X13: 0 | Y13: 0 | Z13: 0 | AA13: 0 | AB13: 0 | AC13: 0 | AD13: 0 | AE13: 0 | AF13: 0 | AG13: 0 | AH13: 0 | AI13: 0 | AJ13: 0 | AK13: 0 | AL13: 0 | AM13: 0 | AN13: 0 | AO13: 0 | AP13: 0 | AQ13: 0 | AR13: 0 | AS13: 0 | AT13: 0 | AU13: 0 | AV13: 0 | AW13: 0 | AX13: 0 | AY13: 0 | AZ13: 0 | BA13: 0 | BB13: 0 | BC13: 0 | BD13: 0 | BE13: 0 | BF13: 0 | BG13: 0 | BH13: 0 | BI13: 0 | BJ13: 0 | BK13: 0 | BL13: 0 | BM13: 0 | BN13: 0 | BO13: 0 | BQ13: =SUM(D13:BO13) -> 0 | BS13: Total Overhead Costs | BT13: 0
A14: Plant Product Tonnes | B14: kt | D14: =D12*($C$15-0.1) -> 0 | E14: =E12*$C$15 -> 0 | F14: =F12*$C$15 -> 0 | G14: =G12*$C$15 -> 0 | H14: =H12*($C$15-20%) -> 81.432 | I14: =I12*($C$15-20%) -> 162.864 | J14: =J12*$C$15 -> 5398.724 | K14: =K12*$C$15 -> 5398.724 | L14: =L12*$C$15 -> 5398.724 | M14: =M12*$C$15 -> 5398.724 | N14: =N12*$C$15 -> 5398.724 | O14: =O12*$C$15 -> 5398.724 | P14: =P12*$C$15 -> 5398.724 | Q14: =Q12*$C$15 -> 5398.724 | ... BO14: =BO12*$C$15 -> 0 | BQ14: =SUM(D14:BO14) -> 96844.518 | BS14: Total Capital Costs | BT14: 0
A15: CHPP Yield | B15: % | C15: 0.68 | D15: =IFERROR(D14/D12,0) -> 0 | E15: =IFERROR(E14/E12,0) -> 0 | F15: =IFERROR(F14/F12,0) -> 0 | G15: =IFERROR(G14/G12,0) -> 0 | H15: =IFERROR(H14/H12,0) -> 0.48 | I15: =IFERROR(I14/I12,0) -> 0.48 | J15: =IFERROR(J14/J12,0) -> 0.68 | K15: =IFERROR(K14/K12,0) -> 0.68 | ... BO15: =IFERROR(BO14/BO12,0) -> 0 | BQ15: =IFERROR(BQ14/BQ12,0) -> 0.67928603
BS16: LOM volumes
A17: Operations Yield | D17: =IFERROR(D19/D9,0) -> 0 | E17: =IFERROR(E19/E9,0) -> 0 | F17: =IFERROR(F19/F9,0) -> 0 | G17: =IFERROR(G19/G9,0) -> 0 | H17: =IFERROR(H19/H9,0) -> 0.48 | I17: =IFERROR(I19/I9,0) -> 0.48 | J17: =IFERROR(J19/J9,0) -> 0.68 | K17: =IFERROR(K19/K9,0) -> 0.68 | ... BO17: =IFERROR(BO19/BO9,0) -> 0 | BQ17: =IFERROR(BQ19/BQ9,0) -> 0.67928603 | BS17: Development metres (km) | BT17: =BQ6/1000 -> 255
BS18: Longwall ROM tonnes / Dev Metres | BT18: =(BT17*1000)/BT20 -> 1.8640351
A19: Saleable Production | B19: kt | D19: =D13+D14 -> 0 | E19: =E13+E14 -> 0 | F19: =F13+F14 -> 0 | G19: =G13+G14 -> 0 | H19: =H13+H14 -> 81.432 | I19: =I13+I14 -> 162.864 | J19: =J13+J14 -> 5398.724 | K19: =K13+K14 -> 5398.724 | ... BO19: =BO13+BO14 -> 0 | BQ19: =SUM(D19:BO19) -> 96844.518 | BS19: Development ROM (kt) | BT19: =BQ7 -> 5768.1
BS20: Longwall ROM (kt) | BT20: =BQ8 -> 136800
A21: Carbon | BS21: Total ROM (kt) | BT21: =BT19+BT20 -> 142568.1
A22: Coal Mine Waste Gass | B22: t CO2e | C22: 0.13 | H22: =IF(H9>0,H9*1000*$C$22+20000,0) -> 42054.5 | I22: =IF(I9>0,I9*1000*$C$22+20000,0) -> 64109 | J22: =IF(J9>0,J9*1000*$C$22+20000,0) -> 1052109 | K22: =IF(K9>0,K9*1000*$C$22+20000,0) -> 1052109 | L22: =IF(L9>0,L9*1000*$C$22+20000,0) -> 1052109 | M22: =IF(M9>0,M9*1000*$C$22+20000,0) -> 1052109 | N22: =IF(N9>0,N9*1000*$C$22+20000,0) -> 1052109 | O22: =IF(O9>0,O9*1000*$C$22+20000,0) -> 1052109 | ... BO22: =IF(BO9>0,BO9*1000*$C$22+20000,0) -> 0 | BQ22: =SUM(D22:BO22) -> 18933853
A23: Decomission Mines Emissions | B23: t CO2e | D23: =IF('Decommissioned Mine'!$B$5="Springbok + Brave Blossom",'Decommissioned Mine'!E2,0) -> 0 | E23: =IF('Decommissioned Mine'!$B$5="Springbok + Brave Blossom",'Decommissioned Mine'!F2,0) -> 0 | F23: =IF('Decommissioned Mine'!$B$5="Springbok + Brave Blossom",'Decommissioned Mine'!G2,0) -> 0 | G23: =IF('Decommissioned Mine'!$B$5="Springbok + Brave Blossom",'Decommissioned Mine'!H2,0) -> 0 | H23: =IF('Decommissioned Mine'!$B$5="Springbok + Brave Blossom",'Decommissioned Mine'!I2,0) -> 0 | I23: =IF('Decommissioned Mine'!$B$5="Springbok + Brave Blossom",'Decommissioned Mine'!J2,0) -> 0 | J23: =IF('Decommissioned Mine'!$B$5="Springbok + Brave Blossom",'Decommissioned Mine'!K2,0) -> 0 | K23: =IF('Decommissioned Mine'!$B$5="Springbok + Brave Blossom",'Decommissioned Mine'!L2,0) -> 0 | ... BO23: =IF('Decommissioned Mine'!$B$5="Springbok + Brave Blossom",'Decommissioned Mine'!BP2,0) -> 0 | BQ23: =SUM(D23:BO23) -> 4678988.7 | BS23: Remaining Mine Life
A24: Total Scope 1 Emissions | B24: t CO2e | H24: =H23+H22 -> 42054.5 | I24: =I23+I22 -> 64109 | J24: =J23+J22 -> 1052109 | K24: =K23+K22 -> 1052109 | L24: =L23+L22 -> 1052109 | M24: =M23+M22 -> 1052109 | N24: =N23+N22 -> 1052109 | O24: =O23+O22 -> 1052109 | ... BO24: =BO23+BO22 -> 0 | BQ24: =SUM(D24:BO24) -> 23612842
A25: Safeguard - Hybrid Declining Baseline | B25: t CO2e | D25: =(D9*1000*'Decommissioned Mine'!E22)+'Decommissioned Mine'!E21*D23 -> 0 | E25: =(E9*1000*'Decommissioned Mine'!F22)+'Decommissioned Mine'!F21*E23 -> 0 | F25: =(F9*1000*'Decommissioned Mine'!G22)+'Decommissioned Mine'!G21*F23 -> 0 | G25: =(G9*1000*'Decommissioned Mine'!H22)+'Decommissioned Mine'!H21*G23 -> 0 | H25: =(H9*1000*'Decommissioned Mine'!I22)+('Decommissioned Mine'!I21*H23) -> 9474.9402 | I25: =(I9*1000*'Decommissioned Mine'!J22)+'Decommissioned Mine'!J21*I23 -> 17925.563 | J25: =(J9*1000*'Decommissioned Mine'!K22)+'Decommissioned Mine'!K21*J23 -> 395473.19 | K25: =(K9*1000*'Decommissioned Mine'!L22)+'Decommissioned Mine'!L21*K23 -> 371505.11 | L25: =(L9*1000*'Decommissioned Mine'!M22)+'Decommissioned Mine'!M21*L23 -> 347537.04 | M25: =(M9*1000*'Decommissioned Mine'!N22)+'Decommissioned Mine'!N21*M23 -> 323568.97 | N25: =(N9*1000*'Decommissioned Mine'!O22)+'Decommissioned Mine'!O21*N23 -> 299600.9 | O25: =(O9*1000*'Decommissioned Mine'!P22)+'Decommissioned Mine'!P21*O23 -> 275632.83 | P25: =(P9*1000*'Decommissioned Mine'!Q22)+'Decommissioned Mine'!Q21*P23 -> 251664.75 | ... AP25: =(AP9*1000*'Decommissioned Mine'!AQ22)+'Decommissioned Mine'!AQ21*AP23 -> 1.1680346e-11 | AQ25: =(AQ9*1000*'Decommissioned Mine'!AQ22)+'Decommissioned Mine'!AQ21*AQ23 -> 1.0604665e-11 | AR25: =(AR9*1000*'Decommissioned Mine'!AR22)+'Decommissioned Mine'!AR21*AR23 -> 9.6552291e-12 | AS25: =(AS9*1000*'Decommissioned Mine'!AS22)+'Decommissioned Mine'!AS21*AS23 -> 8.8122618e-12 | AT25: =(AT9*1000*'Decommissioned Mine'!AT22)+'Decommissioned Mine'!AT21*AT23 -> 8.0598081e-12 | AU25: =(AU9*1000*'Decommissioned Mine'!AU22)+'Decommissioned Mine'!AU21*AU23 -> 2.5179858e-12 | AV25: =(AV9*1000*'Decommissioned Mine'!AV22)+'Decommissioned Mine'!AV21*AV23 -> 0 | AW25: =(AW9*1000*'Decommissioned Mine'!AW22)+'Decommissioned Mine'!AW21*AW23 -> 0 | AX25: =(AX9*1000*'Decommissioned Mine'!AX22)+'Decommissioned Mine'!AX21*AX23 -> 0 | ... BO25: =(BO9*1000*'Decommissioned Mine'!BO22)+'Decommissioned Mine'!BO21*BO23 -> 0 | BQ25: =SUM(D25:BO25) -> 3489506.5
A26: Emissions above (or below) baseline | H26: =H24-H25 -> 32579.56 | I26: =I24-I25 -> 46183.437 | J26: =J24-J25 -> 656635.81 | K26: =K24-K25 -> 680603.89 | L26: =L24-L25 -> 704571.96 | M26: =M24-M25 -> 728540.03 | N26: =N24-N25 -> 752508.1 | O26: =O24-O25 -> 776476.17 | ... BO26: =BO24-BO25 -> 0 | BQ26: =BQ24-BQ25 -> 20123335
A28: Marketing
A30: Sales
A31: PHCC | B31: kt | C31: 0 | D31: =$C$31*D19 -> 0 | E31: =$C$31*E19 -> 0 | F31: =$C$31*F19 -> 0 | G31: =$C$31*G19 -> 0 | H31: =$C$31*H19 -> 0 | I31: =$C$31*I19 -> 0 | J31: =$C$31*J19 -> 0 | K31: =$C$31*K19 -> 0 | ... BO31: =$C$31*BO19 -> 0 | BQ31: =SUM(D31:BO31) -> 0
A32: 88% PHCC | B32: kt | C32: 1 | D32: =$C$32*D19 -> 0 | E32: =$C$32*E19 -> 0 | F32: =$C$32*F19 -> 0 | G32: =$C$32*G19 -> 0 | H32: =$C$32*H19 -> 81.432 | I32: =$C$32*I19 -> 162.864 | J32: =$C$32*J19 -> 5398.724 | K32: =$C$32*K19 -> 5398.724 | ... BO32: =$C$32*BO19 -> 0 | BQ32: =SUM(D32:BO32) -> 96844.518
A33: Thermal GCN | B33: kt | C33: 0 | D33: =$C$33*D19 -> 0 | E33: =$C$33*E19 -> 0 | F33: =$C$33*F19 -> 0 | G33: =$C$33*G19 -> 0 | H33: =$C$33*H19 -> 0 | I33: =$C$33*I19 -> 0 | J33: =$C$33*J19 -> 0 | K33: =$C$33*K19 -> 0 | ... BO33: =$C$33*BO19 -> 0 | BQ33: =SUM(D33:BO33) -> 0
A34: Total Sales | B34: kt | D34: =SUM(D31:D33) -> 0 | E34: =SUM(E31:E33) -> 0 | F34: =SUM(F31:F33) -> 0 | G34: =SUM(G31:G33) -> 0 | H34: =SUM(H31:H33) -> 81.432 | I34: =SUM(I31:I33) -> 162.864 | J34: =SUM(J31:J33) -> 5398.724 | K34: =SUM(K31:K33) -> 5398.724 | ... BO34: =SUM(BO31:BO33) -> 0 | BQ34: =SUM(BQ31:BQ33) -> 96844.518
A36: Product Ash (as received)
A37: =$A$31 -> PHCC | B37: % | H37: 0 | I37: 0 | J37: 0 | K37: 0 | L37: 0 | M37: 0 | N37: 0 | O37: 0 | P37: 0 | Q37: 0 | R37: 0 | S37: 0 | T37: 0 | U37: 0 | V37: 0 | W37: 0 | X37: 0 | Y37: 0 | Z37: 0 | AA37: 0 | AB37: 0 | AC37: 0 | AD37: 0 | AE37: 0 | AF37: 0 | AG37: 0 | AH37: 0 | AI37: 0 | AJ37: 0 | AK37: 0 | AL37: 0 | AM37: 0 | AN37: 0 | AO37: 0 | AP37: 0 | AQ37: 0 | AR37: 0 | AS37: 0 | AT37: 0 | AU37: 0 | AV37: 0 | AW37: 0 | AX37: 0 | AY37: 0 | AZ37: 0 | BA37: 0 | BB37: 0 | BC37: 0 | BD37: 0 | BE37: 0 | BF37: 0 | BG37: 0 | BH37: 0 | BI37: 0 | BJ37: 0 | BK37: 0 | BL37: 0 | BM37: 0 | BN37: 0 | BO37: 0
A38: =$A$32 -> 88% PHCC | B38: % | H38: 0.095 | I38: 0.095 | J38: 0.095 | K38: 0.095 | L38: 0.095 | M38: 0.095 | N38: 0.095 | O38: 0.095 | P38: 0.095 | Q38: 0.095 | R38: 0.095 | S38: 0.095 | T38: 0.095 | U38: 0.095 | V38: 0.095 | W38: 0.095 | X38: 0.095 | Y38: 0.095 | Z38: 0.095 | AA38: 0.095 | AB38: 0.095 | AC38: 0.095 | AD38: 0.095 | AE38: 0.095 | AF38: 0.095 | AG38: 0.095 | AH38: 0.095 | AI38: 0.095 | AJ38: 0.095 | AK38: 0.095 | AL38: 0.095 | AM38: 0.095 | AN38: 0.095 | AO38: 0.095 | AP38: 0.095 | AQ38: 0.095 | AR38: 0.095 | AS38: 0.095 | AT38: 0.095 | AU38: 0.095 | AV38: 0.095 | AW38: 0.095 | AX38: 0.095 | AY38: 0.095 | AZ38: 0.095 | BA38: 0.095 | BB38: 0.095 | BC38: 0.095 | BD38: 0.095 | BE38: 0.095 | BF38: 0.095 | BG38: 0.095 | BH38: 0.095 | BI38: 0.095 | BJ38: 0.095 | BK38: 0.095 | BL38: 0.095 | BM38: 0.095 | BN38: 0.095 | BO38: 0.095
A39: =$A$33 -> Thermal GCN | B39: % | H39: 0 | I39: 0 | J39: 0 | K39: 0 | L39: 0 | M39: 0 | N39: 0 | O39: 0 | P39: 0 | Q39: 0 | R39: 0 | S39: 0 | T39: 0 | U39: 0 | V39: 0 | W39: 0 | X39: 0 | Y39: 0 | Z39: 0 | AA39: 0 | AB39: 0 | AC39: 0 | AD39: 0 | AE39: 0 | AF39: 0 | AG39: 0 | AH39: 0 | AI39: 0 | AJ39: 0 | AK39: 0 | AL39: 0 | AM39: 0 | AN39: 0 | AO39: 0 | AP39: 0 | AQ39: 0 | AR39: 0 | AS39: 0 | AT39: 0 | AU39: 0 | AV39: 0 | AW39: 0 | AX39: 0 | AY39: 0 | AZ39: 0 | BA39: 0 | BB39: 0 | BC39: 0 | BD39: 0 | BE39: 0 | BF39: 0 | BG39: 0 | BH39: 0 | BI39: 0 | BJ39: 0 | BK39: 0 | BL39: 0 | BM39: 0 | BN39: 0 | BO39: 0
A41: Product Energy (gar)
A42: =$A$31 -> PHCC | B42: kcal/kg(gar) | H42: 0 | I42: 0 | J42: 0 | K42: 0 | L42: 0 | M42: 0 | N42: 0 | O42: 0 | P42: 0 | Q42: 0 | R42: 0 | S42: 0 | T42: 0 | U42: 0 | V42: 0 | W42: 0 | X42: 0 | Y42: 0 | Z42: 0 | AA42: 0 | AB42: 0 | AC42: 0 | AD42: 0 | AE42: 0 | AF42: 0 | AG42: 0 | AH42: 0 | AI42: 0 | AJ42: 0 | AK42: 0 | AL42: 0 | AM42: 0 | AN42: 0 | AO42: 0 | AP42: 0 | AQ42: 0 | AR42: 0 | AS42: 0 | AT42: 0 | AU42: 0 | AV42: 0 | AW42: 0 | AX42: 0 | AY42: 0 | AZ42: 0 | BA42: 0 | BB42: 0 | BC42: 0 | BD42: 0 | BE42: 0 | BF42: 0 | BG42: 0 | BH42: 0 | BI42: 0 | BJ42: 0 | BK42: 0 | BL42: 0 | BM42: 0 | BN42: 0 | BO42: 0
A43: =$A$32 -> 88% PHCC | B43: kcal/kg(gar) | H43: 0 | I43: 0 | J43: 0 | K43: 0 | L43: 0 | M43: 0 | N43: 0 | O43: 0 | P43: 0 | Q43: 0 | R43: 0 | S43: 0 | T43: 0 | U43: 0 | V43: 0 | W43: 0 | X43: 0 | Y43: 0 | Z43: 0 | AA43: 0 | AB43: 0 | AC43: 0 | AD43: 0 | AE43: 0 | AF43: 0 | AG43: 0 | AH43: 0 | AI43: 0 | AJ43: 0 | AK43: 0 | AL43: 0 | AM43: 0 | AN43: 0 | AO43: 0 | AP43: 0 | AQ43: 0 | AR43: 0 | AS43: 0 | AT43: 0 | AU43: 0 | AV43: 0 | AW43: 0 | AX43: 0 | AY43: 0 | AZ43: 0 | BA43: 0 | BB43: 0 | BC43: 0 | BD43: 0 | BE43: 0 | BF43: 0 | BG43: 0 | BH43: 0 | BI43: 0 | BJ43: 0 | BK43: 0 | BL43: 0 | BM43: 0 | BN43: 0 | BO43: 0
A44: =$A$33 -> Thermal GCN | B44: kcal/kg(gar) | H44: 6260 | I44: 6260 | J44: 6260 | K44: 6260 | L44: 6260 | M44: 6260 | N44: 6260 | O44: 6260 | P44: 6260 | Q44: 6260 | R44: 6260 | S44: 6260 | T44: 6260 | U44: 6260 | V44: 6260 | W44: 6260 | X44: 6260 | Y44: 6260 | Z44: 6260 | AA44: 6260 | AB44: 6260 | AC44: 6260 | AD44: 6260 | AE44: 6260 | AF44: 6260 | AG44: 6260 | AH44: 6260 | AI44: 6260 | AJ44: 6260 | AK44: 6260 | AL44: 6260 | AM44: 6260 | AN44: 6260 | AO44: 6260 | AP44: 6260 | AQ44: 6260 | AR44: 6260 | AS44: 6260 | AT44: 6260 | AU44: 6260 | AV44: 6260 | AW44: 6260 | AX44: 6260 | AY44: 6260 | AZ44: 6260 | BA44: 6260 | BB44: 6260 | BC44: 6260 | BD44: 6260 | BE44: 6260 | BF44: 6260 | BG44: 6260 | BH44: 6260 | BI44: 6260 | BJ44: 6260 | BK44: 6260 | BL44: 6260 | BM44: 6260 | BN44: 6260 | BO44: 6260
A46: GAR-> NAR adjustment | D46: =Assumptions!$B$16 -> 260 | E46: =Assumptions!$B$16 -> 260 | F46: =Assumptions!$B$16 -> 260 | G46: =Assumptions!$B$16 -> 260 | H46: =Assumptions!$B$16 -> 260 | I46: =Assumptions!$B$16 -> 260 | J46: =Assumptions!$B$16 -> 260 | K46: =Assumptions!$B$16 -> 260 | ... BO46: =Assumptions!$B$16 -> 260
A47: Basis of coal prices | D47: =Assumptions!$B$17 -> 6000 | E47: =Assumptions!$B$17 -> 6000 | F47: =Assumptions!$B$17 -> 6000 | G47: =Assumptions!$B$17 -> 6000 | H47: =Assumptions!$B$17 -> 6000 | I47: =Assumptions!$B$17 -> 6000 | J47: =Assumptions!$B$17 -> 6000 | K47: =Assumptions!$B$17 -> 6000 | ... BO47: =Assumptions!$B$17 -> 6000
A49: Product Energy (nar)
A50: =$A$31 -> PHCC | B50: kcal/kg(nar) | D50: =IF(D31>0,D42-D$46,0) -> 0 | E50: =IF(E31>0,E42-E$46,0) -> 0 | F50: =IF(F31>0,F42-F$46,0) -> 0 | G50: =IF(G31>0,G42-G$46,0) -> 0 | H50: 0 | I50: 0 | J50: 0 | K50: 0 | L50: 0 | M50: 0 | N50: 0 | O50: 0 | P50: 0 | Q50: 0 | R50: 0 | S50: 0 | T50: 0 | U50: 0 | V50: 0 | W50: 0 | X50: 0 | Y50: 0 | Z50: 0 | AA50: 0 | AB50: 0 | AC50: 0 | AD50: 0 | AE50: 0 | AF50: 0 | AG50: 0 | AH50: 0 | AI50: 0 | AJ50: 0 | AK50: 0 | AL50: 0 | AM50: 0 | AN50: 0 | AO50: 0 | AP50: 0 | AQ50: 0 | AR50: 0 | AS50: 0 | AT50: 0 | AU50: 0 | AV50: 0 | AW50: 0 | AX50: 0 | AY50: 0 | AZ50: 0 | BA50: 0 | BB50: 0 | BC50: 0 | BD50: 0 | BE50: 0 | BF50: 0 | BG50: 0 | BH50: 0 | BI50: 0 | BJ50: 0 | BK50: 0 | BL50: 0 | BM50: 0 | BN50: 0 | BO50: 0
A51: =$A$32 -> 88% PHCC | B51: kcal/kg(nar) | D51: =IF(D32>0,D43-D$46,0) -> 0 | E51: =IF(E32>0,E43-E$46,0) -> 0 | F51: =IF(F32>0,F43-F$46,0) -> 0 | G51: =IF(G32>0,G43-G$46,0) -> 0 | H51: 0 | I51: 0 | J51: 0 | K51: 0 | L51: 0 | M51: 0 | N51: 0 | O51: 0 | P51: 0 | Q51: 0 | R51: 0 | S51: 0 | T51: 0 | U51: 0 | V51: 0 | W51: 0 | X51: 0 | Y51: 0 | Z51: 0 | AA51: 0 | AB51: 0 | AC51: 0 | AD51: 0 | AE51: 0 | AF51: 0 | AG51: 0 | AH51: 0 | AI51: 0 | AJ51: 0 | AK51: 0 | AL51: 0 | AM51: 0 | AN51: 0 | AO51: 0 | AP51: 0 | AQ51: 0 | AR51: 0 | AS51: 0 | AT51: 0 | AU51: 0 | AV51: 0 | AW51: 0 | AX51: 0 | AY51: 0 | AZ51: 0 | BA51: 0 | BB51: 0 | BC51: 0 | BD51: 0 | BE51: 0 | BF51: 0 | BG51: 0 | BH51: 0 | BI51: 0 | BJ51: 0 | BK51: 0 | BL51: 0 | BM51: 0 | BN51: 0 | BO51: 0
A52: =$A$33 -> Thermal GCN | B52: kcal/kg(nar) | H52: =IF(H33>0,H44-H$46,0) -> 0 | I52: =IF(I33>0,I44-I$46,0) -> 0 | J52: =IF(J33>0,J44-J$46,0) -> 0 | K52: =IF(K33>0,K44-K$46,0) -> 0 | L52: =IF(L33>0,L44-L$46,0) -> 0 | M52: =IF(M33>0,M44-M$46,0) -> 0 | N52: =IF(N33>0,N44-N$46,0) -> 0 | O52: =IF(O33>0,O44-O$46,0) -> 0 | ... BO52: =IF(BO33>0,BO44-BO$46,0) -> 0
A54: Realised Price
A55: =$A$31 -> PHCC | B55: USD/t | D55: =IF(D31>0,Assumptions!J6,0) -> 0 | E55: =IF(E31>0,Assumptions!K6,0) -> 0 | F55: =IF(F31>0,Assumptions!L6,0) -> 0 | G55: =IF(G31>0,Assumptions!M6,0) -> 0 | H55: =IF(H31>0,Assumptions!N6,0) -> 0 | I55: =IF(I31>0,Assumptions!O6,0) -> 0 | J55: =IF(J31>0,Assumptions!P6,0) -> 0 | K55: =IF(K31>0,Assumptions!Q6,0) -> 0 | ... BO55: =IF(BO31>0,Assumptions!BU6,0) -> 0
A56: =$A$32 -> 88% PHCC | B56: USD/t | D56: =IF(D32>0,Assumptions!J$7,0) -> 0 | E56: =IF(E32>0,Assumptions!K$7,0) -> 0 | F56: =IF(F32>0,Assumptions!L$7,0) -> 0 | G56: =IF(G32>0,Assumptions!M$7,0) -> 0 | H56: =IF(H32>0,Assumptions!N$7,0) -> 211.2 | I56: =IF(I32>0,Assumptions!O$7,0) -> 211.2 | J56: =IF(J32>0,Assumptions!P$7,0) -> 211.2 | K56: =IF(K32>0,Assumptions!Q$7,0) -> 211.2 | ... BO56: =IF(BO32>0,Assumptions!BU$7,0) -> 0
A57: =$A$33 -> Thermal GCN | B57: USD/t | D57: =IF(D33>0,IF(D52>Assumptions!J$12,Assumptions!J$8,IF(D52>Assumptions!J$13,Assumptions!J$8,Assumptions!J$9))*(D52/D$47),0) -> 0 | E57: =IF(E33>0,IF(E52>Assumptions!K$12,Assumptions!K$8,IF(E52>Assumptions!K$13,Assumptions!K$8,Assumptions!K$9))*(E52/E$47),0) -> 0 | F57: =IF(F33>0,IF(F52>Assumptions!L$12,Assumptions!L$8,IF(F52>Assumptions!L$13,Assumptions!L$8,Assumptions!L$9))*(F52/F$47),0) -> 0 | G57: =IF(G33>0,IF(G52>Assumptions!M$12,Assumptions!M$8,IF(G52>Assumptions!M$13,Assumptions!M$8,Assumptions!M$9))*(G52/G$47),0) -> 0 | H57: =IF(H33>0,IF(H52>Assumptions!N$12,Assumptions!N$8,IF(H52>Assumptions!N$13,Assumptions!N$8,Assumptions!N$9))*(H52/H$47),0) -> 0 | I57: =IF(I33>0,IF(I52>Assumptions!O$12,Assumptions!O$8,IF(I52>Assumptions!O$13,Assumptions!O$8,Assumptions!O$9))*(I52/I$47),0) -> 0 | J57: =IF(J33>0,IF(J52>Assumptions!P$12,Assumptions!P$8,IF(J52>Assumptions!P$13,Assumptions!P$8,Assumptions!P$9))*(J52/J$47),0) -> 0 | K57: =IF(K33>0,IF(K52>Assumptions!Q$12,Assumptions!Q$8,IF(K52>Assumptions!Q$13,Assumptions!Q$8,Assumptions!Q$9))*(K52/K$47),0) -> 0 | ... BO57: =IF(BO33>0,IF(BO52>Assumptions!BU$12,Assumptions!BU$8,IF(BO52>Assumptions!BU$13,Assumptions!BU$8,Assumptions!BU$9))*(BO52/BO$47),0) -> 0
A58: Average Export Realised Price | B58: USD/t | D58: =IFERROR(SUMPRODUCT(D31:D33,D55:D57)/D34,0) -> 0 | E58: =IFERROR(SUMPRODUCT(E31:E33,E55:E57)/E34,0) -> 0 | F58: =IFERROR(SUMPRODUCT(F31:F33,F55:F57)/F34,0) -> 0 | G58: =IFERROR(SUMPRODUCT(G31:G33,G55:G57)/G34,0) -> 0 | H58: =IFERROR(SUMPRODUCT(H31:H33,H55:H57)/H34,0) -> 211.2 | I58: =IFERROR(SUMPRODUCT(I31:I33,I55:I57)/I34,0) -> 211.2 | J58: =IFERROR(SUMPRODUCT(J31:J33,J55:J57)/J34,0) -> 211.2 | K58: =IFERROR(SUMPRODUCT(K31:K33,K55:K57)/K34,0) -> 211.2 | ... BO58: =IFERROR(SUMPRODUCT(BO31:BO33,BO55:BO57)/BO34,0) -> 0
A60: Total Revenue | B60: USDk | D60: =SUMPRODUCT(D31:D32,D55:D56) -> 0 | E60: =SUMPRODUCT(E31:E32,E55:E56) -> 0 | F60: =SUMPRODUCT(F31:F32,F55:F56) -> 0 | G60: =SUMPRODUCT(G31:G32,G55:G56) -> 0 | H60: =SUMPRODUCT(H31:H32,H55:H56) -> 17198.438 | I60: =SUMPRODUCT(I31:I32,I55:I56) -> 34396.877 | J60: =SUMPRODUCT(J31:J32,J55:J56) -> 1140210.5 | K60: =SUMPRODUCT(K31:K32,K55:K56) -> 1140210.5 | ... BO60: =SUMPRODUCT(BO31:BO32,BO55:BO56) -> 0 | BQ60: =SUM(D60:BO60) -> 20453562
A61: FX | B61: USD:AUD | D61: =Assumptions!I4 -> 0.69 | E61: =Assumptions!J4 -> 0.69 | F61: =Assumptions!K4 -> 0.69 | G61: =Assumptions!L4 -> 0.69 | H61: =Assumptions!M4 -> 0.69 | I61: =Assumptions!N4 -> 0.69 | J61: =Assumptions!O4 -> 0.69 | K61: =Assumptions!P4 -> 0.69 | ... AD61: =Assumptions!AI4 -> 0.69 | AE61: =Assumptions!AI4 -> 0.69 | AF61: =Assumptions!AJ4 -> 0.69 | AG61: =Assumptions!AK4 -> 0.69 | AH61: =Assumptions!AL4 -> 0.69 | AI61: =Assumptions!AM4 -> 0.69 | AJ61: =Assumptions!AN4 -> 0.69 | AK61: =Assumptions!AO4 -> 0.69 | AL61: =Assumptions!AP4 -> 0.69 | ... BO61: =Assumptions!BS4 -> 0.69
A62: Total Revenue | B62: AUD | D62: =(D60/D61)*(1+$BT$7) -> 0 | E62: =(E60/E61)*(1+$BT$7) -> 0 | F62: =(F60/F61)*(1+$BT$7) -> 0 | G62: =(G60/G61)*(1+$BT$7) -> 0 | H62: =(H60/H61)*(1+$BT$7) -> 24925.273 | I62: =(I60/I61)*(1+$BT$7) -> 49850.546 | J62: =(J60/J61)*(1+$BT$7) -> 1652479 | K62: =(K60/K61)*(1+$BT$7) -> 1652479 | ... BO62: =(BO60/BO61)*(1+$BT$7) -> 0 | BQ62: =SUM(D62:BO62) -> 29642844
A63: Average Realisation | B63: AUD/t | D63: =IFERROR(D62/D19,0) -> 0 | E63: =IFERROR(E62/E19,0) -> 0 | F63: =IFERROR(F62/F19,0) -> 0 | G63: =IFERROR(G62/G19,0) -> 0 | H63: =IFERROR(H62/H19,0) -> 306.08696 | I63: =IFERROR(I62/I19,0) -> 306.08696 | J63: =IFERROR(J62/J19,0) -> 306.08696 | K63: =IFERROR(K62/K19,0) -> 306.08696 | ... BO63: =IFERROR(BO62/BO19,0) -> 0 | BQ63: =IFERROR(BQ62/BQ19,0) -> 306.08696
A65: Costs
A67: Direct Mining Costs
A69: Development Costs | B69: AUD/m | C69: 5600 | D69: =IF(D6>0,$C$69*(1+$BT$8),0) -> 0 | E69: =IF(E6>0,$C$69*(1+$BT$8),0) -> 0 | F69: =IF(F6>0,$C$69*(1+$BT$8),0) -> 0 | G69: =IF(G6>0,$C$69*(1+$BT$8),0) -> 0 | H69: =IF(H6>0,$C$69*(1+$BT$8),0) -> 5600 | I69: =IF(I6>0,$C$69*(1+$BT$8),0) -> 5600 | J69: =IF(J6>0,$C$69*(1+$BT$8),0) -> 5600 | K69: =IF(K6>0,$C$69*(1+$BT$8),0) -> 5600 | ... BO69: =IF(BO6>0,$C$69*(1+$BT$8),0) -> 0
A70: Total Development Costs | B70: AUDk | D70: =D6*D69/1000 -> 0 | E70: =E6*E69/1000 -> 0 | F70: =F6*F69/1000 -> 0 | G70: =G6*G69/1000 -> 0 | H70: =H6*H69/1000 -> 42000 | I70: =I6*I69/1000 -> 84000 | J70: =J6*J69/1000 -> 84000 | K70: =K6*K69/1000 -> 84000 | ... BO70: =BO6*BO69/1000 -> 0 | BQ70: =SUM(D70:BO70) -> 1428000
A72: Longwall Costs | B72: AUD/LWt | C72: 15 | D72: =IF(D8>0,$C$72*(1+$BT$9),0) -> 0 | E72: =IF(E8>0,$C$72*(1+$BT$9),0) -> 0 | F72: =IF(F8>0,$C$72*(1+$BT$9),0) -> 0 | G72: =IF(G8>0,$C$72*(1+$BT$9),0) -> 0 | H72: =IF(H8>0,$C$72*(1+$BT$9),0) -> 0 | I72: =IF(I8>0,$C$72*(1+$BT$9),0) -> 0 | J72: =IF(J8>0,$C$72*(1+$BT$9),0) -> 15 | K72: =IF(K8>0,$C$72*(1+$BT$9),0) -> 15 | ... BO72: =IF(BO8>0,$C$72*(1+$BT$9),0) -> 0
A73: Total Longwall Costs | B73: AUDk | D73: =D8*D72 -> 0 | E73: =E8*E72 -> 0 | F73: =F8*F72 -> 0 | G73: =G8*G72 -> 0 | H73: =H8*H72 -> 0 | I73: =I8*I72 -> 0 | J73: =J8*J72 -> 114000 | K73: =K8*K72 -> 114000 | ... BO73: =BO8*BO72 -> 0 | BQ73: =SUM(D73:BO73) -> 2052000
A75: Total Outbye Costs | B75: AUDk | C75: 240000 | D75: =IF(D9>0,$C$75)*(1+$BT$10) -> 0 | E75: =IF(E9>0,$C$75)*(1+$BT$10) -> 0 | F75: =IF(F9>0,$C$75)*(1+$BT$10) -> 0 | G75: =IF(G9>0,$C$75)*(1+$BT$10) -> 0 | H75: =IF(H9>0,$C$75)*(1+$BT$10)/10 -> 24000 | I75: =IF(I9>0,$C$75)*(1+$BT$10)/10 -> 24000 | J75: =IF(J9>0,$C$75)*(1+$BT$10) -> 240000 | K75: =IF(K9>0,$C$75)*(1+$BT$10) -> 240000 | L75: =IF(L9>0,$C$75)*(1+$BT$10) -> 240000 | M75: =IF(M9>0,$C$75)*(1+$BT$10) -> 240000 | N75: =IF(N9>0,$C$75)*(1+$BT$10) -> 240000 | O75: =IF(O9>0,$C$75)*(1+$BT$10) -> 240000 | P75: =IF(P9>0,$C$75)*(1+$BT$10) -> 240000 | Q75: =IF(Q9>0,$C$75)*(1+$BT$10) -> 240000 | ... BO75: =IF(BO9>0,$C$75)*(1+$BT$10) -> 0 | BQ75: =SUM(D75:BO75) -> 4368000
A77: Gas Drainage Costs | B77: AUD/t | C77: 6 | D77: =IF(D9>0,$C$77*(1+$BT$11),0) -> 0 | E77: =IF(E9>0,$C$77*(1+$BT$11),0) -> 0 | F77: =IF(F9>0,$C$77*(1+$BT$11),0) -> 0 | G77: =IF(G9>0,$C$77*(1+$BT$11),0) -> 0 | H77: =IF(H9>0,$C$77*(1+$BT$11),0) -> 6 | I77: =IF(I9>0,$C$77*(1+$BT$11),0) -> 6 | J77: =IF(J9>0,$C$77*(1+$BT$11),0) -> 6 | K77: =IF(K9>0,$C$77*(1+$BT$11),0) -> 6 | ... BO77: =IF(BO9>0,$C$77*(1+$BT$11),0) -> 0
A78: Total Gas Drainage Costs | B78: AUDk | D78: =D77*D9 -> 0 | E78: =E77*E9 -> 0 | F78: =F77*F9 -> 0 | G78: =G77*G9 -> 0 | H78: =H77*H9 -> 1017.9 | I78: =I77*I9 -> 2035.8 | J78: =J77*J9 -> 47635.8 | K78: =K77*K9 -> 47635.8 | ... BO78: =BO77*BO9 -> 0 | BQ78: =SUM(D78:BO78) -> 855408.6
A80: Fixed CHPP Costs | B80: AUDk | C80: 20000 | D80: =IF(D6>0,$C$80,0) -> 0 | E80: =IF(E6>0,$C$80,0) -> 0 | F80: =IF(F6>0,$C$80,0) -> 0 | G80: =IF(G6>0,$C$80,0) -> 0 | H80: =IF(H6>0,$C$80,0) -> 20000 | I80: =IF(I6>0,$C$80,0) -> 20000 | J80: =IF(J6>0,$C$80,0) -> 20000 | K80: =IF(K6>0,$C$80,0) -> 20000 | ... BO80: =IF(BO6>0,$C$80,0) -> 0
A81: Variable CHPP Costs | B81: AUD/feedt | C81: 9.5 | D81: =IF(D12>0,$C$81*(1+$AI$12),0) -> 0 | E81: =IF(E12>0,$C$81*(1+$AI$12),0) -> 0 | F81: =IF(F12>0,$C$81*(1+$AI$12),0) -> 0 | G81: =IF(G12>0,$C$81*(1+$AI$12),0) -> 0 | H81: =IF(H12>0,$C$81*(1+$AI$12),0) -> 9.5 | I81: =IF(I12>0,$C$81*(1+$AI$12),0) -> 9.5 | J81: =IF(J12>0,$C$81*(1+$AI$12),0) -> 9.5 | K81: =IF(K12>0,$C$81*(1+$AI$12),0) -> 9.5 | ... BO81: =IF(BO12>0,$C$81*(1+$AI$12),0) -> 0
A82: Total CHPP Costs | B82: AUDk | D82: =D9*D81+D80 -> 0 | E82: =E9*E81+E80 -> 0 | F82: =F9*F81+F80 -> 0 | G82: =G9*G81+G80 -> 0 | H82: =H9*H81+H80 -> 21611.675 | I82: =I9*I81+I80 -> 23223.35 | J82: =J9*J81+J80 -> 95423.35 | K82: =K9*K81+K80 -> 95423.35 | ... BO82: =BO9*BO81+BO80 -> 0 | BQ82: =SUM(D82:BO82) -> 1714397
A84: Overhead - Site Administration | B84: AUDk | C84: 45000 | I84: =IF(I$19>0,$C84,0) -> 45000 | J84: =IF(J$19>0,$C84,0) -> 45000 | K84: =IF(K$19>0,$C84,0) -> 45000 | L84: =IF(L$19>0,$C84,0) -> 45000 | M84: =IF(M$19>0,$C84,0) -> 45000 | N84: =IF(N$19>0,$C84,0) -> 45000 | O84: =IF(O$19>0,$C84,0) -> 45000 | P84: =IF(P$19>0,$C84,0) -> 45000 | ... BO84: =IF(BO$19>0,$C84,0) -> 0
A85: Overhead - Town Management | B85: AUDk | C85: 9000 | I85: =IF(I$19>0,$C85,0) -> 9000 | J85: =IF(J$19>0,$C85,0) -> 9000 | K85: =IF(K$19>0,$C85,0) -> 9000 | L85: =IF(L$19>0,$C85,0) -> 9000 | M85: =IF(M$19>0,$C85,0) -> 9000 | N85: =IF(N$19>0,$C85,0) -> 9000 | O85: =IF(O$19>0,$C85,0) -> 9000 | P85: =IF(P$19>0,$C85,0) -> 9000 | ... BO85: =IF(BO$19>0,$C85,0) -> 0
A86: Overhead - Corporate Fees | B86: AUDk | C86: 15000 | I86: =IF(I$19>0,$C86,0) -> 15000 | J86: =IF(J$19>0,$C86,0) -> 15000 | K86: =IF(K$19>0,$C86,0) -> 15000 | L86: =IF(L$19>0,$C86,0) -> 15000 | M86: =IF(M$19>0,$C86,0) -> 15000 | N86: =IF(N$19>0,$C86,0) -> 15000 | O86: =IF(O$19>0,$C86,0) -> 15000 | P86: =IF(P$19>0,$C86,0) -> 15000 | ... BO86: =IF(BO$19>0,$C86,0) -> 0
A87: Total Overhead Costs | B87: AUDk | C87: Brave Blossom Only | D87: =IF(D9>0,SUM(D84:D86)*(1+$BT$13),0) -> 0 | E87: =IF(E9>0,SUM(E84:E86)*(1+$BT$13),0) -> 0 | F87: =IF(F9>0,SUM(F84:F86)*(1+$BT$13),0) -> 0 | G87: =IF(G9>0,SUM(G84:G86)*(1+$BT$13),0) -> 0 | H87: =IF(H9>0,SUM(H84:H86)*(1+$BT$13),0) -> 0 | I87: =IF(I9>0,SUM(I84:I86)*(1+$BT$13),0) -> 69000 | J87: =IF(J9>0,SUM(J84:J86)*(1+$BT$13),0) -> 69000 | K87: =IF(K9>0,SUM(K84:K86)*(1+$BT$13),0) -> 69000 | ... BO87: =IF(BO9>0,SUM(BO84:BO86)*(1+$BT$13),0) -> 0 | BQ87: =SUM(D87:BO87) -> 1311000
A89: Total FOR Costs | D89: =SUM(D70,D73,D75,D78,D82,D87) -> 0 | E89: =SUM(E70,E73,E75,E78,E82,E87) -> 0 | F89: =SUM(F70,F73,F75,F78,F82,F87) -> 0 | G89: =SUM(G70,G73,G75,G78,G82,G87) -> 0 | H89: =SUM(H70,H73,H75,H78,H82,H87) -> 88629.575 | I89: =SUM(I70,I73,I75,I78,I82,I87) -> 202259.15 | J89: =SUM(J70,J73,J75,J78,J82,J87) -> 650059.15 | K89: =SUM(K70,K73,K75,K78,K82,K87) -> 650059.15 | ... BO89: =SUM(BO70,BO73,BO75,BO78,BO82,BO87) -> 0 | BQ89: =SUM(D89:BO89) -> 11728806
A90: FOR Cost/t | B90: AUD/t | D90: =IFERROR(D89/D19,0) -> 0 | E90: =IFERROR(E89/E19,0) -> 0 | F90: =IFERROR(F89/F19,0) -> 0 | G90: =IFERROR(G89/G19,0) -> 0 | H90: =IFERROR(H89/H19,0) -> 1088.3876 | I90: =IFERROR(I89/I19,0) -> 1241.8899 | J90: =IFERROR(J89/J19,0) -> 120.40978 | K90: =IFERROR(K89/K19,0) -> 120.40978 | ... BO90: =IFERROR(BO89/BO19,0) -> 0 | BQ90: =IFERROR(BQ89/BQ19,0) -> 121.10965
A92: Direct Selling Expenses
A93: Total Port, Rail and Selling Costs | B93: AUD/t | C93: 22 | D93: =$C$93*D34 -> 0 | E93: =$C$93*E34 -> 0 | F93: =$C$93*F34 -> 0 | G93: =$C$93*G34 -> 0 | H93: =$C$93*H34 -> 1791.504 | I93: =$C$93*I34 -> 3583.008 | J93: =$C$93*J34 -> 118771.93 | K93: =$C$93*K34 -> 118771.93 | ... BO93: =$C$93*BO34 -> 0 | BQ93: =SUM(D93:BO93) -> 2130579.4
A94: Additional take or pay liability | B94: AUD/t | D94: =IF(D$92="Y",$C$94*D34,0) -> 0 | E94: =IF(E$92="Y",$C$94*E34,0) -> 0 | F94: =IF(F$92="Y",$C$94*F34,0) -> 0 | G94: =IF(G$92="Y",$C$94*G34,0) -> 0 | H94: =IF(H$92="Y",$C$94*H34,0) -> 0 | I94: =IF(I$92="Y",$C$94*I34,0) -> 0 | J94: =IF(J$92="Y",$C$94*J34,0) -> 0 | K94: =IF(K$92="Y",$C$94*K34,0) -> 0 | ... BO94: =IF(BO$92="Y",$C$94*BO34,0) -> 0
A95: Government Royalty | B95: AUDk | D95: =D148*D34 -> 0 | E95: =E148*E34 -> 0 | F95: =F148*F34 -> 0 | G95: =G148*G34 -> 0 | H95: =H148*H34 -> 4488.7278 | I95: =I148*I34 -> 9243.6327 | J95: =J148*J34 -> 315038.14 | K95: =K148*K34 -> 323466.57 | ... BO95: =BO148*BO34 -> 0 | BQ95: =SUM(D95:BO95) -> 6782273
A96: Total Direct Selling Expenses | B96: AUDk | D96: =SUM(D93:D95) -> 0 | E96: =SUM(E93:E95) -> 0 | F96: =SUM(F93:F95) -> 0 | G96: =SUM(G93:G95) -> 0 | H96: =SUM(H93:H95) -> 6280.2318 | I96: =SUM(I93:I95) -> 12826.641 | J96: =SUM(J93:J95) -> 433810.07 | K96: =SUM(K93:K95) -> 442238.5 | ... BO96: =SUM(BO93:BO95) -> 0 | BQ96: =SUM(BQ93:BQ95) -> 8912852.4
A98: Total FOB Costs | B98: AUDk | D98: =D89+D96 -> 0 | E98: =E89+E96 -> 0 | F98: =F89+F96 -> 0 | G98: =G89+G96 -> 0 | H98: =H89+H96 -> 94909.807 | I98: =I89+I96 -> 215085.79 | J98: =J89+J96 -> 1083869.2 | K98: =K89+K96 -> 1092297.6 | ... BO98: =BO89+BO96 -> 0 | BQ98: =SUM(D98:BO98) -> 20641658
A99: FOB Cost/t | B99: AUD/t | D99: =IFERROR(D98/D19,0) -> 0 | E99: =IFERROR(E98/E19,0) -> 0 | F99: =IFERROR(F98/F19,0) -> 0 | G99: =IFERROR(G98/G19,0) -> 0 | H99: =IFERROR(H98/H19,0) -> 1165.51 | I99: =IFERROR(I98/I19,0) -> 1320.6466 | J99: =IFERROR(J98/J19,0) -> 200.76396 | K99: =IFERROR(K98/K19,0) -> 202.32515 | ... BO99: =IFERROR(BO98/BO19,0) -> 0 | BQ99: =IFERROR(BQ98/BQ19,0) -> 213.14224
A101: Mine Earnings before Other Costs and Taxes | B101: AUDk | D101: =D62-D98 -> 0 | E101: =E62-E98 -> 0 | F101: =F62-F98 -> 0 | G101: =G62-G98 -> 0 | H101: =H62-H98 -> -69984.534 | I101: =I62-I98 -> -165235.24 | J101: =J62-J98 -> 568609.78 | K101: =K62-K98 -> 560181.35 | ... BO101: =BO62-BO98 -> 0 | BQ101: =BQ62-BQ98 -> 9001185.8
A103: Other Costs
A104: Progressive Rehabiliation Costs | B104: AUDk | C104: 2500 | D104: =IF(D9>0,$C$104,0) -> 0 | E104: =IF(E9>0,$C$104,0) -> 0 | F104: =IF(F9>0,$C$104,0) -> 0 | G104: =IF(G9>0,$C$104,0) -> 0 | H104: =IF(H9>0,$C$104,0) -> 2500 | I104: =IF(I9>0,$C$104,0) -> 2500 | J104: =IF(J9>0,$C$104,0) -> 2500 | K104: =IF(K9>0,$C$104,0) -> 2500 | ... BO104: =IF(BO9>0,$C$104,0) -> 0 | BQ104: =SUM(D104:BO104) -> 50000
A105: Mine Closure Costs | B105: AUDk | C105: 150000 | AD105: =C105 -> 150000 | AE105: 0 | AF105: 0 | AG105: 0 | AH105: 0 | AI105: 0 | AJ105: 0 | AK105: 0 | AL105: 0 | AM105: 0 | AN105: 0 | AO105: 0 | AP105: 0 | AQ105: 0 | AR105: 0 | AS105: 0 | AT105: 0 | AU105: 0 | AV105: 0 | AW105: 0 | AX105: 0 | AY105: 0 | AZ105: 0 | BA105: 0 | BB105: 0 | BC105: 0 | BD105: 0 | BE105: 0 | BF105: 0 | BG105: 0 | BH105: 0 | BI105: 0 | BJ105: 0 | BK105: 0 | BL105: 0 | BM105: 0 | BN105: 0 | BO105: 0 | BQ105: =SUM(D105:BO105) -> 150000
A106: Carbon Costs | B106: AUDk | D106: =IF(Assumptions!$C$20="Zero Carbon Liability",'Brave Blossom '!D26*Carbon!B2,'Brave Blossom '!D26*Carbon!B3)/1000 -> 0 | E106: =IF(Assumptions!$C$20="Zero Carbon Liability",'Brave Blossom '!E26*Carbon!C2,'Brave Blossom '!E26*Carbon!C3)/1000 -> 0 | F106: =IF(Assumptions!$C$20="Zero Carbon Liability",'Brave Blossom '!F26*Carbon!D2,'Brave Blossom '!F26*Carbon!D3)/1000 -> 0 | G106: =IF(Assumptions!$C$20="Zero Carbon Liability",'Brave Blossom '!G26*Carbon!E2,'Brave Blossom '!G26*Carbon!E3)/1000 -> 0 | H106: =IF(Assumptions!$C$20="Zero Carbon Liability",'Brave Blossom '!H26*Carbon!F2,'Brave Blossom '!H26*Carbon!F3)/1000 -> 2606.3648 | I106: =IF(Assumptions!$C$20="Zero Carbon Liability",'Brave Blossom '!I26*Carbon!G2,'Brave Blossom '!I26*Carbon!G3)/1000 -> 4156.5094 | J106: =IF(Assumptions!$C$20="Zero Carbon Liability",'Brave Blossom '!J26*Carbon!H2,'Brave Blossom '!J26*Carbon!H3)/1000 -> 65663.581 | K106: =IF(Assumptions!$C$20="Zero Carbon Liability",'Brave Blossom '!K26*Carbon!I2,'Brave Blossom '!K26*Carbon!I3)/1000 -> 71463.408 | ... BO106: =IF(Assumptions!$C$20="Zero Carbon Liability",'Brave Blossom '!BO26*Carbon!BM2,'Brave Blossom '!BO26*Carbon!BM3)/1000 -> 0 | BQ106: =SUM(D106:BO106) -> 2561611
A107: Other Revenue | B107: AUDk | D107: 0 | E107: 0 | F107: 0 | G107: 0 | H107: 0 | I107: 0 | J107: 0 | K107: 0 | L107: 0 | M107: 0 | N107: 0 | O107: 0 | P107: 0 | Q107: 0 | R107: 0 | S107: 0 | T107: 0 | U107: 0 | V107: 0 | W107: 0 | X107: 0 | Y107: 0 | Z107: 0 | AA107: 0 | AB107: 0 | AC107: 0 | AD107: 0 | AE107: 0 | AF107: 0 | AG107: 0 | AH107: 0 | AI107: 0 | AJ107: 0 | AK107: 0 | AL107: 0 | AM107: 0 | AN107: 0 | AO107: 0 | AP107: 0 | AQ107: 0 | AR107: 0 | AS107: 0 | AT107: 0 | AU107: 0 | AV107: 0 | AW107: 0 | AX107: 0 | AY107: 0 | AZ107: 0 | BA107: 0 | BB107: 0 | BC107: 0 | BD107: 0 | BE107: 0 | BF107: 0 | BG107: 0 | BH107: 0 | BI107: 0 | BJ107: 0 | BK107: 0 | BL107: 0 | BM107: 0 | BN107: 0 | BO107: 0
A108: Total Other Costs | B108: AUDk | D108: =SUM(D104:D107) -> 0 | E108: =SUM(E104:E107) -> 0 | F108: =SUM(F104:F107) -> 0 | G108: =SUM(G104:G107) -> 0 | H108: =SUM(H104:H107) -> 5106.3648 | I108: =SUM(I104:I107) -> 6656.5094 | J108: =SUM(J104:J107) -> 68163.581 | K108: =SUM(K104:K107) -> 73963.408 | ... BO108: =SUM(BO104:BO107) -> 0 | BQ108: =SUM(BQ104:BQ107) -> 2761611
A109: Total other - closure credits | D109: =IF(D105<=0,(D104+D106),D108) -> 0 | E109: =IF(E105<=0,(E104+E106),E108) -> 0 | F109: =IF(F105<=0,(F104+F106),F108) -> 0 | G109: =IF(G105<=0,(G104+G106),G108) -> 0 | H109: =IF(H105<=0,(H104+H106),H108) -> 5106.3648 | I109: =IF(I105<=0,(I104+I106),I108) -> 6656.5094 | J109: =IF(J105<=0,(J104+J106),J108) -> 68163.581 | K109: =IF(K105<=0,(K104+K106),K108) -> 73963.408 | ... BO109: =IF(BO105<=0,(BO104+BO106),BO108) -> 0 | BQ109: =SUM(BQ104:BQ107) -> 2761611
A111: Capital Costs
A112: Project Capital | B112: AUDk | D112: 0 | E112: 0 | F112: 0 | G112: 0 | H112: 0 | I112: 0 | J112: 0 | K112: 0 | L112: 0 | M112: 0 | N112: 0 | O112: 0 | P112: 0 | Q112: 0 | R112: 0 | S112: 0 | T112: 0 | U112: 0 | V112: 0 | W112: 0 | X112: 0 | Y112: 0 | Z112: 0 | AA112: 0 | AB112: 0 | AC112: 0 | AD112: 0 | AE112: 0 | AF112: 0 | AG112: 0 | AH112: 0 | AI112: 0 | AJ112: 0 | AK112: 0 | AL112: 0 | AM112: 0 | AN112: 0 | AO112: 0 | AP112: 0 | AQ112: 0 | AR112: 0 | AS112: 0 | AT112: 0 | AU112: 0 | AV112: 0 | AW112: 0 | AX112: 0 | AY112: 0 | AZ112: 0 | BA112: 0 | BB112: 0 | BC112: 0 | BD112: 0 | BE112: 0 | BF112: 0 | BG112: 0 | BH112: 0 | BI112: 0 | BJ112: 0 | BK112: 0 | BL112: 0 | BM112: 0 | BN112: 0 | BO112: 0 | BQ112: =SUM(D112:BO112) -> 0
A113: Mining Equipment/Major Capital | B113: AUDk | D113: ='Brave Blossom Capital'!D57 -> 0 | E113: ='Brave Blossom Capital'!E57 -> 0 | F113: ='Brave Blossom Capital'!F57 -> 0 | G113: ='Brave Blossom Capital'!G57 -> 0 | H113: ='Brave Blossom Capital'!H57 -> 0 | I113: ='Brave Blossom Capital'!I57 -> 0 | J113: ='Brave Blossom Capital'!J57 -> 0 | K113: ='Brave Blossom Capital'!K57 -> 0 | ... AD113: ='Brave Blossom Capital'!AD57 -> 0 | AE113: ='Brave Blossom Capital'!AD57 -> 0 | AF113: ='Brave Blossom Capital'!AE57 -> 0 | AG113: ='Brave Blossom Capital'!AF57 -> 0 | AH113: ='Brave Blossom Capital'!AG57 -> 0 | AI113: ='Brave Blossom Capital'!AH57 -> 0 | AJ113: ='Brave Blossom Capital'!AI57 -> 0 | AK113: ='Brave Blossom Capital'!AJ57 -> 0 | AL113: ='Brave Blossom Capital'!AK57 -> 0 | ... BO113: ='Brave Blossom Capital'!BN57 -> 0 | BQ113: =SUM(D113:BO113) -> 0
A114: Sustaining Capital | B114: AUD/ROMt | C114: 6 | D114: =$C$114*D9 -> 0 | E114: =$C$114*E9 -> 0 | F114: =$C$114*F9 -> 0 | G114: =$C$114*G9 -> 0 | H114: =$C$114*H9 -> 1017.9 | I114: =$C$114*I9 -> 2035.8 | J114: =$C$114*J9 -> 47635.8 | K114: =$C$114*K9 -> 47635.8 | ... BO114: =$C$114*BO9 -> 0 | BQ114: =SUM(D114:BO114) -> 855408.6
A115: Total Capital | B115: AUDk | D115: =SUM(D112:D114)*(1+$BT$14) -> 0 | E115: =SUM(E112:E114)*(1+$BT$14) -> 0 | F115: =SUM(F112:F114)*(1+$BT$14) -> 0 | G115: =SUM(G112:G114)*(1+$BT$14) -> 0 | H115: =SUM(H112:H114)*(1+$BT$14) -> 1017.9 | I115: =SUM(I112:I114)*(1+$BT$14) -> 2035.8 | J115: =SUM(J112:J114)*(1+$BT$14) -> 47635.8 | K115: =SUM(K112:K114)*(1+$BT$14) -> 47635.8 | ... BO115: =SUM(BO112:BO114)*(1+$BT$14) -> 0 | BQ115: =SUM(D115:BO115) -> 855408.6
A116: Depreciation | B116: AUDk | D116: =D132 -> 0 | E116: =E132 -> 0 | F116: =F132 -> 0 | G116: =G132 -> 0 | H116: =H132 -> 0 | I116: =I132 -> 48.471429 | J116: =J132 -> 150.26143 | K116: =K132 -> 2657.4088 | ... BO116: =BO132 -> 0
A118: Net Cashflow Before Tax | B118: AUDk | D118: =D101-D108-D115 -> 0 | E118: =E101-E108-E115 -> 0 | F118: =F101-F108-F115 -> 0 | G118: =G101-G108-G115 -> 0 | H118: =H101-H108-H115 -> -76108.799 | I118: =I101-I108-I115 -> -173927.55 | J118: =J101-J108-J115 -> 452810.4 | K118: =K101-K108-K115 -> 438582.14 | ... BO118: =BO101-BO108-BO115 -> 0 | BQ118: =BQ101-BQ108-BQ115 -> 5384166.2
A119: Tax Paid | B119: AUDk | C119: 0.3 | D119: =IF((D101-D109-D116)*$C$119>0,(D101-D109-D116)*$C$119,0) -> 0 | E119: =IF((E101-E109-E116)*$C$119>0,(E101-E109-E116)*$C$119,0) -> 0 | F119: =IF((F101-F109-F116)*$C$119>0,(F101-F109-F116)*$C$119,0) -> 0 | G119: =IF((G101-G109-G116)*$C$119>0,(G101-G109-G116)*$C$119,0) -> 0 | H119: =IF((H101-H109-H116)*$C$119>0,(H101-H109-H116)*$C$119,0) -> 0 | I119: =IF((I101-I109-I116)*$C$119>0,(I101-I109-I116)*$C$119,0) -> 0 | J119: =IF((J101-J109-J116)*$C$119>0,(J101-J109-J116)*$C$119,0) -> 150088.78 | K119: =IF((K101-K109-K116)*$C$119>0,(K101-K109-K116)*$C$119,0) -> 145068.16 | ... BO119: =IF((BO101-BO109-BO116)*$C$119>0,(BO101-BO109-BO116)*$C$119,0) -> 0 | BQ119: =SUM(D119:BO119) -> 2027212.3
D120: 1 | E120: 1 | F120: 1 | G120: 1 | H120: 1 | I120: 1 | J120: 1 | K120: 1 | L120: 1 | M120: 1 | N120: 1 | O120: 1 | P120: 1 | Q120: 1 | R120: 1 | S120: 1 | T120: 1 | U120: 1 | V120: 1 | W120: 1 | X120: 1 | Y120: 1 | Z120: 1 | AA120: 1 | AB120: 1 | AC120: 1 | AD120: 1 | AE120: 1 | AF120: 1 | AG120: 1 | AH120: 1 | AI120: 1 | AJ120: 1 | AK120: 1 | AL120: 1 | AM120: 1 | AN120: 1 | AO120: 1 | AP120: 1 | AQ120: 1 | AR120: 1 | AS120: 1 | AT120: 1 | AU120: 1 | AV120: 1 | AW120: 1 | AX120: 1 | AY120: 1 | AZ120: 1 | BA120: 1 | BB120: 1 | BC120: 1 | BD120: 1 | BE120: 1 | BF120: 1 | BG120: 1 | BH120: 1 | BI120: 1 | BJ120: 1 | BK120: 1 | BL120: 1 | BM120: 1 | BN120: 1 | BO120: 1
A122: Cashflows After Tax | B122: AUDk | D122: =D118-D119 -> 0 | E122: =E118-E119 -> 0 | F122: =F118-F119 -> 0 | G122: =G118-G119 -> 0 | H122: =H118-H119 -> -76108.799 | I122: =I118-I119 -> -173927.55 | J122: =J118-J119 -> 302721.61 | K122: =K118-K119 -> 293513.98 | ... BO122: =BO118-BO119 -> 0 | BQ122: =BQ118-BQ119 -> 3356953.9
A123: Attributable Cashflow After Tax (60%) | B123: AUDk | C123: 0.6 | D123: =IFERROR(D122*$C$123,0) -> 0 | E123: =IFERROR(E122*$C$123,0) -> 0 | F123: =IFERROR(F122*$C$123,0) -> 0 | G123: =IFERROR(G122*$C$123,0) -> 0 | H123: =IFERROR(H122*$C$123,0) -> -45665.279 | I123: =IFERROR(I122*$C$123,0) -> -104356.53 | J123: =IFERROR(J122*$C$123,0) -> 181632.97 | K123: =IFERROR(K122*$C$123,0) -> 176108.39 | ... BO123: =IFERROR(BO122*$C$123,0) -> 0 | BQ123: =SUM(D123:BO123) -> 2014172.3
A124: Discounted Cashflows | B124: AUDk | D124: =D123*Assumptions!I2 -> 0 | E124: =E122*Assumptions!J2 -> 0 | F124: =F122*Assumptions!K2 -> 0 | G124: =G122*Assumptions!L2 -> 0 | H124: =H122*Assumptions!M2 -> -53830.445 | I124: =I122*Assumptions!N2 -> -113903.67 | J124: =J122*Assumptions!O2 -> 183564.64 | K124: =K122*Assumptions!P2 -> 164797.5 | L124: =L122*Assumptions!Q2 -> 147807.83 | ... AD124: =AD122*Assumptions!AI2 -> -29204.179 | AE124: =AE122*Assumptions!AI2 -> -7847.4571 | AF124: =AF122*Assumptions!AJ2 -> -6223.8368 | AG124: =AG122*Assumptions!AK2 -> -4863.9045 | AH124: =AH122*Assumptions!AL2 -> -3980.6194 | AI124: =AI122*Assumptions!AM2 -> -3292.893 | AJ124: =AJ122*Assumptions!AN2 -> -2667.1369 | AK124: =AK122*Assumptions!AO2 -> -2243.8778 | AL124: =AL122*Assumptions!AP2 -> -1899.1388 | ... BO124: =BO122*Assumptions!BS2 -> 0 | BQ124: =SUM(D124:BO124) -> 1320077.8
...

Sheet Brave Blossom Capital
A1: Brave Blossom Capital | D1: ='Brave Blossom '!D2 -> 2027 | E1: =D1+1 -> 2028 | F1: =E1+1 -> 2029 | G1: =F1+1 -> 2030 | H1: =G1+1 -> 2031 | I1: =H1+1 -> 2032 | J1: =I1+1 -> 2033 | K1: =J1+1 -> 2034 | L1: =K1+1 -> 2035 | ... AD1: =AC1+1 -> 2053
A3: Capital Items - Units | D3: Insert Unit Numbers by Year Below
B4: AUD$k | C4: 5000
B5: AUD$k | C5: 5000
B6: AUD$k | C6: 15000
B7: AUD$k | C7: 20000
B8: AUD$k | C8: 5000
B9: AUD$k | C9: 12000
B10: AUD$k | C10: 17000
B11: AUD$k | C11: 5000
B12: AUD$k | C12: 20000
B13: AUD$k | C13: 190000
B14: AUD$k | C14: 69900
B15: AUD$k | C15: 24000
A16: Other Items (as required) | B16: AUD$k
A17: Other Items (as required) | B17: AUD$k
A18: Other Items (as required) | B18: AUD$k
A19: Other Items (as required) | B19: AUD$k
A20: Other Items (as required) | B20: AUD$k
A21: Other Items (as required) | B21: AUD$k
A22: Other Items (as required) | B22: AUD$k
A23: Other Items (as required) | B23: AUD$k
A24: Other Items (as required) | B24: AUD$k
A25: Other Items (as required) | B25: AUD$k
A30: Capital Cost - Cost | D30: Do not change cells below
A31: =A4 -> 0 | B31: AUD$k | C31: =C4 -> 5000 | D31: =$C4*D4 -> 0 | E31: =$C4*E4 -> 0 | F31: =$C4*F4 -> 0 | G31: =$C4*G4 -> 0 | H31: =$C4*H4 -> 0 | I31: =$C4*I4 -> 0 | J31: =$C4*J4 -> 0 | K31: =$C4*K4 -> 0 | ... AD31: =$C4*AD4 -> 0
A32: =A5 -> 0 | B32: AUD$k | C32: =C5 -> 5000 | D32: =$C5*D5 -> 0 | E32: =$C5*E5 -> 0 | F32: =$C5*F5 -> 0 | G32: =$C5*G5 -> 0 | H32: =$C5*H5 -> 0 | I32: =$C5*I5 -> 0 | J32: =$C5*J5 -> 0 | K32: =$C5*K5 -> 0 | ... AD32: =$C5*AD5 -> 0
A33: =A6 -> 0 | B33: AUD$k | C33: =C6 -> 15000 | D33: =$C6*D6 -> 0 | E33: =$C6*E6 -> 0 | F33: =$C6*F6 -> 0 | G33: =$C6*G6 -> 0 | H33: =$C6*H6 -> 0 | I33: =$C6*I6 -> 0 | J33: =$C6*J6 -> 0 | K33: =$C6*K6 -> 0 | ... AD33: =$C6*AD6 -> 0
A34: =A7 -> 0 | B34: AUD$k | C34: =C7 -> 20000 | D34: =$C7*D7 -> 0 | E34: =$C7*E7 -> 0 | F34: =$C7*F7 -> 0 | G34: =$C7*G7 -> 0 | H34: =$C7*H7 -> 0 | I34: =$C7*I7 -> 0 | J34: =$C7*J7 -> 0 | K34: =$C7*K7 -> 0 | ... AD34: =$C7*AD7 -> 0
A35: =A8 -> 0 | B35: AUD$k | C35: =C8 -> 5000 | D35: =$C8*D8 -> 0 | E35: =$C8*E8 -> 0 | F35: =$C8*F8 -> 0 | G35: =$C8*G8 -> 0 | H35: =$C8*H8 -> 0 | I35: =$C8*I8 -> 0 | J35: =$C8*J8 -> 0 | K35: =$C8*K8 -> 0 | ... AD35: =$C8*AD8 -> 0
A36: =A9 -> 0 | B36: AUD$k | C36: =C9 -> 12000 | D36: =$C9*D9 -> 0 | E36: =$C9*E9 -> 0 | F36: =$C9*F9 -> 0 | G36: =$C9*G9 -> 0 | H36: =$C9*H9 -> 0 | I36: =$C9*I9 -> 0 | J36: =$C9*J9 -> 0 | K36: =$C9*K9 -> 0 | ... AD36: =$C9*AD9 -> 0
A37: =A10 -> 0 | B37: AUD$k | C37: =C10 -> 17000 | D37: =$C10*D10 -> 0 | E37: =$C10*E10 -> 0 | F37: =$C10*F10 -> 0 | G37: =$C10*G10 -> 0 | H37: =$C10*H10 -> 0 | I37: =$C10*I10 -> 0 | J37: =$C10*J10 -> 0 | K37: =$C10*K10 -> 0 | ... AD37: =$C10*AD10 -> 0
A38: =A11 -> 0 | B38: AUD$k | C38: =C11 -> 5000 | D38: =$C11*D11 -> 0 | E38: =$C11*E11 -> 0 | F38: =$C11*F11 -> 0 | G38: =$C11*G11 -> 0 | H38: =$C11*H11 -> 0 | I38: =$C11*I11 -> 0 | J38: =$C11*J11 -> 0 | K38: =$C11*K11 -> 0 | ... AD38: =$C11*AD11 -> 0
A39: =A12 -> 0 | B39: AUD$k | C39: =C12 -> 20000 | D39: =$C12*D12 -> 0 | E39: =$C12*E12 -> 0 | F39: =$C12*F12 -> 0 | G39: =$C12*G12 -> 0 | H39: =$C12*H12 -> 0 | I39: =$C12*I12 -> 0 | J39: =$C12*J12 -> 0 | K39: =$C12*K12 -> 0 | ... AD39: =$C12*AD12 -> 0
A40: =A13 -> 0 | B40: AUD$k | C40: =C13 -> 190000 | D40: =$C13*D13 -> 0 | E40: =$C13*E13 -> 0 | F40: =$C13*F13 -> 0 | G40: =$C13*G13 -> 0 | H40: =$C13*H13 -> 0 | I40: =$C13*I13 -> 0 | J40: =$C13*J13 -> 0 | K40: =$C13*K13 -> 0 | ... AD40: =$C13*AD13 -> 0
A41: =A14 -> 0 | B41: AUD$k | C41: =C14 -> 69900 | D41: =$C14*D14 -> 0 | E41: =$C14*E14 -> 0 | F41: =$C14*F14 -> 0 | G41: =$C14*G14 -> 0 | H41: =$C14*H14 -> 0 | I41: =$C14*I14 -> 0 | J41: =$C14*J14 -> 0 | K41: =$C14*K14 -> 0 | ... AD41: =$C14*AD14 -> 0
A42: =A15 -> 0 | B42: AUD$k | C42: =C15 -> 24000 | D42: =$C15*D15 -> 0 | E42: =$C15*E15 -> 0 | F42: =$C15*F15 -> 0 | G42: =$C15*G15 -> 0 | H42: =$C15*H15 -> 0 | I42: =$C15*I15 -> 0 | J42: =$C15*J15 -> 0 | K42: =$C15*K15 -> 0 | ... AD42: =$C15*AD15 -> 0
... A54: =A27 -> 0 | B54: AUD$k | C54: =C27 -> 0 | D54: =$C27*D27 -> 0 | E54: =$C27*E27 -> 0 | F54: =$C27*F27 -> 0 | G54: =$C27*G27 -> 0 | H54: =$C27*H27 -> 0 | I54: =$C27*I27 -> 0 | J54: =$C27*J27 -> 0 | K54: =$C27*K27 -> 0 | ... AD54: =$C27*AD27 -> 0
A55: Total | D55: =SUM(D31:D54) -> 0 | E55: =SUM(E31:E54) -> 0 | F55: =SUM(F31:F54) -> 0 | G55: =SUM(G31:G54) -> 0 | H55: =SUM(H31:H54) -> 0 | I55: =SUM(I31:I54) -> 0 | J55: =SUM(J31:J54) -> 0 | K55: =SUM(K31:K54) -> 0 | ... AD55: =SUM(AD31:AD54) -> 0
A56: Contingency | B56: % | C56: 0.3 | D56: =$C$56*D55 -> 0 | E56: =$C$56*E55 -> 0 | F56: =$C$56*F55 -> 0 | G56: =$C$56*G55 -> 0 | H56: =$C$56*H55 -> 0 | I56: =$C$56*I55 -> 0 | J56: =$C$56*J55 -> 0 | K56: =$C$56*K55 -> 0 | ... AD56: =$C$56*AD55 -> 0
A57: Total Capital | D57: =D56+D55 -> 0 | E57: =E56+E55 -> 0 | F57: =F56+F55 -> 0 | G57: =G56+G55 -> 0 | H57: =H56+H55 -> 0 | I57: =I56+I55 -> 0 | J57: =J56+J55 -> 0 | K57: =K56+K55 -> 0 | ... AD57: =AD56+AD55 -> 0

Sheet Historical Performance BrumbyOC
B3: Brumby OC Historical Performance | D3: 2011 | E3: =D3+1 -> 2012 | F3: =E3+1 -> 2013 | G3: =F3+1 -> 2014 | H3: =G3+1 -> 2015
B4: PRODUCTION
B6: Rom Tonnes | C6: kt | D6: 1286.2549 | E6: 1281.1511 | F6: 1349.068 | G6: 1281.2426 | H6: 1000
B7: Prime Waste TS | C7: kbcm | D7: 6022.1684 | E7: 5784.568 | F7: 6373.7345 | G7: 5948.3679 | H7: 4948.3679
B8: Prime Waste Dragline | C8: kbcm | D8: 0 | E8: 0 | F8: 0 | G8: 0 | H8: 0
B9: Strip Ratio | C9: kt | D9: =D7/D6 -> 4.6819401 | E9: =E7/E6 -> 4.5151332 | F9: =F7/F6 -> 4.7245466 | G9: =G7/G6 -> 4.6426552 | H9: =H7/H6 -> 4.9483679
B10: Ebcm | C10: kbcm | D10: =D6*1.45+D7 -> 7887.238 | E10: =E6*1.45+E7 -> 7642.2371 | F10: =F6*1.45+F7 -> 8329.8831 | G10: =G6*1.45+G7 -> 7806.1697 | H10: =H6*1.45+H7 -> 6398.3679
B12: CHPP
B13: Primary Feed Tonnes | C13: kt | D13: =D6 -> 1286.2549 | E13: =E6 -> 1281.1511 | F13: =F6 -> 1349.068 | G13: =G6 -> 1281.2426 | H13: =H6 -> 1000
B14: Bypass Tonnes | C14: kt | D14: 0 | E14: 0 | F14: 0 | G14: 0 | H14: 0
B15: Plant Product Tonnes | C15: kt | D15: 900.37843 | E15: 885 | F15: 925 | G15: 929.36927 | H15: 750
B16: CHPP Yield | C16: % | D16: =D15/(D13+D14) -> 0.7 | E16: =E15/(E13+E14) -> 0.69078502 | F16: =F15/(F13+F14) -> 0.68565855 | G16: =G15/(G13+G14) -> 0.72536554 | H16: =H15/(H13+H14) -> 0.75
B18: Marketing
B19: PHCC | C19: kt | D19: 270.11353 | E19: 309.75 | F19: 296 | G19: 232.34232 | H19: 300
B20: GCN | C20: kt | D20: =D15-D19 -> 630.2649 | E20: =E15-E19 -> 575.25 | F20: =F15-F19 -> 629 | G20: =G15-G19 -> 697.02695 | H20: =H15-H19 -> 450
B21: Total Sales | C21: kt | D21: =SUM(D19:D20) -> 900.37843 | E21: =SUM(E19:E20) -> 885 | F21: =SUM(F19:F20) -> 925 | G21: =SUM(G19:G20) -> 929.36927 | H21: =SUM(H19:H20) -> 750
B24: GCN Energy | C24: kcal/kg(gar) | D24: 6250 | E24: 6250 | F24: 6250 | G24: 6212 | H24: 6290
B25: GCN Ash | C25: % | D25: 9.6 | E25: 9.6 | F25: 9.6 | G25: 10.1 | H25: 9.2

Sheet OC Clean
D1: 2 | E1: =+D1+1 -> 3 | F1: =+E1+1 -> 4 | G1: =+F1+1 -> 5 | H1: =+G1+1 -> 6 | I1: =+H1+1 -> 7 | J1: =+I1+1 -> 8 | K1: =+J1+1 -> 9 | L1: =+K1+1 -> 10 | ... AD1: =+AC1+1 -> 28
A2: OC - Proposal | D2: =Assumptions!J1 -> 2027 | E2: =Assumptions!J1 -> 2027 | F2: =Assumptions!K1 -> 2028 | G2: =Assumptions!L1 -> 2029 | H2: =Assumptions!M1 -> 2030 | I2: =Assumptions!N1 -> 2031 | J2: =Assumptions!O1 -> 2032 | K2: =Assumptions!P1 -> 2033 | L2: =Assumptions!Q1 -> 2034 | ... AD2: =Assumptions!AI1 -> 2052 | AF2: Total | AH2: Valuation Summary
A3: Physicals | AH3: Net Present Value (AUDM) | AI3: =AF126/1000 -> 0
A4: Reserves | B4: kt | C4: 20000
A5: Mining
A6: Prime Waste Removed (T&S) | B6: kbcm | D6: =$C$6 -> 0 | E6: =$C$6 -> 0 | F6: =$C$6 -> 0 | G6: =$C$6 -> 0 | H6: =$C$6 -> 0 | I6: =$C$6 -> 0 | J6: =$C$6 -> 0 | K6: =$C$6 -> 0 | ... AD6: =$C$6 -> 0 | AF6: =SUM(D6:AD6) -> 0 | AH6: Sensitivities Table
A7: Prime Waste Removed (Dragline) | B7: kbcm | D7: =C7 -> 0 | E7: =D7 -> 0 | F7: =E7 -> 0 | G7: =F7 -> 0 | H7: =G7 -> 0 | I7: =H7 -> 0 | J7: =I7 -> 0 | K7: =J7 -> 0 | ... AD7: =AC7 -> 0 | AF7: =SUM(D7:AD7) -> 0 | AH7: Sales Price | AI7: 0
A8: Total Prime Waste Removed | B8: kbcm | D8: =SUM(D6:D7) -> 0 | E8: =SUM(E6:E7) -> 0 | F8: =SUM(F6:F7) -> 0 | G8: =SUM(G6:G7) -> 0 | H8: =SUM(H6:H7) -> 0 | I8: =SUM(I6:I7) -> 0 | J8: =SUM(J6:J7) -> 0 | K8: =SUM(K6:K7) -> 0 | ... AD8: =SUM(AD6:AD7) -> 0 | AF8: =SUM(D8:AD8) -> 0 | AH8: T&S Costs | AI8: 0
A9: Prime Waste Blasted | B9: kbcm | D9: =D8 -> 0 | E9: =E8 -> 0 | F9: =F8 -> 0 | G9: =G8 -> 0 | H9: =H8 -> 0 | I9: =I8 -> 0 | J9: =J8 -> 0 | K9: =K8 -> 0 | ... AD9: =AD8 -> 0 | AF9: =SUM(D9:AD9) -> 0 | AH9: Dragline Costs | AI9: 0
AH10: Drill & Blast Costs | AI10: 0
A11: Coal Mined (ROM) | B11: kt | D11: =$C$11 -> 0 | E11: =$C$11 -> 0 | F11: =$C$11 -> 0 | G11: =$C$11 -> 0 | H11: =$C$11 -> 0 | I11: =$C$11 -> 0 | J11: =$C$11 -> 0 | K11: =$C$11 -> 0 | ... AD11: =$C$11 -> 0 | AF11: =SUM(D11:AD11) -> 0 | AH11: Services Costs | AI11: 0
A12: Strip Ratio | D12: =IFERROR(D8/D11,0) -> 0 | E12: =IFERROR(E8/E11,0) -> 0 | F12: =IFERROR(F8/F11,0) -> 0 | G12: =IFERROR(G8/G11,0) -> 0 | H12: =IFERROR(H8/H11,0) -> 0 | I12: =IFERROR(I8/I11,0) -> 0 | J12: =IFERROR(J8/J11,0) -> 0 | K12: =IFERROR(K8/K11,0) -> 0 | ... AD12: =IFERROR(AD8/AD11,0) -> 0 | AF12: =IFERROR(AF8/AF11,0) -> 0 | AH12: Coal Mining Costs | AI12: 0
AH13: CHPP Costs | AI13: 0
A14: Total Material Moved | B14: kebcm | D14: =D8+(D11/1.45) -> 0 | E14: =E8+(E11/1.45) -> 0 | F14: =F8+(F11/1.45) -> 0 | G14: =G8+(G11/1.45) -> 0 | H14: =H8+(H11/1.45) -> 0 | I14: =I8+(I11/1.45) -> 0 | J14: =J8+(J11/1.45) -> 0 | K14: =K8+(K11/1.45) -> 0 | ... Q14: =Q8+(Q11/1.45) -> 0 | R14: =R8+(R11/1.4) -> 0 | S14: =S8+(S11/1.4) -> 0 | T14: =T8+(T11/1.4) -> 0 | U14: =U8+(U11/1.4) -> 0 | V14: =V8+(V11/1.4) -> 0 | W14: =W8+(W11/1.4) -> 0 | X14: =X8+(X11/1.4) -> 0 | Y14: =Y8+(Y11/1.4) -> 0 | ... AD14: =AD8+(AD11/1.4) -> 0 | AF14: =SUM(D14:AD14) -> 0 | AH14: Total Overhead Costs | AI14: 0
AH15: Total Capital Costs | AI15: 0
A16: CHPP
A17: Plant Feed Tonnes | B17: kt | D17: =$C$17*D11 -> 0 | E17: =$C$17*E11 -> 0 | F17: =$C$17*F11 -> 0 | G17: =$C$17*G11 -> 0 | H17: =$C$17*H11 -> 0 | I17: =$C$17*I11 -> 0 | J17: =$C$17*J11 -> 0 | K17: =$C$17*K11 -> 0 | ... AD17: =$C$17*AD11 -> 0 | AF17: =SUM(D17:AD17) -> 0
A18: Bypass Tonnes | B18: kt | D18: =$C$18*D11 -> 0 | E18: =$C$18*E11 -> 0 | F18: =$C$18*F11 -> 0 | G18: =$C$18*G11 -> 0 | H18: =$C$18*H11 -> 0 | I18: =$C$18*I11 -> 0 | J18: =$C$18*J11 -> 0 | K18: =$C$18*K11 -> 0 | ... AD18: =$C$18*AD11 -> 0 | AF18: =SUM(D18:AD18) -> 0
A19: Plant Product Tonnes | B19: kt | D19: =D20*D17 -> 0 | E19: =E20*E17 -> 0 | F19: =F20*F17 -> 0 | G19: =G20*G17 -> 0 | H19: =H20*H17 -> 0 | I19: =I20*I17 -> 0 | J19: =J20*J17 -> 0 | K19: =K20*K17 -> 0 | ... AD19: =AD20*AD17 -> 0 | AF19: =SUM(D19:W19) -> 0
A20: CHPP Yield | D20: =$C$20 -> 0 | E20: =$C$20 -> 0 | F20: =$C$20 -> 0 | G20: =$C$20 -> 0 | H20: =$C$20 -> 0 | I20: =$C$20 -> 0 | J20: =$C$20 -> 0 | K20: =$C$20 -> 0 | ... AD20: =$C$20 -> 0 | AF20: =IFERROR(AF19/AF17,0) -> 0
AH21: LOM volumes
A22: Operations Yield | D22: =IFERROR(D24/D11,0) -> 0 | E22: =IFERROR(E24/E11,0) -> 0 | F22: =IFERROR(F24/F11,0) -> 0 | G22: =IFERROR(G24/G11,0) -> 0 | H22: =IFERROR(H24/H11,0) -> 0 | I22: =IFERROR(I24/I11,0) -> 0 | J22: =IFERROR(J24/J11,0) -> 0 | K22: =IFERROR(K24/K11,0) -> 0 | ... AD22: =IFERROR(AD24/AD11,0) -> 0 | AF22: =IFERROR(AF24/AF9,0) -> 0
A24: Saleable Production | B24: kt | D24: =D19+D18 -> 0 | E24: =E19+E18 -> 0 | F24: =F19+F18 -> 0 | G24: =G19+G18 -> 0 | H24: =H19+H18 -> 0 | I24: =I19+I18 -> 0 | J24: =J18+J19 -> 0 | K24: =K18+K19 -> 0 | L24: =L18+L19 -> 0 | M24: =M18+M19 -> 0 | N24: =N18+N19 -> 0 | O24: =O18+O19 -> 0 | P24: =P18+P19 -> 0 | Q24: =Q18+Q19 -> 0 | ... AD24: =AD18+AD19 -> 0 | AF24: =SUM(D24:AD24) -> 0 | AH24: Prime Waste Removed (Kbcm) | AI24: =AF7 -> 0
A26: Carbon | D26: =C26-(1/26) -> -0.038461538 | E26: =D26-(1/26) -> -0.076923077 | F26: =E26-(1/26) -> -0.11538462 | G26: =F26-(1/26) -> -0.15384615 | H26: =G26-(1/26) -> -0.19230769 | I26: =H26-(1/26) -> -0.23076923 | J26: =I26-(1/26) -> -0.26923077 | K26: =J26-(1/26) -> -0.30769231 | ... AD26: =AC26-(1/26) -> -1.0384615 | AH26: Total ROM (kt) | AI26: =AF11 -> 0
A27: Scope 1 Emissions | B27: t CO2e | C27: 0.1 | D27: =D9*1000*$C$27 -> 0 | E27: =E9*1000*$C$27 -> 0 | F27: =F9*1000*$C$27 -> 0 | G27: =G9*1000*$C$27 -> 0 | H27: =H9*1000*$C$27 -> 0 | I27: =I9*1000*$C$27 -> 0 | J27: =J9*1000*$C$27 -> 0 | K27: =K9*1000*$C$27 -> 0 | ... AD27: =AD9*1000*$C$27 -> 0 | AF27: =SUM(D27:AD27) -> 0 | AH27: Remaining Mine Life | AI27: 21
A28: Safeguard - Hybrid Declining Baseline | B28: t CO2e | C28: 0 | D28: =D11*'Decommissioned Mine'!E35 -> 0 | E28: =E11*'Decommissioned Mine'!F35 -> 0 | F28: =F11*'Decommissioned Mine'!G35 -> 0 | G28: =G11*'Decommissioned Mine'!H35 -> 0 | H28: =H11*'Decommissioned Mine'!I35 -> 0 | I28: =I11*'Decommissioned Mine'!J35 -> 0 | J28: =J11*'Decommissioned Mine'!K35 -> 0 | K28: =K11*'Decommissioned Mine'!L35 -> 0 | ... AD28: =AD11*'Decommissioned Mine'!AE35 -> 0
A29: Emissions above (or below) baseline | B29: t CO2e | D29: =D27-D28 -> 0 | E29: =E27-E28 -> 0 | F29: =F27-F28 -> 0 | G29: =G27-G28 -> 0 | H29: =H27-H28 -> 0 | I29: =I27-I28 -> 0 | J29: =J27-J28 -> 0 | K29: =K27-K28 -> 0 | ... AD29: =AD27-AD28 -> 0
A31: Marketing
A33: Sales
A34: Coking Product A | B34: kt | D34: =D24*$C$34 -> 0 | E34: =E24*$C$34 -> 0 | F34: =F24*$C$34 -> 0 | G34: =G24*$C$34 -> 0 | H34: =H24*$C$34 -> 0 | I34: =I24*$C$34 -> 0 | J34: =J24*$C$34 -> 0 | K34: =K24*$C$34 -> 0 | ... AD34: =AD24*$C$34 -> 0 | AF34: =SUM(D34:AD34) -> 0
A35: Thermal Product A | B35: kt | D35: =$C$35*D24 -> 0 | E35: =$C$35*E24 -> 0 | F35: =$C$35*F24 -> 0 | G35: =$C$35*G24 -> 0 | H35: =$C$35*H24 -> 0 | I35: =$C$35*I24 -> 0 | J35: =$C$35*J24 -> 0 | K35: =$C$35*K24 -> 0 | ... AD35: =$C$35*AD24 -> 0 | AF35: =SUM(D35:AD35) -> 0
A36: Total Sales | B36: kt | D36: =SUM(D34:D35) -> 0 | E36: =SUM(E34:E35) -> 0 | F36: =SUM(F34:F35) -> 0 | G36: =SUM(G34:G35) -> 0 | H36: =SUM(H34:H35) -> 0 | I36: =SUM(I34:I35) -> 0 | J36: =SUM(J34:J35) -> 0 | K36: =SUM(K34:K35) -> 0 | ... AD36: =SUM(AD34:AD35) -> 0 | AF36: =SUM(AF34:AF35) -> 0
A38: Product Ash (as received)
A39: Coking Product A | B39: % | D39: =$C$39 -> 0 | E39: =$C$39 -> 0 | F39: =$C$39 -> 0 | G39: =$C$39 -> 0 | H39: =$C$39 -> 0 | I39: =$C$39 -> 0 | J39: =$C$39 -> 0 | K39: =$C$39 -> 0 | ... AD39: =$C$39 -> 0
A40: Thermal Product A | B40: % | D40: =$C$40 -> 0 | E40: =$C$40 -> 0 | F40: =$C$40 -> 0 | G40: =$C$40 -> 0 | H40: =$C$40 -> 0 | I40: =$C$40 -> 0 | J40: =$C$40 -> 0 | K40: =$C$40 -> 0 | ... AD40: =$C$40 -> 0
A42: Product Energy (gar)
A43: Coking Product A
A44: Thermal Product A | B44: kcal/kg(gar) | D44: =$C$44 -> 0 | E44: =$C$44 -> 0 | F44: =$C$44 -> 0 | G44: =$C$44 -> 0 | H44: =$C$44 -> 0 | I44: =$C$44 -> 0 | J44: =$C$44 -> 0 | K44: =$C$44 -> 0 | ... AD44: =$C$44 -> 0
A46: GAR-> NAR adjustment | D46: =Assumptions!$B$16 -> 260 | E46: =Assumptions!$B$16 -> 260 | F46: =Assumptions!$B$16 -> 260 | G46: =Assumptions!$B$16 -> 260 | H46: =Assumptions!$B$16 -> 260 | I46: =Assumptions!$B$16 -> 260 | J46: =Assumptions!$B$16 -> 260 | K46: =Assumptions!$B$16 -> 260 | ... AD46: =Assumptions!$B$16 -> 260
A47: Basis of coal prices | D47: =Assumptions!$B$17 -> 6000 | E47: =Assumptions!$B$17 -> 6000 | F47: =Assumptions!$B$17 -> 6000 | G47: =Assumptions!$B$17 -> 6000 | H47: =Assumptions!$B$17 -> 6000 | I47: =Assumptions!$B$17 -> 6000 | J47: =Assumptions!$B$17 -> 6000 | K47: =Assumptions!$B$17 -> 6000 | ... AD47: =Assumptions!$B$17 -> 6000
A49: Product Energy (nar)
A50: Coking Product A | B50: kcal/kg(nar)
A51: Thermal Product A | B51: kcal/kg(nar) | D51: =IF(D35>0,D44-D$46,0) -> 0 | E51: =IF(E35>0,E44-E$46,0) -> 0 | F51: =IF(F35>0,F44-F$46,0) -> 0 | G51: =IF(G35>0,G44-G$46,0) -> 0 | H51: =IF(H35>0,H44-H$46,0) -> 0 | I51: =IF(I35>0,I44-I$46,0) -> 0 | J51: =IF(J35>0,J44-J$46,0) -> 0 | K51: =IF(K35>0,K44-K$46,0) -> 0 | ... AD51: =IF(AD35>0,AD44-AD$46,0) -> 0
A53: Realised Price
A54: Coking Product A | B54: USD/t | D54: =IF(D34>0,Assumptions!J6,0) -> 0 | E54: =IF(E34>0,Assumptions!K6,0) -> 0 | F54: =IF(F34>0,Assumptions!L6,0) -> 0 | G54: =IF(G34>0,Assumptions!M6,0) -> 0 | H54: =IF(H34>0,Assumptions!N6,0) -> 0 | I54: =IF(I34>0,Assumptions!O6,0) -> 0 | J54: =IF(J34>0,Assumptions!P6,0) -> 0 | K54: =IF(K34>0,Assumptions!Q6,0) -> 0 | ... AD54: =IF(AD34>0,Assumptions!AJ6,0) -> 0 | AF54: =X54 -> 0
A55: Thermal Product A | B55: USD/t | D55: =IF(D35>0,IF(D51>Assumptions!J$12,Assumptions!J$7,IF(D51>Assumptions!J$13,Assumptions!J$8,Assumptions!J$9))*(D51/D$47),0) -> 0 | E55: =IF(E35>0,IF(E51>Assumptions!K$12,Assumptions!K$7,IF(E51>Assumptions!K$13,Assumptions!K$8,Assumptions!K$9))*(E51/E$47),0) -> 0 | F55: =IF(F35>0,IF(F51>Assumptions!L$12,Assumptions!L$7,IF(F51>Assumptions!L$13,Assumptions!L$8,Assumptions!L$9))*(F51/F$47),0) -> 0 | G55: =IF(G35>0,IF(G51>Assumptions!M$12,Assumptions!M$7,IF(G51>Assumptions!M$13,Assumptions!M$8,Assumptions!M$9))*(G51/G$47),0) -> 0 | H55: =IF(H35>0,IF(H51>Assumptions!N$12,Assumptions!N$7,IF(H51>Assumptions!N$13,Assumptions!N$8,Assumptions!N$9))*(H51/H$47),0) -> 0 | I55: =IF(I35>0,IF(I51>Assumptions!O$12,Assumptions!O$7,IF(I51>Assumptions!O$13,Assumptions!O$8,Assumptions!O$9))*(I51/I$47),0) -> 0 | J55: =IF(J35>0,IF(J51>Assumptions!P$12,Assumptions!P$7,IF(J51>Assumptions!P$13,Assumptions!P$8,Assumptions!P$9))*(J51/J$47),0) -> 0 | K55: =IF(K35>0,IF(K51>Assumptions!Q$12,Assumptions!Q$7,IF(K51>Assumptions!Q$13,Assumptions!Q$8,Assumptions!Q$9))*(K51/K$47),0) -> 0 | ... AD55: =IF(AD35>0,IF(AD51>Assumptions!AJ$12,Assumptions!AJ$7,IF(AD51>Assumptions!AJ$13,Assumptions!AJ$8,Assumptions!AJ$9))*(AD51/AD$47),0) -> 0 | AF55: =X55 -> 0
A56: Average Export Realised Price | B56: USD/t | D56: =IFERROR(SUMPRODUCT(D34:D35,D54:D55)/D36,0) -> 0 | E56: =IFERROR(SUMPRODUCT(E34:E35,E54:E55)/E36,0) -> 0 | F56: =IFERROR(SUMPRODUCT(F34:F35,F54:F55)/F36,0) -> 0 | G56: =IFERROR(SUMPRODUCT(G34:G35,G54:G55)/G36,0) -> 0 | H56: =IFERROR(SUMPRODUCT(H34:H35,H54:H55)/H36,0) -> 0 | I56: =IFERROR(SUMPRODUCT(I34:I35,I54:I55)/I36,0) -> 0 | J56: =IFERROR(SUMPRODUCT(J34:J35,J54:J55)/J36,0) -> 0 | K56: =IFERROR(SUMPRODUCT(K34:K35,K54:K55)/K36,0) -> 0 | ... AD56: =IFERROR(SUMPRODUCT(AD34:AD35,AD54:AD55)/AD36,0) -> 0 | AF56: =X56 -> 0
A58: Total Revenue | B58: USDk | D58: =SUMPRODUCT(D34:D35,D54:D55) -> 0 | E58: =SUMPRODUCT(E34:E35,E54:E55) -> 0 | F58: =SUMPRODUCT(F34:F35,F54:F55) -> 0 | G58: =SUMPRODUCT(G34:G35,G54:G55) -> 0 | H58: =SUMPRODUCT(H34:H35,H54:H55) -> 0 | I58: =SUMPRODUCT(I34:I35,I54:I55) -> 0 | J58: =SUMPRODUCT(J34:J35,J54:J55) -> 0 | K58: =SUMPRODUCT(K34:K35,K54:K55) -> 0 | ... AD58: =SUMPRODUCT(AD34:AD35,AD54:AD55) -> 0 | AF58: =SUM(D58:AD58) -> 0
A59: FX | B59: USD:AUD | D59: =Assumptions!I4 -> 0.69 | E59: =Assumptions!J4 -> 0.69 | F59: =Assumptions!K4 -> 0.69 | G59: =Assumptions!L4 -> 0.69 | H59: =Assumptions!M4 -> 0.69 | I59: =Assumptions!N4 -> 0.69 | J59: =Assumptions!O4 -> 0.69 | K59: =Assumptions!P4 -> 0.69 | ... AD59: =Assumptions!AI4 -> 0.69
A60: Total Revenue | B60: AUD | D60: =(D58/D59)*(1+$AI$7) -> 0 | E60: =(E58/E59)*(1+$AI$7) -> 0 | F60: =(F58/F59)*(1+$AI$7) -> 0 | G60: =(G58/G59)*(1+$AI$7) -> 0 | H60: =(H58/H59)*(1+$AI$7) -> 0 | I60: =(I58/I59)*(1+$AI$7) -> 0 | J60: =(J58/J59)*(1+$AI$7) -> 0 | K60: =(K58/K59)*(1+$AI$7) -> 0 | ... AD60: =(AD58/AD59)*(1+$AI$7) -> 0 | AF60: =SUM(D60:AD60) -> 0
A61: Average Realisation | B61: AUD/t | D61: =IFERROR(D60/D24,0) -> 0 | E61: =IFERROR(E60/E24,0) -> 0 | F61: =IFERROR(F60/F24,0) -> 0 | G61: =IFERROR(G60/G24,0) -> 0 | H61: =IFERROR(H60/H24,0) -> 0 | I61: =IFERROR(I60/I24,0) -> 0 | J61: =IFERROR(J60/J24,0) -> 0 | K61: =IFERROR(K60/K24,0) -> 0 | ... AD61: =IFERROR(AD60/AD24,0) -> 0 | AF61: =IFERROR(AF60/AF24,0) -> 0
A63: Costs
A65: Direct Mining Costs
A67: Truck and Shovel Costs | B67: AUD/bcm | D67: =IF(D6>0,$C$67*(1+$AI$8),0) -> 0 | E67: =IF(E6>0,$C$67*(1+$AI$8),0) -> 0 | F67: =IF(F6>0,$C$67*(1+$AI$8),0) -> 0 | G67: =IF(G6>0,$C$67*(1+$AI$8),0) -> 0 | H67: =IF(H6>0,$C$67*(1+$AI$8),0) -> 0 | I67: =IF(I6>0,$C$67*(1+$AI$8),0) -> 0 | J67: =IF(J6>0,$C$67*(1+$AI$8),0) -> 0 | K67: =IF(K6>0,$C$67*(1+$AI$8),0) -> 0 | ... AD67: =IF(AD6>0,$C$67*(1+$AI$8),0) -> 0
A68: Total Truck and Shovel Costs | B68: AUDk | D68: =D6*D67 -> 0 | E68: =E6*E67 -> 0 | F68: =F6*F67 -> 0 | G68: =G6*G67 -> 0 | H68: =H6*H67 -> 0 | I68: =I6*I67 -> 0 | J68: =J6*J67 -> 0 | K68: =K6*K67 -> 0 | ... AD68: =AD6*AD67 -> 0 | AF68: =SUM(D68:W68) -> 0
A70: Dragline Costs | B70: AUD/bcm | D70: =IF(D7>0,$C$70*(1+$AI$9),0) -> 0 | E70: =IF(E7>0,$C$70*(1+$AI$9),0) -> 0 | F70: =IF(F7>0,$C$70*(1+$AI$9),0) -> 0 | G70: =IF(G7>0,$C$70*(1+$AI$9),0) -> 0 | H70: =IF(H7>0,$C$70*(1+$AI$9),0) -> 0 | I70: =IF(I7>0,$C$70*(1+$AI$9),0) -> 0 | J70: =IF(J7>0,$C$70*(1+$AI$9),0) -> 0 | K70: =IF(K7>0,$C$70*(1+$AI$9),0) -> 0 | ... AD70: =IF(AD7>0,$C$70*(1+$AI$9),0) -> 0
A71: Total Dragline Costs | B71: AUDk | D71: =D7*D70 -> 0 | E71: =E7*E70 -> 0 | F71: =F7*F70 -> 0 | G71: =G7*G70 -> 0 | H71: =H7*H70 -> 0 | I71: =I7*I70 -> 0 | J71: =J7*J70 -> 0 | K71: =K7*K70 -> 0 | ... AD71: =AD7*AD70 -> 0 | AF71: =SUM(D71:AD71) -> 0
A73: Drill and Blast Costs | B73: AUD/bcm | D73: =IF(D9>0,$C$73*(1+$AI$10),0) -> 0 | E73: =IF(E9>0,$C$73*(1+$AI$10),0) -> 0 | F73: =IF(F9>0,$C$73*(1+$AI$10),0) -> 0 | G73: =IF(G9>0,$C$73*(1+$AI$10),0) -> 0 | H73: =IF(H9>0,$C$73*(1+$AI$10),0) -> 0 | I73: =IF(I9>0,$C$73*(1+$AI$10),0) -> 0 | J73: =IF(J9>0,$C$73*(1+$AI$10),0) -> 0 | K73: =IF(K9>0,$C$73*(1+$AI$10),0) -> 0 | ... AD73: =IF(AD9>0,$C$73*(1+$AI$10),0) -> 0
A74: Total Drill and Blast Costs Costs | B74: AUDk | D74: =D9*D73 -> 0 | E74: =E9*E73 -> 0 | F74: =F9*F73 -> 0 | G74: =G9*G73 -> 0 | H74: =H9*H73 -> 0 | I74: =I9*I73 -> 0 | J74: =J9*J73 -> 0 | K74: =K9*K73 -> 0 | ... AD74: =AD9*AD73 -> 0 | AF74: =SUM(D74:AD74) -> 0
A76: Mine Services Costs | B76: AUDk | D76: =IF(D14>0,$C$76)*(1+$AI$11) -> 0 | E76: =IF(E14>0,$C$76)*(1+$AI$11) -> 0 | F76: =IF(F14>0,$C$76)*(1+$AI$11) -> 0 | G76: =IF(G14>0,$C$76)*(1+$AI$11) -> 0 | H76: =IF(H14>0,$C$76)*(1+$AI$11) -> 0 | I76: =IF(I14>0,$C$76)*(1+$AI$11) -> 0 | J76: =IF(J14>0,$C$76)*(1+$AI$11) -> 0 | K76: =IF(K14>0,$C$76)*(1+$AI$11) -> 0 | ... AD76: =IF(AD14>0,$C$76)*(1+$AI$11) -> 0 | AF76: =SUM(D76:AE76) -> 0
A78: Coal Mining Costs | B78: AUD/ROMt | D78: =IF(D11>0,$C$78*(1+$AI$12),0) -> 0 | E78: =IF(E11>0,$C$78*(1+$AI$12),0) -> 0 | F78: =IF(F11>0,$C$78*(1+$AI$12),0) -> 0 | G78: =IF(G11>0,$C$78*(1+$AI$12),0) -> 0 | H78: =IF(H11>0,$C$78*(1+$AI$12),0) -> 0 | I78: =IF(I11>0,$C$78*(1+$AI$12),0) -> 0 | J78: =IF(J11>0,$C$78*(1+$AI$12),0) -> 0 | K78: =IF(K11>0,$C$78*(1+$AI$12),0) -> 0 | ... AD78: =IF(AD11>0,$C$78*(1+$AI$12),0) -> 0
A79: Total Coal Mining Costs | B79: AUDk | D79: =D78*D11 -> 0 | E79: =E78*E11 -> 0 | F79: =F78*F11 -> 0 | G79: =G78*G11 -> 0 | H79: =H78*H11 -> 0 | I79: =I78*I11 -> 0 | J79: =J78*J11 -> 0 | K79: =K78*K11 -> 0 | ... AD79: =AD78*AD11 -> 0 | AF79: =SUM(D79:AD79) -> 0
A81: Total CHPP Costs (incl. haulage) | B81: AUD/feedt | D81: =IF(D17>0,$C$81*(1+$AI$13),0) -> 0 | E81: =IF(E17>0,$C$81*(1+$AI$13),0) -> 0 | F81: =IF(F17>0,$C$81*(1+$AI$13),0) -> 0 | G81: =IF(G17>0,$C$81*(1+$AI$13),0) -> 0 | H81: =IF(H17>0,$C$81*(1+$AI$13),0) -> 0 | I81: =IF(I17>0,$C$81*(1+$AI$13),0) -> 0 | J81: =IF(J17>0,$C$81*(1+$AI$13),0) -> 0 | K81: =IF(K17>0,$C$81*(1+$AI$13),0) -> 0 | ... AD81: =IF(AD17>0,$C$81*(1+$AI$13),0) -> 0
A82: Total CHPP Costs (incl. haulage) | B82: AUDk | D82: =D17*D81 -> 0 | E82: =E17*E81 -> 0 | F82: =F17*F81 -> 0 | G82: =G17*G81 -> 0 | H82: =H17*H81 -> 0 | I82: =I17*I81 -> 0 | J82: =J17*J81 -> 0 | K82: =K17*K81 -> 0 | ... AD82: =AD17*AD81 -> 0 | AF82: =SUM(D82:AD82) -> 0
A84: Overhead - Site Administration | B84: AUDk | D84: =IF(D$24>0,$C84,0) -> 0 | E84: =IF(E$24>0,$C84,0) -> 0 | F84: =IF(F$24>0,$C84,0) -> 0 | G84: =IF(G$24>0,$C84,0) -> 0 | H84: =IF(H$24>0,$C84,0) -> 0 | I84: =IF(I$24>0,$C84,0) -> 0 | J84: =IF(J$24>0,$C84,0) -> 0 | K84: =IF(K$24>0,$C84,0) -> 0 | ... AD84: =IF(AD$24>0,$C84,0) -> 0
A85: Overhead - Town Management | B85: AUDk | D85: =IF(D$24>0,$C85,0) -> 0 | E85: =IF(E$24>0,$C85,0) -> 0 | F85: =IF(F$24>0,$C85,0) -> 0 | G85: =IF(G$24>0,$C85,0) -> 0 | H85: =IF(H$24>0,$C85,0) -> 0 | I85: =IF(I$24>0,$C85,0) -> 0 | J85: =IF(J$24>0,$C85,0) -> 0 | K85: =IF(K$24>0,$C85,0) -> 0 | ... AD85: =IF(AD$24>0,$C85,0) -> 0
A86: Overhead - Corporate Fees | B86: AUDk | D86: =IF(D$24>0,$C86,0) -> 0 | E86: =IF(E$24>0,$C86,0) -> 0 | F86: =IF(F$24>0,$C86,0) -> 0 | G86: =IF(G$24>0,$C86,0) -> 0 | H86: =IF(H$24>0,$C86,0) -> 0 | I86: =IF(I$24>0,$C86,0) -> 0 | J86: =IF(J$24>0,$C86,0) -> 0 | K86: =IF(K$24>0,$C86,0) -> 0 | ... AD86: =IF(AD$24>0,$C86,0) -> 0
A87: Overhead - Remote Innovation Division | B87: AUDk | D87: =IF(D$24>0,$C87,0) -> 0 | E87: =IF(E$24>0,$C87,0) -> 0 | F87: =IF(F$24>0,$C87,0) -> 0 | G87: =IF(G$24>0,$C87,0) -> 0 | H87: =IF(H$24>0,$C87,0) -> 0 | I87: =IF(I$24>0,$C87,0) -> 0 | J87: =IF(J$24>0,$C87,0) -> 0 | K87: =IF(K$24>0,$C87,0) -> 0 | ... AD87: =IF(AD$24>0,$C87,0) -> 0
A88: Total Overhead Costs | B88: AUDk | D88: =IF(D9>0,SUM(D84:D87)*(1+$AI$14),0) -> 0 | E88: =IF(E9>0,SUM(E84:E87)*(1+$AI$14),0) -> 0 | F88: =IF(F9>0,SUM(F84:F87)*(1+$AI$14),0) -> 0 | G88: =IF(G9>0,SUM(G84:G87)*(1+$AI$14),0) -> 0 | H88: =IF(H9>0,SUM(H84:H87)*(1+$AI$14),0) -> 0 | I88: =IF(I9>0,SUM(I84:I87)*(1+$AI$14),0) -> 0 | J88: =IF(J9>0,SUM(J84:J87)*(1+$AI$14),0) -> 0 | K88: =IF(K9>0,SUM(K84:K87)*(1+$AI$14),0) -> 0 | ... AD88: =IF(AD9>0,SUM(AD84:AD87)*(1+$AI$14),0) -> 0 | AF88: =SUM(D88:AD88) -> 0
A90: Total FOR Costs | D90: =SUM(D68,D71,D74,D76,D79,D82,D88) -> 0 | E90: =SUM(E68,E71,E74,E76,E79,E82,E88) -> 0 | F90: =SUM(F68,F71,F74,F76,F79,F82,F88) -> 0 | G90: =SUM(G68,G71,G74,G76,G79,G82,G88) -> 0 | H90: =SUM(H68,H71,H74,H76,H79,H82,H88) -> 0 | I90: =SUM(I68,I71,I74,I76,I79,I82,I88) -> 0 | J90: =SUM(J68,J71,J74,J76,J79,J82,J88) -> 0 | K90: =SUM(K68,K71,K74,K76,K79,K82,K88) -> 0 | ... AD90: =SUM(AD68,AD71,AD74,AD76,AD79,AD82,AD88) -> 0 | AF90: =SUM(D90:AD90) -> 0
A91: FOR Cost/t | B91: AUD/t | D91: =IFERROR(D90/D24,0) -> 0 | E91: =IFERROR(E90/E24,0) -> 0 | F91: =IFERROR(F90/F24,0) -> 0 | G91: =IFERROR(G90/G24,0) -> 0 | H91: =IFERROR(H90/H24,0) -> 0 | I91: =IFERROR(I90/I24,0) -> 0 | J91: =IFERROR(J90/J24,0) -> 0 | K91: =IFERROR(K90/K24,0) -> 0 | ... AD91: =IFERROR(AD90/AD24,0) -> 0 | AF91: =IFERROR(AF90/AF24,0) -> 0
A93: Direct Selling Expenses
A94: Total Port, Rail and Selling Costs | B94: AUD/t | D94: =$C$94*D36 -> 0 | E94: =$C$94*E36 -> 0 | F94: =$C$94*F36 -> 0 | G94: =$C$94*G36 -> 0 | H94: =$C$94*H36 -> 0 | I94: =$C$94*I36 -> 0 | J94: =$C$94*J36 -> 0 | K94: =$C$94*K36 -> 0 | ... AD94: =$C$94*AD36 -> 0 | AF94: =SUM(D94:AD94) -> 0
A95: Additional take or pay liability | B95: AUD/t | D95: =IF(D$93="Y",$C$95*D36,0) -> 0 | E95: =IF(E$93="Y",$C$95*E36,0) -> 0 | F95: =IF(F$93="Y",$C$95*F36,0) -> 0 | G95: =IF(G$93="Y",$C$95*G36,0) -> 0 | H95: =IF(H$93="Y",$C$95*H36,0) -> 0 | I95: =IF(I$93="Y",$C$95*I36,0) -> 0 | J95: =IF(J$93="Y",$C$95*J36,0) -> 0 | K95: =IF(K$93="Y",$C$95*K36,0) -> 0 | ... AD95: =IF(AD$93="Y",$C$95*AD36,0) -> 0
A96: Government Royalty | B96: AUDk | D96: =D151*D36 -> 0 | E96: =E151*E36 -> 0 | F96: =F151*F36 -> 0 | G96: =G151*G36 -> 0 | H96: =H151*H36 -> 0 | I96: =I151*I36 -> 0 | J96: =J151*J36 -> 0 | K96: =K151*K36 -> 0 | ... AD96: =AD151*AD36 -> 0 | AF96: =SUM(D96:AD96) -> 0
A97: Total Direct Selling Expenses | B97: AUDk | D97: =SUM(D94:D96) -> 0 | E97: =SUM(E94:E96) -> 0 | F97: =SUM(F94:F96) -> 0 | G97: =SUM(G94:G96) -> 0 | H97: =SUM(H94:H96) -> 0 | I97: =SUM(I94:I96) -> 0 | J97: =SUM(J94:J96) -> 0 | K97: =SUM(K94:K96) -> 0 | ... AD97: =SUM(AD94:AD96) -> 0 | AF97: =SUM(AF94:AF96) -> 0
A99: Total FOB Costs | B99: AUDk | D99: =D90+D97 -> 0 | E99: =E90+E97 -> 0 | F99: =F90+F97 -> 0 | G99: =G90+G97 -> 0 | H99: =H90+H97 -> 0 | I99: =I90+I97 -> 0 | J99: =J90+J97 -> 0 | K99: =K90+K97 -> 0 | ... AD99: =AD90+AD97 -> 0 | AF99: =SUM(D99:AD99) -> 0
A100: FOB Cost/t | B100: AUD/t | D100: =IFERROR(D99/D24,0) -> 0 | E100: =IFERROR(E99/E24,0) -> 0 | F100: =IFERROR(F99/F24,0) -> 0 | G100: =IFERROR(G99/G24,0) -> 0 | H100: =IFERROR(H99/H24,0) -> 0 | I100: =IFERROR(I99/I24,0) -> 0 | J100: =IFERROR(J99/J24,0) -> 0 | K100: =IFERROR(K99/K24,0) -> 0 | ... AD100: =IFERROR(AD99/AD24,0) -> 0 | AF100: =IFERROR(AF99/AF24,0) -> 0
A102: Mine Earnings before Other Costs and Taxes | B102: AUDk | D102: =D60-D99 -> 0 | E102: =E60-E99 -> 0 | F102: =F60-F99 -> 0 | G102: =G60-G99 -> 0 | H102: =H60-H99 -> 0 | I102: =I60-I99 -> 0 | J102: =J60-J99 -> 0 | K102: =K60-K99 -> 0 | ... AD102: =AD60-AD99 -> 0 | AF102: =AF60-AF99 -> 0
A104: Other Costs
A105: Progressive Rehabiliation Costs | B105: AUDk | D105: =IF(D9>0,$C$105,0) -> 0 | E105: =IF(E9>0,$C$105,0) -> 0 | F105: =IF(F9>0,$C$105,0) -> 0 | G105: =IF(G9>0,$C$105,0) -> 0 | H105: =IF(H9>0,$C$105,0) -> 0 | I105: =IF(I9>0,$C$105,0) -> 0 | J105: =IF(J9>0,$C$105,0) -> 0 | K105: =IF(K9>0,$C$105,0) -> 0 | ... AD105: =IF(AD9>0,$C$105,0) -> 0 | AF105: =SUM(D105:AD105) -> 0
A106: Mine Closure Costs | B106: AUDk | AF106: =SUM(D106:AD106) -> 0
A107: Carbon Costs | B107: AUDk | D107: =IF(Assumptions!$C$20="Zero Carbon Liability",'OC Clean'!D29*Carbon!B2,'OC Clean'!D29*Carbon!B3)/1000 -> 0 | E107: =IF(Assumptions!$C$20="Zero Carbon Liability",'OC Clean'!E29*Carbon!C2,'OC Clean'!E29*Carbon!C3)/1000 -> 0 | F107: =IF(Assumptions!$C$20="Zero Carbon Liability",'OC Clean'!F29*Carbon!D2,'OC Clean'!F29*Carbon!D3)/1000 -> 0 | G107: =IF(Assumptions!$C$20="Zero Carbon Liability",'OC Clean'!G29*Carbon!E2,'OC Clean'!G29*Carbon!E3)/1000 -> 0 | H107: =IF(Assumptions!$C$20="Zero Carbon Liability",'OC Clean'!H29*Carbon!F2,'OC Clean'!H29*Carbon!F3)/1000 -> 0 | I107: =IF(Assumptions!$C$20="Zero Carbon Liability",'OC Clean'!I29*Carbon!G2,'OC Clean'!I29*Carbon!G3)/1000 -> 0 | J107: =IF(Assumptions!$C$20="Zero Carbon Liability",'OC Clean'!J29*Carbon!H2,'OC Clean'!J29*Carbon!H3)/1000 -> 0 | K107: =IF(Assumptions!$C$20="Zero Carbon Liability",'OC Clean'!K29*Carbon!I2,'OC Clean'!K29*Carbon!I3)/1000 -> 0 | ... AD107: =IF(Assumptions!$C$20="Zero Carbon Liability",'OC Clean'!AD29*Carbon!AB2,'OC Clean'!AD29*Carbon!AB3)/1000 -> 0
A108: Other Revenue | B108: AUDk | D108: 0 | E108: 0 | F108: 0 | G108: 0 | H108: 0 | I108: 0 | J108: 0 | K108: 0 | L108: 0 | M108: 0 | N108: 0 | O108: 0 | P108: 0 | Q108: 0 | R108: 0 | S108: 0 | T108: 0 | U108: 0 | V108: 0 | W108: 0 | X108: 0 | Y108: 0 | Z108: 0 | AA108: 0 | AB108: 0 | AC108: 0 | AD108: 0
A109: Saleable Tonne Royalty | B109: AUDk | D109: =$C$109*D36 -> 0 | E109: =$C$109*E36 -> 0 | F109: =$C$109*F36 -> 0 | G109: =$C$109*G36 -> 0 | H109: =$C$109*H36 -> 0 | I109: =$C$109*I36 -> 0 | J109: =$C$109*J36 -> 0 | K109: =$C$109*K36 -> 0 | ... AD109: =$C$109*AD36 -> 0
A110: Total Other Costs | B110: AUDk | D110: =SUM(D105:D108) -> 0 | E110: =SUM(E105:E108) -> 0 | F110: =SUM(F105:F108) -> 0 | G110: =SUM(G105:G108) -> 0 | H110: =SUM(H105:H108) -> 0 | I110: =SUM(I105:I108) -> 0 | J110: =SUM(J105:J108) -> 0 | K110: =SUM(K105:K108) -> 0 | ... AD110: =SUM(AD105:AD108) -> 0 | AF110: =SUM(AF105:AF106) -> 0
A111: Total other - closure credits | D111: =IF(D106<=0,(D105+D107),D110) -> 0 | E111: =IF(E106<=0,(E105+E107),E110) -> 0 | F111: =IF(F106<=0,(F105+F107),F110) -> 0 | G111: =IF(G106<=0,(G105+G107),G110) -> 0 | H111: =IF(H106<=0,(H105+H107),H110) -> 0 | I111: =IF(I106<=0,(I105+I107),I110) -> 0 | J111: =IF(J106<=0,(J105+J107),J110) -> 0 | K111: =IF(K106<=0,(K105+K107),K110) -> 0 | ... AD111: =IF(AD106<=0,(AD105+AD107),AD110) -> 0
A113: Capital Costs
A114: Project Capital | B114: AUDk | D114: 0 | E114: 0 | F114: 0 | G114: 0 | H114: 0 | I114: 0 | J114: 0 | K114: 0 | L114: 0 | M114: 0 | N114: 0 | O114: 0 | P114: 0 | Q114: 0 | R114: 0 | S114: 0 | T114: 0 | U114: 0 | V114: 0 | W114: 0 | X114: 0 | Y114: 0 | Z114: 0 | AA114: 0 | AB114: 0 | AC114: 0 | AD114: 0 | AF114: =SUM(D114:AD114) -> 0
A115: Mining Equipment/Major Capital | B115: AUDk | D115: ='OC Clean Capital'!D62 -> 0 | E115: ='OC Clean Capital'!E62 -> 0 | F115: ='OC Clean Capital'!F62 -> 0 | G115: ='OC Clean Capital'!G62 -> 0 | H115: ='OC Clean Capital'!H62 -> 0 | I115: ='OC Clean Capital'!I62 -> 0 | J115: ='OC Clean Capital'!J62 -> 0 | K115: ='OC Clean Capital'!K62 -> 0 | ... AB115: ='OC Clean Capital'!AB62 -> 0 | AC115: ='OC Clean Capital'!AA62 -> 0 | AD115: ='OC Clean Capital'!AB62 -> 0 | AF115: =SUM(D115:AD115) -> 0
A116: Sustaining Capital | B116: AUD/ROMt | D116: =$C$116*D11 -> 0 | E116: =$C$116*E11 -> 0 | F116: =$C$116*F11 -> 0 | G116: =$C$116*G11 -> 0 | H116: =$C$116*H11 -> 0 | I116: =$C$116*I11 -> 0 | J116: =$C$116*J11 -> 0 | K116: =$C$116*K11 -> 0 | ... AD116: =$C$116*AD11 -> 0 | AF116: =SUM(D116:AD116) -> 0
A117: Total Capital | B117: AUDk | D117: =SUM(D114:D116)*(1+$AI$15) -> 0 | E117: =SUM(E114:E116)*(1+$AI$15) -> 0 | F117: =SUM(F114:F116)*(1+$AI$15) -> 0 | G117: =SUM(G114:G116)*(1+$AI$15) -> 0 | H117: =SUM(H114:H116)*(1+$AI$15) -> 0 | I117: =SUM(I114:I116)*(1+$AI$15) -> 0 | J117: =SUM(J114:J116)*(1+$AI$15) -> 0 | K117: =SUM(K114:K116)*(1+$AI$15) -> 0 | ... AD117: =SUM(AD114:AD116)*(1+$AI$15) -> 0 | AF117: =SUM(D117:AD117) -> 0
A118: Depreciation | B118: AUDk | D118: =D134 -> 0 | E118: =E134 -> 0 | F118: =F134 -> 0 | G118: =G134 -> 0 | H118: =H134 -> 0 | I118: =I134 -> 0 | J118: =J134 -> 0 | K118: =K134 -> 0 | ... AD118: =AD134 -> 0 | AF118: =SUM(D118:AD118) -> 0
A120: Net Cashflow Before Tax | B120: AUDk | D120: =D102-D110-D117 -> 0 | E120: =E102-E110-E117 -> 0 | F120: =F102-F110-F117 -> 0 | G120: =G102-G110-G117 -> 0 | H120: =H102-H110-H117 -> 0 | I120: =I102-I110-I117 -> 0 | J120: =J102-J110-J117 -> 0 | K120: =K102-K110-K117 -> 0 | ... AD120: =AD102-AD110-AD117 -> 0 | AF120: =AF102-AF110-AF117 -> 0
A121: Tax Paid | B121: AUDk | C121: 0.3 | D121: =IF((D102-D111-D118)*$C$121>0,(D102-D111-D118)*$C$121,0) -> 0 | E121: =IF((E102-E111-E118)*$C$121>0,(E102-E111-E118)*$C$121,0) -> 0 | F121: =IF((F102-F111-F118)*$C$121>0,(F102-F111-F118)*$C$121,0) -> 0 | G121: =IF((G102-G111-G118)*$C$121>0,(G102-G111-G118)*$C$121,0) -> 0 | H121: =IF((H102-H111-H118)*$C$121>0,(H102-H111-H118)*$C$121,0) -> 0 | I121: =IF((I102-I111-I118)*$C$121>0,(I102-I111-I118)*$C$121,0) -> 0 | J121: =IF((J102-J111-J118)*$C$121>0,(J102-J111-J118)*$C$121,0) -> 0 | K121: =IF((K102-K111-K118)*$C$121>0,(K102-K111-K118)*$C$121,0) -> 0 | ... AD121: =IF((AD102-AD111-AD118)*$C$121>0,(AD102-AD111-AD118)*$C$121,0) -> 0 | AF121: =SUM(D121:AD121) -> 0
D122: 1 | E122: 1 | F122: 1 | G122: 1 | H122: 1 | I122: 1 | J122: 1 | K122: 1 | L122: 1 | M122: 1 | N122: 1 | O122: 1 | P122: 1 | Q122: 1 | R122: 1 | S122: 1 | T122: 1 | U122: 1 | V122: 1 | W122: 1 | X122: 1 | Y122: 1 | Z122: 1 | AA122: 1 | AB122: 1 | AC122: 1 | AD122: 1
A124: Cashflows After Tax | B124: AUDk | D124: =D120-D121 -> 0 | E124: =E120-E121 -> 0 | F124: =F120-F121 -> 0 | G124: =G120-G121 -> 0 | H124: =H120-H121 -> 0 | I124: =I120-I121 -> 0 | J124: =J120-J121 -> 0 | K124: =K120-K121 -> 0 | ... AD124: =AD120-AD121 -> 0 | AF124: =AF120-AF121 -> 0
A125: Attributable Cashflow After Tax (60%) | B125: AUDk | D125: =IFERROR(D124*$C$125,0) -> 0 | E125: =IFERROR(E124*$C$125,0) -> 0 | F125: =IFERROR(F124*$C$125,0) -> 0 | G125: =IFERROR(G124*$C$125,0) -> 0 | H125: =IFERROR(H124*$C$125,0) -> 0 | I125: =IFERROR(I124*$C$125,0) -> 0 | J125: =IFERROR(J124*$C$125,0) -> 0 | K125: =IFERROR(K124*$C$125,0) -> 0 | ... AD125: =IFERROR(AD124*$C$125,0) -> 0
A126: Discounted Cashflows | B126: AUDk | D126: =D124*Assumptions!I2 -> 0 | E126: =E124*Assumptions!J2 -> 0 | F126: =F124*Assumptions!K2 -> 0 | G126: =G124*Assumptions!L2 -> 0 | H126: =H124*Assumptions!M2 -> 0 | I126: =I124*Assumptions!N2 -> 0 | J126: =J124*Assumptions!O2 -> 0 | K126: =K124*Assumptions!P2 -> 0 | ... AD126: =AD124*Assumptions!AI2 -> 0 | AF126: =SUM(D126:AD126) -> 0
A127: Payback Calculation | D127: =IFERROR(IF(SUM($D$124:D124)/ABS(D124)>1,0,IF(SUM($D$124:D124)<=0,1*D122,1-(SUM($D$124:D124)/D124)*D122)),0) -> 0 | E127: =IFERROR(IF(SUM($D$124:E124)/ABS(E124)>1,0,IF(SUM($D$124:E124)<=0,1*E122,1-(SUM($D$124:E124)/E124)*E122)),0) -> 0 | F127: =IFERROR(IF(SUM($D$124:F124)/ABS(F124)>1,0,IF(SUM($D$124:F124)<=0,1*F122,1-(SUM($D$124:F124)/F124)*F122)),0) -> 0 | G127: =IFERROR(IF(SUM($D$124:G124)/ABS(G124)>1,0,IF(SUM($D$124:G124)<=0,1*G122,1-(SUM($D$124:G124)/G124)*G122)),0) -> 0 | H127: =IFERROR(IF(SUM($D$124:H124)/ABS(H124)>1,0,IF(SUM($D$124:H124)<=0,1*H122,1-(SUM($D$124:H124)/H124)*H122)),0) -> 0 | I127: =IFERROR(IF(SUM($D$124:I124)/ABS(I124)>1,0,IF(SUM($D$124:I124)<=0,1*I122,1-(SUM($D$124:I124)/I124)*I122)),0) -> 0 | J127: =IFERROR(IF(SUM($D$124:J124)/ABS(J124)>1,0,IF(SUM($D$124:J124)<=0,1*J122,1-(SUM($D$124:J124)/J124)*J122)),0) -> 0 | K127: =IFERROR(IF(SUM($D$124:K124)/ABS(K124)>1,0,IF(SUM($D$124:K124)<=0,1*K122,1-(SUM($D$124:K124)/K124)*K122)),0) -> 0 | ... AD127: =IFERROR(IF(SUM($D$124:AD124)/ABS(AD124)>1,0,IF(SUM($D$124:AD124)<=0,1*AD122,1-(SUM($D$124:AD124)/AD124)*AD122)),0) -> 0
...

Sheet OC Clean Capital
A1: SandsEnd Capital | D1: ='OC Clean'!D2 -> 2027 | E1: =D1+1 -> 2028 | F1: =E1+1 -> 2029 | G1: =F1+1 -> 2030 | H1: =G1+1 -> 2031 | I1: =H1+1 -> 2032 | J1: =I1+1 -> 2033 | K1: =J1+1 -> 2034 | L1: =K1+1 -> 2035 | ... Y1: =X1+1 -> 2048
A3: Capital Items - Units | D3: Insert Unit Numbers by Year Below
A4: Project Cost (Feasibility and exploration) | B4: AUD$k | C4: 8000
A5: 1 x 300t Excavator | B5: AUD$k | C5: 5000
A6: 1 x 400t Excavator | B6: AUD$k | C6: 10000
A7: 1 x 600t Excavator | B7: AUD$k | C7: 14000
A8: 1 x 800t Excavator | B8: AUD$k | C8: 20000
A9: 1 x 320t Truck | B9: AUD$k | C9: 8000
A10: 1 x 230t Truck | B10: AUD$k | C10: 6000
A11: 1 x 190t Truck | B11: AUD$k | C11: 5000
A12: 1 x 130t Truck | B12: AUD$k | C12: 3000
A13: Dragline | B13: AUD$k | C13: 100000
A14: 1 x D11 Dozer | B14: AUD$k | C14: 3000
A15: 1 x D10 Dozer | B15: AUD$k | C15: 2000
... A29: Dry Processing Plant | B29: AUD$k | C29: 20000
A34: Capital Cost - Cost | D34: Do not change cells below
A35: =A4 -> Project Cost (Feasibility and exploration) | B35: AUD$k | C35: =C4 -> 8000 | D35: =$C4*D4 -> 0 | E35: =$C4*E4 -> 0 | F35: =$C4*F4 -> 0 | G35: =$C4*G4 -> 0 | H35: =$C4*H4 -> 0 | I35: =$C4*I4 -> 0 | J35: =$C4*J4 -> 0 | K35: =$C4*K4 -> 0 | ... Y35: =$C4*Y4 -> 0
A36: =A5 -> 1 x 300t Excavator | B36: AUD$k | C36: =C5 -> 5000 | D36: =$C5*D5 -> 0 | E36: =$C5*E5 -> 0 | F36: =$C5*F5 -> 0 | G36: =$C5*G5 -> 0 | H36: =$C5*H5 -> 0 | I36: =$C5*I5 -> 0 | J36: =$C5*J5 -> 0 | K36: =$C5*K5 -> 0 | ... Y36: =$C5*Y5 -> 0
A37: =A6 -> 1 x 400t Excavator | B37: AUD$k | C37: =C6 -> 10000 | D37: =$C6*D6 -> 0 | E37: =$C6*E6 -> 0 | F37: =$C6*F6 -> 0 | G37: =$C6*G6 -> 0 | H37: =$C6*H6 -> 0 | I37: =$C6*I6 -> 0 | J37: =$C6*J6 -> 0 | K37: =$C6*K6 -> 0 | ... Y37: =$C6*Y6 -> 0
A38: =A7 -> 1 x 600t Excavator | B38: AUD$k | C38: =C7 -> 14000 | D38: =$C7*D7 -> 0 | E38: =$C7*E7 -> 0 | F38: =$C7*F7 -> 0 | G38: =$C7*G7 -> 0 | H38: =$C7*H7 -> 0 | I38: =$C7*I7 -> 0 | J38: =$C7*J7 -> 0 | K38: =$C7*K7 -> 0 | ... Y38: =$C7*Y7 -> 0
A39: =A9 -> 1 x 320t Truck | B39: AUD$k | C39: =C9 -> 8000 | D39: =$C9*D9 -> 0 | E39: =$C9*E9 -> 0 | F39: =$C9*F9 -> 0 | G39: =$C9*G9 -> 0 | H39: =$C9*H9 -> 0 | I39: =$C9*I9 -> 0 | J39: =$C9*J9 -> 0 | K39: =$C9*K9 -> 0 | ... Y39: =$C9*Y9 -> 0
A40: =A10 -> 1 x 230t Truck | B40: AUD$k | C40: =C10 -> 6000 | D40: =$C10*D10 -> 0 | E40: =$C10*E10 -> 0 | F40: =$C10*F10 -> 0 | G40: =$C10*G10 -> 0 | H40: =$C10*H10 -> 0 | I40: =$C10*I10 -> 0 | J40: =$C10*J10 -> 0 | K40: =$C10*K10 -> 0 | ... Y40: =$C10*Y10 -> 0
A41: =A13 -> Dragline | B41: AUD$k | C41: =C13 -> 100000 | D41: =$C13*D13 -> 0 | E41: =$C13*E13 -> 0 | F41: =$C13*F13 -> 0 | G41: =$C13*G13 -> 0 | H41: =$C13*H13 -> 0 | I41: =$C13*I13 -> 0 | J41: =$C13*J13 -> 0 | K41: =$C13*K13 -> 0 | ... Y41: =$C13*Y13 -> 0
A42: =A14 -> 1 x D11 Dozer | B42: AUD$k | C42: =C14 -> 3000 | D42: =$C14*D14 -> 0 | E42: =$C14*E14 -> 0 | F42: =$C14*F14 -> 0 | G42: =$C14*G14 -> 0 | H42: =$C14*H14 -> 0 | I42: =$C14*I14 -> 0 | J42: =$C14*J14 -> 0 | K42: =$C14*K14 -> 0 | ... Y42: =$C14*Y14 -> 0
A43: =A15 -> 1 x D10 Dozer | B43: AUD$k | C43: =C15 -> 2000 | D43: =$C15*D15 -> 0 | E43: =$C15*E15 -> 0 | F43: =$C15*F15 -> 0 | G43: =$C15*G15 -> 0 | H43: =$C15*H15 -> 0 | I43: =$C15*I15 -> 0 | J43: =$C15*J15 -> 0 | K43: =$C15*K15 -> 0 | ... Y43: =$C15*Y15 -> 0
A44: =A16 -> 1 x Water truck | B44: AUD$k | C44: =C16 -> 1500 | D44: =$C16*D16 -> 0 | E44: =$C16*E16 -> 0 | F44: =$C16*F16 -> 0 | G44: =$C16*G16 -> 0 | H44: =$C16*H16 -> 0 | I44: =$C16*I16 -> 0 | J44: =$C16*J16 -> 0 | K44: =$C16*K16 -> 0 | ... Y44: =$C16*Y16 -> 0
A45: =A17 -> 1 x Overburden Drill | B45: AUD$k | C45: =C17 -> 1500 | D45: =$C17*D17 -> 0 | E45: =$C17*E17 -> 0 | F45: =$C17*F17 -> 0 | G45: =$C17*G17 -> 0 | H45: =$C17*H17 -> 0 | I45: =$C17*I17 -> 0 | J45: =$C17*J17 -> 0 | K45: =$C17*K17 -> 0 | ... Y45: =$C17*Y17 -> 0
A46: =A18 -> 1 x Grader | B46: AUD$k | C46: =C18 -> 1500 | D46: =$C18*D18 -> 0 | E46: =$C18*E18 -> 0 | F46: =$C18*F18 -> 0 | G46: =$C18*G18 -> 0 | H46: =$C18*H18 -> 0 | I46: =$C18*I18 -> 0 | J46: =$C18*J18 -> 0 | K46: =$C18*K18 -> 0 | ... Y46: =$C18*Y18 -> 0
A47: =A19 -> ROM Pad | B47: AUD$k | C47: =C19 -> 20000 | D47: =$C19*D19 -> 0 | E47: =$C19*E19 -> 0 | F47: =$C19*F19 -> 0 | G47: =$C19*G19 -> 0 | H47: =$C19*H19 -> 0 | I47: =$C19*I19 -> 0 | J47: =$C19*J19 -> 0 | K47: =$C19*K19 -> 0 | ... Y47: =$C19*Y19 -> 0
A48: =A20 -> CHPP Upgrade | B48: AUD$k | C48: =C20 -> 50000 | D48: =$C20*D20 -> 0 | E48: =$C20*E20 -> 0 | F48: =$C20*F20 -> 0 | G48: =$C20*G20 -> 0 | H48: =$C20*H20 -> 0 | I48: =$C20*I20 -> 0 | J48: =$C20*J20 -> 0 | K48: =$C20*K20 -> 0 | ... Y48: =$C20*Y20 -> 0
A49: =A21 -> Topsoil Stripping | B49: AUD$k | C49: =C21 -> 5000 | D49: =$C21*D21 -> 0 | E49: =$C21*E21 -> 0 | F49: =$C21*F21 -> 0 | G49: =$C21*G21 -> 0 | H49: =$C21*H21 -> 0 | I49: =$C21*I21 -> 0 | J49: =$C21*J21 -> 0 | K49: =$C21*K21 -> 0 | ... Y49: =$C21*Y21 -> 0
A50: =A22 -> Comms Tower Installation | B50: AUD$k | C50: =C22 -> 10000 | D50: =$C22*D22 -> 0 | E50: =$C22*E22 -> 0 | F50: =$C22*F22 -> 0 | G50: =$C22*G22 -> 0 | H50: =$C22*H22 -> 0 | I50: =$C22*I22 -> 0 | J50: =$C22*J22 -> 0 | K50: =$C22*K22 -> 0 | ... Y50: =$C22*Y22 -> 0
A51: =A23 -> 25 km Powerline | B51: AUD$k | C51: =C23 -> 20000 | D51: =$C23*D23 -> 0 | E51: =$C23*E23 -> 0 | F51: =$C23*F23 -> 0 | G51: =$C23*G23 -> 0 | H51: =$C23*H23 -> 0 | I51: =$C23*I23 -> 0 | J51: =$C23*J23 -> 0 | K51: =$C23*K23 -> 0 | ... Y51: =$C23*Y23 -> 0
A52: =A24 -> Substation | B52: AUD$k | C52: =C24 -> 10000 | D52: =$C24*D24 -> 0 | E52: =$C24*E24 -> 0 | F52: =$C24*F24 -> 0 | G52: =$C24*G24 -> 0 | H52: =$C24*H24 -> 0 | I52: =$C24*I24 -> 0 | J52: =$C24*J24 -> 0 | K52: =$C24*K24 -> 0 | ... Y52: =$C24*Y24 -> 0
... A59: =A31 -> 0 | B59: AUD$k | C59: =C31 -> 0 | D59: =$C31*D31 -> 0 | E59: =$C31*E31 -> 0 | F59: =$C31*F31 -> 0 | G59: =$C31*G31 -> 0 | H59: =$C31*H31 -> 0 | I59: =$C31*I31 -> 0 | J59: =$C31*J31 -> 0 | K59: =$C31*K31 -> 0 | ... Y59: =$C31*Y31 -> 0
A60: Total | D60: =SUM(D35:D59) -> 0 | E60: =SUM(E35:E59) -> 0 | F60: =SUM(F35:F59) -> 0 | G60: =SUM(G35:G59) -> 0 | H60: =SUM(H35:H59) -> 0 | I60: =SUM(I35:I59) -> 0 | J60: =SUM(J35:J59) -> 0 | K60: =SUM(K35:K59) -> 0 | ... Y60: =SUM(Y35:Y59) -> 0
A61: Contingency | B61: % | C61: 0.2 | D61: =$C$61*D60 -> 0 | E61: =$C$61*E60 -> 0 | F61: =$C$61*F60 -> 0 | G61: =$C$61*G60 -> 0 | H61: =$C$61*H60 -> 0 | I61: =$C$61*I60 -> 0 | J61: =$C$61*J60 -> 0 | K61: =$C$61*K60 -> 0 | ... Y61: =$C$61*Y60 -> 0
A62: Total Capital | D62: =D61+D60 -> 0 | E62: =E61+E60 -> 0 | F62: =F61+F60 -> 0 | G62: =G61+G60 -> 0 | H62: =H61+H60 -> 0 | I62: =I61+I60 -> 0 | J62: =J61+J60 -> 0 | K62: =K61+K60 -> 0 | ... Y62: =Y61+Y60 -> 0

Sheet Carbon
A1: Carbon Cost | B1: 2026 | C1: =B1+1 -> 2027 | D1: =C1+1 -> 2028 | E1: =D1+1 -> 2029 | F1: =E1+1 -> 2030 | G1: =F1+1 -> 2031 | H1: =G1+1 -> 2032 | I1: =H1+1 -> 2033 | J1: =I1+1 -> 2034 | ... AY1: =AX1+1 -> 2075
A2: Zero Carbon Liability | B2: 0 | C2: 0 | D2: 0 | E2: 0 | F2: 0 | G2: 0 | H2: 0 | I2: 0 | J2: 0 | K2: 0 | L2: 0 | M2: 0 | N2: 0 | O2: 0 | P2: 0 | Q2: 0 | R2: 0 | S2: 0 | T2: 0 | U2: 0 | V2: 0 | W2: 0 | X2: 0 | Y2: 0 | Z2: 0 | AA2: 0 | AB2: 0 | AC2: 0 | AD2: 0 | AE2: 0 | AF2: 0 | AG2: 0 | AH2: 0 | AI2: 0 | AJ2: 0 | AK2: 0 | AL2: 0 | AM2: 0 | AN2: 0 | AO2: 0 | AP2: 0 | AQ2: 0 | AR2: 0 | AS2: 0 | AT2: 0 | AU2: 0 | AV2: 0 | AW2: 0 | AX2: 0 | AY2: 0
A3: Accelerated Transition | B3: 45 | C3: 50 | D3: 55 | E3: 65 | F3: 80 | G3: 90 | H3: 100 | I3: 105 | J3: 110 | K3: 115 | L3: 115 | M3: 115 | N3: 120 | O3: 120 | P3: 120 | Q3: 120 | R3: 120 | S3: 120 | T3: 115 | U3: 115 | V3: 115 | W3: 120 | X3: 130 | Y3: 140 | Z3: 140 | AA3: 145 | AB3: 150 | AC3: 150 | AD3: 155 | AE3: 155 | AF3: 160 | AG3: 165 | AH3: 165 | AI3: 170 | AJ3: 175 | AK3: 175 | AL3: 180 | AM3: 185 | AN3: 190 | AO3: 190 | AP3: 195 | AQ3: 200 | AR3: 200 | AS3: 200 | AT3: 200 | AU3: 200 | AV3: 200 | AW3: 200 | AX3: 200 | AY3: 200

Sheet Decommissioned Mine
A1: Decommissioned Mines | E1: =E5 -> 46752 | F1: =F5 -> 47118 | G1: =G5 -> 47483 | H1: =H5 -> 47848 | I1: =I5 -> 48213 | J1: =J5 -> 48579 | K1: =K5 -> 48944 | L1: =L5 -> 49309 | ... AW1: =AW5 -> 62823
A2: Methane (CH4) | B2: =CONCATENATE("Emissions from Decom Mine: "," ",B5) -> Emissions from Decom Mine: Springbok + Brave Blossom | D2: tCO2-e | E2: =IFERROR(IF(E5<$B$11,IF(E5>$B$6,MAX(E3:E4),0),0),0) -> 0 | F2: =IFERROR(IF(F5<$B$11,IF(F5>$B$6,MAX(F3:F4),0),0),0) -> 0 | G2: =IFERROR(IF(G5<$B$11,IF(G5>$B$6,MAX(G3:G4),0),0),0) -> 0 | H2: =IFERROR(IF(H5<$B$11,IF(H5>$B$6,MAX(H3:H4),0),0),0) -> 0 | I2: =IFERROR(IF(I5<$B$11,IF(I5>$B$6,MAX(I3:I4),0),0),0) -> 0 | J2: =IFERROR(IF(J5<$B$11,IF(J5>$B$6,MAX(J3:J4),0),0),0) -> 0 | K2: =IFERROR(IF(K5<$B$11,IF(K5>$B$6,MAX(K3:K4),0),0),0) -> 0 | L2: =IFERROR(IF(L5<$B$11,IF(L5>$B$6,MAX(L3:L4),0),0),0) -> 0 | ... AW2: =IFERROR(IF(AW5<$B$11,IF(AW5>$B$6,MAX(AW3:AW4),0),0),0) -> 0
D3: (3.32 (1)) | E3: =E16 -> 0 | F3: =F16 -> 0 | G3: =G16 -> 0 | H3: =H16 -> 0 | I3: =I16 -> 0 | J3: =J16 -> 0 | K3: =K16 -> 0 | L3: =L16 -> 0 | ... AW3: =AW16 -> 0
A4: DATA ENTRY | D4: (3.32 (2)) | E4: =0.02*E6 -> 20160 | F4: =0.02*F6 -> 20160 | G4: =0.02*G6 -> 20160 | H4: =0.02*H6 -> 20160 | I4: =0.02*I6 -> 20160 | J4: =0.02*J6 -> 20160 | K4: =0.02*K6 -> 20160 | L4: =0.02*L6 -> 20160 | ... AW4: =0.02*AW6 -> 20160
A5: Site | B5: Springbok + Brave Blossom | E5: 46752 | F5: =E5+366 -> 47118 | G5: =F5+365 -> 47483 | H5: =G5+365 -> 47848 | I5: =H5+365 -> 48213 | J5: =I5+366 -> 48579 | K5: =J5+365 -> 48944 | L5: =K5+365 -> 49309 | M5: =L5+365 -> 49674 | N5: =M5+366 -> 50040 | O5: =N5+365 -> 50405 | P5: =O5+365 -> 50770 | Q5: =P5+365 -> 51135 | R5: =Q5+366 -> 51501 | S5: =R5+365 -> 51866 | T5: =S5+365 -> 52231 | U5: =T5+365 -> 52596 | V5: =U5+366 -> 52962 | W5: =V5+365 -> 53327 | X5: =W5+365 -> 53692 | Y5: =X5+365 -> 54057 | Z5: =Y5+366 -> 54423 | AA5: =Z5+365 -> 54788 | AB5: =AA5+365 -> 55153 | AC5: =AB5+365 -> 55518 | AD5: =AC5+366 -> 55884 | AE5: =AD5+365 -> 56249 | AF5: =AE5+365 -> 56614 | AG5: =AF5+365 -> 56979 | AH5: =AG5+366 -> 57345 | AI5: =AH5+365 -> 57710 | AJ5: =AI5+365 -> 58075 | AK5: =AJ5+365 -> 58440 | AL5: =AK5+366 -> 58806 | AM5: =AL5+365 -> 59171 | AN5: =AM5+365 -> 59536 | AO5: =AN5+365 -> 59901 | AP5: =AO5+366 -> 60267 | AQ5: =AP5+365 -> 60632 | AR5: =AQ5+365 -> 60997 | AS5: =AR5+365 -> 61362 | AT5: =AS5+366 -> 61728 | AU5: =AT5+365 -> 62093 | AV5: =AU5+365 -> 62458 | AW5: =AV5+365 -> 62823
A6: Date Mine Closed | B6: =VLOOKUP(B5,A29:J31,6) -> 55153 | D6: Etdm | E6: =$B$8 -> 1008000 | F6: =$B$8 -> 1008000 | G6: =$B$8 -> 1008000 | H6: =$B$8 -> 1008000 | I6: =$B$8 -> 1008000 | J6: =$B$8 -> 1008000 | K6: =$B$8 -> 1008000 | L6: =$B$8 -> 1008000 | ... AW6: =$B$8 -> 1008000
A7: Gassy/Non-Gassy | B7: =VLOOKUP($B$5,$A$29:$J$31,3) -> Gassy | D7: A | E7: =0.23/12 -> 0.019166667 | F7: =0.23/12 -> 0.019166667 | G7: =0.23/12 -> 0.019166667 | H7: =0.23/12 -> 0.019166667 | I7: =0.23/12 -> 0.019166667 | J7: =0.23/12 -> 0.019166667 | K7: =0.23/12 -> 0.019166667 | L7: =0.23/12 -> 0.019166667 | ... AW7: =0.23/12 -> 0.019166667
A8: CH4 emissions from mine 12 month prior to closure | B8: =VLOOKUP($B$5,$A$29:$J$31,4) -> 1008000 | D8: b | E8: -1.45 | F8: -1.45 | G8: -1.45 | H8: -1.45 | I8: -1.45 | J8: -1.45 | K8: -1.45 | L8: -1.45 | M8: -1.45 | N8: -1.45 | O8: -1.45 | P8: -1.45 | Q8: -1.45 | R8: -1.45 | S8: -1.45 | T8: -1.45 | U8: -1.45 | V8: -1.45 | W8: -1.45 | X8: -1.45 | Y8: -1.45 | Z8: -1.45 | AA8: -1.45 | AB8: -1.45 | AC8: -1.45 | AD8: -1.45 | AE8: -1.45 | AF8: -1.45 | AG8: -1.45 | AH8: -1.45 | AI8: -1.45 | AJ8: -1.45 | AK8: -1.45 | AL8: -1.45 | AM8: -1.45 | AN8: -1.45 | AO8: -1.45 | AP8: -1.45 | AQ8: -1.45 | AR8: -1.45 | AS8: -1.45 | AT8: -1.45 | AU8: -1.45 | AV8: -1.45 | AW8: -1.45
A9: Mine Void Volume (m3) | B9: =VLOOKUP($B$5,$A$29:$J$31,5) -> 42319176 | D9: c | E9: 0.024 | F9: 0.024 | G9: 0.024 | H9: 0.024 | I9: 0.024 | J9: 0.024 | K9: 0.024 | L9: 0.024 | M9: 0.024 | N9: 0.024 | O9: 0.024 | P9: 0.024 | Q9: 0.024 | R9: 0.024 | S9: 0.024 | T9: 0.024 | U9: 0.024 | V9: 0.024 | W9: 0.024 | X9: 0.024 | Y9: 0.024 | Z9: 0.024 | AA9: 0.024 | AB9: 0.024 | AC9: 0.024 | AD9: 0.024 | AE9: 0.024 | AF9: 0.024 | AG9: 0.024 | AH9: 0.024 | AI9: 0.024 | AJ9: 0.024 | AK9: 0.024 | AL9: 0.024 | AM9: 0.024 | AN9: 0.024 | AO9: 0.024 | AP9: 0.024 | AQ9: 0.024 | AR9: 0.024 | AS9: 0.024 | AT9: 0.024 | AU9: 0.024 | AV9: 0.024 | AW9: 0.024
A10: Year to Stop Reporting | B10: =(YEAR(B6))+21 -> 2071 | D10: Months (T) | E10: =IFERROR(DATEDIF($B$6,E$5,"M"),0) -> 0 | F10: =IFERROR(DATEDIF($B$6,F$5,"M"),0) -> 0 | G10: =IFERROR(DATEDIF($B$6,G$5,"M"),0) -> 0 | H10: =IFERROR(DATEDIF($B$6,H$5,"M"),0) -> 0 | I10: =IFERROR(DATEDIF($B$6,I$5,"M"),0) -> 0 | J10: =IFERROR(DATEDIF($B$6,J$5,"M"),0) -> 0 | K10: =IFERROR(DATEDIF($B$6,K$5,"M"),0) -> 0 | L10: =IFERROR(DATEDIF($B$6,L$5,"M"),0) -> 0 | ... AW10: =IFERROR(DATEDIF($B$6,AW$5,"M"),0) -> 252
B11: =DATE(B10,12,31) -> 62823 | D11: Mwi | E11: =B13+B12 -> 74000 | F11: =$E$11 -> 74000 | G11: =$E$11 -> 74000 | H11: =$E$11 -> 74000 | I11: =$E$11 -> 74000 | J11: =$E$11 -> 74000 | K11: =$E$11 -> 74000 | L11: =$E$11 -> 74000 | M11: =$E$11 -> 74000 | ... AW11: =$E$11 -> 74000
A12: Additional Annual Flood Volume m3 | B12: 0 | D12: N | E12: =IF(E10<12,E10,12) -> 0 | F12: =IF(F10<12,F10,12) -> 0 | G12: =IF(G10<12,G10,12) -> 0 | H12: =IF(H10<12,H10,12) -> 0 | I12: =IF(I10<12,I10,12) -> 0 | J12: =IF(J10<12,J10,12) -> 0 | K12: =IF(K10<12,K10,12) -> 0 | L12: =IF(L10<12,L10,12) -> 0 | ... AW12: =IF(AW10<12,AW10,12) -> 12
A13: QLD Default Flood Volume M3 | B13: 74000 | D13: Mvv | E13: =$B$9 -> 42319176 | F13: =$B$9 -> 42319176 | G13: =$B$9 -> 42319176 | H13: =$B$9 -> 42319176 | I13: =$B$9 -> 42319176 | J13: =$B$9 -> 42319176 | K13: =$B$9 -> 42319176 | L13: =$B$9 -> 42319176 | ... AW13: =$B$9 -> 42319176
D14: EFdm | E14: =(((1+E7*E10)^(1+E8)-(1+E7*(E10-E12))^(1+E8))/(E7*(1+E8))-E9*E12)/12 -> 0 | F14: =(((1+F7*F10)^(1+F8)-(1+F7*(F10-F12))^(1+F8))/(F7*(1+F8))-F9*F12)/12 -> 0 | G14: =(((1+G7*G10)^(1+G8)-(1+G7*(G10-G12))^(1+G8))/(G7*(1+G8))-G9*G12)/12 -> 0 | H14: =(((1+H7*H10)^(1+H8)-(1+H7*(H10-H12))^(1+H8))/(H7*(1+H8))-H9*H12)/12 -> 0 | I14: =(((1+I7*I10)^(1+I8)-(1+I7*(I10-I12))^(1+I8))/(I7*(1+I8))-I9*I12)/12 -> 0 | J14: =(((1+J7*J10)^(1+J8)-(1+J7*(J10-J12))^(1+J8))/(J7*(1+J8))-J9*J12)/12 -> 0 | K14: =(((1+K7*K10)^(1+K8)-(1+K7*(K10-K12))^(1+K8))/(K7*(1+K8))-K9*K12)/12 -> 0 | L14: =(((1+L7*L10)^(1+L8)-(1+L7*(L10-L12))^(1+L8))/(L7*(1+L8))-L9*L12)/12 -> 0 | ... AW14: =(((1+AW7*AW10)^(1+AW8)-(1+AW7*(AW10-AW12))^(1+AW8))/(AW7*(1+AW8))-AW9*AW12)/12 -> 0.055878628
D15: Fdm | E15: =IFERROR(MIN(E11/E13*E10/12,1),0) -> 0 | F15: =IFERROR(MIN(F11/F13*F10/12,1),0) -> 0 | G15: =IFERROR(MIN(G11/G13*G10/12,1),0) -> 0 | H15: =IFERROR(MIN(H11/H13*H10/12,1),0) -> 0 | I15: =IFERROR(MIN(I11/I13*I10/12,1),0) -> 0 | J15: =IFERROR(MIN(J11/J13*J10/12,1),0) -> 0 | K15: =IFERROR(MIN(K11/K13*K10/12,1),0) -> 0 | L15: =IFERROR(MIN(L11/L13*L10/12,1),0) -> 0 | ... AW15: =IFERROR(MIN(AW11/AW13*AW10/12,1),0) -> 0.036720942
D16: Edm | E16: =IF(E10/12<20,(E6*E14*(1-E15)),0) -> 0 | F16: =IF(F10/12<20,(F6*F14*(1-F15)),0) -> 0 | G16: =IF(G10/12<20,(G6*G14*(1-G15)),"0") -> 0 | H16: =IF(H10/12<20,(H6*H14*(1-H15)),"0") -> 0 | I16: =IF(I10/12<20,(I6*I14*(1-I15)),"0") -> 0 | J16: =IF(J10/12<20,(J6*J14*(1-J15)),"0") -> 0 | K16: =IF(K10/12<20,(K6*K14*(1-K15)),"0") -> 0 | L16: =IF(L10/12<20,(L6*L14*(1-L15)),"0") -> 0 | M16: =IF(M10/12<20,(M6*M14*(1-M15)),"0") -> 0 | N16: =IF(N10/12<20,(N6*N14*(1-N15)),"0") -> 0 | ... AW16: =IF(AW10/12<20,(AW6*AW14*(1-AW15)),"0") -> 0
D20: Baseline Calculation Inputs
D21: Decom Mines emissions Baseline EI | E21: 0.7795 | F21: 0.7305 | G21: 0.6815 | H21: 0.640575 | I21: 0.607725 | J21: 0.574875 | K21: 0.542025 | L21: 0.509175 | M21: 0.476325 | N21: 0.443475 | O21: 0.410625 | P21: 0.377775 | Q21: 0.344925 | R21: 0.312075 | S21: 0.279225 | T21: 0.246375 | U21: 0.213525 | V21: 0.180675 | W21: 0.147825 | X21: 0.114975 | Y21: 0.082125 | Z21: 0.049275 | AA21: 0.016425 | AB21: 1.2490009e-16 | AC21: 1.2490009e-16 | AD21: 1.2490009e-16 | AE21: 1.2490009e-16 | AF21: 1.2490009e-16 | AG21: 1.2490009e-16 | AH21: 1.2490009e-16 | AI21: 1.2490009e-16 | AJ21: 1.2490009e-16 | AK21: 1.2490009e-16 | AL21: 1.2490009e-16 | AM21: 1.2490009e-16 | AN21: 1.2490009e-16 | AO21: 1.2490009e-16 | AP21: 1.2490009e-16 | AQ21: 1.2490009e-16 | AR21: 1.2490009e-16 | AS21: 1.2490009e-16 | AT21: 1.2490009e-16 | AU21: 1.2490009e-16 | AV21: 1.2490009e-16 | AW21: 1.2490009e-16
D22: ROM Baseline EI | E22: 0.08206857 | F22: 0.07302751 | G22: 0.06450781 | H22: 0.058868842 | I22: 0.055849927 | J22: 0.052831012 | K22: 0.049812097 | L22: 0.046793182 | M22: 0.043774267 | N22: 0.040755352 | O22: 0.037736437 | P22: 0.034717523 | Q22: 0.031698608 | R22: 0.028679692 | S22: 0.025660778 | T22: 0.022641863 | U22: 0.019622948 | V22: 0.016604033 | W22: 0.013585118 | X22: 0.010566203 | Y22: 0.0075472875 | Z22: 0.0045283725 | AA22: 0.0015094575 | AB22: 1.1478318e-17 | AC22: 1.1478318e-17 | AD22: 1.1478318e-17 | AE22: 1.1478318e-17 | AF22: 1.1478318e-17 | AG22: 1.1478318e-17 | AH22: 1.1478318e-17 | AI22: 1.1478318e-17 | AJ22: 1.1478318e-17 | AK22: 1.1478318e-17 | AL22: 1.1478318e-17 | AM22: 1.1478318e-17 | AN22: 1.1478318e-17 | AO22: 1.1478318e-17 | AP22: 1.1478318e-17 | AQ22: 1.1478318e-17 | AR22: 1.1478318e-17 | AS22: 1.1478318e-17 | AT22: 1.1478318e-17 | AU22: 1.1478318e-17 | AV22: 1.1478318e-17 | AW22: 1.1478318e-17
A27: Change the drop down in B5 to match the selected proposal
A28: Option | B28: the tonnes of coal mine waste gas (CO2-e) flared | C28: whether the mine is a gassy mine or a non-gassy mine | D28: The tonnes of methane emissions (CO2-e) from the mine in the last 12 month period before the mine became a decommissioned underground coal mine | E28: Mine Void (m3) | F28: the date that the mine was Sealed | G28: Mine Closure Year | H28: Year to Stop Reporting | I28: Method | J28: Flood Rate m3 per year
A29: Springbok | B29: 0 | C29: Gassy | D29: =Springbok!H22 -> 649511.87 | E29: 21159588 | F29: 48213 | G29: =YEAR(F29) -> 2031 | H29: =G29+20 -> 2051 | I29: Method 1 (3.32 Pt2) | J29: 74000
A30: Springbok + Brave Blossom | B30: 0 | C30: Gassy | D30: ='Brave Blossom '!AA22 -> 1008000 | E30: 42319176 | F30: 55153 | G30: 2050 | H30: =G30+20 -> 2070 | I30: Method 1 (3.32 Pt2) | J30: 74000
A31: Springbok Delayed 12 Months | B31: 0 | C31: Gassy | D31: =D29*0.5 -> 324755.93 | E31: 21159588 | F31: 48579 | G31: =YEAR(F31) -> 2032 | H31: =G31+20 -> 2052 | I31: Method 1 (3.32 Pt2) | J31: 74000
A34: Baseline Calculation Inputs - OC Clean | B34: 2024 | C34: =B34+1 -> 2025 | D34: =C34+1 -> 2026 | E34: =D34+1 -> 2027 | F34: =E34+1 -> 2028 | G34: =F34+1 -> 2029 | H34: =G34+1 -> 2030 | I34: =H34+1 -> 2031 | J34: =I34+1 -> 2032 | ... AW34: =AV34+1 -> 2071
A35: ROM Baseline EI | B35: 0.024231693 | C35: 0.026451601 | D35: 0.02867151 | E35: 0.032001373 | F35: 0.03644119 | G35: 0.040881007 | H35: 0.043100915 | I35: 0.043100915 | J35: 0.043100915 | K35: 0.043100915 | L35: 0.043100915 | M35: 0.043100915 | N35: 0.043100915 | O35: 0.043100915 | P35: 0.043100915 | Q35: 0.043100915 | R35: 0.043100915 | S35: 0.043100915 | T35: 0.043100915 | U35: 0.043100915 | V35: 0.043100915 | W35: 0.043100915 | X35: 0.043100915 | Y35: 0.043100915 | Z35: 0.043100915 | AA35: 0.043100915 | AB35: 0.043100915 | AC35: 0.043100915 | AD35: 0.043100915 | AE35: 0.043100915 | AF35: 0.043100915 | AG35: 0.043100915 | AH35: 0.043100915 | AI35: 0.043100915 | AJ35: 0.043100915 | AK35: 0.043100915 | AL35: 0.043100915 | AM35: 0.043100915 | AN35: 0.043100915 | AO35: 0.043100915 | AP35: 0.043100915 | AQ35: 0.043100915 | AR35: 0.043100915 | AS35: 0.043100915 | AT35: 0.043100915 | AU35: 0.043100915 | AV35: 0.043100915 | AW35: 0.043100915
